Workbook

Sheet CODORL
O1: códigos ok
O2: VISITADOR | P2: INICIALES | Q2: CODORL | R2: TIPO | S2: NOMBRE ORL | T2: Nombre | U2: CONTROLVENTAS
O3: Maika Blázquez (Madrid) | P3: MBM | Q3: MBM187 | R3: A | S3: Dr, Abel Bogoya Castaño | T3: Abel Bogoya Castaño | U3: MBM187
O4: Ramon Ferrando(Valencia) | P4: RFV | Q4: RFV08 | R4: B | S4: Dr, Abel Guzmán Calvete | T4: Abel Guzmán Calvete | U4: RFV08
O5: Maika Blázquez (Madrid) | P5: MBM | Q5: MBM86 | R5: A | S5: Dra, Adela Cordero Devesa | T5: Adela Cordero Devesa | U5: MBM86
O6: Roberto Pereira (Galicia) | P6: RPG | Q6: RPG33 | R6: A | S6: Dra, Adela Pérez-Caro Ríos | T6: Adela Pérez-Caro Ríos | U6: RPG33
O7: Lisandro Russian (Madrid,Cáceres, Toledo, Talavera y Logroño) | P7: LRM | Q7: LRM01 | R7: A | S7: Dr, Adolfo Carlos Hinojar Gutierrez | T7: Adolfo Carlos Hinojar Gutierrez | U7: LRM01
O8: Alberto Moreno | P8: AMM | Q8: AMM01 | R8: A | S8: Dr, Adolfo del Valle Zapico | T8: Adolfo del Valle Zapico | U8: AMM01
O9: Maika Blázquez (Madrid) | P9: MBM | Q9: MBM01 | R9: A | S9: Dr, Adolfo Toledano Muñoz | T9: Adolfo Toledano Muñoz | U9: MBM01
O10: Lisandro Russian (Madrid,Cáceres, Toledo, Talavera y Logroño) | P10: LRM | Q10: LRM123 | R10: A | S10: Dra, Adriana Pardo Maza | T10: Adriana Pardo Maza | U10: LRM123
O11: Maika Blázquez (Madrid) | P11: MBM | Q11: MBM87 | R11: A | S11: Dra, Adriana Pérez García | T11: Adriana Pérez García | U11: MBM87
O12: Iván Sánchez (Levante y Albacete) | P12: ISL | Q12: ISL82 | R12: B | S12: Dra, Africa Jiménez de la Rosa | T12: Africa Jiménez de la Rosa | U12: ISL82
O13: Ramon Ferrando(Valencia) | P13: RFV | Q13: RFV09 | R13: B | S13: Dr, Agustín Campos Catalá | T13: Agustín Campos Catalá | U13: RFV09
... O931: Ramon Ferrando(Valencia) | P931: RFV | Q931: RFV45 | R931: B | S931: Dr, Ángel Ángel de Miguel | T931: Ángel Ángel de Miguel | U931: RFV45
O932: Lisandro Russian (Madrid, Cáceres, Toledo, Talavera Y Logroño) | P932: LRM | Q932: LRM259 | R932: A | S932: Dr, Carlos Montero García | T932: Carlos Montero García | U932: =Q932 -> LRM259

Sheet códigosORL
F1: Códigos actualizados
F5: =IFERROR(__xludf.DUMMYFUNCTION("QUERY(IMPORTRANGE(""1vYjGeYY0Fv1uPTb97Gbjvlxd4khfYQOQJB5UlsSt3ZY/edit?gid=0#gid=0"",""CODORL!A:F""),""SELECT *"",2)"),"🟢 Introduce los datos en la fila 3 y pulsa el botón para generar el código ORL VISITADOR") -> 🟢 Introduce los datos en la fila 3 y pulsa el botón para generar el código ORL VISITADOR | G5: =IFERROR(__xludf.DUMMYFUNCTION("""COMPUTED_VALUE""")," INICIALES") -> INICIALES | H5: =IFERROR(__xludf.DUMMYFUNCTION("""COMPUTED_VALUE""")," CODORL") -> CODORL | I5: =IFERROR(__xludf.DUMMYFUNCTION("""COMPUTED_VALUE""")," TIPO") -> TIPO | J5: =IFERROR(__xludf.DUMMYFUNCTION("""COMPUTED_VALUE""")," NOMBRE ORL") -> NOMBRE ORL | K5: =IFERROR(__xludf.DUMMYFUNCTION("""COMPUTED_VALUE""")," OBSERVACIONES") -> OBSERVACIONES
F7: =IFERROR(__xludf.DUMMYFUNCTION("""COMPUTED_VALUE"""),"Luis Alberto Rodríguez") -> Luis Alberto Rodríguez | G7: =IFERROR(__xludf.DUMMYFUNCTION("""COMPUTED_VALUE"""),"LAA") -> LAA | H7: =IFERROR(__xludf.DUMMYFUNCTION("""COMPUTED_VALUE"""),"LAA91") -> LAA91 | I7: =IFERROR(__xludf.DUMMYFUNCTION("""COMPUTED_VALUE"""),"C") -> C | J7: =IFERROR(__xludf.DUMMYFUNCTION("""COMPUTED_VALUE"""),"Julio César Ariza Lizcano") -> Julio César Ariza Lizcano | L7: =H7 -> LAA91 | M7: =G7 -> LAA
F8: =IFERROR(__xludf.DUMMYFUNCTION("""COMPUTED_VALUE"""),"Lisandro Russian") -> Lisandro Russian | G8: =IFERROR(__xludf.DUMMYFUNCTION("""COMPUTED_VALUE"""),"LRM") -> LRM | H8: =IFERROR(__xludf.DUMMYFUNCTION("""COMPUTED_VALUE"""),"LRM274") -> LRM274 | I8: =IFERROR(__xludf.DUMMYFUNCTION("""COMPUTED_VALUE"""),"A") -> A | J8: =IFERROR(__xludf.DUMMYFUNCTION("""COMPUTED_VALUE"""),"Ane Díez Fernández") -> Ane Díez Fernández | L8: =H8 -> LRM274 | M8: =G8 -> LRM
F9: =IFERROR(__xludf.DUMMYFUNCTION("""COMPUTED_VALUE"""),"Maika Blázquez") -> Maika Blázquez | G9: =IFERROR(__xludf.DUMMYFUNCTION("""COMPUTED_VALUE"""),"MBM") -> MBM | H9: =IFERROR(__xludf.DUMMYFUNCTION("""COMPUTED_VALUE"""),"MBM235") -> MBM235 | I9: =IFERROR(__xludf.DUMMYFUNCTION("""COMPUTED_VALUE"""),"A") -> A | J9: =IFERROR(__xludf.DUMMYFUNCTION("""COMPUTED_VALUE"""),"Andrés Bejarano Bueno") -> Andrés Bejarano Bueno | L9: =H9 -> MBM235 | M9: =G9 -> MBM
F10: =IFERROR(__xludf.DUMMYFUNCTION("""COMPUTED_VALUE"""),"Iván Sánchez") -> Iván Sánchez | G10: =IFERROR(__xludf.DUMMYFUNCTION("""COMPUTED_VALUE"""),"ISL") -> ISL | H10: =IFERROR(__xludf.DUMMYFUNCTION("""COMPUTED_VALUE"""),"ISL155") -> ISL155 | I10: =IFERROR(__xludf.DUMMYFUNCTION("""COMPUTED_VALUE"""),"B") -> B | J10: =IFERROR(__xludf.DUMMYFUNCTION("""COMPUTED_VALUE"""),"Andreina Betancourt Martínez") -> Andreina Betancourt Martínez | L10: =H10 -> ISL155 | M10: =G10 -> ISL
F11: =IFERROR(__xludf.DUMMYFUNCTION("""COMPUTED_VALUE"""),"Maika Blázquez") -> Maika Blázquez | G11: =IFERROR(__xludf.DUMMYFUNCTION("""COMPUTED_VALUE"""),"MBM") -> MBM | H11: =IFERROR(__xludf.DUMMYFUNCTION("""COMPUTED_VALUE"""),"MBM234") -> MBM234 | I11: =IFERROR(__xludf.DUMMYFUNCTION("""COMPUTED_VALUE"""),"A") -> A | J11: =IFERROR(__xludf.DUMMYFUNCTION("""COMPUTED_VALUE"""),"Andrea López") -> Andrea López | L11: =H11 -> MBM234 | M11: =G11 -> MBM
F12: =IFERROR(__xludf.DUMMYFUNCTION("""COMPUTED_VALUE"""),"Maika Blázquez") -> Maika Blázquez | G12: =IFERROR(__xludf.DUMMYFUNCTION("""COMPUTED_VALUE"""),"MBM") -> MBM | H12: =IFERROR(__xludf.DUMMYFUNCTION("""COMPUTED_VALUE"""),"MBM233") -> MBM233 | I12: =IFERROR(__xludf.DUMMYFUNCTION("""COMPUTED_VALUE"""),"A") -> A | J12: =IFERROR(__xludf.DUMMYFUNCTION("""COMPUTED_VALUE"""),"Ana Clemente Arias") -> Ana Clemente Arias | L12: =H12 -> MBM233 | M12: =G12 -> MBM
F13: =IFERROR(__xludf.DUMMYFUNCTION("""COMPUTED_VALUE"""),"Luis Alberto Rodríguez") -> Luis Alberto Rodríguez | G13: =IFERROR(__xludf.DUMMYFUNCTION("""COMPUTED_VALUE"""),"LAA") -> LAA | H13: =IFERROR(__xludf.DUMMYFUNCTION("""COMPUTED_VALUE"""),"LAA90") -> LAA90 | I13: =IFERROR(__xludf.DUMMYFUNCTION("""COMPUTED_VALUE"""),"C") -> C | J13: =IFERROR(__xludf.DUMMYFUNCTION("""COMPUTED_VALUE"""),"Amparo Postigo Madueño") -> Amparo Postigo Madueño | L13: =H13 -> LAA90 | M13: =G13 -> LAA
F14: =IFERROR(__xludf.DUMMYFUNCTION("""COMPUTED_VALUE"""),"Maika Blázquez") -> Maika Blázquez | G14: =IFERROR(__xludf.DUMMYFUNCTION("""COMPUTED_VALUE"""),"MBM") -> MBM | H14: =IFERROR(__xludf.DUMMYFUNCTION("""COMPUTED_VALUE"""),"MBM232") -> MBM232 | I14: =IFERROR(__xludf.DUMMYFUNCTION("""COMPUTED_VALUE"""),"A") -> A | J14: =IFERROR(__xludf.DUMMYFUNCTION("""COMPUTED_VALUE"""),"Ali Ibrahim Farhat") -> Ali Ibrahim Farhat | L14: =H14 -> MBM232 | M14: =G14 -> MBM
F15: =IFERROR(__xludf.DUMMYFUNCTION("""COMPUTED_VALUE"""),"Maika Blázquez") -> Maika Blázquez | G15: =IFERROR(__xludf.DUMMYFUNCTION("""COMPUTED_VALUE"""),"MBM") -> MBM | H15: =IFERROR(__xludf.DUMMYFUNCTION("""COMPUTED_VALUE"""),"MBM231") -> MBM231 | I15: =IFERROR(__xludf.DUMMYFUNCTION("""COMPUTED_VALUE"""),"A") -> A | J15: =IFERROR(__xludf.DUMMYFUNCTION("""COMPUTED_VALUE"""),"Itziar Jimenez Gomez") -> Itziar Jimenez Gomez | L15: =H15 -> MBM231 | M15: =G15 -> MBM
F16: =IFERROR(__xludf.DUMMYFUNCTION("""COMPUTED_VALUE"""),"Iván Sánchez") -> Iván Sánchez | G16: =IFERROR(__xludf.DUMMYFUNCTION("""COMPUTED_VALUE"""),"ISL") -> ISL | H16: =IFERROR(__xludf.DUMMYFUNCTION("""COMPUTED_VALUE"""),"ISL154") -> ISL154 | I16: =IFERROR(__xludf.DUMMYFUNCTION("""COMPUTED_VALUE"""),"B") -> B | J16: =IFERROR(__xludf.DUMMYFUNCTION("""COMPUTED_VALUE"""),"Alfonso Rodríguez Fabio") -> Alfonso Rodríguez Fabio | L16: =H16 -> ISL154 | M16: =G16 -> ISL
F17: =IFERROR(__xludf.DUMMYFUNCTION("""COMPUTED_VALUE"""),"Iván Sánchez") -> Iván Sánchez | G17: =IFERROR(__xludf.DUMMYFUNCTION("""COMPUTED_VALUE"""),"ISL") -> ISL | H17: =IFERROR(__xludf.DUMMYFUNCTION("""COMPUTED_VALUE"""),"ISL153") -> ISL153 | I17: =IFERROR(__xludf.DUMMYFUNCTION("""COMPUTED_VALUE"""),"B") -> B | J17: =IFERROR(__xludf.DUMMYFUNCTION("""COMPUTED_VALUE"""),"Alejandra Arellano Bárcenas") -> Alejandra Arellano Bárcenas | L17: =H17 -> ISL153 | M17: =G17 -> ISL
F18: =IFERROR(__xludf.DUMMYFUNCTION("""COMPUTED_VALUE"""),"Lisandro Russian") -> Lisandro Russian | G18: =IFERROR(__xludf.DUMMYFUNCTION("""COMPUTED_VALUE"""),"LRM") -> LRM | H18: =IFERROR(__xludf.DUMMYFUNCTION("""COMPUTED_VALUE"""),"LRM273") -> LRM273 | I18: =IFERROR(__xludf.DUMMYFUNCTION("""COMPUTED_VALUE"""),"A") -> A | J18: =IFERROR(__xludf.DUMMYFUNCTION("""COMPUTED_VALUE"""),"Ainhoa Leceta Sáez de Cámara") -> Ainhoa Leceta Sáez de Cámara | L18: =H18 -> LRM273 | M18: =G18 -> LRM
F19: =IFERROR(__xludf.DUMMYFUNCTION("""COMPUTED_VALUE"""),"Luis Alberto Rodríguez") -> Luis Alberto Rodríguez | G19: =IFERROR(__xludf.DUMMYFUNCTION("""COMPUTED_VALUE"""),"LAA") -> LAA | H19: =IFERROR(__xludf.DUMMYFUNCTION("""COMPUTED_VALUE"""),"LAA89") -> LAA89 | I19: =IFERROR(__xludf.DUMMYFUNCTION("""COMPUTED_VALUE"""),"C") -> C | J19: =IFERROR(__xludf.DUMMYFUNCTION("""COMPUTED_VALUE"""),"Agustín Alcalá Fernández") -> Agustín Alcalá Fernández | L19: =H19 -> LAA89 | M19: =G19 -> LAA
F20: =IFERROR(__xludf.DUMMYFUNCTION("""COMPUTED_VALUE"""),"Maika Blázquez") -> Maika Blázquez | G20: =IFERROR(__xludf.DUMMYFUNCTION("""COMPUTED_VALUE"""),"MBM") -> MBM | H20: =IFERROR(__xludf.DUMMYFUNCTION("""COMPUTED_VALUE"""),"MBM187") -> MBM187 | I20: =IFERROR(__xludf.DUMMYFUNCTION("""COMPUTED_VALUE"""),"A") -> A | J20: =IFERROR(__xludf.DUMMYFUNCTION("""COMPUTED_VALUE"""),"Abel Bogoya Castaño") -> Abel Bogoya Castaño | L20: =H20 -> MBM187 | M20: =G20 -> MBM
F21: =IFERROR(__xludf.DUMMYFUNCTION("""COMPUTED_VALUE"""),"Ramon Ferrando") -> Ramon Ferrando | G21: =IFERROR(__xludf.DUMMYFUNCTION("""COMPUTED_VALUE"""),"RFV") -> RFV | H21: =IFERROR(__xludf.DUMMYFUNCTION("""COMPUTED_VALUE"""),"RFV08") -> RFV08 | I21: =IFERROR(__xludf.DUMMYFUNCTION("""COMPUTED_VALUE"""),"B") -> B | J21: =IFERROR(__xludf.DUMMYFUNCTION("""COMPUTED_VALUE"""),"Abel Guzmán Calvete") -> Abel Guzmán Calvete | L21: =H21 -> RFV08 | M21: =G21 -> RFV
F22: =IFERROR(__xludf.DUMMYFUNCTION("""COMPUTED_VALUE"""),"Maika Blázquez") -> Maika Blázquez | G22: =IFERROR(__xludf.DUMMYFUNCTION("""COMPUTED_VALUE"""),"MBM") -> MBM | H22: =IFERROR(__xludf.DUMMYFUNCTION("""COMPUTED_VALUE"""),"MBM86") -> MBM86 | I22: =IFERROR(__xludf.DUMMYFUNCTION("""COMPUTED_VALUE"""),"A") -> A | J22: =IFERROR(__xludf.DUMMYFUNCTION("""COMPUTED_VALUE"""),"Adela Cordero Devesa") -> Adela Cordero Devesa | L22: =H22 -> MBM86 | M22: =G22 -> MBM
F23: =IFERROR(__xludf.DUMMYFUNCTION("""COMPUTED_VALUE"""),"Roberto Pereira") -> Roberto Pereira | G23: =IFERROR(__xludf.DUMMYFUNCTION("""COMPUTED_VALUE"""),"RPG") -> RPG | H23: =IFERROR(__xludf.DUMMYFUNCTION("""COMPUTED_VALUE"""),"RPG33") -> RPG33 | I23: =IFERROR(__xludf.DUMMYFUNCTION("""COMPUTED_VALUE"""),"A") -> A | J23: =IFERROR(__xludf.DUMMYFUNCTION("""COMPUTED_VALUE"""),"Adela Pérez-Caro Ríos") -> Adela Pérez-Caro Ríos | L23: =H23 -> RPG33 | M23: =G23 -> RPG
F24: =IFERROR(__xludf.DUMMYFUNCTION("""COMPUTED_VALUE"""),"Lisandro Russian") -> Lisandro Russian | G24: =IFERROR(__xludf.DUMMYFUNCTION("""COMPUTED_VALUE"""),"LRM") -> LRM | H24: =IFERROR(__xludf.DUMMYFUNCTION("""COMPUTED_VALUE"""),"LRM01") -> LRM01 | I24: =IFERROR(__xludf.DUMMYFUNCTION("""COMPUTED_VALUE"""),"A") -> A | J24: =IFERROR(__xludf.DUMMYFUNCTION("""COMPUTED_VALUE"""),"Adolfo Carlos Hinojar Gutierrez") -> Adolfo Carlos Hinojar Gutierrez | L24: =H24 -> LRM01 | M24: =G24 -> LRM
F25: =IFERROR(__xludf.DUMMYFUNCTION("""COMPUTED_VALUE"""),"Alberto Moreno") -> Alberto Moreno | G25: =IFERROR(__xludf.DUMMYFUNCTION("""COMPUTED_VALUE"""),"AMM") -> AMM | H25: =IFERROR(__xludf.DUMMYFUNCTION("""COMPUTED_VALUE"""),"AMM01") -> AMM01 | I25: =IFERROR(__xludf.DUMMYFUNCTION("""COMPUTED_VALUE"""),"A") -> A | J25: =IFERROR(__xludf.DUMMYFUNCTION("""COMPUTED_VALUE"""),"Adolfo del Valle Zapico") -> Adolfo del Valle Zapico | L25: =H25 -> AMM01 | M25: =G25 -> AMM
F26: =IFERROR(__xludf.DUMMYFUNCTION("""COMPUTED_VALUE"""),"Maika Blázquez") -> Maika Blázquez | G26: =IFERROR(__xludf.DUMMYFUNCTION("""COMPUTED_VALUE"""),"MBM") -> MBM | H26: =IFERROR(__xludf.DUMMYFUNCTION("""COMPUTED_VALUE"""),"MBM01") -> MBM01 | I26: =IFERROR(__xludf.DUMMYFUNCTION("""COMPUTED_VALUE"""),"A") -> A | J26: =IFERROR(__xludf.DUMMYFUNCTION("""COMPUTED_VALUE"""),"Adolfo Toledano Muñoz") -> Adolfo Toledano Muñoz | L26: =H26 -> MBM01 | M26: =G26 -> MBM
F27: =IFERROR(__xludf.DUMMYFUNCTION("""COMPUTED_VALUE"""),"Lisandro Russian") -> Lisandro Russian | G27: =IFERROR(__xludf.DUMMYFUNCTION("""COMPUTED_VALUE"""),"LRM") -> LRM | H27: =IFERROR(__xludf.DUMMYFUNCTION("""COMPUTED_VALUE"""),"LRM123") -> LRM123 | I27: =IFERROR(__xludf.DUMMYFUNCTION("""COMPUTED_VALUE"""),"A") -> A | J27: =IFERROR(__xludf.DUMMYFUNCTION("""COMPUTED_VALUE"""),"Adriana Pardo Maza") -> Adriana Pardo Maza | L27: =H27 -> LRM123 | M27: =G27 -> LRM
F28: =IFERROR(__xludf.DUMMYFUNCTION("""COMPUTED_VALUE"""),"Maika Blázquez") -> Maika Blázquez | G28: =IFERROR(__xludf.DUMMYFUNCTION("""COMPUTED_VALUE"""),"MBM") -> MBM | H28: =IFERROR(__xludf.DUMMYFUNCTION("""COMPUTED_VALUE"""),"MBM87") -> MBM87 | I28: =IFERROR(__xludf.DUMMYFUNCTION("""COMPUTED_VALUE"""),"A") -> A | J28: =IFERROR(__xludf.DUMMYFUNCTION("""COMPUTED_VALUE"""),"Adriana Pérez García") -> Adriana Pérez García | L28: =H28 -> MBM87 | M28: =G28 -> MBM
F29: =IFERROR(__xludf.DUMMYFUNCTION("""COMPUTED_VALUE"""),"Iván Sánchez") -> Iván Sánchez | G29: =IFERROR(__xludf.DUMMYFUNCTION("""COMPUTED_VALUE"""),"ISL") -> ISL | H29: =IFERROR(__xludf.DUMMYFUNCTION("""COMPUTED_VALUE"""),"ISL82") -> ISL82 | I29: =IFERROR(__xludf.DUMMYFUNCTION("""COMPUTED_VALUE"""),"B") -> B | J29: =IFERROR(__xludf.DUMMYFUNCTION("""COMPUTED_VALUE"""),"Africa Jiménez de la Rosa") -> Africa Jiménez de la Rosa | L29: =H29 -> ISL82 | M29: =G29 -> ISL
F30: =IFERROR(__xludf.DUMMYFUNCTION("""COMPUTED_VALUE"""),"Ramon Ferrando") -> Ramon Ferrando | G30: =IFERROR(__xludf.DUMMYFUNCTION("""COMPUTED_VALUE"""),"RFV") -> RFV | H30: =IFERROR(__xludf.DUMMYFUNCTION("""COMPUTED_VALUE"""),"RFV09") -> RFV09 | I30: =IFERROR(__xludf.DUMMYFUNCTION("""COMPUTED_VALUE"""),"B") -> B | J30: =IFERROR(__xludf.DUMMYFUNCTION("""COMPUTED_VALUE"""),"Agustín Campos Catalá") -> Agustín Campos Catalá | L30: =H30 -> RFV09 | M30: =G30 -> RFV
F31: =IFERROR(__xludf.DUMMYFUNCTION("""COMPUTED_VALUE"""),"Maika Blázquez") -> Maika Blázquez | G31: =IFERROR(__xludf.DUMMYFUNCTION("""COMPUTED_VALUE"""),"MBM") -> MBM | H31: =IFERROR(__xludf.DUMMYFUNCTION("""COMPUTED_VALUE"""),"MBM205") -> MBM205 | I31: =IFERROR(__xludf.DUMMYFUNCTION("""COMPUTED_VALUE"""),"A") -> A | J31: =IFERROR(__xludf.DUMMYFUNCTION("""COMPUTED_VALUE"""),"Agustina Nicole Arbia Kalutich") -> Agustina Nicole Arbia Kalutich | L31: =H31 -> MBM205 | M31: =G31 -> MBM
F32: =IFERROR(__xludf.DUMMYFUNCTION("""COMPUTED_VALUE"""),"Iván Sánchez") -> Iván Sánchez | G32: =IFERROR(__xludf.DUMMYFUNCTION("""COMPUTED_VALUE"""),"ISL") -> ISL | H32: =IFERROR(__xludf.DUMMYFUNCTION("""COMPUTED_VALUE"""),"ISL83") -> ISL83 | I32: =IFERROR(__xludf.DUMMYFUNCTION("""COMPUTED_VALUE"""),"B") -> B | J32: =IFERROR(__xludf.DUMMYFUNCTION("""COMPUTED_VALUE"""),"Aida Aviñoa Arias") -> Aida Aviñoa Arias | L32: =H32 -> ISL83 | M32: =G32 -> ISL
F33: =IFERROR(__xludf.DUMMYFUNCTION("""COMPUTED_VALUE"""),"Mercè Cabrera") -> Mercè Cabrera | G33: =IFERROR(__xludf.DUMMYFUNCTION("""COMPUTED_VALUE"""),"MCC") -> MCC | H33: =IFERROR(__xludf.DUMMYFUNCTION("""COMPUTED_VALUE"""),"MCC35") -> MCC35 | I33: =IFERROR(__xludf.DUMMYFUNCTION("""COMPUTED_VALUE"""),"A") -> A | J33: =IFERROR(__xludf.DUMMYFUNCTION("""COMPUTED_VALUE"""),"Aina Brunet García") -> Aina Brunet García | L33: =H33 -> MCC35 | M33: =G33 -> MCC
F34: =IFERROR(__xludf.DUMMYFUNCTION("""COMPUTED_VALUE"""),"Lisandro Russian") -> Lisandro Russian | G34: =IFERROR(__xludf.DUMMYFUNCTION("""COMPUTED_VALUE"""),"LRM") -> LRM | H34: =IFERROR(__xludf.DUMMYFUNCTION("""COMPUTED_VALUE"""),"LRM124") -> LRM124 | I34: =IFERROR(__xludf.DUMMYFUNCTION("""COMPUTED_VALUE"""),"A") -> A | J34: =IFERROR(__xludf.DUMMYFUNCTION("""COMPUTED_VALUE"""),"Ainhoa Beato Martínez") -> Ainhoa Beato Martínez | L34: =H34 -> LRM124 | M34: =G34 -> LRM
F35: =IFERROR(__xludf.DUMMYFUNCTION("""COMPUTED_VALUE"""),"Ramon Ferrando") -> Ramon Ferrando | G35: =IFERROR(__xludf.DUMMYFUNCTION("""COMPUTED_VALUE"""),"RFV") -> RFV | H35: =IFERROR(__xludf.DUMMYFUNCTION("""COMPUTED_VALUE"""),"RFV26") -> RFV26 | I35: =IFERROR(__xludf.DUMMYFUNCTION("""COMPUTED_VALUE"""),"B") -> B | J35: =IFERROR(__xludf.DUMMYFUNCTION("""COMPUTED_VALUE"""),"Ainhoa García-Lliberos de Miguel") -> Ainhoa García-Lliberos de Miguel | L35: =H35 -> RFV26 | M35: =G35 -> RFV
F36: =IFERROR(__xludf.DUMMYFUNCTION("""COMPUTED_VALUE"""),"Lisandro Russian") -> Lisandro Russian | G36: =IFERROR(__xludf.DUMMYFUNCTION("""COMPUTED_VALUE"""),"LRM") -> LRM | H36: =IFERROR(__xludf.DUMMYFUNCTION("""COMPUTED_VALUE"""),"LRM125") -> LRM125 | I36: =IFERROR(__xludf.DUMMYFUNCTION("""COMPUTED_VALUE"""),"A") -> A | J36: =IFERROR(__xludf.DUMMYFUNCTION("""COMPUTED_VALUE"""),"Ainhoa Moreno Bravo") -> Ainhoa Moreno Bravo | L36: =H36 -> LRM125 | M36: =G36 -> LRM
F37: =IFERROR(__xludf.DUMMYFUNCTION("""COMPUTED_VALUE"""),"Roberto Pereira") -> Roberto Pereira | G37: =IFERROR(__xludf.DUMMYFUNCTION("""COMPUTED_VALUE"""),"RPG") -> RPG | H37: =IFERROR(__xludf.DUMMYFUNCTION("""COMPUTED_VALUE"""),"RPG34") -> RPG34 | I37: =IFERROR(__xludf.DUMMYFUNCTION("""COMPUTED_VALUE"""),"A") -> A | J37: =IFERROR(__xludf.DUMMYFUNCTION("""COMPUTED_VALUE"""),"Alba Carrero González") -> Alba Carrero González | L37: =H37 -> RPG34 | M37: =G37 -> RPG
F38: =IFERROR(__xludf.DUMMYFUNCTION("""COMPUTED_VALUE"""),"Maika Blázquez") -> Maika Blázquez | G38: =IFERROR(__xludf.DUMMYFUNCTION("""COMPUTED_VALUE"""),"MBM") -> MBM | H38: =IFERROR(__xludf.DUMMYFUNCTION("""COMPUTED_VALUE"""),"MBM88") -> MBM88 | I38: =IFERROR(__xludf.DUMMYFUNCTION("""COMPUTED_VALUE"""),"A") -> A | J38: =IFERROR(__xludf.DUMMYFUNCTION("""COMPUTED_VALUE"""),"Alba Domínguez Palos") -> Alba Domínguez Palos | L38: =H38 -> MBM88 | M38: =G38 -> MBM
F39: =IFERROR(__xludf.DUMMYFUNCTION("""COMPUTED_VALUE"""),"Iván Sánchez") -> Iván Sánchez | G39: =IFERROR(__xludf.DUMMYFUNCTION("""COMPUTED_VALUE"""),"ISL") -> ISL | H39: =IFERROR(__xludf.DUMMYFUNCTION("""COMPUTED_VALUE"""),"ISL84") -> ISL84 | I39: =IFERROR(__xludf.DUMMYFUNCTION("""COMPUTED_VALUE"""),"B") -> B | J39: =IFERROR(__xludf.DUMMYFUNCTION("""COMPUTED_VALUE"""),"Alba Molina Moreno") -> Alba Molina Moreno | L39: =H39 -> ISL84 | M39: =G39 -> ISL
F40: =IFERROR(__xludf.DUMMYFUNCTION("""COMPUTED_VALUE"""),"Mercè Cabrera") -> Mercè Cabrera | G40: =IFERROR(__xludf.DUMMYFUNCTION("""COMPUTED_VALUE"""),"MCC") -> MCC | H40: =IFERROR(__xludf.DUMMYFUNCTION("""COMPUTED_VALUE"""),"MCC01") -> MCC01 | I40: =IFERROR(__xludf.DUMMYFUNCTION("""COMPUTED_VALUE"""),"A") -> A | J40: =IFERROR(__xludf.DUMMYFUNCTION("""COMPUTED_VALUE"""),"Albert Llansana Ríos") -> Albert Llansana Ríos | L40: =H40 -> MCC01 | M40: =G40 -> MCC
F41: =IFERROR(__xludf.DUMMYFUNCTION("""COMPUTED_VALUE"""),"Mercè Cabrera") -> Mercè Cabrera | G41: =IFERROR(__xludf.DUMMYFUNCTION("""COMPUTED_VALUE"""),"MCC") -> MCC | H41: =IFERROR(__xludf.DUMMYFUNCTION("""COMPUTED_VALUE"""),"MCC76") -> MCC76 | I41: =IFERROR(__xludf.DUMMYFUNCTION("""COMPUTED_VALUE"""),"A") -> A | J41: =IFERROR(__xludf.DUMMYFUNCTION("""COMPUTED_VALUE"""),"Albert Pla Esperanzi") -> Albert Pla Esperanzi | L41: =H41 -> MCC76 | M41: =G41 -> MCC
F42: =IFERROR(__xludf.DUMMYFUNCTION("""COMPUTED_VALUE"""),"Lisandro Russian") -> Lisandro Russian | G42: =IFERROR(__xludf.DUMMYFUNCTION("""COMPUTED_VALUE"""),"LRM") -> LRM | H42: =IFERROR(__xludf.DUMMYFUNCTION("""COMPUTED_VALUE"""),"LRM02") -> LRM02 | I42: =IFERROR(__xludf.DUMMYFUNCTION("""COMPUTED_VALUE"""),"A") -> A | J42: =IFERROR(__xludf.DUMMYFUNCTION("""COMPUTED_VALUE"""),"Alberto García Guzmán") -> Alberto García Guzmán | L42: =H42 -> LRM02 | M42: =G42 -> LRM
F43: =IFERROR(__xludf.DUMMYFUNCTION("""COMPUTED_VALUE"""),"Iván Sánchez") -> Iván Sánchez | G43: =IFERROR(__xludf.DUMMYFUNCTION("""COMPUTED_VALUE"""),"ISL") -> ISL | H43: =IFERROR(__xludf.DUMMYFUNCTION("""COMPUTED_VALUE"""),"ISL152") -> ISL152 | I43: =IFERROR(__xludf.DUMMYFUNCTION("""COMPUTED_VALUE"""),"B") -> B | J43: =IFERROR(__xludf.DUMMYFUNCTION("""COMPUTED_VALUE"""),"Alberto Guillén Martínez") -> Alberto Guillén Martínez | L43: =H43 -> ISL152 | M43: =G43 -> ISL
F44: =IFERROR(__xludf.DUMMYFUNCTION("""COMPUTED_VALUE"""),"Iván Sánchez") -> Iván Sánchez | G44: =IFERROR(__xludf.DUMMYFUNCTION("""COMPUTED_VALUE"""),"ISL") -> ISL | H44: =IFERROR(__xludf.DUMMYFUNCTION("""COMPUTED_VALUE"""),"ISL01") -> ISL01 | I44: =IFERROR(__xludf.DUMMYFUNCTION("""COMPUTED_VALUE"""),"B") -> B | J44: =IFERROR(__xludf.DUMMYFUNCTION("""COMPUTED_VALUE"""),"Alberto Raposo Jiménez") -> Alberto Raposo Jiménez | L44: =H44 -> ISL01 | M44: =G44 -> ISL
F45: =IFERROR(__xludf.DUMMYFUNCTION("""COMPUTED_VALUE"""),"Maika Blázquez") -> Maika Blázquez | G45: =IFERROR(__xludf.DUMMYFUNCTION("""COMPUTED_VALUE"""),"MBM") -> MBM | H45: =IFERROR(__xludf.DUMMYFUNCTION("""COMPUTED_VALUE"""),"MBM02") -> MBM02 | I45: =IFERROR(__xludf.DUMMYFUNCTION("""COMPUTED_VALUE"""),"A") -> A | J45: =IFERROR(__xludf.DUMMYFUNCTION("""COMPUTED_VALUE"""),"Alberto Tauste Gómez") -> Alberto Tauste Gómez | L45: =H45 -> MBM02 | M45: =G45 -> MBM
F46: =IFERROR(__xludf.DUMMYFUNCTION("""COMPUTED_VALUE"""),"Lisandro Russian") -> Lisandro Russian | G46: =IFERROR(__xludf.DUMMYFUNCTION("""COMPUTED_VALUE"""),"LRM") -> LRM | H46: =IFERROR(__xludf.DUMMYFUNCTION("""COMPUTED_VALUE"""),"LRM126") -> LRM126 | I46: =IFERROR(__xludf.DUMMYFUNCTION("""COMPUTED_VALUE"""),"A") -> A | J46: =IFERROR(__xludf.DUMMYFUNCTION("""COMPUTED_VALUE"""),"Alejandra Aguirre Figueroa") -> Alejandra Aguirre Figueroa | L46: =H46 -> LRM126 | M46: =G46 -> LRM
F47: =IFERROR(__xludf.DUMMYFUNCTION("""COMPUTED_VALUE"""),"Iván Sánchez") -> Iván Sánchez | G47: =IFERROR(__xludf.DUMMYFUNCTION("""COMPUTED_VALUE"""),"ISL") -> ISL | H47: =IFERROR(__xludf.DUMMYFUNCTION("""COMPUTED_VALUE"""),"ISL150") -> ISL150 | I47: =IFERROR(__xludf.DUMMYFUNCTION("""COMPUTED_VALUE"""),"B") -> B | J47: =IFERROR(__xludf.DUMMYFUNCTION("""COMPUTED_VALUE"""),"Alejandra Alvarado Namen") -> Alejandra Alvarado Namen | L47: =H47 -> ISL150 | M47: =G47 -> ISL
F48: =IFERROR(__xludf.DUMMYFUNCTION("""COMPUTED_VALUE"""),"Maika Blázquez") -> Maika Blázquez | G48: =IFERROR(__xludf.DUMMYFUNCTION("""COMPUTED_VALUE"""),"MBM") -> MBM | H48: =IFERROR(__xludf.DUMMYFUNCTION("""COMPUTED_VALUE"""),"MBM89") -> MBM89 | I48: =IFERROR(__xludf.DUMMYFUNCTION("""COMPUTED_VALUE"""),"A") -> A | J48: =IFERROR(__xludf.DUMMYFUNCTION("""COMPUTED_VALUE"""),"Alejandra Carrasco Gómez") -> Alejandra Carrasco Gómez | L48: =H48 -> MBM89 | M48: =G48 -> MBM
F49: =IFERROR(__xludf.DUMMYFUNCTION("""COMPUTED_VALUE"""),"Iván Sánchez") -> Iván Sánchez | G49: =IFERROR(__xludf.DUMMYFUNCTION("""COMPUTED_VALUE"""),"ISL") -> ISL | H49: =IFERROR(__xludf.DUMMYFUNCTION("""COMPUTED_VALUE"""),"ISL91") -> ISL91 | I49: =IFERROR(__xludf.DUMMYFUNCTION("""COMPUTED_VALUE"""),"B") -> B | J49: =IFERROR(__xludf.DUMMYFUNCTION("""COMPUTED_VALUE"""),"Alejandra Jara Maquilón") -> Alejandra Jara Maquilón | L49: =H49 -> ISL91 | M49: =G49 -> ISL
F50: =IFERROR(__xludf.DUMMYFUNCTION("""COMPUTED_VALUE"""),"Iván Sánchez") -> Iván Sánchez | G50: =IFERROR(__xludf.DUMMYFUNCTION("""COMPUTED_VALUE"""),"ISL") -> ISL | H50: =IFERROR(__xludf.DUMMYFUNCTION("""COMPUTED_VALUE"""),"ISL86") -> ISL86 | I50: =IFERROR(__xludf.DUMMYFUNCTION("""COMPUTED_VALUE"""),"B") -> B | J50: =IFERROR(__xludf.DUMMYFUNCTION("""COMPUTED_VALUE"""),"Alejandra Pérez Ferrando") -> Alejandra Pérez Ferrando | L50: =H50 -> ISL86 | M50: =G50 -> ISL
F51: =IFERROR(__xludf.DUMMYFUNCTION("""COMPUTED_VALUE"""),"Roberto Pereira") -> Roberto Pereira | G51: =IFERROR(__xludf.DUMMYFUNCTION("""COMPUTED_VALUE"""),"RPG") -> RPG | H51: =IFERROR(__xludf.DUMMYFUNCTION("""COMPUTED_VALUE"""),"RPG01") -> RPG01 | I51: =IFERROR(__xludf.DUMMYFUNCTION("""COMPUTED_VALUE"""),"A") -> A | J51: =IFERROR(__xludf.DUMMYFUNCTION("""COMPUTED_VALUE"""),"Alejandro Díaz Uña") -> Alejandro Díaz Uña | L51: =H51 -> RPG01 | M51: =G51 -> RPG
F52: =IFERROR(__xludf.DUMMYFUNCTION("""COMPUTED_VALUE"""),"Maika Blázquez") -> Maika Blázquez | G52: =IFERROR(__xludf.DUMMYFUNCTION("""COMPUTED_VALUE"""),"MBM") -> MBM | H52: =IFERROR(__xludf.DUMMYFUNCTION("""COMPUTED_VALUE"""),"MBM03") -> MBM03 | I52: =IFERROR(__xludf.DUMMYFUNCTION("""COMPUTED_VALUE"""),"A") -> A | J52: =IFERROR(__xludf.DUMMYFUNCTION("""COMPUTED_VALUE"""),"Alejandro Harguindey Antoli-Candela") -> Alejandro Harguindey Antoli-Candela | L52: =H52 -> MBM03 | M52: =G52 -> MBM
F53: =IFERROR(__xludf.DUMMYFUNCTION("""COMPUTED_VALUE"""),"Lisandro Russian") -> Lisandro Russian | G53: =IFERROR(__xludf.DUMMYFUNCTION("""COMPUTED_VALUE"""),"LRM") -> LRM | H53: =IFERROR(__xludf.DUMMYFUNCTION("""COMPUTED_VALUE"""),"LRM03") -> LRM03 | I53: =IFERROR(__xludf.DUMMYFUNCTION("""COMPUTED_VALUE"""),"A") -> A | J53: =IFERROR(__xludf.DUMMYFUNCTION("""COMPUTED_VALUE"""),"Alejandro Martínez Morán") -> Alejandro Martínez Morán | L53: =H53 -> LRM03 | M53: =G53 -> LRM
F54: =IFERROR(__xludf.DUMMYFUNCTION("""COMPUTED_VALUE"""),"Lisandro Russian") -> Lisandro Russian | G54: =IFERROR(__xludf.DUMMYFUNCTION("""COMPUTED_VALUE"""),"LRM") -> LRM | H54: =IFERROR(__xludf.DUMMYFUNCTION("""COMPUTED_VALUE"""),"LRM04") -> LRM04 | I54: =IFERROR(__xludf.DUMMYFUNCTION("""COMPUTED_VALUE"""),"A") -> A | J54: =IFERROR(__xludf.DUMMYFUNCTION("""COMPUTED_VALUE"""),"Alejandro Tejero-Garcés Monclús") -> Alejandro Tejero-Garcés Monclús | L54: =H54 -> LRM04 | M54: =G54 -> LRM
F55: =IFERROR(__xludf.DUMMYFUNCTION("""COMPUTED_VALUE"""),"Mercè Cabrera") -> Mercè Cabrera | G55: =IFERROR(__xludf.DUMMYFUNCTION("""COMPUTED_VALUE"""),"MCC") -> MCC | H55: =IFERROR(__xludf.DUMMYFUNCTION("""COMPUTED_VALUE"""),"MCC02") -> MCC02 | I55: =IFERROR(__xludf.DUMMYFUNCTION("""COMPUTED_VALUE"""),"A") -> A | J55: =IFERROR(__xludf.DUMMYFUNCTION("""COMPUTED_VALUE"""),"Alex Portillo Medina") -> Alex Portillo Medina | L55: =H55 -> MCC02 | M55: =G55 -> MCC
F56: =IFERROR(__xludf.DUMMYFUNCTION("""COMPUTED_VALUE"""),"Maika Blázquez") -> Maika Blázquez | G56: =IFERROR(__xludf.DUMMYFUNCTION("""COMPUTED_VALUE"""),"MBM") -> MBM | H56: =IFERROR(__xludf.DUMMYFUNCTION("""COMPUTED_VALUE"""),"MBM04") -> MBM04 | I56: =IFERROR(__xludf.DUMMYFUNCTION("""COMPUTED_VALUE"""),"A") -> A | J56: =IFERROR(__xludf.DUMMYFUNCTION("""COMPUTED_VALUE"""),"Àlex Ramírez Rosa") -> Àlex Ramírez Rosa | L56: =H56 -> MBM04 | M56: =G56 -> MBM
F57: =IFERROR(__xludf.DUMMYFUNCTION("""COMPUTED_VALUE"""),"Iván Sánchez") -> Iván Sánchez | G57: =IFERROR(__xludf.DUMMYFUNCTION("""COMPUTED_VALUE"""),"ISL") -> ISL | H57: =IFERROR(__xludf.DUMMYFUNCTION("""COMPUTED_VALUE"""),"ISL02") -> ISL02 | I57: =IFERROR(__xludf.DUMMYFUNCTION("""COMPUTED_VALUE"""),"B") -> B | J57: =IFERROR(__xludf.DUMMYFUNCTION("""COMPUTED_VALUE"""),"Alfonso Aracil Montesinos") -> Alfonso Aracil Montesinos | L57: =H57 -> ISL02 | M57: =G57 -> ISL
F58: =IFERROR(__xludf.DUMMYFUNCTION("""COMPUTED_VALUE"""),"Lisandro Russian") -> Lisandro Russian | G58: =IFERROR(__xludf.DUMMYFUNCTION("""COMPUTED_VALUE"""),"LRM") -> LRM | H58: =IFERROR(__xludf.DUMMYFUNCTION("""COMPUTED_VALUE"""),"LRM05") -> LRM05 | I58: =IFERROR(__xludf.DUMMYFUNCTION("""COMPUTED_VALUE"""),"A") -> A | J58: =IFERROR(__xludf.DUMMYFUNCTION("""COMPUTED_VALUE"""),"Alfonso Campos González") -> Alfonso Campos González | L58: =H58 -> LRM05 | M58: =G58 -> LRM
F59: =IFERROR(__xludf.DUMMYFUNCTION("""COMPUTED_VALUE"""),"Iván Sánchez") -> Iván Sánchez | G59: =IFERROR(__xludf.DUMMYFUNCTION("""COMPUTED_VALUE"""),"ISL") -> ISL | H59: =IFERROR(__xludf.DUMMYFUNCTION("""COMPUTED_VALUE"""),"ISL03") -> ISL03 | I59: =IFERROR(__xludf.DUMMYFUNCTION("""COMPUTED_VALUE"""),"B") -> B | J59: =IFERROR(__xludf.DUMMYFUNCTION("""COMPUTED_VALUE"""),"Alfonso Capitan Guarnizo") -> Alfonso Capitan Guarnizo | L59: =H59 -> ISL03 | M59: =G59 -> ISL
F60: =IFERROR(__xludf.DUMMYFUNCTION("""COMPUTED_VALUE"""),"Iván Sánchez") -> Iván Sánchez | G60: =IFERROR(__xludf.DUMMYFUNCTION("""COMPUTED_VALUE"""),"ISL") -> ISL | H60: =IFERROR(__xludf.DUMMYFUNCTION("""COMPUTED_VALUE"""),"ISL04") -> ISL04 | I60: =IFERROR(__xludf.DUMMYFUNCTION("""COMPUTED_VALUE"""),"B") -> B | J60: =IFERROR(__xludf.DUMMYFUNCTION("""COMPUTED_VALUE"""),"Alfonso García Piñero") -> Alfonso García Piñero | L60: =H60 -> ISL04 | M60: =G60 -> ISL
F61: =IFERROR(__xludf.DUMMYFUNCTION("""COMPUTED_VALUE"""),"Iván Sánchez") -> Iván Sánchez | G61: =IFERROR(__xludf.DUMMYFUNCTION("""COMPUTED_VALUE"""),"ISL") -> ISL | H61: =IFERROR(__xludf.DUMMYFUNCTION("""COMPUTED_VALUE"""),"ISL05") -> ISL05 | I61: =IFERROR(__xludf.DUMMYFUNCTION("""COMPUTED_VALUE"""),"B") -> B | J61: =IFERROR(__xludf.DUMMYFUNCTION("""COMPUTED_VALUE"""),"Alfonso Marco Garrido") -> Alfonso Marco Garrido | L61: =H61 -> ISL05 | M61: =G61 -> ISL
F62: =IFERROR(__xludf.DUMMYFUNCTION("""COMPUTED_VALUE"""),"Luis Alberto Rodríguez") -> Luis Alberto Rodríguez | G62: =IFERROR(__xludf.DUMMYFUNCTION("""COMPUTED_VALUE"""),"LAA") -> LAA | H62: =IFERROR(__xludf.DUMMYFUNCTION("""COMPUTED_VALUE"""),"LAA83") -> LAA83 | I62: =IFERROR(__xludf.DUMMYFUNCTION("""COMPUTED_VALUE"""),"C") -> C | J62: =IFERROR(__xludf.DUMMYFUNCTION("""COMPUTED_VALUE"""),"Alfonso María Pérez Sánchez") -> Alfonso María Pérez Sánchez | L62: =H62 -> LAA83 | M62: =G62 -> LAA
F63: =IFERROR(__xludf.DUMMYFUNCTION("""COMPUTED_VALUE"""),"Lisandro Russian") -> Lisandro Russian | G63: =IFERROR(__xludf.DUMMYFUNCTION("""COMPUTED_VALUE"""),"LRM") -> LRM | H63: =IFERROR(__xludf.DUMMYFUNCTION("""COMPUTED_VALUE"""),"LRM06") -> LRM06 | I63: =IFERROR(__xludf.DUMMYFUNCTION("""COMPUTED_VALUE"""),"A") -> A | J63: =IFERROR(__xludf.DUMMYFUNCTION("""COMPUTED_VALUE"""),"Alfonso Plaza López") -> Alfonso Plaza López | L63: =H63 -> LRM06 | M63: =G63 -> LRM
F64: =IFERROR(__xludf.DUMMYFUNCTION("""COMPUTED_VALUE"""),"Maika Blázquez") -> Maika Blázquez | G64: =IFERROR(__xludf.DUMMYFUNCTION("""COMPUTED_VALUE"""),"MBM") -> MBM | H64: =IFERROR(__xludf.DUMMYFUNCTION("""COMPUTED_VALUE"""),"MBM05") -> MBM05 | I64: =IFERROR(__xludf.DUMMYFUNCTION("""COMPUTED_VALUE"""),"A") -> A | J64: =IFERROR(__xludf.DUMMYFUNCTION("""COMPUTED_VALUE"""),"Alfonso Santamaría Gadea") -> Alfonso Santamaría Gadea | L64: =H64 -> MBM05 | M64: =G64 -> MBM
F65: =IFERROR(__xludf.DUMMYFUNCTION("""COMPUTED_VALUE"""),"Lisandro Russian") -> Lisandro Russian | G65: =IFERROR(__xludf.DUMMYFUNCTION("""COMPUTED_VALUE"""),"LRM") -> LRM | H65: =IFERROR(__xludf.DUMMYFUNCTION("""COMPUTED_VALUE"""),"LRM255") -> LRM255 | I65: =IFERROR(__xludf.DUMMYFUNCTION("""COMPUTED_VALUE"""),"A") -> A | J65: =IFERROR(__xludf.DUMMYFUNCTION("""COMPUTED_VALUE"""),"Alicia Gómez cabezas") -> Alicia Gómez cabezas | L65: =H65 -> LRM255 | M65: =G65 -> LRM
F66: =IFERROR(__xludf.DUMMYFUNCTION("""COMPUTED_VALUE"""),"Mercè Cabrera") -> Mercè Cabrera | G66: =IFERROR(__xludf.DUMMYFUNCTION("""COMPUTED_VALUE"""),"MCC") -> MCC | H66: =IFERROR(__xludf.DUMMYFUNCTION("""COMPUTED_VALUE"""),"MCC36") -> MCC36 | I66: =IFERROR(__xludf.DUMMYFUNCTION("""COMPUTED_VALUE"""),"A") -> A | J66: =IFERROR(__xludf.DUMMYFUNCTION("""COMPUTED_VALUE"""),"Alicia González Moreno") -> Alicia González Moreno | L66: =H66 -> MCC36 | M66: =G66 -> MCC
F67: =IFERROR(__xludf.DUMMYFUNCTION("""COMPUTED_VALUE"""),"Iván Sánchez") -> Iván Sánchez | G67: =IFERROR(__xludf.DUMMYFUNCTION("""COMPUTED_VALUE"""),"ISL") -> ISL | H67: =IFERROR(__xludf.DUMMYFUNCTION("""COMPUTED_VALUE"""),"ISL87") -> ISL87 | I67: =IFERROR(__xludf.DUMMYFUNCTION("""COMPUTED_VALUE"""),"B") -> B | J67: =IFERROR(__xludf.DUMMYFUNCTION("""COMPUTED_VALUE"""),"Alicia Mateo Espinosa") -> Alicia Mateo Espinosa | L67: =H67 -> ISL87 | M67: =G67 -> ISL
F68: =IFERROR(__xludf.DUMMYFUNCTION("""COMPUTED_VALUE"""),"Lisandro Russian") -> Lisandro Russian | G68: =IFERROR(__xludf.DUMMYFUNCTION("""COMPUTED_VALUE"""),"LRM") -> LRM | H68: =IFERROR(__xludf.DUMMYFUNCTION("""COMPUTED_VALUE"""),"LRM127") -> LRM127 | I68: =IFERROR(__xludf.DUMMYFUNCTION("""COMPUTED_VALUE"""),"C") -> C | J68: =IFERROR(__xludf.DUMMYFUNCTION("""COMPUTED_VALUE"""),"Alicia Suárez Calvo") -> Alicia Suárez Calvo | L68: =H68 -> LRM127 | M68: =G68 -> LRM
F69: =IFERROR(__xludf.DUMMYFUNCTION("""COMPUTED_VALUE"""),"Maika Blázquez") -> Maika Blázquez | G69: =IFERROR(__xludf.DUMMYFUNCTION("""COMPUTED_VALUE"""),"MBM") -> MBM | H69: =IFERROR(__xludf.DUMMYFUNCTION("""COMPUTED_VALUE"""),"MBM206") -> MBM206 | I69: =IFERROR(__xludf.DUMMYFUNCTION("""COMPUTED_VALUE"""),"A") -> A | J69: =IFERROR(__xludf.DUMMYFUNCTION("""COMPUTED_VALUE"""),"Alvaro Borque Sanz") -> Alvaro Borque Sanz | L69: =H69 -> MBM206 | M69: =G69 -> MBM
F70: =IFERROR(__xludf.DUMMYFUNCTION("""COMPUTED_VALUE"""),"Maika Blázquez") -> Maika Blázquez | G70: =IFERROR(__xludf.DUMMYFUNCTION("""COMPUTED_VALUE"""),"MBM") -> MBM | H70: =IFERROR(__xludf.DUMMYFUNCTION("""COMPUTED_VALUE"""),"MBM06") -> MBM06 | I70: =IFERROR(__xludf.DUMMYFUNCTION("""COMPUTED_VALUE"""),"A") -> A | J70: =IFERROR(__xludf.DUMMYFUNCTION("""COMPUTED_VALUE"""),"Álvaro Carrillo Sotos") -> Álvaro Carrillo Sotos | L70: =H70 -> MBM06 | M70: =G70 -> MBM
F71: =IFERROR(__xludf.DUMMYFUNCTION("""COMPUTED_VALUE"""),"Ramon Ferrando") -> Ramon Ferrando | G71: =IFERROR(__xludf.DUMMYFUNCTION("""COMPUTED_VALUE"""),"RFV") -> RFV | H71: =IFERROR(__xludf.DUMMYFUNCTION("""COMPUTED_VALUE"""),"RFV10") -> RFV10 | I71: =IFERROR(__xludf.DUMMYFUNCTION("""COMPUTED_VALUE"""),"B") -> B | J71: =IFERROR(__xludf.DUMMYFUNCTION("""COMPUTED_VALUE"""),"Álvaro Pérez Llinares") -> Álvaro Pérez Llinares | L71: =H71 -> RFV10 | M71: =G71 -> RFV
F72: =IFERROR(__xludf.DUMMYFUNCTION("""COMPUTED_VALUE"""),"Lisandro Russian") -> Lisandro Russian | G72: =IFERROR(__xludf.DUMMYFUNCTION("""COMPUTED_VALUE"""),"LRM") -> LRM | H72: =IFERROR(__xludf.DUMMYFUNCTION("""COMPUTED_VALUE"""),"LRM07") -> LRM07 | I72: =IFERROR(__xludf.DUMMYFUNCTION("""COMPUTED_VALUE"""),"A") -> A | J72: =IFERROR(__xludf.DUMMYFUNCTION("""COMPUTED_VALUE"""),"Álvaro Sánchez Álvarez") -> Álvaro Sánchez Álvarez | L72: =H72 -> LRM07 | M72: =G72 -> LRM
F73: =IFERROR(__xludf.DUMMYFUNCTION("""COMPUTED_VALUE"""),"Lisandro Russian") -> Lisandro Russian | G73: =IFERROR(__xludf.DUMMYFUNCTION("""COMPUTED_VALUE"""),"LRM") -> LRM | H73: =IFERROR(__xludf.DUMMYFUNCTION("""COMPUTED_VALUE"""),"LRM08") -> LRM08 | I73: =IFERROR(__xludf.DUMMYFUNCTION("""COMPUTED_VALUE"""),"A") -> A | J73: =IFERROR(__xludf.DUMMYFUNCTION("""COMPUTED_VALUE"""),"Álvaro Sánchez Barrueco") -> Álvaro Sánchez Barrueco | L73: =H73 -> LRM08 | M73: =G73 -> LRM
F74: =IFERROR(__xludf.DUMMYFUNCTION("""COMPUTED_VALUE"""),"Lisandro Russian") -> Lisandro Russian | G74: =IFERROR(__xludf.DUMMYFUNCTION("""COMPUTED_VALUE"""),"LRM") -> LRM | H74: =IFERROR(__xludf.DUMMYFUNCTION("""COMPUTED_VALUE"""),"LRM09") -> LRM09 | I74: =IFERROR(__xludf.DUMMYFUNCTION("""COMPUTED_VALUE"""),"A") -> A | J74: =IFERROR(__xludf.DUMMYFUNCTION("""COMPUTED_VALUE"""),"Álvaro Sánchez de Arriba") -> Álvaro Sánchez de Arriba | L74: =H74 -> LRM09 | M74: =G74 -> LRM
F75: =IFERROR(__xludf.DUMMYFUNCTION("""COMPUTED_VALUE"""),"Maika Blázquez") -> Maika Blázquez | G75: =IFERROR(__xludf.DUMMYFUNCTION("""COMPUTED_VALUE"""),"MBM") -> MBM | H75: =IFERROR(__xludf.DUMMYFUNCTION("""COMPUTED_VALUE"""),"MBM207") -> MBM207 | I75: =IFERROR(__xludf.DUMMYFUNCTION("""COMPUTED_VALUE"""),"A") -> A | J75: =IFERROR(__xludf.DUMMYFUNCTION("""COMPUTED_VALUE"""),"Amalia Fiestas Tartiere") -> Amalia Fiestas Tartiere | L75: =H75 -> MBM207 | M75: =G75 -> MBM
F76: =IFERROR(__xludf.DUMMYFUNCTION("""COMPUTED_VALUE"""),"Mercè Cabrera") -> Mercè Cabrera | G76: =IFERROR(__xludf.DUMMYFUNCTION("""COMPUTED_VALUE"""),"MCC") -> MCC | H76: =IFERROR(__xludf.DUMMYFUNCTION("""COMPUTED_VALUE"""),"MCC37") -> MCC37 | I76: =IFERROR(__xludf.DUMMYFUNCTION("""COMPUTED_VALUE"""),"A") -> A | J76: =IFERROR(__xludf.DUMMYFUNCTION("""COMPUTED_VALUE"""),"Amaya Lázaro Sánchez") -> Amaya Lázaro Sánchez | L76: =H76 -> MCC37 | M76: =G76 -> MCC
F77: =IFERROR(__xludf.DUMMYFUNCTION("""COMPUTED_VALUE"""),"Roberto Pereira") -> Roberto Pereira | G77: =IFERROR(__xludf.DUMMYFUNCTION("""COMPUTED_VALUE"""),"RPG") -> RPG | H77: =IFERROR(__xludf.DUMMYFUNCTION("""COMPUTED_VALUE"""),"RPG64") -> RPG64 | I77: =IFERROR(__xludf.DUMMYFUNCTION("""COMPUTED_VALUE"""),"A") -> A | J77: =IFERROR(__xludf.DUMMYFUNCTION("""COMPUTED_VALUE"""),"Amer Souki Chmeitt") -> Amer Souki Chmeitt | L77: =H77 -> RPG64 | M77: =G77 -> RPG
F78: =IFERROR(__xludf.DUMMYFUNCTION("""COMPUTED_VALUE"""),"Lisandro Russian") -> Lisandro Russian | G78: =IFERROR(__xludf.DUMMYFUNCTION("""COMPUTED_VALUE"""),"LRM") -> LRM | H78: =IFERROR(__xludf.DUMMYFUNCTION("""COMPUTED_VALUE"""),"LRM128") -> LRM128 | I78: =IFERROR(__xludf.DUMMYFUNCTION("""COMPUTED_VALUE"""),"A") -> A | J78: =IFERROR(__xludf.DUMMYFUNCTION("""COMPUTED_VALUE"""),"Amparo Castellote Armero") -> Amparo Castellote Armero | L78: =H78 -> LRM128 | M78: =G78 -> LRM
F79: =IFERROR(__xludf.DUMMYFUNCTION("""COMPUTED_VALUE"""),"Iván Sánchez") -> Iván Sánchez | G79: =IFERROR(__xludf.DUMMYFUNCTION("""COMPUTED_VALUE"""),"ISL") -> ISL | H79: =IFERROR(__xludf.DUMMYFUNCTION("""COMPUTED_VALUE"""),"ISL88") -> ISL88 | I79: =IFERROR(__xludf.DUMMYFUNCTION("""COMPUTED_VALUE"""),"B") -> B | J79: =IFERROR(__xludf.DUMMYFUNCTION("""COMPUTED_VALUE"""),"Amparo Roca Martínez") -> Amparo Roca Martínez | L79: =H79 -> ISL88 | M79: =G79 -> ISL
F80: =IFERROR(__xludf.DUMMYFUNCTION("""COMPUTED_VALUE"""),"Lisandro Russian") -> Lisandro Russian | G80: =IFERROR(__xludf.DUMMYFUNCTION("""COMPUTED_VALUE"""),"LRM") -> LRM | H80: =IFERROR(__xludf.DUMMYFUNCTION("""COMPUTED_VALUE"""),"LRM129") -> LRM129 | I80: =IFERROR(__xludf.DUMMYFUNCTION("""COMPUTED_VALUE"""),"A") -> A | J80: =IFERROR(__xludf.DUMMYFUNCTION("""COMPUTED_VALUE"""),"Ana Belén Herrero Egea") -> Ana Belén Herrero Egea | L80: =H80 -> LRM129 | M80: =G80 -> LRM
F81: =IFERROR(__xludf.DUMMYFUNCTION("""COMPUTED_VALUE"""),"Lisandro Russian") -> Lisandro Russian | G81: =IFERROR(__xludf.DUMMYFUNCTION("""COMPUTED_VALUE"""),"LRM") -> LRM | H81: =IFERROR(__xludf.DUMMYFUNCTION("""COMPUTED_VALUE"""),"LRM130") -> LRM130 | I81: =IFERROR(__xludf.DUMMYFUNCTION("""COMPUTED_VALUE"""),"A") -> A | J81: =IFERROR(__xludf.DUMMYFUNCTION("""COMPUTED_VALUE"""),"Ana Belén Rodríguez Vences") -> Ana Belén Rodríguez Vences | L81: =H81 -> LRM130 | M81: =G81 -> LRM
F82: =IFERROR(__xludf.DUMMYFUNCTION("""COMPUTED_VALUE"""),"Roberto Pereira") -> Roberto Pereira | G82: =IFERROR(__xludf.DUMMYFUNCTION("""COMPUTED_VALUE"""),"RPG") -> RPG | H82: =IFERROR(__xludf.DUMMYFUNCTION("""COMPUTED_VALUE"""),"RPG35") -> RPG35 | I82: =IFERROR(__xludf.DUMMYFUNCTION("""COMPUTED_VALUE"""),"A") -> A | J82: =IFERROR(__xludf.DUMMYFUNCTION("""COMPUTED_VALUE"""),"Ana Faraldo García") -> Ana Faraldo García | L82: =H82 -> RPG35 | M82: =G82 -> RPG
F83: =IFERROR(__xludf.DUMMYFUNCTION("""COMPUTED_VALUE"""),"Patricia Solache") -> Patricia Solache | G83: =IFERROR(__xludf.DUMMYFUNCTION("""COMPUTED_VALUE"""),"PSC") -> PSC | H83: =IFERROR(__xludf.DUMMYFUNCTION("""COMPUTED_VALUE"""),"PSC31") -> PSC31 | I83: =IFERROR(__xludf.DUMMYFUNCTION("""COMPUTED_VALUE"""),"A") -> A | J83: =IFERROR(__xludf.DUMMYFUNCTION("""COMPUTED_VALUE"""),"Ana Fernández Rodríguez") -> Ana Fernández Rodríguez | L83: =H83 -> PSC31 | M83: =G83 -> PSC
F84: =IFERROR(__xludf.DUMMYFUNCTION("""COMPUTED_VALUE"""),"Iván Sánchez") -> Iván Sánchez | G84: =IFERROR(__xludf.DUMMYFUNCTION("""COMPUTED_VALUE"""),"ISL") -> ISL | H84: =IFERROR(__xludf.DUMMYFUNCTION("""COMPUTED_VALUE"""),"ISL89") -> ISL89 | I84: =IFERROR(__xludf.DUMMYFUNCTION("""COMPUTED_VALUE"""),"B") -> B | J84: =IFERROR(__xludf.DUMMYFUNCTION("""COMPUTED_VALUE"""),"Ana Gabriela Jover Espla") -> Ana Gabriela Jover Espla | L84: =H84 -> ISL89 | M84: =G84 -> ISL
F85: =IFERROR(__xludf.DUMMYFUNCTION("""COMPUTED_VALUE"""),"Iván Sánchez") -> Iván Sánchez | G85: =IFERROR(__xludf.DUMMYFUNCTION("""COMPUTED_VALUE"""),"ISL") -> ISL | H85: =IFERROR(__xludf.DUMMYFUNCTION("""COMPUTED_VALUE"""),"ISL90") -> ISL90 | I85: =IFERROR(__xludf.DUMMYFUNCTION("""COMPUTED_VALUE"""),"B") -> B | J85: =IFERROR(__xludf.DUMMYFUNCTION("""COMPUTED_VALUE"""),"Ana Giribet Fernández-Pacheco") -> Ana Giribet Fernández-Pacheco | L85: =H85 -> ISL90 | M85: =G85 -> ISL
F86: =IFERROR(__xludf.DUMMYFUNCTION("""COMPUTED_VALUE"""),"Lisandro Russian") -> Lisandro Russian | G86: =IFERROR(__xludf.DUMMYFUNCTION("""COMPUTED_VALUE"""),"LRM") -> LRM | H86: =IFERROR(__xludf.DUMMYFUNCTION("""COMPUTED_VALUE"""),"LRM131") -> LRM131 | I86: =IFERROR(__xludf.DUMMYFUNCTION("""COMPUTED_VALUE"""),"A") -> A | J86: =IFERROR(__xludf.DUMMYFUNCTION("""COMPUTED_VALUE"""),"Ana Herrero Egea") -> Ana Herrero Egea | L86: =H86 -> LRM131 | M86: =G86 -> LRM
F87: =IFERROR(__xludf.DUMMYFUNCTION("""COMPUTED_VALUE"""),"Roberto Pereira") -> Roberto Pereira | G87: =IFERROR(__xludf.DUMMYFUNCTION("""COMPUTED_VALUE"""),"RPG") -> RPG | H87: =IFERROR(__xludf.DUMMYFUNCTION("""COMPUTED_VALUE"""),"RPG36") -> RPG36 | I87: =IFERROR(__xludf.DUMMYFUNCTION("""COMPUTED_VALUE"""),"A") -> A | J87: =IFERROR(__xludf.DUMMYFUNCTION("""COMPUTED_VALUE"""),"Ana Isabel Lorenzo Lorenzo") -> Ana Isabel Lorenzo Lorenzo | L87: =H87 -> RPG36 | M87: =G87 -> RPG
F88: =IFERROR(__xludf.DUMMYFUNCTION("""COMPUTED_VALUE"""),"Lisandro Russian") -> Lisandro Russian | G88: =IFERROR(__xludf.DUMMYFUNCTION("""COMPUTED_VALUE"""),"LRM") -> LRM | H88: =IFERROR(__xludf.DUMMYFUNCTION("""COMPUTED_VALUE"""),"LRM132") -> LRM132 | I88: =IFERROR(__xludf.DUMMYFUNCTION("""COMPUTED_VALUE"""),"A") -> A | J88: =IFERROR(__xludf.DUMMYFUNCTION("""COMPUTED_VALUE"""),"Ana María Sánchez-Prieto Fernández") -> Ana María Sánchez-Prieto Fernández | L88: =H88 -> LRM132 | M88: =G88 -> LRM
F89: =IFERROR(__xludf.DUMMYFUNCTION("""COMPUTED_VALUE"""),"Mercè Cabrera") -> Mercè Cabrera | G89: =IFERROR(__xludf.DUMMYFUNCTION("""COMPUTED_VALUE"""),"MCC") -> MCC | H89: =IFERROR(__xludf.DUMMYFUNCTION("""COMPUTED_VALUE"""),"MCC38") -> MCC38 | I89: =IFERROR(__xludf.DUMMYFUNCTION("""COMPUTED_VALUE"""),"A") -> A | J89: =IFERROR(__xludf.DUMMYFUNCTION("""COMPUTED_VALUE"""),"Ana Moreno Valor") -> Ana Moreno Valor | L89: =H89 -> MCC38 | M89: =G89 -> MCC
F90: =IFERROR(__xludf.DUMMYFUNCTION("""COMPUTED_VALUE"""),"Lisandro Russian") -> Lisandro Russian | G90: =IFERROR(__xludf.DUMMYFUNCTION("""COMPUTED_VALUE"""),"LRM") -> LRM | H90: =IFERROR(__xludf.DUMMYFUNCTION("""COMPUTED_VALUE"""),"LRM133") -> LRM133 | I90: =IFERROR(__xludf.DUMMYFUNCTION("""COMPUTED_VALUE"""),"A") -> A | J90: =IFERROR(__xludf.DUMMYFUNCTION("""COMPUTED_VALUE"""),"Ana Pérez del Notario") -> Ana Pérez del Notario | L90: =H90 -> LRM133 | M90: =G90 -> LRM
F91: =IFERROR(__xludf.DUMMYFUNCTION("""COMPUTED_VALUE"""),"Roberto Pereira") -> Roberto Pereira | G91: =IFERROR(__xludf.DUMMYFUNCTION("""COMPUTED_VALUE"""),"RPG") -> RPG | H91: =IFERROR(__xludf.DUMMYFUNCTION("""COMPUTED_VALUE"""),"RPG37") -> RPG37 | I91: =IFERROR(__xludf.DUMMYFUNCTION("""COMPUTED_VALUE"""),"A") -> A | J91: =IFERROR(__xludf.DUMMYFUNCTION("""COMPUTED_VALUE"""),"Ana Quintana Sanjuan") -> Ana Quintana Sanjuan | L91: =H91 -> RPG37 | M91: =G91 -> RPG
F92: =IFERROR(__xludf.DUMMYFUNCTION("""COMPUTED_VALUE"""),"Mercè Cabrera") -> Mercè Cabrera | G92: =IFERROR(__xludf.DUMMYFUNCTION("""COMPUTED_VALUE"""),"MCC") -> MCC | H92: =IFERROR(__xludf.DUMMYFUNCTION("""COMPUTED_VALUE"""),"MCC62") -> MCC62 | I92: =IFERROR(__xludf.DUMMYFUNCTION("""COMPUTED_VALUE"""),"A") -> A | J92: =IFERROR(__xludf.DUMMYFUNCTION("""COMPUTED_VALUE"""),"Ana Rodríguez Rodríguez") -> Ana Rodríguez Rodríguez | L92: =H92 -> MCC62 | M92: =G92 -> MCC
F93: =IFERROR(__xludf.DUMMYFUNCTION("""COMPUTED_VALUE"""),"Maika Blázquez") -> Maika Blázquez | G93: =IFERROR(__xludf.DUMMYFUNCTION("""COMPUTED_VALUE"""),"MBM") -> MBM | H93: =IFERROR(__xludf.DUMMYFUNCTION("""COMPUTED_VALUE"""),"MBM90") -> MBM90 | I93: =IFERROR(__xludf.DUMMYFUNCTION("""COMPUTED_VALUE"""),"A") -> A | J93: =IFERROR(__xludf.DUMMYFUNCTION("""COMPUTED_VALUE"""),"Ana Ruiz Fornells Noreña") -> Ana Ruiz Fornells Noreña | L93: =H93 -> MBM90 | M93: =G93 -> MBM
F94: =IFERROR(__xludf.DUMMYFUNCTION("""COMPUTED_VALUE"""),"Maika Blázquez") -> Maika Blázquez | G94: =IFERROR(__xludf.DUMMYFUNCTION("""COMPUTED_VALUE"""),"MBM") -> MBM | H94: =IFERROR(__xludf.DUMMYFUNCTION("""COMPUTED_VALUE"""),"MBM208") -> MBM208 | I94: =IFERROR(__xludf.DUMMYFUNCTION("""COMPUTED_VALUE"""),"A") -> A | J94: =IFERROR(__xludf.DUMMYFUNCTION("""COMPUTED_VALUE"""),"Ana Solís Fesser") -> Ana Solís Fesser | L94: =H94 -> MBM208 | M94: =G94 -> MBM
F95: =IFERROR(__xludf.DUMMYFUNCTION("""COMPUTED_VALUE"""),"Maika Blázquez") -> Maika Blázquez | G95: =IFERROR(__xludf.DUMMYFUNCTION("""COMPUTED_VALUE"""),"MBM") -> MBM | H95: =IFERROR(__xludf.DUMMYFUNCTION("""COMPUTED_VALUE"""),"MBM195") -> MBM195 | I95: =IFERROR(__xludf.DUMMYFUNCTION("""COMPUTED_VALUE"""),"A") -> A | J95: =IFERROR(__xludf.DUMMYFUNCTION("""COMPUTED_VALUE"""),"Anastasiya Audiyuk Martynyuk") -> Anastasiya Audiyuk Martynyuk | L95: =H95 -> MBM195 | M95: =G95 -> MBM
F96: =IFERROR(__xludf.DUMMYFUNCTION("""COMPUTED_VALUE"""),"Lisandro Russian") -> Lisandro Russian | G96: =IFERROR(__xludf.DUMMYFUNCTION("""COMPUTED_VALUE"""),"LRM") -> LRM | H96: =IFERROR(__xludf.DUMMYFUNCTION("""COMPUTED_VALUE"""),"LRM258") -> LRM258 | I96: =IFERROR(__xludf.DUMMYFUNCTION("""COMPUTED_VALUE"""),"A") -> A | J96: =IFERROR(__xludf.DUMMYFUNCTION("""COMPUTED_VALUE"""),"Andrea Cifuentes Navas") -> Andrea Cifuentes Navas | L96: =H96 -> LRM258 | M96: =G96 -> LRM
F97: =IFERROR(__xludf.DUMMYFUNCTION("""COMPUTED_VALUE"""),"Lisandro Russian") -> Lisandro Russian | G97: =IFERROR(__xludf.DUMMYFUNCTION("""COMPUTED_VALUE"""),"LRM") -> LRM | H97: =IFERROR(__xludf.DUMMYFUNCTION("""COMPUTED_VALUE"""),"LRM135") -> LRM135 | I97: =IFERROR(__xludf.DUMMYFUNCTION("""COMPUTED_VALUE"""),"A") -> A | J97: =IFERROR(__xludf.DUMMYFUNCTION("""COMPUTED_VALUE"""),"Andrea Escribano Peñalva") -> Andrea Escribano Peñalva | L97: =H97 -> LRM135 | M97: =G97 -> LRM
F98: =IFERROR(__xludf.DUMMYFUNCTION("""COMPUTED_VALUE"""),"Maika Blázquez") -> Maika Blázquez | G98: =IFERROR(__xludf.DUMMYFUNCTION("""COMPUTED_VALUE"""),"MBM") -> MBM | H98: =IFERROR(__xludf.DUMMYFUNCTION("""COMPUTED_VALUE"""),"MBM209") -> MBM209 | I98: =IFERROR(__xludf.DUMMYFUNCTION("""COMPUTED_VALUE"""),"A") -> A | J98: =IFERROR(__xludf.DUMMYFUNCTION("""COMPUTED_VALUE"""),"Andrea Gil Pro") -> Andrea Gil Pro | L98: =H98 -> MBM209 | M98: =G98 -> MBM
F99: =IFERROR(__xludf.DUMMYFUNCTION("""COMPUTED_VALUE"""),"Maika Blázquez") -> Maika Blázquez | G99: =IFERROR(__xludf.DUMMYFUNCTION("""COMPUTED_VALUE"""),"MBM") -> MBM | H99: =IFERROR(__xludf.DUMMYFUNCTION("""COMPUTED_VALUE"""),"MBM91") -> MBM91 | I99: =IFERROR(__xludf.DUMMYFUNCTION("""COMPUTED_VALUE"""),"A") -> A | J99: =IFERROR(__xludf.DUMMYFUNCTION("""COMPUTED_VALUE"""),"Andrea López Salcedo") -> Andrea López Salcedo | L99: =H99 -> MBM91 | M99: =G99 -> MBM
F100: =IFERROR(__xludf.DUMMYFUNCTION("""COMPUTED_VALUE"""),"Maika Blázquez") -> Maika Blázquez | G100: =IFERROR(__xludf.DUMMYFUNCTION("""COMPUTED_VALUE"""),"MBM") -> MBM | H100: =IFERROR(__xludf.DUMMYFUNCTION("""COMPUTED_VALUE"""),"MBM07") -> MBM07 | I100: =IFERROR(__xludf.DUMMYFUNCTION("""COMPUTED_VALUE"""),"A") -> A | J100: =IFERROR(__xludf.DUMMYFUNCTION("""COMPUTED_VALUE"""),"Andreas Schilling Borghesi") -> Andreas Schilling Borghesi | L100: =H100 -> MBM07 | M100: =G100 -> MBM
F101: =IFERROR(__xludf.DUMMYFUNCTION("""COMPUTED_VALUE"""),"Iván Sánchez") -> Iván Sánchez | G101: =IFERROR(__xludf.DUMMYFUNCTION("""COMPUTED_VALUE"""),"ISL") -> ISL | H101: =IFERROR(__xludf.DUMMYFUNCTION("""COMPUTED_VALUE"""),"ISL06") -> ISL06 | I101: =IFERROR(__xludf.DUMMYFUNCTION("""COMPUTED_VALUE"""),"B") -> B | J101: =IFERROR(__xludf.DUMMYFUNCTION("""COMPUTED_VALUE"""),"Andrés Barrios Recio") -> Andrés Barrios Recio | L101: =H101 -> ISL06 | M101: =G101 -> ISL
F102: =IFERROR(__xludf.DUMMYFUNCTION("""COMPUTED_VALUE"""),"Lisandro Russian") -> Lisandro Russian | G102: =IFERROR(__xludf.DUMMYFUNCTION("""COMPUTED_VALUE"""),"LRM") -> LRM | H102: =IFERROR(__xludf.DUMMYFUNCTION("""COMPUTED_VALUE"""),"LRM271") -> LRM271 | I102: =IFERROR(__xludf.DUMMYFUNCTION("""COMPUTED_VALUE"""),"A") -> A | J102: =IFERROR(__xludf.DUMMYFUNCTION("""COMPUTED_VALUE"""),"Andrés González Fernández") -> Andrés González Fernández | L102: =H102 -> LRM271 | M102: =G102 -> LRM
F103: =IFERROR(__xludf.DUMMYFUNCTION("""COMPUTED_VALUE"""),"Lisandro Russian") -> Lisandro Russian | G103: =IFERROR(__xludf.DUMMYFUNCTION("""COMPUTED_VALUE"""),"LRM") -> LRM | H103: =IFERROR(__xludf.DUMMYFUNCTION("""COMPUTED_VALUE"""),"LRM240") -> LRM240 | I103: =IFERROR(__xludf.DUMMYFUNCTION("""COMPUTED_VALUE"""),"A") -> A | J103: =IFERROR(__xludf.DUMMYFUNCTION("""COMPUTED_VALUE"""),"Andrés Paulino Herrera") -> Andrés Paulino Herrera | L103: =H103 -> LRM240 | M103: =G103 -> LRM
F104: =IFERROR(__xludf.DUMMYFUNCTION("""COMPUTED_VALUE"""),"Luis Alberto Rodríguez") -> Luis Alberto Rodríguez | G104: =IFERROR(__xludf.DUMMYFUNCTION("""COMPUTED_VALUE"""),"LAA") -> LAA | H104: =IFERROR(__xludf.DUMMYFUNCTION("""COMPUTED_VALUE"""),"LAA01") -> LAA01 | I104: =IFERROR(__xludf.DUMMYFUNCTION("""COMPUTED_VALUE"""),"C") -> C | J104: =IFERROR(__xludf.DUMMYFUNCTION("""COMPUTED_VALUE"""),"Andrés Ruiz Moreno") -> Andrés Ruiz Moreno | L104: =H104 -> LAA01 | M104: =G104 -> LAA
...

Sheet datos 2026
A1: ACTUALIZACIÓN A | B1: código visitador | C1: =IFERROR(__xludf.DUMMYFUNCTION("QUERY(IMPORTRANGE(""1y_3LleCxvzurbj_vKa53p6-h3HGan0CBvsIGq6qCvKU/edit?gid=1277712770#gid=1277712770"",""DATOSANALISIS!C:AM""),""SELECT Col1, Col4, Col5, Col6, Col7, Col8, Col9, Col13, Col14, Col15, Col16, Col18, Col19, Col21, Col29, Col35, Col36, Col37"","&"1)"),"cód ORL") -> cód ORL | D1: =IFERROR(__xludf.DUMMYFUNCTION("""COMPUTED_VALUE"""),"TIPO") -> TIPO | E1: =IFERROR(__xludf.DUMMYFUNCTION("""COMPUTED_VALUE"""),"Año Estado") -> Año Estado | F1: =IFERROR(__xludf.DUMMYFUNCTION("""COMPUTED_VALUE"""),"Mes Estado") -> Mes Estado | G1: =IFERROR(__xludf.DUMMYFUNCTION("""COMPUTED_VALUE"""),"SUCURSAL") -> SUCURSAL | H1: =IFERROR(__xludf.DUMMYFUNCTION("""COMPUTED_VALUE"""),"COD CLIENTE") -> COD CLIENTE | I1: =IFERROR(__xludf.DUMMYFUNCTION("""COMPUTED_VALUE"""),"NOMBRE CLIENTE") -> NOMBRE CLIENTE | J1: =IFERROR(__xludf.DUMMYFUNCTION("""COMPUTED_VALUE"""),"FECHA INICIO OPORTUNIDAD") -> FECHA INICIO OPORTUNIDAD | K1: =IFERROR(__xludf.DUMMYFUNCTION("""COMPUTED_VALUE"""),"ESTADO OPORTUNIDAD") -> ESTADO OPORTUNIDAD | L1: =IFERROR(__xludf.DUMMYFUNCTION("""COMPUTED_VALUE"""),"FECHA ESTADO OPORTUNIDAD") -> FECHA ESTADO OPORTUNIDAD | M1: =IFERROR(__xludf.DUMMYFUNCTION("""COMPUTED_VALUE"""),"RECOMPRA") -> RECOMPRA | N1: =IFERROR(__xludf.DUMMYFUNCTION("""COMPUTED_VALUE"""),"NUM AUDIFONOS") -> NUM AUDIFONOS | O1: =IFERROR(__xludf.DUMMYFUNCTION("""COMPUTED_VALUE"""),"MODELO (AUDIF 1)") -> MODELO (AUDIF 1) | P1: =IFERROR(__xludf.DUMMYFUNCTION("""COMPUTED_VALUE"""),"IMPORTE SIN IVA") -> IMPORTE SIN IVA | Q1: =IFERROR(__xludf.DUMMYFUNCTION("""COMPUTED_VALUE"""),"VISITADOR") -> VISITADOR | R1: =IFERROR(__xludf.DUMMYFUNCTION("""COMPUTED_VALUE"""),"NOMBRE ORL/CAMPAÑA") -> NOMBRE ORL/CAMPAÑA | S1: =IFERROR(__xludf.DUMMYFUNCTION("""COMPUTED_VALUE"""),"CANAL") -> CANAL | T1: =IFERROR(__xludf.DUMMYFUNCTION("""COMPUTED_VALUE"""),"SUBCANAL") -> SUBCANAL
A2: 46119 | B2: =IF($C2="","",LEFT(C2,3)) -> RFV | C2: =IFERROR(__xludf.DUMMYFUNCTION("""COMPUTED_VALUE"""),"RFV29") -> RFV29 | D2: =IFERROR(__xludf.DUMMYFUNCTION("""COMPUTED_VALUE"""),"PROPIOS") -> PROPIOS | E2: =IFERROR(__xludf.DUMMYFUNCTION("""COMPUTED_VALUE"""),2026) -> 2026 | F2: =IFERROR(__xludf.DUMMYFUNCTION("""COMPUTED_VALUE"""),1) -> 1 | G2: =IFERROR(__xludf.DUMMYFUNCTION("""COMPUTED_VALUE"""),"Valencia- Parra") -> Valencia- Parra | H2: =IFERROR(__xludf.DUMMYFUNCTION("""COMPUTED_VALUE"""),"C202511592157270489") -> C202511592157270489 | I2: =IFERROR(__xludf.DUMMYFUNCTION("""COMPUTED_VALUE"""),"HEINZ WIEST") -> HEINZ WIEST | J2: =IFERROR(__xludf.DUMMYFUNCTION("""COMPUTED_VALUE"""),45966) -> 45966 | K2: =IFERROR(__xludf.DUMMYFUNCTION("""COMPUTED_VALUE"""),"Factura audífonos") -> Factura audífonos | L2: =IFERROR(__xludf.DUMMYFUNCTION("""COMPUTED_VALUE"""),46024) -> 46024 | M2: =IFERROR(__xludf.DUMMYFUNCTION("""COMPUTED_VALUE"""),"NO") -> NO | N2: =IFERROR(__xludf.DUMMYFUNCTION("""COMPUTED_VALUE"""),2) -> 2 | O2: =IFERROR(__xludf.DUMMYFUNCTION("""COMPUTED_VALUE"""),"PRO") -> PRO | P2: =IFERROR(__xludf.DUMMYFUNCTION("""COMPUTED_VALUE"""),4536.36) -> 4536.36 | Q2: =IFERROR(__xludf.DUMMYFUNCTION("""COMPUTED_VALUE"""),"Ramon Ferrando") -> Ramon Ferrando | R2: =IFERROR(__xludf.DUMMYFUNCTION("""COMPUTED_VALUE"""),"Fe Rubio Escolano") -> Fe Rubio Escolano | S2: =IFERROR(__xludf.DUMMYFUNCTION("""COMPUTED_VALUE"""),"03 ORL") -> 03 ORL | T2: =IFERROR(__xludf.DUMMYFUNCTION("""COMPUTED_VALUE"""),"06 ORL") -> 06 ORL
B3: =IF($C3="","",LEFT(C3,3)) -> LRM | C3: =IFERROR(__xludf.DUMMYFUNCTION("""COMPUTED_VALUE"""),"LRM240") -> LRM240 | D3: =IFERROR(__xludf.DUMMYFUNCTION("""COMPUTED_VALUE"""),"ASOCIADOS") -> ASOCIADOS | E3: =IFERROR(__xludf.DUMMYFUNCTION("""COMPUTED_VALUE"""),2026) -> 2026 | F3: =IFERROR(__xludf.DUMMYFUNCTION("""COMPUTED_VALUE"""),1) -> 1 | G3: =IFERROR(__xludf.DUMMYFUNCTION("""COMPUTED_VALUE"""),"Cáceres") -> Cáceres | H3: =IFERROR(__xludf.DUMMYFUNCTION("""COMPUTED_VALUE"""),"C202512110551976531") -> C202512110551976531 | I3: =IFERROR(__xludf.DUMMYFUNCTION("""COMPUTED_VALUE"""),"JUAN MANUEL CORCHERO HIGUERO") -> JUAN MANUEL CORCHERO HIGUERO | J3: =IFERROR(__xludf.DUMMYFUNCTION("""COMPUTED_VALUE"""),45992) -> 45992 | K3: =IFERROR(__xludf.DUMMYFUNCTION("""COMPUTED_VALUE"""),"Factura audífonos") -> Factura audífonos | L3: =IFERROR(__xludf.DUMMYFUNCTION("""COMPUTED_VALUE"""),46024) -> 46024 | M3: =IFERROR(__xludf.DUMMYFUNCTION("""COMPUTED_VALUE"""),"NO") -> NO | N3: =IFERROR(__xludf.DUMMYFUNCTION("""COMPUTED_VALUE"""),2) -> 2 | O3: =IFERROR(__xludf.DUMMYFUNCTION("""COMPUTED_VALUE"""),"QUIET") -> QUIET | P3: =IFERROR(__xludf.DUMMYFUNCTION("""COMPUTED_VALUE"""),3636.36) -> 3636.36 | Q3: =IFERROR(__xludf.DUMMYFUNCTION("""COMPUTED_VALUE"""),"Lisandro Russian") -> Lisandro Russian | R3: =IFERROR(__xludf.DUMMYFUNCTION("""COMPUTED_VALUE"""),"Andrés Paulino Herrera") -> Andrés Paulino Herrera | S3: =IFERROR(__xludf.DUMMYFUNCTION("""COMPUTED_VALUE"""),"03 ORL") -> 03 ORL | T3: =IFERROR(__xludf.DUMMYFUNCTION("""COMPUTED_VALUE"""),"06 ORL") -> 06 ORL
B4: =IF($C4="","",LEFT(C4,3)) -> PSC | C4: =IFERROR(__xludf.DUMMYFUNCTION("""COMPUTED_VALUE"""),"PSC06") -> PSC06 | D4: =IFERROR(__xludf.DUMMYFUNCTION("""COMPUTED_VALUE"""),"ASOCIADOS") -> ASOCIADOS | E4: =IFERROR(__xludf.DUMMYFUNCTION("""COMPUTED_VALUE"""),2026) -> 2026 | F4: =IFERROR(__xludf.DUMMYFUNCTION("""COMPUTED_VALUE"""),1) -> 1 | G4: =IFERROR(__xludf.DUMMYFUNCTION("""COMPUTED_VALUE"""),"Valladolid") -> Valladolid | H4: =IFERROR(__xludf.DUMMYFUNCTION("""COMPUTED_VALUE"""),"VLL-474") -> VLL-474 | I4: =IFERROR(__xludf.DUMMYFUNCTION("""COMPUTED_VALUE"""),"GAUDENCIO GARCIA REGUERO") -> GAUDENCIO GARCIA REGUERO | J4: =IFERROR(__xludf.DUMMYFUNCTION("""COMPUTED_VALUE"""),45964) -> 45964 | K4: =IFERROR(__xludf.DUMMYFUNCTION("""COMPUTED_VALUE"""),"Factura audífonos") -> Factura audífonos | L4: =IFERROR(__xludf.DUMMYFUNCTION("""COMPUTED_VALUE"""),46027) -> 46027 | M4: =IFERROR(__xludf.DUMMYFUNCTION("""COMPUTED_VALUE"""),"NO") -> NO | N4: =IFERROR(__xludf.DUMMYFUNCTION("""COMPUTED_VALUE"""),2) -> 2 | O4: =IFERROR(__xludf.DUMMYFUNCTION("""COMPUTED_VALUE"""),"CONFORT") -> CONFORT | P4: =IFERROR(__xludf.DUMMYFUNCTION("""COMPUTED_VALUE"""),3522.73) -> 3522.73 | Q4: =IFERROR(__xludf.DUMMYFUNCTION("""COMPUTED_VALUE"""),"Alberto Moreno") -> Alberto Moreno | R4: =IFERROR(__xludf.DUMMYFUNCTION("""COMPUTED_VALUE"""),"Carlos Miguel Salvador Martínez") -> Carlos Miguel Salvador Martínez | S4: =IFERROR(__xludf.DUMMYFUNCTION("""COMPUTED_VALUE"""),"03 ORL") -> 03 ORL | T4: =IFERROR(__xludf.DUMMYFUNCTION("""COMPUTED_VALUE"""),"06 ORL") -> 06 ORL
B5: =IF($C5="","",LEFT(C5,3)) -> MBM | C5: =IFERROR(__xludf.DUMMYFUNCTION("""COMPUTED_VALUE"""),"MBM156") -> MBM156 | D5: =IFERROR(__xludf.DUMMYFUNCTION("""COMPUTED_VALUE"""),"PROPIOS") -> PROPIOS | E5: =IFERROR(__xludf.DUMMYFUNCTION("""COMPUTED_VALUE"""),2026) -> 2026 | F5: =IFERROR(__xludf.DUMMYFUNCTION("""COMPUTED_VALUE"""),1) -> 1 | G5: =IFERROR(__xludf.DUMMYFUNCTION("""COMPUTED_VALUE"""),"Getafe") -> Getafe | H5: =IFERROR(__xludf.DUMMYFUNCTION("""COMPUTED_VALUE"""),"C202511141135536493") -> C202511141135536493 | I5: =IFERROR(__xludf.DUMMYFUNCTION("""COMPUTED_VALUE"""),"ANTONIO CALVETE OLIVA") -> ANTONIO CALVETE OLIVA | J5: =IFERROR(__xludf.DUMMYFUNCTION("""COMPUTED_VALUE"""),45975) -> 45975 | K5: =IFERROR(__xludf.DUMMYFUNCTION("""COMPUTED_VALUE"""),"Factura audífonos") -> Factura audífonos | L5: =IFERROR(__xludf.DUMMYFUNCTION("""COMPUTED_VALUE"""),46027) -> 46027 | M5: =IFERROR(__xludf.DUMMYFUNCTION("""COMPUTED_VALUE"""),"NO") -> NO | N5: =IFERROR(__xludf.DUMMYFUNCTION("""COMPUTED_VALUE"""),1) -> 1 | O5: =IFERROR(__xludf.DUMMYFUNCTION("""COMPUTED_VALUE"""),"CONFORT") -> CONFORT | P5: =IFERROR(__xludf.DUMMYFUNCTION("""COMPUTED_VALUE"""),2180.91) -> 2180.91 | Q5: =IFERROR(__xludf.DUMMYFUNCTION("""COMPUTED_VALUE"""),"Maika Blázquez") -> Maika Blázquez | R5: =IFERROR(__xludf.DUMMYFUNCTION("""COMPUTED_VALUE"""),"Marta Colmenero Ruiz") -> Marta Colmenero Ruiz | S5: =IFERROR(__xludf.DUMMYFUNCTION("""COMPUTED_VALUE"""),"03 ORL") -> 03 ORL | T5: =IFERROR(__xludf.DUMMYFUNCTION("""COMPUTED_VALUE"""),"06 ORL") -> 06 ORL
B6: =IF($C6="","",LEFT(C6,3)) -> MBM | C6: =IFERROR(__xludf.DUMMYFUNCTION("""COMPUTED_VALUE"""),"MBM07") -> MBM07 | D6: =IFERROR(__xludf.DUMMYFUNCTION("""COMPUTED_VALUE"""),"PARTICIPADOS") -> PARTICIPADOS | E6: =IFERROR(__xludf.DUMMYFUNCTION("""COMPUTED_VALUE"""),2026) -> 2026 | F6: =IFERROR(__xludf.DUMMYFUNCTION("""COMPUTED_VALUE"""),1) -> 1 | G6: =IFERROR(__xludf.DUMMYFUNCTION("""COMPUTED_VALUE"""),"Madrid- La Oca") -> Madrid- La Oca | H6: =IFERROR(__xludf.DUMMYFUNCTION("""COMPUTED_VALUE"""),"C202511171016459133") -> C202511171016459133 | I6: =IFERROR(__xludf.DUMMYFUNCTION("""COMPUTED_VALUE"""),"AMELIA DIAZ VAZQUEZ") -> AMELIA DIAZ VAZQUEZ | J6: =IFERROR(__xludf.DUMMYFUNCTION("""COMPUTED_VALUE"""),45978) -> 45978 | K6: =IFERROR(__xludf.DUMMYFUNCTION("""COMPUTED_VALUE"""),"Factura audífonos") -> Factura audífonos | L6: =IFERROR(__xludf.DUMMYFUNCTION("""COMPUTED_VALUE"""),46029) -> 46029 | M6: =IFERROR(__xludf.DUMMYFUNCTION("""COMPUTED_VALUE"""),"NO") -> NO | N6: =IFERROR(__xludf.DUMMYFUNCTION("""COMPUTED_VALUE"""),2) -> 2 | O6: =IFERROR(__xludf.DUMMYFUNCTION("""COMPUTED_VALUE"""),"QUIET") -> QUIET | P6: =IFERROR(__xludf.DUMMYFUNCTION("""COMPUTED_VALUE"""),2718.18) -> 2718.18 | Q6: =IFERROR(__xludf.DUMMYFUNCTION("""COMPUTED_VALUE"""),"Maika Blázquez") -> Maika Blázquez | R6: =IFERROR(__xludf.DUMMYFUNCTION("""COMPUTED_VALUE"""),"Andreas Schilling Borghesi") -> Andreas Schilling Borghesi | S6: =IFERROR(__xludf.DUMMYFUNCTION("""COMPUTED_VALUE"""),"03 ORL") -> 03 ORL | T6: =IFERROR(__xludf.DUMMYFUNCTION("""COMPUTED_VALUE"""),"06 ORL") -> 06 ORL
B7: =IF($C7="","",LEFT(C7,3)) -> MBM | C7: =IFERROR(__xludf.DUMMYFUNCTION("""COMPUTED_VALUE"""),"MBM52") -> MBM52 | D7: =IFERROR(__xludf.DUMMYFUNCTION("""COMPUTED_VALUE"""),"PARTICIPADOS") -> PARTICIPADOS | E7: =IFERROR(__xludf.DUMMYFUNCTION("""COMPUTED_VALUE"""),2026) -> 2026 | F7: =IFERROR(__xludf.DUMMYFUNCTION("""COMPUTED_VALUE"""),1) -> 1 | G7: =IFERROR(__xludf.DUMMYFUNCTION("""COMPUTED_VALUE"""),"Madrid- La Oca") -> Madrid- La Oca | H7: =IFERROR(__xludf.DUMMYFUNCTION("""COMPUTED_VALUE"""),"C202512911304031492") -> C202512911304031492 | I7: =IFERROR(__xludf.DUMMYFUNCTION("""COMPUTED_VALUE"""),"REMEDIOS VECINO PRIETO") -> REMEDIOS VECINO PRIETO | J7: =IFERROR(__xludf.DUMMYFUNCTION("""COMPUTED_VALUE"""),46000) -> 46000 | K7: =IFERROR(__xludf.DUMMYFUNCTION("""COMPUTED_VALUE"""),"Factura audífonos") -> Factura audífonos | L7: =IFERROR(__xludf.DUMMYFUNCTION("""COMPUTED_VALUE"""),46030) -> 46030 | M7: =IFERROR(__xludf.DUMMYFUNCTION("""COMPUTED_VALUE"""),"NO") -> NO | N7: =IFERROR(__xludf.DUMMYFUNCTION("""COMPUTED_VALUE"""),2) -> 2 | O7: =IFERROR(__xludf.DUMMYFUNCTION("""COMPUTED_VALUE"""),"QUIET") -> QUIET | P7: =IFERROR(__xludf.DUMMYFUNCTION("""COMPUTED_VALUE"""),2718.18) -> 2718.18 | Q7: =IFERROR(__xludf.DUMMYFUNCTION("""COMPUTED_VALUE"""),"Maika Blázquez") -> Maika Blázquez | R7: =IFERROR(__xludf.DUMMYFUNCTION("""COMPUTED_VALUE"""),"José Joaquín Gutiérrez Barquín") -> José Joaquín Gutiérrez Barquín | S7: =IFERROR(__xludf.DUMMYFUNCTION("""COMPUTED_VALUE"""),"03 ORL") -> 03 ORL | T7: =IFERROR(__xludf.DUMMYFUNCTION("""COMPUTED_VALUE"""),"06 ORL") -> 06 ORL
B8: =IF($C8="","",LEFT(C8,3)) | D8: =IFERROR(__xludf.DUMMYFUNCTION("""COMPUTED_VALUE"""),"ASOCIADOS") -> ASOCIADOS | E8: =IFERROR(__xludf.DUMMYFUNCTION("""COMPUTED_VALUE"""),2026) -> 2026 | F8: =IFERROR(__xludf.DUMMYFUNCTION("""COMPUTED_VALUE"""),1) -> 1 | G8: =IFERROR(__xludf.DUMMYFUNCTION("""COMPUTED_VALUE"""),"Sevilla- Ciencias") -> Sevilla- Ciencias | H8: =IFERROR(__xludf.DUMMYFUNCTION("""COMPUTED_VALUE"""),"C202511201556282288") -> C202511201556282288 | I8: =IFERROR(__xludf.DUMMYFUNCTION("""COMPUTED_VALUE"""),"CONCEPCION ORTIZ SANTIAGO") -> CONCEPCION ORTIZ SANTIAGO | J8: =IFERROR(__xludf.DUMMYFUNCTION("""COMPUTED_VALUE"""),45981) -> 45981 | K8: =IFERROR(__xludf.DUMMYFUNCTION("""COMPUTED_VALUE"""),"Factura audífonos") -> Factura audífonos | L8: =IFERROR(__xludf.DUMMYFUNCTION("""COMPUTED_VALUE"""),46030) -> 46030 | M8: =IFERROR(__xludf.DUMMYFUNCTION("""COMPUTED_VALUE"""),"NO") -> NO | N8: =IFERROR(__xludf.DUMMYFUNCTION("""COMPUTED_VALUE"""),2) -> 2 | O8: =IFERROR(__xludf.DUMMYFUNCTION("""COMPUTED_VALUE"""),"ADVANCED") -> ADVANCED | P8: =IFERROR(__xludf.DUMMYFUNCTION("""COMPUTED_VALUE"""),4120) -> 4120 | Q8: =IFERROR(__xludf.DUMMYFUNCTION("""COMPUTED_VALUE"""),"Luis Alberto Rodríguez") -> Luis Alberto Rodríguez | R8: =IFERROR(__xludf.DUMMYFUNCTION("""COMPUTED_VALUE"""),"No recuerda ORL") -> No recuerda ORL | S8: =IFERROR(__xludf.DUMMYFUNCTION("""COMPUTED_VALUE"""),"03 ORL") -> 03 ORL | T8: =IFERROR(__xludf.DUMMYFUNCTION("""COMPUTED_VALUE"""),"06 ORL") -> 06 ORL
B9: =IF($C9="","",LEFT(C9,3)) -> MBM | C9: =IFERROR(__xludf.DUMMYFUNCTION("""COMPUTED_VALUE"""),"MBM156") -> MBM156 | D9: =IFERROR(__xludf.DUMMYFUNCTION("""COMPUTED_VALUE"""),"PROPIOS") -> PROPIOS | E9: =IFERROR(__xludf.DUMMYFUNCTION("""COMPUTED_VALUE"""),2026) -> 2026 | F9: =IFERROR(__xludf.DUMMYFUNCTION("""COMPUTED_VALUE"""),1) -> 1 | G9: =IFERROR(__xludf.DUMMYFUNCTION("""COMPUTED_VALUE"""),"Getafe") -> Getafe | H9: =IFERROR(__xludf.DUMMYFUNCTION("""COMPUTED_VALUE"""),"C202511271003718318") -> C202511271003718318 | I9: =IFERROR(__xludf.DUMMYFUNCTION("""COMPUTED_VALUE"""),"MARIA ROSA ALONSO GONZÁLEZ") -> MARIA ROSA ALONSO GONZÁLEZ | J9: =IFERROR(__xludf.DUMMYFUNCTION("""COMPUTED_VALUE"""),45988) -> 45988 | K9: =IFERROR(__xludf.DUMMYFUNCTION("""COMPUTED_VALUE"""),"Factura audífonos") -> Factura audífonos | L9: =IFERROR(__xludf.DUMMYFUNCTION("""COMPUTED_VALUE"""),46030) -> 46030 | M9: =IFERROR(__xludf.DUMMYFUNCTION("""COMPUTED_VALUE"""),"NO") -> NO | N9: =IFERROR(__xludf.DUMMYFUNCTION("""COMPUTED_VALUE"""),2) -> 2 | O9: =IFERROR(__xludf.DUMMYFUNCTION("""COMPUTED_VALUE"""),"ADVANCED") -> ADVANCED | P9: =IFERROR(__xludf.DUMMYFUNCTION("""COMPUTED_VALUE"""),4136.36) -> 4136.36 | Q9: =IFERROR(__xludf.DUMMYFUNCTION("""COMPUTED_VALUE"""),"Maika Blázquez") -> Maika Blázquez | R9: =IFERROR(__xludf.DUMMYFUNCTION("""COMPUTED_VALUE"""),"Marta Colmenero Ruiz") -> Marta Colmenero Ruiz | S9: =IFERROR(__xludf.DUMMYFUNCTION("""COMPUTED_VALUE"""),"03 ORL") -> 03 ORL | T9: =IFERROR(__xludf.DUMMYFUNCTION("""COMPUTED_VALUE"""),"06 ORL") -> 06 ORL
B10: =IF($C10="","",LEFT(C10,3)) -> MBM | C10: =IFERROR(__xludf.DUMMYFUNCTION("""COMPUTED_VALUE"""),"MBM45") -> MBM45 | D10: =IFERROR(__xludf.DUMMYFUNCTION("""COMPUTED_VALUE"""),"PROPIOS") -> PROPIOS | E10: =IFERROR(__xludf.DUMMYFUNCTION("""COMPUTED_VALUE"""),2026) -> 2026 | F10: =IFERROR(__xludf.DUMMYFUNCTION("""COMPUTED_VALUE"""),1) -> 1 | G10: =IFERROR(__xludf.DUMMYFUNCTION("""COMPUTED_VALUE"""),"Madrid- Juan Bravo") -> Madrid- Juan Bravo | H10: =IFERROR(__xludf.DUMMYFUNCTION("""COMPUTED_VALUE"""),"JBR-1800") -> JBR-1800 | I10: =IFERROR(__xludf.DUMMYFUNCTION("""COMPUTED_VALUE"""),"JOSE LUIS RODRIGUEZ SIERRA") -> JOSE LUIS RODRIGUEZ SIERRA | J10: =IFERROR(__xludf.DUMMYFUNCTION("""COMPUTED_VALUE"""),45058) -> 45058 | K10: =IFERROR(__xludf.DUMMYFUNCTION("""COMPUTED_VALUE"""),"Factura audífonos") -> Factura audífonos | L10: =IFERROR(__xludf.DUMMYFUNCTION("""COMPUTED_VALUE"""),46030) -> 46030 | M10: =IFERROR(__xludf.DUMMYFUNCTION("""COMPUTED_VALUE"""),"SI") -> SI | N10: =IFERROR(__xludf.DUMMYFUNCTION("""COMPUTED_VALUE"""),1) -> 1 | O10: =IFERROR(__xludf.DUMMYFUNCTION("""COMPUTED_VALUE"""),"QUIET") -> QUIET | P10: =IFERROR(__xludf.DUMMYFUNCTION("""COMPUTED_VALUE"""),1543.52) -> 1543.52 | Q10: =IFERROR(__xludf.DUMMYFUNCTION("""COMPUTED_VALUE"""),"Maika Blázquez") -> Maika Blázquez | R10: =IFERROR(__xludf.DUMMYFUNCTION("""COMPUTED_VALUE"""),"Joaquín Alacio Casero") -> Joaquín Alacio Casero | S10: =IFERROR(__xludf.DUMMYFUNCTION("""COMPUTED_VALUE"""),"04 TIENDA") -> 04 TIENDA | T10: =IFERROR(__xludf.DUMMYFUNCTION("""COMPUTED_VALUE"""),"10 REVISIÓN POST-VENTA") -> 10 REVISIÓN POST-VENTA
B11: =IF($C11="","",LEFT(C11,3)) -> MBM | C11: =IFERROR(__xludf.DUMMYFUNCTION("""COMPUTED_VALUE"""),"MBM45") -> MBM45 | D11: =IFERROR(__xludf.DUMMYFUNCTION("""COMPUTED_VALUE"""),"PARTICIPADOS") -> PARTICIPADOS | E11: =IFERROR(__xludf.DUMMYFUNCTION("""COMPUTED_VALUE"""),2026) -> 2026 | F11: =IFERROR(__xludf.DUMMYFUNCTION("""COMPUTED_VALUE"""),1) -> 1 | G11: =IFERROR(__xludf.DUMMYFUNCTION("""COMPUTED_VALUE"""),"Madrid- La Oca") -> Madrid- La Oca | H11: =IFERROR(__xludf.DUMMYFUNCTION("""COMPUTED_VALUE"""),"C202511241158254265") -> C202511241158254265 | I11: =IFERROR(__xludf.DUMMYFUNCTION("""COMPUTED_VALUE"""),"MARIA DEL CARMEN GARCIA ROYO") -> MARIA DEL CARMEN GARCIA ROYO | J11: =IFERROR(__xludf.DUMMYFUNCTION("""COMPUTED_VALUE"""),45985) -> 45985 | K11: =IFERROR(__xludf.DUMMYFUNCTION("""COMPUTED_VALUE"""),"Factura audífonos") -> Factura audífonos | L11: =IFERROR(__xludf.DUMMYFUNCTION("""COMPUTED_VALUE"""),46031) -> 46031 | M11: =IFERROR(__xludf.DUMMYFUNCTION("""COMPUTED_VALUE"""),"NO") -> NO | N11: =IFERROR(__xludf.DUMMYFUNCTION("""COMPUTED_VALUE"""),2) -> 2 | O11: =IFERROR(__xludf.DUMMYFUNCTION("""COMPUTED_VALUE"""),"CONFORT") -> CONFORT | P11: =IFERROR(__xludf.DUMMYFUNCTION("""COMPUTED_VALUE"""),3631.82) -> 3631.82 | Q11: =IFERROR(__xludf.DUMMYFUNCTION("""COMPUTED_VALUE"""),"Maika Blázquez") -> Maika Blázquez | R11: =IFERROR(__xludf.DUMMYFUNCTION("""COMPUTED_VALUE"""),"Joaquín Alacio Casero") -> Joaquín Alacio Casero | S11: =IFERROR(__xludf.DUMMYFUNCTION("""COMPUTED_VALUE"""),"03 ORL") -> 03 ORL | T11: =IFERROR(__xludf.DUMMYFUNCTION("""COMPUTED_VALUE"""),"06 ORL") -> 06 ORL
B12: =IF($C12="","",LEFT(C12,3)) -> LRM | C12: =IFERROR(__xludf.DUMMYFUNCTION("""COMPUTED_VALUE"""),"LRM56") -> LRM56 | D12: =IFERROR(__xludf.DUMMYFUNCTION("""COMPUTED_VALUE"""),"ASOCIADOS") -> ASOCIADOS | E12: =IFERROR(__xludf.DUMMYFUNCTION("""COMPUTED_VALUE"""),2026) -> 2026 | F12: =IFERROR(__xludf.DUMMYFUNCTION("""COMPUTED_VALUE"""),1) -> 1 | G12: =IFERROR(__xludf.DUMMYFUNCTION("""COMPUTED_VALUE"""),"Zaragoza- León XIII") -> Zaragoza- León XIII | H12: =IFERROR(__xludf.DUMMYFUNCTION("""COMPUTED_VALUE"""),"C202510711221228") -> C202510711221228 | I12: =IFERROR(__xludf.DUMMYFUNCTION("""COMPUTED_VALUE"""),"MIGUEL ÁNGEL GASCA SANCHO") -> MIGUEL ÁNGEL GASCA SANCHO | J12: =IFERROR(__xludf.DUMMYFUNCTION("""COMPUTED_VALUE"""),45932) -> 45932 | K12: =IFERROR(__xludf.DUMMYFUNCTION("""COMPUTED_VALUE"""),"Factura audífonos") -> Factura audífonos | L12: =IFERROR(__xludf.DUMMYFUNCTION("""COMPUTED_VALUE"""),46031) -> 46031 | M12: =IFERROR(__xludf.DUMMYFUNCTION("""COMPUTED_VALUE"""),"NO") -> NO | N12: =IFERROR(__xludf.DUMMYFUNCTION("""COMPUTED_VALUE"""),2) -> 2 | O12: =IFERROR(__xludf.DUMMYFUNCTION("""COMPUTED_VALUE"""),"CONFORT") -> CONFORT | P12: =IFERROR(__xludf.DUMMYFUNCTION("""COMPUTED_VALUE"""),3424.55) -> 3424.55 | Q12: =IFERROR(__xludf.DUMMYFUNCTION("""COMPUTED_VALUE"""),"Mercè Cabrera") -> Mercè Cabrera | R12: =IFERROR(__xludf.DUMMYFUNCTION("""COMPUTED_VALUE"""),"Jaime Leache Pueyo") -> Jaime Leache Pueyo | S12: =IFERROR(__xludf.DUMMYFUNCTION("""COMPUTED_VALUE"""),"03 ORL") -> 03 ORL | T12: =IFERROR(__xludf.DUMMYFUNCTION("""COMPUTED_VALUE"""),"06 ORL") -> 06 ORL
B13: =IF($C13="","",LEFT(C13,3)) -> MBM | C13: =IFERROR(__xludf.DUMMYFUNCTION("""COMPUTED_VALUE"""),"MBM113") -> MBM113 | D13: =IFERROR(__xludf.DUMMYFUNCTION("""COMPUTED_VALUE"""),"PROPIOS") -> PROPIOS | E13: =IFERROR(__xludf.DUMMYFUNCTION("""COMPUTED_VALUE"""),2026) -> 2026 | F13: =IFERROR(__xludf.DUMMYFUNCTION("""COMPUTED_VALUE"""),1) -> 1 | G13: =IFERROR(__xludf.DUMMYFUNCTION("""COMPUTED_VALUE"""),"Fuenlabrada") -> Fuenlabrada | H13: =IFERROR(__xludf.DUMMYFUNCTION("""COMPUTED_VALUE"""),"C202512151217324826") -> C202512151217324826 | I13: =IFERROR(__xludf.DUMMYFUNCTION("""COMPUTED_VALUE"""),"Mª CARMEN DELGADO ANTON") -> Mª CARMEN DELGADO ANTON | J13: =IFERROR(__xludf.DUMMYFUNCTION("""COMPUTED_VALUE"""),46006) -> 46006 | K13: =IFERROR(__xludf.DUMMYFUNCTION("""COMPUTED_VALUE"""),"Factura audífonos") -> Factura audífonos | L13: =IFERROR(__xludf.DUMMYFUNCTION("""COMPUTED_VALUE"""),46031) -> 46031 | M13: =IFERROR(__xludf.DUMMYFUNCTION("""COMPUTED_VALUE"""),"NO") -> NO | N13: =IFERROR(__xludf.DUMMYFUNCTION("""COMPUTED_VALUE"""),1) -> 1 | O13: =IFERROR(__xludf.DUMMYFUNCTION("""COMPUTED_VALUE"""),"CONFORT") -> CONFORT | P13: =IFERROR(__xludf.DUMMYFUNCTION("""COMPUTED_VALUE"""),2180.91) -> 2180.91 | Q13: =IFERROR(__xludf.DUMMYFUNCTION("""COMPUTED_VALUE"""),"Maika Blázquez") -> Maika Blázquez | R13: =IFERROR(__xludf.DUMMYFUNCTION("""COMPUTED_VALUE"""),"Estefania Miranda Sánchez") -> Estefania Miranda Sánchez | S13: =IFERROR(__xludf.DUMMYFUNCTION("""COMPUTED_VALUE"""),"03 ORL") -> 03 ORL | T13: =IFERROR(__xludf.DUMMYFUNCTION("""COMPUTED_VALUE"""),"06 ORL") -> 06 ORL
B14: =IF($C14="","",LEFT(C14,3)) -> LAA | C14: =IFERROR(__xludf.DUMMYFUNCTION("""COMPUTED_VALUE"""),"LAA54") -> LAA54 | D14: =IFERROR(__xludf.DUMMYFUNCTION("""COMPUTED_VALUE"""),"PROPIOS") -> PROPIOS | E14: =IFERROR(__xludf.DUMMYFUNCTION("""COMPUTED_VALUE"""),2026) -> 2026 | F14: =IFERROR(__xludf.DUMMYFUNCTION("""COMPUTED_VALUE"""),1) -> 1 | G14: =IFERROR(__xludf.DUMMYFUNCTION("""COMPUTED_VALUE"""),"Sevilla- Montoto") -> Sevilla- Montoto | H14: =IFERROR(__xludf.DUMMYFUNCTION("""COMPUTED_VALUE"""),"C2024112910652762") -> C2024112910652762 | I14: =IFERROR(__xludf.DUMMYFUNCTION("""COMPUTED_VALUE"""),"SONIA SUAREZ FERNANDEZ") -> SONIA SUAREZ FERNANDEZ | J14: =IFERROR(__xludf.DUMMYFUNCTION("""COMPUTED_VALUE"""),45623) -> 45623 | K14: =IFERROR(__xludf.DUMMYFUNCTION("""COMPUTED_VALUE"""),"Factura audífonos") -> Factura audífonos | L14: =IFERROR(__xludf.DUMMYFUNCTION("""COMPUTED_VALUE"""),46034) -> 46034 | M14: =IFERROR(__xludf.DUMMYFUNCTION("""COMPUTED_VALUE"""),"NO") -> NO | N14: =IFERROR(__xludf.DUMMYFUNCTION("""COMPUTED_VALUE"""),1) -> 1 | O14: =IFERROR(__xludf.DUMMYFUNCTION("""COMPUTED_VALUE"""),"CONFORT") -> CONFORT | P14: =IFERROR(__xludf.DUMMYFUNCTION("""COMPUTED_VALUE"""),2072.73) -> 2072.73 | Q14: =IFERROR(__xludf.DUMMYFUNCTION("""COMPUTED_VALUE"""),"Luis Alberto Rodríguez") -> Luis Alberto Rodríguez | R14: =IFERROR(__xludf.DUMMYFUNCTION("""COMPUTED_VALUE"""),"María Luisa Calero Ramos") -> María Luisa Calero Ramos | S14: =IFERROR(__xludf.DUMMYFUNCTION("""COMPUTED_VALUE"""),"03 ORL") -> 03 ORL | T14: =IFERROR(__xludf.DUMMYFUNCTION("""COMPUTED_VALUE"""),"06 ORL") -> 06 ORL
B15: =IF($C15="","",LEFT(C15,3)) -> ISL | C15: =IFERROR(__xludf.DUMMYFUNCTION("""COMPUTED_VALUE"""),"ISL99") -> ISL99 | D15: =IFERROR(__xludf.DUMMYFUNCTION("""COMPUTED_VALUE"""),"PROPIOS") -> PROPIOS | E15: =IFERROR(__xludf.DUMMYFUNCTION("""COMPUTED_VALUE"""),2026) -> 2026 | F15: =IFERROR(__xludf.DUMMYFUNCTION("""COMPUTED_VALUE"""),1) -> 1 | G15: =IFERROR(__xludf.DUMMYFUNCTION("""COMPUTED_VALUE"""),"Alicante") -> Alicante | H15: =IFERROR(__xludf.DUMMYFUNCTION("""COMPUTED_VALUE"""),"C202512158433763329") -> C202512158433763329 | I15: =IFERROR(__xludf.DUMMYFUNCTION("""COMPUTED_VALUE"""),"TERESA VENTURA RODRIGUEZ") -> TERESA VENTURA RODRIGUEZ | J15: =IFERROR(__xludf.DUMMYFUNCTION("""COMPUTED_VALUE"""),46006) -> 46006 | K15: =IFERROR(__xludf.DUMMYFUNCTION("""COMPUTED_VALUE"""),"Factura audífonos") -> Factura audífonos | L15: =IFERROR(__xludf.DUMMYFUNCTION("""COMPUTED_VALUE"""),46034) -> 46034 | M15: =IFERROR(__xludf.DUMMYFUNCTION("""COMPUTED_VALUE"""),"NO") -> NO | N15: =IFERROR(__xludf.DUMMYFUNCTION("""COMPUTED_VALUE"""),2) -> 2 | O15: =IFERROR(__xludf.DUMMYFUNCTION("""COMPUTED_VALUE"""),"QUIET") -> QUIET | P15: =IFERROR(__xludf.DUMMYFUNCTION("""COMPUTED_VALUE"""),2718.18) -> 2718.18 | Q15: =IFERROR(__xludf.DUMMYFUNCTION("""COMPUTED_VALUE"""),"Iván Sánchez") -> Iván Sánchez | R15: =IFERROR(__xludf.DUMMYFUNCTION("""COMPUTED_VALUE"""),"Cristina Muñoz Pinto") -> Cristina Muñoz Pinto | S15: =IFERROR(__xludf.DUMMYFUNCTION("""COMPUTED_VALUE"""),"03 ORL") -> 03 ORL | T15: =IFERROR(__xludf.DUMMYFUNCTION("""COMPUTED_VALUE"""),"06 ORL") -> 06 ORL
B16: =IF($C16="","",LEFT(C16,3)) -> MBM | C16: =IFERROR(__xludf.DUMMYFUNCTION("""COMPUTED_VALUE"""),"MBM219") -> MBM219 | D16: =IFERROR(__xludf.DUMMYFUNCTION("""COMPUTED_VALUE"""),"PROPIOS") -> PROPIOS | E16: =IFERROR(__xludf.DUMMYFUNCTION("""COMPUTED_VALUE"""),2026) -> 2026 | F16: =IFERROR(__xludf.DUMMYFUNCTION("""COMPUTED_VALUE"""),1) -> 1 | G16: =IFERROR(__xludf.DUMMYFUNCTION("""COMPUTED_VALUE"""),"Getafe") -> Getafe | H16: =IFERROR(__xludf.DUMMYFUNCTION("""COMPUTED_VALUE"""),"C202511594452200485") -> C202511594452200485 | I16: =IFERROR(__xludf.DUMMYFUNCTION("""COMPUTED_VALUE"""),"JUAN JESÚS MAYA TORREJÓN") -> JUAN JESÚS MAYA TORREJÓN | J16: =IFERROR(__xludf.DUMMYFUNCTION("""COMPUTED_VALUE"""),45966) -> 45966 | K16: =IFERROR(__xludf.DUMMYFUNCTION("""COMPUTED_VALUE"""),"Factura audífonos") -> Factura audífonos | L16: =IFERROR(__xludf.DUMMYFUNCTION("""COMPUTED_VALUE"""),46034) -> 46034 | M16: =IFERROR(__xludf.DUMMYFUNCTION("""COMPUTED_VALUE"""),"NO") -> NO | N16: =IFERROR(__xludf.DUMMYFUNCTION("""COMPUTED_VALUE"""),1) -> 1 | O16: =IFERROR(__xludf.DUMMYFUNCTION("""COMPUTED_VALUE"""),"ADVANCED") -> ADVANCED | P16: =IFERROR(__xludf.DUMMYFUNCTION("""COMPUTED_VALUE"""),2481.82) -> 2481.82 | Q16: =IFERROR(__xludf.DUMMYFUNCTION("""COMPUTED_VALUE"""),"Maika Blázquez") -> Maika Blázquez | R16: =IFERROR(__xludf.DUMMYFUNCTION("""COMPUTED_VALUE"""),"Paula Morales Chacchi") -> Paula Morales Chacchi | S16: =IFERROR(__xludf.DUMMYFUNCTION("""COMPUTED_VALUE"""),"03 ORL") -> 03 ORL | T16: =IFERROR(__xludf.DUMMYFUNCTION("""COMPUTED_VALUE"""),"06 ORL") -> 06 ORL
B17: =IF($C17="","",LEFT(C17,3)) -> LRM | C17: =IFERROR(__xludf.DUMMYFUNCTION("""COMPUTED_VALUE"""),"LRM253") -> LRM253 | D17: =IFERROR(__xludf.DUMMYFUNCTION("""COMPUTED_VALUE"""),"ASOCIADOS") -> ASOCIADOS | E17: =IFERROR(__xludf.DUMMYFUNCTION("""COMPUTED_VALUE"""),2026) -> 2026 | F17: =IFERROR(__xludf.DUMMYFUNCTION("""COMPUTED_VALUE"""),1) -> 1 | G17: =IFERROR(__xludf.DUMMYFUNCTION("""COMPUTED_VALUE"""),"Cáceres") -> Cáceres | H17: =IFERROR(__xludf.DUMMYFUNCTION("""COMPUTED_VALUE"""),"C202512594841242568") -> C202512594841242568 | I17: =IFERROR(__xludf.DUMMYFUNCTION("""COMPUTED_VALUE"""),"MARIA ISABEL GUERRERO CASTRO") -> MARIA ISABEL GUERRERO CASTRO | J17: =IFERROR(__xludf.DUMMYFUNCTION("""COMPUTED_VALUE"""),45996) -> 45996 | K17: =IFERROR(__xludf.DUMMYFUNCTION("""COMPUTED_VALUE"""),"Factura audífonos") -> Factura audífonos | L17: =IFERROR(__xludf.DUMMYFUNCTION("""COMPUTED_VALUE"""),46035) -> 46035 | M17: =IFERROR(__xludf.DUMMYFUNCTION("""COMPUTED_VALUE"""),"NO") -> NO | N17: =IFERROR(__xludf.DUMMYFUNCTION("""COMPUTED_VALUE"""),1) -> 1 | O17: =IFERROR(__xludf.DUMMYFUNCTION("""COMPUTED_VALUE"""),"PRO") -> PRO | P17: =IFERROR(__xludf.DUMMYFUNCTION("""COMPUTED_VALUE"""),2745) -> 2745 | Q17: =IFERROR(__xludf.DUMMYFUNCTION("""COMPUTED_VALUE"""),"Lisandro Russian") -> Lisandro Russian | R17: =IFERROR(__xludf.DUMMYFUNCTION("""COMPUTED_VALUE"""),"Marta García Jiménez") -> Marta García Jiménez | S17: =IFERROR(__xludf.DUMMYFUNCTION("""COMPUTED_VALUE"""),"03 ORL") -> 03 ORL | T17: =IFERROR(__xludf.DUMMYFUNCTION("""COMPUTED_VALUE"""),"06 ORL") -> 06 ORL
B18: =IF($C18="","",LEFT(C18,3)) -> MBM | C18: =IFERROR(__xludf.DUMMYFUNCTION("""COMPUTED_VALUE"""),"MBM104") -> MBM104 | D18: =IFERROR(__xludf.DUMMYFUNCTION("""COMPUTED_VALUE"""),"PROPIOS") -> PROPIOS | E18: =IFERROR(__xludf.DUMMYFUNCTION("""COMPUTED_VALUE"""),2026) -> 2026 | F18: =IFERROR(__xludf.DUMMYFUNCTION("""COMPUTED_VALUE"""),1) -> 1 | G18: =IFERROR(__xludf.DUMMYFUNCTION("""COMPUTED_VALUE"""),"Fuenlabrada") -> Fuenlabrada | H18: =IFERROR(__xludf.DUMMYFUNCTION("""COMPUTED_VALUE"""),"C202512179181772442") -> C202512179181772442 | I18: =IFERROR(__xludf.DUMMYFUNCTION("""COMPUTED_VALUE"""),"CARMEN DIOS CAAMAÑO") -> CARMEN DIOS CAAMAÑO | J18: =IFERROR(__xludf.DUMMYFUNCTION("""COMPUTED_VALUE"""),46008) -> 46008 | K18: =IFERROR(__xludf.DUMMYFUNCTION("""COMPUTED_VALUE"""),"Factura audífonos") -> Factura audífonos | L18: =IFERROR(__xludf.DUMMYFUNCTION("""COMPUTED_VALUE"""),46035) -> 46035 | M18: =IFERROR(__xludf.DUMMYFUNCTION("""COMPUTED_VALUE"""),"NO") -> NO | N18: =IFERROR(__xludf.DUMMYFUNCTION("""COMPUTED_VALUE"""),1) -> 1 | O18: =IFERROR(__xludf.DUMMYFUNCTION("""COMPUTED_VALUE"""),"CONFORT") -> CONFORT | P18: =IFERROR(__xludf.DUMMYFUNCTION("""COMPUTED_VALUE"""),2180.91) -> 2180.91 | Q18: =IFERROR(__xludf.DUMMYFUNCTION("""COMPUTED_VALUE"""),"Maika Blázquez") -> Maika Blázquez | R18: =IFERROR(__xludf.DUMMYFUNCTION("""COMPUTED_VALUE"""),"Concepcion Rodríguez Izquierdo") -> Concepcion Rodríguez Izquierdo | S18: =IFERROR(__xludf.DUMMYFUNCTION("""COMPUTED_VALUE"""),"03 ORL") -> 03 ORL | T18: =IFERROR(__xludf.DUMMYFUNCTION("""COMPUTED_VALUE"""),"06 ORL") -> 06 ORL
B19: =IF($C19="","",LEFT(C19,3)) -> ISL | C19: =IFERROR(__xludf.DUMMYFUNCTION("""COMPUTED_VALUE"""),"ISL91") -> ISL91 | D19: =IFERROR(__xludf.DUMMYFUNCTION("""COMPUTED_VALUE"""),"PROPIOS") -> PROPIOS | E19: =IFERROR(__xludf.DUMMYFUNCTION("""COMPUTED_VALUE"""),2026) -> 2026 | F19: =IFERROR(__xludf.DUMMYFUNCTION("""COMPUTED_VALUE"""),1) -> 1 | G19: =IFERROR(__xludf.DUMMYFUNCTION("""COMPUTED_VALUE"""),"Murcia") -> Murcia | H19: =IFERROR(__xludf.DUMMYFUNCTION("""COMPUTED_VALUE"""),"C202512121136583127") -> C202512121136583127 | I19: =IFERROR(__xludf.DUMMYFUNCTION("""COMPUTED_VALUE"""),"JESUS MORENO LOPEZ") -> JESUS MORENO LOPEZ | J19: =IFERROR(__xludf.DUMMYFUNCTION("""COMPUTED_VALUE"""),46003) -> 46003 | K19: =IFERROR(__xludf.DUMMYFUNCTION("""COMPUTED_VALUE"""),"Factura audífonos") -> Factura audífonos | L19: =IFERROR(__xludf.DUMMYFUNCTION("""COMPUTED_VALUE"""),46035) -> 46035 | M19: =IFERROR(__xludf.DUMMYFUNCTION("""COMPUTED_VALUE"""),"NO") -> NO | N19: =IFERROR(__xludf.DUMMYFUNCTION("""COMPUTED_VALUE"""),2) -> 2 | O19: =IFERROR(__xludf.DUMMYFUNCTION("""COMPUTED_VALUE"""),"QUIET") -> QUIET | P19: =IFERROR(__xludf.DUMMYFUNCTION("""COMPUTED_VALUE"""),2580.77) -> 2580.77 | Q19: =IFERROR(__xludf.DUMMYFUNCTION("""COMPUTED_VALUE"""),"Iván Sánchez") -> Iván Sánchez | R19: =IFERROR(__xludf.DUMMYFUNCTION("""COMPUTED_VALUE"""),"Alejandra Jara Maquilón") -> Alejandra Jara Maquilón | S19: =IFERROR(__xludf.DUMMYFUNCTION("""COMPUTED_VALUE"""),"03 ORL") -> 03 ORL | T19: =IFERROR(__xludf.DUMMYFUNCTION("""COMPUTED_VALUE"""),"06 ORL") -> 06 ORL
B20: =IF($C20="","",LEFT(C20,3)) -> LAA | C20: =IFERROR(__xludf.DUMMYFUNCTION("""COMPUTED_VALUE"""),"LAA13") -> LAA13 | D20: =IFERROR(__xludf.DUMMYFUNCTION("""COMPUTED_VALUE"""),"PROPIOS") -> PROPIOS | E20: =IFERROR(__xludf.DUMMYFUNCTION("""COMPUTED_VALUE"""),2026) -> 2026 | F20: =IFERROR(__xludf.DUMMYFUNCTION("""COMPUTED_VALUE"""),1) -> 1 | G20: =IFERROR(__xludf.DUMMYFUNCTION("""COMPUTED_VALUE"""),"Sevilla- Montoto") -> Sevilla- Montoto | H20: =IFERROR(__xludf.DUMMYFUNCTION("""COMPUTED_VALUE"""),"C202511241120341965") -> C202511241120341965 | I20: =IFERROR(__xludf.DUMMYFUNCTION("""COMPUTED_VALUE"""),"MIGUEL FONTANILLA RABANEDA") -> MIGUEL FONTANILLA RABANEDA | J20: =IFERROR(__xludf.DUMMYFUNCTION("""COMPUTED_VALUE"""),45985) -> 45985 | K20: =IFERROR(__xludf.DUMMYFUNCTION("""COMPUTED_VALUE"""),"Factura audífonos") -> Factura audífonos | L20: =IFERROR(__xludf.DUMMYFUNCTION("""COMPUTED_VALUE"""),46036) -> 46036 | M20: =IFERROR(__xludf.DUMMYFUNCTION("""COMPUTED_VALUE"""),"NO") -> NO | N20: =IFERROR(__xludf.DUMMYFUNCTION("""COMPUTED_VALUE"""),2) -> 2 | O20: =IFERROR(__xludf.DUMMYFUNCTION("""COMPUTED_VALUE"""),"CONFORT") -> CONFORT | P20: =IFERROR(__xludf.DUMMYFUNCTION("""COMPUTED_VALUE"""),3631.82) -> 3631.82 | Q20: =IFERROR(__xludf.DUMMYFUNCTION("""COMPUTED_VALUE"""),"Luis Alberto Rodríguez") -> Luis Alberto Rodríguez | R20: =IFERROR(__xludf.DUMMYFUNCTION("""COMPUTED_VALUE"""),"Francisco Javier Aguilar Vera") -> Francisco Javier Aguilar Vera | S20: =IFERROR(__xludf.DUMMYFUNCTION("""COMPUTED_VALUE"""),"01 MARKETING ON LINE") -> 01 MARKETING ON LINE | T20: =IFERROR(__xludf.DUMMYFUNCTION("""COMPUTED_VALUE"""),"04 AUDIFONO,ES") -> 04 AUDIFONO,ES
B21: =IF($C21="","",LEFT(C21,3)) -> MBM | C21: =IFERROR(__xludf.DUMMYFUNCTION("""COMPUTED_VALUE"""),"MBM110") -> MBM110 | D21: =IFERROR(__xludf.DUMMYFUNCTION("""COMPUTED_VALUE"""),"PARTICIPADOS") -> PARTICIPADOS | E21: =IFERROR(__xludf.DUMMYFUNCTION("""COMPUTED_VALUE"""),2026) -> 2026 | F21: =IFERROR(__xludf.DUMMYFUNCTION("""COMPUTED_VALUE"""),1) -> 1 | G21: =IFERROR(__xludf.DUMMYFUNCTION("""COMPUTED_VALUE"""),"Madrid- La Oca") -> Madrid- La Oca | H21: =IFERROR(__xludf.DUMMYFUNCTION("""COMPUTED_VALUE"""),"C202512111114179041") -> C202512111114179041 | I21: =IFERROR(__xludf.DUMMYFUNCTION("""COMPUTED_VALUE"""),"PEDRO DOMINGO NAVARRO DIAZ") -> PEDRO DOMINGO NAVARRO DIAZ | J21: =IFERROR(__xludf.DUMMYFUNCTION("""COMPUTED_VALUE"""),46002) -> 46002 | K21: =IFERROR(__xludf.DUMMYFUNCTION("""COMPUTED_VALUE"""),"Factura audífonos") -> Factura audífonos | L21: =IFERROR(__xludf.DUMMYFUNCTION("""COMPUTED_VALUE"""),46036) -> 46036 | M21: =IFERROR(__xludf.DUMMYFUNCTION("""COMPUTED_VALUE"""),"NO") -> NO | N21: =IFERROR(__xludf.DUMMYFUNCTION("""COMPUTED_VALUE"""),2) -> 2 | O21: =IFERROR(__xludf.DUMMYFUNCTION("""COMPUTED_VALUE"""),"QUIET") -> QUIET | P21: =IFERROR(__xludf.DUMMYFUNCTION("""COMPUTED_VALUE"""),2581.82) -> 2581.82 | Q21: =IFERROR(__xludf.DUMMYFUNCTION("""COMPUTED_VALUE"""),"Maika Blázquez") -> Maika Blázquez | R21: =IFERROR(__xludf.DUMMYFUNCTION("""COMPUTED_VALUE"""),"Diana Hernán Pérez") -> Diana Hernán Pérez | S21: =IFERROR(__xludf.DUMMYFUNCTION("""COMPUTED_VALUE"""),"03 ORL") -> 03 ORL | T21: =IFERROR(__xludf.DUMMYFUNCTION("""COMPUTED_VALUE"""),"06 ORL") -> 06 ORL
B22: =IF($C22="","",LEFT(C22,3)) -> ISL | C22: =IFERROR(__xludf.DUMMYFUNCTION("""COMPUTED_VALUE"""),"ISL150") -> ISL150 | D22: =IFERROR(__xludf.DUMMYFUNCTION("""COMPUTED_VALUE"""),"PROPIOS") -> PROPIOS | E22: =IFERROR(__xludf.DUMMYFUNCTION("""COMPUTED_VALUE"""),2026) -> 2026 | F22: =IFERROR(__xludf.DUMMYFUNCTION("""COMPUTED_VALUE"""),1) -> 1 | G22: =IFERROR(__xludf.DUMMYFUNCTION("""COMPUTED_VALUE"""),"Toledo") -> Toledo | H22: =IFERROR(__xludf.DUMMYFUNCTION("""COMPUTED_VALUE"""),"C202512231029369451") -> C202512231029369451 | I22: =IFERROR(__xludf.DUMMYFUNCTION("""COMPUTED_VALUE"""),"Dolores Sanz Contreras") -> Dolores Sanz Contreras | J22: =IFERROR(__xludf.DUMMYFUNCTION("""COMPUTED_VALUE"""),46014) -> 46014 | K22: =IFERROR(__xludf.DUMMYFUNCTION("""COMPUTED_VALUE"""),"Factura audífonos") -> Factura audífonos | L22: =IFERROR(__xludf.DUMMYFUNCTION("""COMPUTED_VALUE"""),46036) -> 46036 | M22: =IFERROR(__xludf.DUMMYFUNCTION("""COMPUTED_VALUE"""),"NO") -> NO | N22: =IFERROR(__xludf.DUMMYFUNCTION("""COMPUTED_VALUE"""),1) -> 1 | O22: =IFERROR(__xludf.DUMMYFUNCTION("""COMPUTED_VALUE"""),"QUIET") -> QUIET | P22: =IFERROR(__xludf.DUMMYFUNCTION("""COMPUTED_VALUE"""),1550.23) -> 1550.23 | Q22: =IFERROR(__xludf.DUMMYFUNCTION("""COMPUTED_VALUE"""),"Lisandro Russian") -> Lisandro Russian | R22: =IFERROR(__xludf.DUMMYFUNCTION("""COMPUTED_VALUE"""),"Alejandra Alvarado Namen") -> Alejandra Alvarado Namen | S22: =IFERROR(__xludf.DUMMYFUNCTION("""COMPUTED_VALUE"""),"03 ORL") -> 03 ORL | T22: =IFERROR(__xludf.DUMMYFUNCTION("""COMPUTED_VALUE"""),"06 ORL") -> 06 ORL
B23: =IF($C23="","",LEFT(C23,3)) -> MBM | C23: =IFERROR(__xludf.DUMMYFUNCTION("""COMPUTED_VALUE"""),"MBM52") -> MBM52 | D23: =IFERROR(__xludf.DUMMYFUNCTION("""COMPUTED_VALUE"""),"PARTICIPADOS") -> PARTICIPADOS | E23: =IFERROR(__xludf.DUMMYFUNCTION("""COMPUTED_VALUE"""),2026) -> 2026 | F23: =IFERROR(__xludf.DUMMYFUNCTION("""COMPUTED_VALUE"""),1) -> 1 | G23: =IFERROR(__xludf.DUMMYFUNCTION("""COMPUTED_VALUE"""),"Madrid- La Oca") -> Madrid- La Oca | H23: =IFERROR(__xludf.DUMMYFUNCTION("""COMPUTED_VALUE"""),"C202512911118838876") -> C202512911118838876 | I23: =IFERROR(__xludf.DUMMYFUNCTION("""COMPUTED_VALUE"""),"MARIA JOSEFA DE MELCHOR DIEZ") -> MARIA JOSEFA DE MELCHOR DIEZ | J23: =IFERROR(__xludf.DUMMYFUNCTION("""COMPUTED_VALUE"""),46000) -> 46000 | K23: =IFERROR(__xludf.DUMMYFUNCTION("""COMPUTED_VALUE"""),"Factura audífonos") -> Factura audífonos | L23: =IFERROR(__xludf.DUMMYFUNCTION("""COMPUTED_VALUE"""),46036) -> 46036 | M23: =IFERROR(__xludf.DUMMYFUNCTION("""COMPUTED_VALUE"""),"NO") -> NO | N23: =IFERROR(__xludf.DUMMYFUNCTION("""COMPUTED_VALUE"""),2) -> 2 | O23: =IFERROR(__xludf.DUMMYFUNCTION("""COMPUTED_VALUE"""),"CONFORT") -> CONFORT | P23: =IFERROR(__xludf.DUMMYFUNCTION("""COMPUTED_VALUE"""),3631.82) -> 3631.82 | Q23: =IFERROR(__xludf.DUMMYFUNCTION("""COMPUTED_VALUE"""),"Maika Blázquez") -> Maika Blázquez | R23: =IFERROR(__xludf.DUMMYFUNCTION("""COMPUTED_VALUE"""),"José Joaquín Gutiérrez Barquín") -> José Joaquín Gutiérrez Barquín | S23: =IFERROR(__xludf.DUMMYFUNCTION("""COMPUTED_VALUE"""),"03 ORL") -> 03 ORL | T23: =IFERROR(__xludf.DUMMYFUNCTION("""COMPUTED_VALUE"""),"06 ORL") -> 06 ORL
B24: =IF($C24="","",LEFT(C24,3)) -> LRM | C24: =IFERROR(__xludf.DUMMYFUNCTION("""COMPUTED_VALUE"""),"LRM239") -> LRM239 | D24: =IFERROR(__xludf.DUMMYFUNCTION("""COMPUTED_VALUE"""),"PROPIOS") -> PROPIOS | E24: =IFERROR(__xludf.DUMMYFUNCTION("""COMPUTED_VALUE"""),2026) -> 2026 | F24: =IFERROR(__xludf.DUMMYFUNCTION("""COMPUTED_VALUE"""),1) -> 1 | G24: =IFERROR(__xludf.DUMMYFUNCTION("""COMPUTED_VALUE"""),"Madrid- Juan Bravo") -> Madrid- Juan Bravo | H24: =IFERROR(__xludf.DUMMYFUNCTION("""COMPUTED_VALUE"""),"C202512181052238972") -> C202512181052238972 | I24: =IFERROR(__xludf.DUMMYFUNCTION("""COMPUTED_VALUE"""),"CONCEPCION FERNANDEZ LOPEZ") -> CONCEPCION FERNANDEZ LOPEZ | J24: =IFERROR(__xludf.DUMMYFUNCTION("""COMPUTED_VALUE"""),46009) -> 46009 | K24: =IFERROR(__xludf.DUMMYFUNCTION("""COMPUTED_VALUE"""),"Factura audífonos") -> Factura audífonos | L24: =IFERROR(__xludf.DUMMYFUNCTION("""COMPUTED_VALUE"""),46036) -> 46036 | M24: =IFERROR(__xludf.DUMMYFUNCTION("""COMPUTED_VALUE"""),"NO") -> NO | N24: =IFERROR(__xludf.DUMMYFUNCTION("""COMPUTED_VALUE"""),2) -> 2 | O24: =IFERROR(__xludf.DUMMYFUNCTION("""COMPUTED_VALUE"""),"ADVANCED") -> ADVANCED | P24: =IFERROR(__xludf.DUMMYFUNCTION("""COMPUTED_VALUE"""),3929.55) -> 3929.55 | Q24: =IFERROR(__xludf.DUMMYFUNCTION("""COMPUTED_VALUE"""),"Lisandro Russian") -> Lisandro Russian | R24: =IFERROR(__xludf.DUMMYFUNCTION("""COMPUTED_VALUE"""),"Carlos Barajas del Rosal") -> Carlos Barajas del Rosal | S24: =IFERROR(__xludf.DUMMYFUNCTION("""COMPUTED_VALUE"""),"03 ORL") -> 03 ORL | T24: =IFERROR(__xludf.DUMMYFUNCTION("""COMPUTED_VALUE"""),"06 ORL") -> 06 ORL
B25: =IF($C25="","",LEFT(C25,3)) | D25: =IFERROR(__xludf.DUMMYFUNCTION("""COMPUTED_VALUE"""),"PARTICIPADOS") -> PARTICIPADOS | E25: =IFERROR(__xludf.DUMMYFUNCTION("""COMPUTED_VALUE"""),2026) -> 2026 | F25: =IFERROR(__xludf.DUMMYFUNCTION("""COMPUTED_VALUE"""),1) -> 1 | G25: =IFERROR(__xludf.DUMMYFUNCTION("""COMPUTED_VALUE"""),"Ourense") -> Ourense | H25: =IFERROR(__xludf.DUMMYFUNCTION("""COMPUTED_VALUE"""),"C202511241525371421") -> C202511241525371421 | I25: =IFERROR(__xludf.DUMMYFUNCTION("""COMPUTED_VALUE"""),"ESTHER CAMINO BLANCO") -> ESTHER CAMINO BLANCO | J25: =IFERROR(__xludf.DUMMYFUNCTION("""COMPUTED_VALUE"""),45985) -> 45985 | K25: =IFERROR(__xludf.DUMMYFUNCTION("""COMPUTED_VALUE"""),"Factura audífonos") -> Factura audífonos | L25: =IFERROR(__xludf.DUMMYFUNCTION("""COMPUTED_VALUE"""),46036) -> 46036 | M25: =IFERROR(__xludf.DUMMYFUNCTION("""COMPUTED_VALUE"""),"NO") -> NO | N25: =IFERROR(__xludf.DUMMYFUNCTION("""COMPUTED_VALUE"""),2) -> 2 | O25: =IFERROR(__xludf.DUMMYFUNCTION("""COMPUTED_VALUE"""),"CONFORT") -> CONFORT | P25: =IFERROR(__xludf.DUMMYFUNCTION("""COMPUTED_VALUE"""),3631.82) -> 3631.82 | Q25: =IFERROR(__xludf.DUMMYFUNCTION("""COMPUTED_VALUE"""),"Alberto Moreno") -> Alberto Moreno | R25: =IFERROR(__xludf.DUMMYFUNCTION("""COMPUTED_VALUE"""),"No recuerda ORL") -> No recuerda ORL | S25: =IFERROR(__xludf.DUMMYFUNCTION("""COMPUTED_VALUE"""),"03 ORL") -> 03 ORL | T25: =IFERROR(__xludf.DUMMYFUNCTION("""COMPUTED_VALUE"""),"06 ORL") -> 06 ORL
B26: =IF($C26="","",LEFT(C26,3)) -> MBM | C26: =IFERROR(__xludf.DUMMYFUNCTION("""COMPUTED_VALUE"""),"MBM124") -> MBM124 | D26: =IFERROR(__xludf.DUMMYFUNCTION("""COMPUTED_VALUE"""),"PROPIOS") -> PROPIOS | E26: =IFERROR(__xludf.DUMMYFUNCTION("""COMPUTED_VALUE"""),2026) -> 2026 | F26: =IFERROR(__xludf.DUMMYFUNCTION("""COMPUTED_VALUE"""),1) -> 1 | G26: =IFERROR(__xludf.DUMMYFUNCTION("""COMPUTED_VALUE"""),"Fuenlabrada") -> Fuenlabrada | H26: =IFERROR(__xludf.DUMMYFUNCTION("""COMPUTED_VALUE"""),"C202512171612178703") -> C202512171612178703 | I26: =IFERROR(__xludf.DUMMYFUNCTION("""COMPUTED_VALUE"""),"EMILIO CAMACHO BALLERO") -> EMILIO CAMACHO BALLERO | J26: =IFERROR(__xludf.DUMMYFUNCTION("""COMPUTED_VALUE"""),46008) -> 46008 | K26: =IFERROR(__xludf.DUMMYFUNCTION("""COMPUTED_VALUE"""),"Factura audífonos") -> Factura audífonos | L26: =IFERROR(__xludf.DUMMYFUNCTION("""COMPUTED_VALUE"""),46037) -> 46037 | M26: =IFERROR(__xludf.DUMMYFUNCTION("""COMPUTED_VALUE"""),"NO") -> NO | N26: =IFERROR(__xludf.DUMMYFUNCTION("""COMPUTED_VALUE"""),2) -> 2 | O26: =IFERROR(__xludf.DUMMYFUNCTION("""COMPUTED_VALUE"""),"PRO") -> PRO | P26: =IFERROR(__xludf.DUMMYFUNCTION("""COMPUTED_VALUE"""),4536.36) -> 4536.36 | Q26: =IFERROR(__xludf.DUMMYFUNCTION("""COMPUTED_VALUE"""),"Maika Blázquez") -> Maika Blázquez | R26: =IFERROR(__xludf.DUMMYFUNCTION("""COMPUTED_VALUE"""),"Ithzel Maria Villarreal Patiño") -> Ithzel Maria Villarreal Patiño | S26: =IFERROR(__xludf.DUMMYFUNCTION("""COMPUTED_VALUE"""),"03 ORL") -> 03 ORL | T26: =IFERROR(__xludf.DUMMYFUNCTION("""COMPUTED_VALUE"""),"06 ORL") -> 06 ORL
B27: =IF($C27="","",LEFT(C27,3)) -> RPG | C27: =IFERROR(__xludf.DUMMYFUNCTION("""COMPUTED_VALUE"""),"RPG30") -> RPG30 | D27: =IFERROR(__xludf.DUMMYFUNCTION("""COMPUTED_VALUE"""),"PARTICIPADOS") -> PARTICIPADOS | E27: =IFERROR(__xludf.DUMMYFUNCTION("""COMPUTED_VALUE"""),2026) -> 2026 | F27: =IFERROR(__xludf.DUMMYFUNCTION("""COMPUTED_VALUE"""),1) -> 1 | G27: =IFERROR(__xludf.DUMMYFUNCTION("""COMPUTED_VALUE"""),"Lugo") -> Lugo | H27: =IFERROR(__xludf.DUMMYFUNCTION("""COMPUTED_VALUE"""),"C202512318124615792") -> C202512318124615792 | I27: =IFERROR(__xludf.DUMMYFUNCTION("""COMPUTED_VALUE"""),"ANDRES BARREIRO LOIS") -> ANDRES BARREIRO LOIS | J27: =IFERROR(__xludf.DUMMYFUNCTION("""COMPUTED_VALUE"""),45994) -> 45994 | K27: =IFERROR(__xludf.DUMMYFUNCTION("""COMPUTED_VALUE"""),"Factura audífonos") -> Factura audífonos | L27: =IFERROR(__xludf.DUMMYFUNCTION("""COMPUTED_VALUE"""),46037) -> 46037 | M27: =IFERROR(__xludf.DUMMYFUNCTION("""COMPUTED_VALUE"""),"NO") -> NO | N27: =IFERROR(__xludf.DUMMYFUNCTION("""COMPUTED_VALUE"""),2) -> 2 | O27: =IFERROR(__xludf.DUMMYFUNCTION("""COMPUTED_VALUE"""),"ADVANCED") -> ADVANCED | P27: =IFERROR(__xludf.DUMMYFUNCTION("""COMPUTED_VALUE"""),3929.09) -> 3929.09 | Q27: =IFERROR(__xludf.DUMMYFUNCTION("""COMPUTED_VALUE"""),"Alberto Moreno") -> Alberto Moreno | R27: =IFERROR(__xludf.DUMMYFUNCTION("""COMPUTED_VALUE"""),"Pedro Juiz López") -> Pedro Juiz López | S27: =IFERROR(__xludf.DUMMYFUNCTION("""COMPUTED_VALUE"""),"03 ORL") -> 03 ORL | T27: =IFERROR(__xludf.DUMMYFUNCTION("""COMPUTED_VALUE"""),"06 ORL") -> 06 ORL
B28: =IF($C28="","",LEFT(C28,3)) -> MBM | C28: =IFERROR(__xludf.DUMMYFUNCTION("""COMPUTED_VALUE"""),"MBM21") -> MBM21 | D28: =IFERROR(__xludf.DUMMYFUNCTION("""COMPUTED_VALUE"""),"PARTICIPADOS") -> PARTICIPADOS | E28: =IFERROR(__xludf.DUMMYFUNCTION("""COMPUTED_VALUE"""),2026) -> 2026 | F28: =IFERROR(__xludf.DUMMYFUNCTION("""COMPUTED_VALUE"""),1) -> 1 | G28: =IFERROR(__xludf.DUMMYFUNCTION("""COMPUTED_VALUE"""),"Madrid- La Oca") -> Madrid- La Oca | H28: =IFERROR(__xludf.DUMMYFUNCTION("""COMPUTED_VALUE"""),"C202511201642289976") -> C202511201642289976 | I28: =IFERROR(__xludf.DUMMYFUNCTION("""COMPUTED_VALUE"""),"MANUELA LLAMAS DE PAZ") -> MANUELA LLAMAS DE PAZ | J28: =IFERROR(__xludf.DUMMYFUNCTION("""COMPUTED_VALUE"""),45981) -> 45981 | K28: =IFERROR(__xludf.DUMMYFUNCTION("""COMPUTED_VALUE"""),"Factura audífonos") -> Factura audífonos | L28: =IFERROR(__xludf.DUMMYFUNCTION("""COMPUTED_VALUE"""),46037) -> 46037 | M28: =IFERROR(__xludf.DUMMYFUNCTION("""COMPUTED_VALUE"""),"NO") -> NO | N28: =IFERROR(__xludf.DUMMYFUNCTION("""COMPUTED_VALUE"""),2) -> 2 | O28: =IFERROR(__xludf.DUMMYFUNCTION("""COMPUTED_VALUE"""),"QUIET") -> QUIET | P28: =IFERROR(__xludf.DUMMYFUNCTION("""COMPUTED_VALUE"""),2581.82) -> 2581.82 | Q28: =IFERROR(__xludf.DUMMYFUNCTION("""COMPUTED_VALUE"""),"Maika Blázquez") -> Maika Blázquez | R28: =IFERROR(__xludf.DUMMYFUNCTION("""COMPUTED_VALUE"""),"Félix Rodríguez Paz") -> Félix Rodríguez Paz | S28: =IFERROR(__xludf.DUMMYFUNCTION("""COMPUTED_VALUE"""),"03 ORL") -> 03 ORL | T28: =IFERROR(__xludf.DUMMYFUNCTION("""COMPUTED_VALUE"""),"06 ORL") -> 06 ORL
B29: =IF($C29="","",LEFT(C29,3)) -> MBM | C29: =IFERROR(__xludf.DUMMYFUNCTION("""COMPUTED_VALUE"""),"MBM50") -> MBM50 | D29: =IFERROR(__xludf.DUMMYFUNCTION("""COMPUTED_VALUE"""),"PROPIOS") -> PROPIOS | E29: =IFERROR(__xludf.DUMMYFUNCTION("""COMPUTED_VALUE"""),2026) -> 2026 | F29: =IFERROR(__xludf.DUMMYFUNCTION("""COMPUTED_VALUE"""),1) -> 1 | G29: =IFERROR(__xludf.DUMMYFUNCTION("""COMPUTED_VALUE"""),"Madrid- Canillas") -> Madrid- Canillas | H29: =IFERROR(__xludf.DUMMYFUNCTION("""COMPUTED_VALUE"""),"C202511271715586820") -> C202511271715586820 | I29: =IFERROR(__xludf.DUMMYFUNCTION("""COMPUTED_VALUE"""),"ROSA DE LA FLOR GONZÁLEZ") -> ROSA DE LA FLOR GONZÁLEZ | J29: =IFERROR(__xludf.DUMMYFUNCTION("""COMPUTED_VALUE"""),45988) -> 45988 | K29: =IFERROR(__xludf.DUMMYFUNCTION("""COMPUTED_VALUE"""),"Factura audífonos") -> Factura audífonos | L29: =IFERROR(__xludf.DUMMYFUNCTION("""COMPUTED_VALUE"""),46037) -> 46037 | M29: =IFERROR(__xludf.DUMMYFUNCTION("""COMPUTED_VALUE"""),"NO") -> NO | N29: =IFERROR(__xludf.DUMMYFUNCTION("""COMPUTED_VALUE"""),2) -> 2 | O29: =IFERROR(__xludf.DUMMYFUNCTION("""COMPUTED_VALUE"""),"QUIET") -> QUIET | P29: =IFERROR(__xludf.DUMMYFUNCTION("""COMPUTED_VALUE"""),2718.18) -> 2718.18 | Q29: =IFERROR(__xludf.DUMMYFUNCTION("""COMPUTED_VALUE"""),"Maika Blázquez") -> Maika Blázquez | R29: =IFERROR(__xludf.DUMMYFUNCTION("""COMPUTED_VALUE"""),"José Gustavo Barroso Braojos") -> José Gustavo Barroso Braojos | S29: =IFERROR(__xludf.DUMMYFUNCTION("""COMPUTED_VALUE"""),"03 ORL") -> 03 ORL | T29: =IFERROR(__xludf.DUMMYFUNCTION("""COMPUTED_VALUE"""),"06 ORL") -> 06 ORL
B30: =IF($C30="","",LEFT(C30,3)) -> MBM | C30: =IFERROR(__xludf.DUMMYFUNCTION("""COMPUTED_VALUE"""),"MBM39") -> MBM39 | D30: =IFERROR(__xludf.DUMMYFUNCTION("""COMPUTED_VALUE"""),"PROPIOS") -> PROPIOS | E30: =IFERROR(__xludf.DUMMYFUNCTION("""COMPUTED_VALUE"""),2026) -> 2026 | F30: =IFERROR(__xludf.DUMMYFUNCTION("""COMPUTED_VALUE"""),1) -> 1 | G30: =IFERROR(__xludf.DUMMYFUNCTION("""COMPUTED_VALUE"""),"Madrid- Juan Bravo") -> Madrid- Juan Bravo | H30: =IFERROR(__xludf.DUMMYFUNCTION("""COMPUTED_VALUE"""),"C202512191021357942") -> C202512191021357942 | I30: =IFERROR(__xludf.DUMMYFUNCTION("""COMPUTED_VALUE"""),"LUCAS ROMERO MILLAN") -> LUCAS ROMERO MILLAN | J30: =IFERROR(__xludf.DUMMYFUNCTION("""COMPUTED_VALUE"""),46010) -> 46010 | K30: =IFERROR(__xludf.DUMMYFUNCTION("""COMPUTED_VALUE"""),"Factura audífonos") -> Factura audífonos | L30: =IFERROR(__xludf.DUMMYFUNCTION("""COMPUTED_VALUE"""),46038) -> 46038 | M30: =IFERROR(__xludf.DUMMYFUNCTION("""COMPUTED_VALUE"""),"NO") -> NO | N30: =IFERROR(__xludf.DUMMYFUNCTION("""COMPUTED_VALUE"""),1) -> 1 | O30: =IFERROR(__xludf.DUMMYFUNCTION("""COMPUTED_VALUE"""),"CONFORT") -> CONFORT | P30: =IFERROR(__xludf.DUMMYFUNCTION("""COMPUTED_VALUE"""),2180.91) -> 2180.91 | Q30: =IFERROR(__xludf.DUMMYFUNCTION("""COMPUTED_VALUE"""),"Maika Blázquez") -> Maika Blázquez | R30: =IFERROR(__xludf.DUMMYFUNCTION("""COMPUTED_VALUE"""),"Javier García Domínguez") -> Javier García Domínguez | S30: =IFERROR(__xludf.DUMMYFUNCTION("""COMPUTED_VALUE"""),"03 ORL") -> 03 ORL | T30: =IFERROR(__xludf.DUMMYFUNCTION("""COMPUTED_VALUE"""),"06 ORL") -> 06 ORL
B31: =IF($C31="","",LEFT(C31,3)) -> LRM | C31: =IFERROR(__xludf.DUMMYFUNCTION("""COMPUTED_VALUE"""),"LRM113") -> LRM113 | D31: =IFERROR(__xludf.DUMMYFUNCTION("""COMPUTED_VALUE"""),"ASOCIADOS") -> ASOCIADOS | E31: =IFERROR(__xludf.DUMMYFUNCTION("""COMPUTED_VALUE"""),2026) -> 2026 | F31: =IFERROR(__xludf.DUMMYFUNCTION("""COMPUTED_VALUE"""),1) -> 1 | G31: =IFERROR(__xludf.DUMMYFUNCTION("""COMPUTED_VALUE"""),"Cáceres") -> Cáceres | H31: =IFERROR(__xludf.DUMMYFUNCTION("""COMPUTED_VALUE"""),"C202512161810167638") -> C202512161810167638 | I31: =IFERROR(__xludf.DUMMYFUNCTION("""COMPUTED_VALUE"""),"PEDRO BARROSO PEREZ") -> PEDRO BARROSO PEREZ | J31: =IFERROR(__xludf.DUMMYFUNCTION("""COMPUTED_VALUE"""),46007) -> 46007 | K31: =IFERROR(__xludf.DUMMYFUNCTION("""COMPUTED_VALUE"""),"Factura audífonos") -> Factura audífonos | L31: =IFERROR(__xludf.DUMMYFUNCTION("""COMPUTED_VALUE"""),46038) -> 46038 | M31: =IFERROR(__xludf.DUMMYFUNCTION("""COMPUTED_VALUE"""),"NO") -> NO | N31: =IFERROR(__xludf.DUMMYFUNCTION("""COMPUTED_VALUE"""),2) -> 2 | O31: =IFERROR(__xludf.DUMMYFUNCTION("""COMPUTED_VALUE"""),"QUIET") -> QUIET | P31: =IFERROR(__xludf.DUMMYFUNCTION("""COMPUTED_VALUE"""),3583.64) -> 3583.64 | Q31: =IFERROR(__xludf.DUMMYFUNCTION("""COMPUTED_VALUE"""),"Lisandro Russian") -> Lisandro Russian | R31: =IFERROR(__xludf.DUMMYFUNCTION("""COMPUTED_VALUE"""),"Raed Maqued El Maqued") -> Raed Maqued El Maqued | S31: =IFERROR(__xludf.DUMMYFUNCTION("""COMPUTED_VALUE"""),"03 ORL") -> 03 ORL | T31: =IFERROR(__xludf.DUMMYFUNCTION("""COMPUTED_VALUE"""),"06 ORL") -> 06 ORL
B32: =IF($C32="","",LEFT(C32,3)) -> MBM | C32: =IFERROR(__xludf.DUMMYFUNCTION("""COMPUTED_VALUE"""),"MBM166") -> MBM166 | D32: =IFERROR(__xludf.DUMMYFUNCTION("""COMPUTED_VALUE"""),"PROPIOS") -> PROPIOS | E32: =IFERROR(__xludf.DUMMYFUNCTION("""COMPUTED_VALUE"""),2026) -> 2026 | F32: =IFERROR(__xludf.DUMMYFUNCTION("""COMPUTED_VALUE"""),1) -> 1 | G32: =IFERROR(__xludf.DUMMYFUNCTION("""COMPUTED_VALUE"""),"Leganés") -> Leganés | H32: =IFERROR(__xludf.DUMMYFUNCTION("""COMPUTED_VALUE"""),"C202512112053437517") -> C202512112053437517 | I32: =IFERROR(__xludf.DUMMYFUNCTION("""COMPUTED_VALUE"""),"MANUEL MANJON CABELLO") -> MANUEL MANJON CABELLO | J32: =IFERROR(__xludf.DUMMYFUNCTION("""COMPUTED_VALUE"""),45992) -> 45992 | K32: =IFERROR(__xludf.DUMMYFUNCTION("""COMPUTED_VALUE"""),"Factura audífonos") -> Factura audífonos | L32: =IFERROR(__xludf.DUMMYFUNCTION("""COMPUTED_VALUE"""),46038) -> 46038 | M32: =IFERROR(__xludf.DUMMYFUNCTION("""COMPUTED_VALUE"""),"NO") -> NO | N32: =IFERROR(__xludf.DUMMYFUNCTION("""COMPUTED_VALUE"""),2) -> 2 | O32: =IFERROR(__xludf.DUMMYFUNCTION("""COMPUTED_VALUE"""),"QUIET") -> QUIET | P32: =IFERROR(__xludf.DUMMYFUNCTION("""COMPUTED_VALUE"""),2581.82) -> 2581.82 | Q32: =IFERROR(__xludf.DUMMYFUNCTION("""COMPUTED_VALUE"""),"Maika Blázquez") -> Maika Blázquez | R32: =IFERROR(__xludf.DUMMYFUNCTION("""COMPUTED_VALUE"""),"Patricia García Vicente") -> Patricia García Vicente | S32: =IFERROR(__xludf.DUMMYFUNCTION("""COMPUTED_VALUE"""),"03 ORL") -> 03 ORL | T32: =IFERROR(__xludf.DUMMYFUNCTION("""COMPUTED_VALUE"""),"06 ORL") -> 06 ORL
B33: =IF($C33="","",LEFT(C33,3)) -> MBM | C33: =IFERROR(__xludf.DUMMYFUNCTION("""COMPUTED_VALUE"""),"MBM129") -> MBM129 | D33: =IFERROR(__xludf.DUMMYFUNCTION("""COMPUTED_VALUE"""),"PROPIOS") -> PROPIOS | E33: =IFERROR(__xludf.DUMMYFUNCTION("""COMPUTED_VALUE"""),2026) -> 2026 | F33: =IFERROR(__xludf.DUMMYFUNCTION("""COMPUTED_VALUE"""),1) -> 1 | G33: =IFERROR(__xludf.DUMMYFUNCTION("""COMPUTED_VALUE"""),"Alcorcón") -> Alcorcón | H33: =IFERROR(__xludf.DUMMYFUNCTION("""COMPUTED_VALUE"""),"C202512183458643917") -> C202512183458643917 | I33: =IFERROR(__xludf.DUMMYFUNCTION("""COMPUTED_VALUE"""),"VANESA SACRISTAN HERNÁNDEZ") -> VANESA SACRISTAN HERNÁNDEZ | J33: =IFERROR(__xludf.DUMMYFUNCTION("""COMPUTED_VALUE"""),45992) -> 45992 | K33: =IFERROR(__xludf.DUMMYFUNCTION("""COMPUTED_VALUE"""),"Factura audífonos") -> Factura audífonos | L33: =IFERROR(__xludf.DUMMYFUNCTION("""COMPUTED_VALUE"""),46038) -> 46038 | M33: =IFERROR(__xludf.DUMMYFUNCTION("""COMPUTED_VALUE"""),"NO") -> NO | N33: =IFERROR(__xludf.DUMMYFUNCTION("""COMPUTED_VALUE"""),1) -> 1 | O33: =IFERROR(__xludf.DUMMYFUNCTION("""COMPUTED_VALUE"""),"CONFORT") -> CONFORT | P33: =IFERROR(__xludf.DUMMYFUNCTION("""COMPUTED_VALUE"""),2180.91) -> 2180.91 | Q33: =IFERROR(__xludf.DUMMYFUNCTION("""COMPUTED_VALUE"""),"Maika Blázquez") -> Maika Blázquez | R33: =IFERROR(__xludf.DUMMYFUNCTION("""COMPUTED_VALUE"""),"Laura del Toro Gil") -> Laura del Toro Gil | S33: =IFERROR(__xludf.DUMMYFUNCTION("""COMPUTED_VALUE"""),"03 ORL") -> 03 ORL | T33: =IFERROR(__xludf.DUMMYFUNCTION("""COMPUTED_VALUE"""),"06 ORL") -> 06 ORL
B34: =IF($C34="","",LEFT(C34,3)) -> MBM | C34: =IFERROR(__xludf.DUMMYFUNCTION("""COMPUTED_VALUE"""),"MBM21") -> MBM21 | D34: =IFERROR(__xludf.DUMMYFUNCTION("""COMPUTED_VALUE"""),"PARTICIPADOS") -> PARTICIPADOS | E34: =IFERROR(__xludf.DUMMYFUNCTION("""COMPUTED_VALUE"""),2026) -> 2026 | F34: =IFERROR(__xludf.DUMMYFUNCTION("""COMPUTED_VALUE"""),1) -> 1 | G34: =IFERROR(__xludf.DUMMYFUNCTION("""COMPUTED_VALUE"""),"Madrid- La Oca") -> Madrid- La Oca | H34: =IFERROR(__xludf.DUMMYFUNCTION("""COMPUTED_VALUE"""),"C202511251148389618") -> C202511251148389618 | I34: =IFERROR(__xludf.DUMMYFUNCTION("""COMPUTED_VALUE"""),"VISITACION RODRIGUEZ PEÑARANDA") -> VISITACION RODRIGUEZ PEÑARANDA | J34: =IFERROR(__xludf.DUMMYFUNCTION("""COMPUTED_VALUE"""),45986) -> 45986 | K34: =IFERROR(__xludf.DUMMYFUNCTION("""COMPUTED_VALUE"""),"Factura audífonos") -> Factura audífonos | L34: =IFERROR(__xludf.DUMMYFUNCTION("""COMPUTED_VALUE"""),46038) -> 46038 | M34: =IFERROR(__xludf.DUMMYFUNCTION("""COMPUTED_VALUE"""),"NO") -> NO | N34: =IFERROR(__xludf.DUMMYFUNCTION("""COMPUTED_VALUE"""),2) -> 2 | O34: =IFERROR(__xludf.DUMMYFUNCTION("""COMPUTED_VALUE"""),"QUIET") -> QUIET | P34: =IFERROR(__xludf.DUMMYFUNCTION("""COMPUTED_VALUE"""),2718.18) -> 2718.18 | Q34: =IFERROR(__xludf.DUMMYFUNCTION("""COMPUTED_VALUE"""),"Maika Blázquez") -> Maika Blázquez | R34: =IFERROR(__xludf.DUMMYFUNCTION("""COMPUTED_VALUE"""),"Félix Rodríguez Paz") -> Félix Rodríguez Paz | S34: =IFERROR(__xludf.DUMMYFUNCTION("""COMPUTED_VALUE"""),"03 ORL") -> 03 ORL | T34: =IFERROR(__xludf.DUMMYFUNCTION("""COMPUTED_VALUE"""),"06 ORL") -> 06 ORL
B35: =IF($C35="","",LEFT(C35,3)) -> ISL | C35: =IFERROR(__xludf.DUMMYFUNCTION("""COMPUTED_VALUE"""),"ISL45") -> ISL45 | D35: =IFERROR(__xludf.DUMMYFUNCTION("""COMPUTED_VALUE"""),"PROPIOS") -> PROPIOS | E35: =IFERROR(__xludf.DUMMYFUNCTION("""COMPUTED_VALUE"""),2026) -> 2026 | F35: =IFERROR(__xludf.DUMMYFUNCTION("""COMPUTED_VALUE"""),1) -> 1 | G35: =IFERROR(__xludf.DUMMYFUNCTION("""COMPUTED_VALUE"""),"Murcia") -> Murcia | H35: =IFERROR(__xludf.DUMMYFUNCTION("""COMPUTED_VALUE"""),"C202511201717376391") -> C202511201717376391 | I35: =IFERROR(__xludf.DUMMYFUNCTION("""COMPUTED_VALUE"""),"ESPERANZA ÁLVAREZ MUÑOZ") -> ESPERANZA ÁLVAREZ MUÑOZ | J35: =IFERROR(__xludf.DUMMYFUNCTION("""COMPUTED_VALUE"""),45981) -> 45981 | K35: =IFERROR(__xludf.DUMMYFUNCTION("""COMPUTED_VALUE"""),"Factura audífonos") -> Factura audífonos | L35: =IFERROR(__xludf.DUMMYFUNCTION("""COMPUTED_VALUE"""),46038) -> 46038 | M35: =IFERROR(__xludf.DUMMYFUNCTION("""COMPUTED_VALUE"""),"NO") -> NO | N35: =IFERROR(__xludf.DUMMYFUNCTION("""COMPUTED_VALUE"""),1) -> 1 | O35: =IFERROR(__xludf.DUMMYFUNCTION("""COMPUTED_VALUE"""),"QUIET") -> QUIET | P35: =IFERROR(__xludf.DUMMYFUNCTION("""COMPUTED_VALUE"""),1631.73) -> 1631.73 | Q35: =IFERROR(__xludf.DUMMYFUNCTION("""COMPUTED_VALUE"""),"Iván Sánchez") -> Iván Sánchez | R35: =IFERROR(__xludf.DUMMYFUNCTION("""COMPUTED_VALUE"""),"Jesús Miguel Iniesta Turpín") -> Jesús Miguel Iniesta Turpín | S35: =IFERROR(__xludf.DUMMYFUNCTION("""COMPUTED_VALUE"""),"03 ORL") -> 03 ORL | T35: =IFERROR(__xludf.DUMMYFUNCTION("""COMPUTED_VALUE"""),"06 ORL") -> 06 ORL
B36: =IF($C36="","",LEFT(C36,3)) -> LRM | C36: =IFERROR(__xludf.DUMMYFUNCTION("""COMPUTED_VALUE"""),"LRM151") -> LRM151 | D36: =IFERROR(__xludf.DUMMYFUNCTION("""COMPUTED_VALUE"""),"PROPIOS") -> PROPIOS | E36: =IFERROR(__xludf.DUMMYFUNCTION("""COMPUTED_VALUE"""),2026) -> 2026 | F36: =IFERROR(__xludf.DUMMYFUNCTION("""COMPUTED_VALUE"""),1) -> 1 | G36: =IFERROR(__xludf.DUMMYFUNCTION("""COMPUTED_VALUE"""),"Logroño") -> Logroño | H36: =IFERROR(__xludf.DUMMYFUNCTION("""COMPUTED_VALUE"""),"C202510110530975") -> C202510110530975 | I36: =IFERROR(__xludf.DUMMYFUNCTION("""COMPUTED_VALUE"""),"SEVERIANA MARIN GOMEZ") -> SEVERIANA MARIN GOMEZ | J36: =IFERROR(__xludf.DUMMYFUNCTION("""COMPUTED_VALUE"""),45929) -> 45929 | K36: =IFERROR(__xludf.DUMMYFUNCTION("""COMPUTED_VALUE"""),"Factura audífonos") -> Factura audífonos | L36: =IFERROR(__xludf.DUMMYFUNCTION("""COMPUTED_VALUE"""),46038) -> 46038 | M36: =IFERROR(__xludf.DUMMYFUNCTION("""COMPUTED_VALUE"""),"NO") -> NO | N36: =IFERROR(__xludf.DUMMYFUNCTION("""COMPUTED_VALUE"""),2) -> 2 | O36: =IFERROR(__xludf.DUMMYFUNCTION("""COMPUTED_VALUE"""),"CONFORT") -> CONFORT | P36: =IFERROR(__xludf.DUMMYFUNCTION("""COMPUTED_VALUE"""),3604.55) -> 3604.55 | Q36: =IFERROR(__xludf.DUMMYFUNCTION("""COMPUTED_VALUE"""),"Lisandro Russian") -> Lisandro Russian | R36: =IFERROR(__xludf.DUMMYFUNCTION("""COMPUTED_VALUE"""),"Cristina Ibañez Muñoz") -> Cristina Ibañez Muñoz | S36: =IFERROR(__xludf.DUMMYFUNCTION("""COMPUTED_VALUE"""),"03 ORL") -> 03 ORL | T36: =IFERROR(__xludf.DUMMYFUNCTION("""COMPUTED_VALUE"""),"06 ORL") -> 06 ORL
B37: =IF($C37="","",LEFT(C37,3)) -> MBM | C37: =IFERROR(__xludf.DUMMYFUNCTION("""COMPUTED_VALUE"""),"MBM145") -> MBM145 | D37: =IFERROR(__xludf.DUMMYFUNCTION("""COMPUTED_VALUE"""),"PROPIOS") -> PROPIOS | E37: =IFERROR(__xludf.DUMMYFUNCTION("""COMPUTED_VALUE"""),2026) -> 2026 | F37: =IFERROR(__xludf.DUMMYFUNCTION("""COMPUTED_VALUE"""),1) -> 1 | G37: =IFERROR(__xludf.DUMMYFUNCTION("""COMPUTED_VALUE"""),"Alcorcón") -> Alcorcón | H37: =IFERROR(__xludf.DUMMYFUNCTION("""COMPUTED_VALUE"""),"C202511181813490985") -> C202511181813490985 | I37: =IFERROR(__xludf.DUMMYFUNCTION("""COMPUTED_VALUE"""),"SUSANA PERUCHO MARTINEZ") -> SUSANA PERUCHO MARTINEZ | J37: =IFERROR(__xludf.DUMMYFUNCTION("""COMPUTED_VALUE"""),45979) -> 45979 | K37: =IFERROR(__xludf.DUMMYFUNCTION("""COMPUTED_VALUE"""),"Factura audífonos") -> Factura audífonos | L37: =IFERROR(__xludf.DUMMYFUNCTION("""COMPUTED_VALUE"""),46038) -> 46038 | M37: =IFERROR(__xludf.DUMMYFUNCTION("""COMPUTED_VALUE"""),"NO") -> NO | N37: =IFERROR(__xludf.DUMMYFUNCTION("""COMPUTED_VALUE"""),2) -> 2 | O37: =IFERROR(__xludf.DUMMYFUNCTION("""COMPUTED_VALUE"""),"ADVANCED") -> ADVANCED | P37: =IFERROR(__xludf.DUMMYFUNCTION("""COMPUTED_VALUE"""),4136.36) -> 4136.36 | Q37: =IFERROR(__xludf.DUMMYFUNCTION("""COMPUTED_VALUE"""),"Maika Blázquez") -> Maika Blázquez | R37: =IFERROR(__xludf.DUMMYFUNCTION("""COMPUTED_VALUE"""),"María del Mar Martínez Ruiz-coello") -> María del Mar Martínez Ruiz-coello | S37: =IFERROR(__xludf.DUMMYFUNCTION("""COMPUTED_VALUE"""),"03 ORL") -> 03 ORL | T37: =IFERROR(__xludf.DUMMYFUNCTION("""COMPUTED_VALUE"""),"06 ORL") -> 06 ORL
B38: =IF($C38="","",LEFT(C38,3)) | D38: =IFERROR(__xludf.DUMMYFUNCTION("""COMPUTED_VALUE"""),"PROPIOS") -> PROPIOS | E38: =IFERROR(__xludf.DUMMYFUNCTION("""COMPUTED_VALUE"""),2026) -> 2026 | F38: =IFERROR(__xludf.DUMMYFUNCTION("""COMPUTED_VALUE"""),1) -> 1 | G38: =IFERROR(__xludf.DUMMYFUNCTION("""COMPUTED_VALUE"""),"Sevilla- Montoto") -> Sevilla- Montoto | H38: =IFERROR(__xludf.DUMMYFUNCTION("""COMPUTED_VALUE"""),"C202512191110453673") -> C202512191110453673 | I38: =IFERROR(__xludf.DUMMYFUNCTION("""COMPUTED_VALUE"""),"JOSE ANTONIO SANCHEZ TORRECILLA") -> JOSE ANTONIO SANCHEZ TORRECILLA | J38: =IFERROR(__xludf.DUMMYFUNCTION("""COMPUTED_VALUE"""),46010) -> 46010 | K38: =IFERROR(__xludf.DUMMYFUNCTION("""COMPUTED_VALUE"""),"Factura audífonos") -> Factura audífonos | L38: =IFERROR(__xludf.DUMMYFUNCTION("""COMPUTED_VALUE"""),46038) -> 46038 | M38: =IFERROR(__xludf.DUMMYFUNCTION("""COMPUTED_VALUE"""),"NO") -> NO | N38: =IFERROR(__xludf.DUMMYFUNCTION("""COMPUTED_VALUE"""),2) -> 2 | O38: =IFERROR(__xludf.DUMMYFUNCTION("""COMPUTED_VALUE"""),"QUIET") -> QUIET | P38: =IFERROR(__xludf.DUMMYFUNCTION("""COMPUTED_VALUE"""),2718.19) -> 2718.19 | Q38: =IFERROR(__xludf.DUMMYFUNCTION("""COMPUTED_VALUE"""),"Luis Alberto Rodríguez") -> Luis Alberto Rodríguez | R38: =IFERROR(__xludf.DUMMYFUNCTION("""COMPUTED_VALUE"""),"No recuerda ORL") -> No recuerda ORL | S38: =IFERROR(__xludf.DUMMYFUNCTION("""COMPUTED_VALUE"""),"03 ORL") -> 03 ORL | T38: =IFERROR(__xludf.DUMMYFUNCTION("""COMPUTED_VALUE"""),"06 ORL") -> 06 ORL
B39: =IF($C39="","",LEFT(C39,3)) -> LRM | C39: =IFERROR(__xludf.DUMMYFUNCTION("""COMPUTED_VALUE"""),"LRM239") -> LRM239 | D39: =IFERROR(__xludf.DUMMYFUNCTION("""COMPUTED_VALUE"""),"PROPIOS") -> PROPIOS | E39: =IFERROR(__xludf.DUMMYFUNCTION("""COMPUTED_VALUE"""),2026) -> 2026 | F39: =IFERROR(__xludf.DUMMYFUNCTION("""COMPUTED_VALUE"""),1) -> 1 | G39: =IFERROR(__xludf.DUMMYFUNCTION("""COMPUTED_VALUE"""),"Madrid- Juan Bravo") -> Madrid- Juan Bravo | H39: =IFERROR(__xludf.DUMMYFUNCTION("""COMPUTED_VALUE"""),"C202561217436304") -> C202561217436304 | I39: =IFERROR(__xludf.DUMMYFUNCTION("""COMPUTED_VALUE"""),"CATALINA RAMOS MARIN") -> CATALINA RAMOS MARIN | J39: =IFERROR(__xludf.DUMMYFUNCTION("""COMPUTED_VALUE"""),45814) -> 45814 | K39: =IFERROR(__xludf.DUMMYFUNCTION("""COMPUTED_VALUE"""),"Factura audífonos") -> Factura audífonos | L39: =IFERROR(__xludf.DUMMYFUNCTION("""COMPUTED_VALUE"""),46041) -> 46041 | M39: =IFERROR(__xludf.DUMMYFUNCTION("""COMPUTED_VALUE"""),"NO") -> NO | N39: =IFERROR(__xludf.DUMMYFUNCTION("""COMPUTED_VALUE"""),1) -> 1 | O39: =IFERROR(__xludf.DUMMYFUNCTION("""COMPUTED_VALUE"""),"QUIET") -> QUIET | P39: =IFERROR(__xludf.DUMMYFUNCTION("""COMPUTED_VALUE"""),1631.82) -> 1631.82 | Q39: =IFERROR(__xludf.DUMMYFUNCTION("""COMPUTED_VALUE"""),"Lisandro Russian") -> Lisandro Russian | R39: =IFERROR(__xludf.DUMMYFUNCTION("""COMPUTED_VALUE"""),"Carlos Barajas del Rosal") -> Carlos Barajas del Rosal | S39: =IFERROR(__xludf.DUMMYFUNCTION("""COMPUTED_VALUE"""),"03 ORL") -> 03 ORL | T39: =IFERROR(__xludf.DUMMYFUNCTION("""COMPUTED_VALUE"""),"06 ORL") -> 06 ORL
B40: =IF($C40="","",LEFT(C40,3)) -> LRM | C40: =IFERROR(__xludf.DUMMYFUNCTION("""COMPUTED_VALUE"""),"LRM58") -> LRM58 | D40: =IFERROR(__xludf.DUMMYFUNCTION("""COMPUTED_VALUE"""),"ASOCIADOS") -> ASOCIADOS | E40: =IFERROR(__xludf.DUMMYFUNCTION("""COMPUTED_VALUE"""),2026) -> 2026 | F40: =IFERROR(__xludf.DUMMYFUNCTION("""COMPUTED_VALUE"""),1) -> 1 | G40: =IFERROR(__xludf.DUMMYFUNCTION("""COMPUTED_VALUE"""),"Cáceres") -> Cáceres | H40: =IFERROR(__xludf.DUMMYFUNCTION("""COMPUTED_VALUE"""),"C202512151041598226") -> C202512151041598226 | I40: =IFERROR(__xludf.DUMMYFUNCTION("""COMPUTED_VALUE"""),"CLAUDIA MORENO CEBRIAN") -> CLAUDIA MORENO CEBRIAN | J40: =IFERROR(__xludf.DUMMYFUNCTION("""COMPUTED_VALUE"""),46006) -> 46006 | K40: =IFERROR(__xludf.DUMMYFUNCTION("""COMPUTED_VALUE"""),"Factura audífonos") -> Factura audífonos | L40: =IFERROR(__xludf.DUMMYFUNCTION("""COMPUTED_VALUE"""),46041) -> 46041 | M40: =IFERROR(__xludf.DUMMYFUNCTION("""COMPUTED_VALUE"""),"NO") -> NO | N40: =IFERROR(__xludf.DUMMYFUNCTION("""COMPUTED_VALUE"""),2) -> 2 | O40: =IFERROR(__xludf.DUMMYFUNCTION("""COMPUTED_VALUE"""),"ADVANCED") -> ADVANCED | P40: =IFERROR(__xludf.DUMMYFUNCTION("""COMPUTED_VALUE"""),4500) -> 4500 | Q40: =IFERROR(__xludf.DUMMYFUNCTION("""COMPUTED_VALUE"""),"Lisandro Russian") -> Lisandro Russian | R40: =IFERROR(__xludf.DUMMYFUNCTION("""COMPUTED_VALUE"""),"Javier García Gómez") -> Javier García Gómez | S40: =IFERROR(__xludf.DUMMYFUNCTION("""COMPUTED_VALUE"""),"03 ORL") -> 03 ORL | T40: =IFERROR(__xludf.DUMMYFUNCTION("""COMPUTED_VALUE"""),"06 ORL") -> 06 ORL
B41: =IF($C41="","",LEFT(C41,3)) -> MCC | C41: =IFERROR(__xludf.DUMMYFUNCTION("""COMPUTED_VALUE"""),"MCC18") -> MCC18 | D41: =IFERROR(__xludf.DUMMYFUNCTION("""COMPUTED_VALUE"""),"PARTICIPADOS") -> PARTICIPADOS | E41: =IFERROR(__xludf.DUMMYFUNCTION("""COMPUTED_VALUE"""),2026) -> 2026 | F41: =IFERROR(__xludf.DUMMYFUNCTION("""COMPUTED_VALUE"""),1) -> 1 | G41: =IFERROR(__xludf.DUMMYFUNCTION("""COMPUTED_VALUE"""),"Barcelona- Córcega") -> Barcelona- Córcega | H41: =IFERROR(__xludf.DUMMYFUNCTION("""COMPUTED_VALUE"""),"C202594115953981") -> C202594115953981 | I41: =IFERROR(__xludf.DUMMYFUNCTION("""COMPUTED_VALUE"""),"FRANCISCA HERNANDEZ LORENTE") -> FRANCISCA HERNANDEZ LORENTE | J41: =IFERROR(__xludf.DUMMYFUNCTION("""COMPUTED_VALUE"""),45901) -> 45901 | K41: =IFERROR(__xludf.DUMMYFUNCTION("""COMPUTED_VALUE"""),"Factura audífonos") -> Factura audífonos | L41: =IFERROR(__xludf.DUMMYFUNCTION("""COMPUTED_VALUE"""),46041) -> 46041 | M41: =IFERROR(__xludf.DUMMYFUNCTION("""COMPUTED_VALUE"""),"NO") -> NO | N41: =IFERROR(__xludf.DUMMYFUNCTION("""COMPUTED_VALUE"""),1) -> 1 | O41: =IFERROR(__xludf.DUMMYFUNCTION("""COMPUTED_VALUE"""),"ADVANCED") -> ADVANCED | P41: =IFERROR(__xludf.DUMMYFUNCTION("""COMPUTED_VALUE"""),2268.14) -> 2268.14 | Q41: =IFERROR(__xludf.DUMMYFUNCTION("""COMPUTED_VALUE"""),"Mercè Cabrera") -> Mercè Cabrera | R41: =IFERROR(__xludf.DUMMYFUNCTION("""COMPUTED_VALUE"""),"Jesus-Maria Grasa Pérez") -> Jesus-Maria Grasa Pérez | S41: =IFERROR(__xludf.DUMMYFUNCTION("""COMPUTED_VALUE"""),"03 ORL") -> 03 ORL | T41: =IFERROR(__xludf.DUMMYFUNCTION("""COMPUTED_VALUE"""),"06 ORL") -> 06 ORL
B42: =IF($C42="","",LEFT(C42,3)) -> ISL | C42: =IFERROR(__xludf.DUMMYFUNCTION("""COMPUTED_VALUE"""),"ISL136") -> ISL136 | D42: =IFERROR(__xludf.DUMMYFUNCTION("""COMPUTED_VALUE"""),"PROPIOS") -> PROPIOS | E42: =IFERROR(__xludf.DUMMYFUNCTION("""COMPUTED_VALUE"""),2026) -> 2026 | F42: =IFERROR(__xludf.DUMMYFUNCTION("""COMPUTED_VALUE"""),1) -> 1 | G42: =IFERROR(__xludf.DUMMYFUNCTION("""COMPUTED_VALUE"""),"Orihuela") -> Orihuela | H42: =IFERROR(__xludf.DUMMYFUNCTION("""COMPUTED_VALUE"""),"C202512101420127206") -> C202512101420127206 | I42: =IFERROR(__xludf.DUMMYFUNCTION("""COMPUTED_VALUE"""),"CHRISTOPHER HUGH IBBETSON") -> CHRISTOPHER HUGH IBBETSON | J42: =IFERROR(__xludf.DUMMYFUNCTION("""COMPUTED_VALUE"""),46001) -> 46001 | K42: =IFERROR(__xludf.DUMMYFUNCTION("""COMPUTED_VALUE"""),"Factura audífonos") -> Factura audífonos | L42: =IFERROR(__xludf.DUMMYFUNCTION("""COMPUTED_VALUE"""),46041) -> 46041 | M42: =IFERROR(__xludf.DUMMYFUNCTION("""COMPUTED_VALUE"""),"NO") -> NO | N42: =IFERROR(__xludf.DUMMYFUNCTION("""COMPUTED_VALUE"""),2) -> 2 | O42: =IFERROR(__xludf.DUMMYFUNCTION("""COMPUTED_VALUE"""),"CONFORT") -> CONFORT | P42: =IFERROR(__xludf.DUMMYFUNCTION("""COMPUTED_VALUE"""),3631.82) -> 3631.82 | Q42: =IFERROR(__xludf.DUMMYFUNCTION("""COMPUTED_VALUE"""),"Iván Sánchez") -> Iván Sánchez | R42: =IFERROR(__xludf.DUMMYFUNCTION("""COMPUTED_VALUE"""),"Oreana Carolina Camacaro González") -> Oreana Carolina Camacaro González | S42: =IFERROR(__xludf.DUMMYFUNCTION("""COMPUTED_VALUE"""),"03 ORL") -> 03 ORL | T42: =IFERROR(__xludf.DUMMYFUNCTION("""COMPUTED_VALUE"""),"06 ORL") -> 06 ORL
B43: =IF($C43="","",LEFT(C43,3)) -> ISL | C43: =IFERROR(__xludf.DUMMYFUNCTION("""COMPUTED_VALUE"""),"ISL122") -> ISL122 | D43: =IFERROR(__xludf.DUMMYFUNCTION("""COMPUTED_VALUE"""),"PROPIOS") -> PROPIOS | E43: =IFERROR(__xludf.DUMMYFUNCTION("""COMPUTED_VALUE"""),2026) -> 2026 | F43: =IFERROR(__xludf.DUMMYFUNCTION("""COMPUTED_VALUE"""),1) -> 1 | G43: =IFERROR(__xludf.DUMMYFUNCTION("""COMPUTED_VALUE"""),"Murcia") -> Murcia | H43: =IFERROR(__xludf.DUMMYFUNCTION("""COMPUTED_VALUE"""),"MUR-1258") -> MUR-1258 | I43: =IFERROR(__xludf.DUMMYFUNCTION("""COMPUTED_VALUE"""),"JULIA LOPEZ LOPEZ") -> JULIA LOPEZ LOPEZ | J43: =IFERROR(__xludf.DUMMYFUNCTION("""COMPUTED_VALUE"""),44960) -> 44960 | K43: =IFERROR(__xludf.DUMMYFUNCTION("""COMPUTED_VALUE"""),"Factura audífonos") -> Factura audífonos | L43: =IFERROR(__xludf.DUMMYFUNCTION("""COMPUTED_VALUE"""),46041) -> 46041 | M43: =IFERROR(__xludf.DUMMYFUNCTION("""COMPUTED_VALUE"""),"NO") -> NO | N43: =IFERROR(__xludf.DUMMYFUNCTION("""COMPUTED_VALUE"""),2) -> 2 | O43: =IFERROR(__xludf.DUMMYFUNCTION("""COMPUTED_VALUE"""),"QUIET") -> QUIET | P43: =IFERROR(__xludf.DUMMYFUNCTION("""COMPUTED_VALUE"""),2718.18) -> 2718.18 | Q43: =IFERROR(__xludf.DUMMYFUNCTION("""COMPUTED_VALUE"""),"Iván Sánchez") -> Iván Sánchez | R43: =IFERROR(__xludf.DUMMYFUNCTION("""COMPUTED_VALUE"""),"María Agustina Sevilla García") -> María Agustina Sevilla García | S43: =IFERROR(__xludf.DUMMYFUNCTION("""COMPUTED_VALUE"""),"03 ORL") -> 03 ORL | T43: =IFERROR(__xludf.DUMMYFUNCTION("""COMPUTED_VALUE"""),"06 ORL") -> 06 ORL
B44: =IF($C44="","",LEFT(C44,3)) -> MBM | C44: =IFERROR(__xludf.DUMMYFUNCTION("""COMPUTED_VALUE"""),"MBM39") -> MBM39 | D44: =IFERROR(__xludf.DUMMYFUNCTION("""COMPUTED_VALUE"""),"PROPIOS") -> PROPIOS | E44: =IFERROR(__xludf.DUMMYFUNCTION("""COMPUTED_VALUE"""),2026) -> 2026 | F44: =IFERROR(__xludf.DUMMYFUNCTION("""COMPUTED_VALUE"""),1) -> 1 | G44: =IFERROR(__xludf.DUMMYFUNCTION("""COMPUTED_VALUE"""),"Madrid- Moratalaz") -> Madrid- Moratalaz | H44: =IFERROR(__xludf.DUMMYFUNCTION("""COMPUTED_VALUE"""),"C202512161155416397") -> C202512161155416397 | I44: =IFERROR(__xludf.DUMMYFUNCTION("""COMPUTED_VALUE"""),"MARIA DE LOS ANGELES CABAL NUÑEZ DE HOYO") -> MARIA DE LOS ANGELES CABAL NUÑEZ DE HOYO | J44: =IFERROR(__xludf.DUMMYFUNCTION("""COMPUTED_VALUE"""),46007) -> 46007 | K44: =IFERROR(__xludf.DUMMYFUNCTION("""COMPUTED_VALUE"""),"Factura audífonos") -> Factura audífonos | L44: =IFERROR(__xludf.DUMMYFUNCTION("""COMPUTED_VALUE"""),46041) -> 46041 | M44: =IFERROR(__xludf.DUMMYFUNCTION("""COMPUTED_VALUE"""),"NO") -> NO | N44: =IFERROR(__xludf.DUMMYFUNCTION("""COMPUTED_VALUE"""),2) -> 2 | O44: =IFERROR(__xludf.DUMMYFUNCTION("""COMPUTED_VALUE"""),"CONFORT") -> CONFORT | P44: =IFERROR(__xludf.DUMMYFUNCTION("""COMPUTED_VALUE"""),3377.6) -> 3377.6 | Q44: =IFERROR(__xludf.DUMMYFUNCTION("""COMPUTED_VALUE"""),"Maika Blázquez") -> Maika Blázquez | R44: =IFERROR(__xludf.DUMMYFUNCTION("""COMPUTED_VALUE"""),"Javier García Domínguez") -> Javier García Domínguez | S44: =IFERROR(__xludf.DUMMYFUNCTION("""COMPUTED_VALUE"""),"03 ORL") -> 03 ORL | T44: =IFERROR(__xludf.DUMMYFUNCTION("""COMPUTED_VALUE"""),"06 ORL") -> 06 ORL
B45: =IF($C45="","",LEFT(C45,3)) -> MBM | C45: =IFERROR(__xludf.DUMMYFUNCTION("""COMPUTED_VALUE"""),"MBM149") -> MBM149 | D45: =IFERROR(__xludf.DUMMYFUNCTION("""COMPUTED_VALUE"""),"PROPIOS") -> PROPIOS | E45: =IFERROR(__xludf.DUMMYFUNCTION("""COMPUTED_VALUE"""),2026) -> 2026 | F45: =IFERROR(__xludf.DUMMYFUNCTION("""COMPUTED_VALUE"""),1) -> 1 | G45: =IFERROR(__xludf.DUMMYFUNCTION("""COMPUTED_VALUE"""),"Getafe") -> Getafe | H45: =IFERROR(__xludf.DUMMYFUNCTION("""COMPUTED_VALUE"""),"C202511171120372888") -> C202511171120372888 | I45: =IFERROR(__xludf.DUMMYFUNCTION("""COMPUTED_VALUE"""),"PILAR TORREJÓN ALONSO") -> PILAR TORREJÓN ALONSO | J45: =IFERROR(__xludf.DUMMYFUNCTION("""COMPUTED_VALUE"""),45978) -> 45978 | K45: =IFERROR(__xludf.DUMMYFUNCTION("""COMPUTED_VALUE"""),"Factura audífonos") -> Factura audífonos | L45: =IFERROR(__xludf.DUMMYFUNCTION("""COMPUTED_VALUE"""),46041) -> 46041 | M45: =IFERROR(__xludf.DUMMYFUNCTION("""COMPUTED_VALUE"""),"NO") -> NO | N45: =IFERROR(__xludf.DUMMYFUNCTION("""COMPUTED_VALUE"""),2) -> 2 | O45: =IFERROR(__xludf.DUMMYFUNCTION("""COMPUTED_VALUE"""),"CONFORT") -> CONFORT | P45: =IFERROR(__xludf.DUMMYFUNCTION("""COMPUTED_VALUE"""),3631.82) -> 3631.82 | Q45: =IFERROR(__xludf.DUMMYFUNCTION("""COMPUTED_VALUE"""),"Maika Blázquez") -> Maika Blázquez | R45: =IFERROR(__xludf.DUMMYFUNCTION("""COMPUTED_VALUE"""),"María Garrote Garrote") -> María Garrote Garrote | S45: =IFERROR(__xludf.DUMMYFUNCTION("""COMPUTED_VALUE"""),"03 ORL") -> 03 ORL | T45: =IFERROR(__xludf.DUMMYFUNCTION("""COMPUTED_VALUE"""),"06 ORL") -> 06 ORL
B46: =IF($C46="","",LEFT(C46,3)) -> LRM | C46: =IFERROR(__xludf.DUMMYFUNCTION("""COMPUTED_VALUE"""),"LRM153") -> LRM153 | D46: =IFERROR(__xludf.DUMMYFUNCTION("""COMPUTED_VALUE"""),"ASOCIADOS") -> ASOCIADOS | E46: =IFERROR(__xludf.DUMMYFUNCTION("""COMPUTED_VALUE"""),2026) -> 2026 | F46: =IFERROR(__xludf.DUMMYFUNCTION("""COMPUTED_VALUE"""),1) -> 1 | G46: =IFERROR(__xludf.DUMMYFUNCTION("""COMPUTED_VALUE"""),"Cáceres") -> Cáceres | H46: =IFERROR(__xludf.DUMMYFUNCTION("""COMPUTED_VALUE"""),"C202512161238444364") -> C202512161238444364 | I46: =IFERROR(__xludf.DUMMYFUNCTION("""COMPUTED_VALUE"""),"FERMINA ISABEL PIZARRO VALLE") -> FERMINA ISABEL PIZARRO VALLE | J46: =IFERROR(__xludf.DUMMYFUNCTION("""COMPUTED_VALUE"""),46007) -> 46007 | K46: =IFERROR(__xludf.DUMMYFUNCTION("""COMPUTED_VALUE"""),"Factura audífonos") -> Factura audífonos | L46: =IFERROR(__xludf.DUMMYFUNCTION("""COMPUTED_VALUE"""),46042) -> 46042 | M46: =IFERROR(__xludf.DUMMYFUNCTION("""COMPUTED_VALUE"""),"NO") -> NO | N46: =IFERROR(__xludf.DUMMYFUNCTION("""COMPUTED_VALUE"""),2) -> 2 | O46: =IFERROR(__xludf.DUMMYFUNCTION("""COMPUTED_VALUE"""),"PRO") -> PRO | P46: =IFERROR(__xludf.DUMMYFUNCTION("""COMPUTED_VALUE"""),4990.91) -> 4990.91 | Q46: =IFERROR(__xludf.DUMMYFUNCTION("""COMPUTED_VALUE"""),"Lisandro Russian") -> Lisandro Russian | R46: =IFERROR(__xludf.DUMMYFUNCTION("""COMPUTED_VALUE"""),"Daniela Carolina Laguado Bulgheroni") -> Daniela Carolina Laguado Bulgheroni | S46: =IFERROR(__xludf.DUMMYFUNCTION("""COMPUTED_VALUE"""),"03 ORL") -> 03 ORL | T46: =IFERROR(__xludf.DUMMYFUNCTION("""COMPUTED_VALUE"""),"06 ORL") -> 06 ORL
B47: =IF($C47="","",LEFT(C47,3)) -> MCC | C47: =IFERROR(__xludf.DUMMYFUNCTION("""COMPUTED_VALUE"""),"MCC30") -> MCC30 | D47: =IFERROR(__xludf.DUMMYFUNCTION("""COMPUTED_VALUE"""),"ASOCIADOS") -> ASOCIADOS | E47: =IFERROR(__xludf.DUMMYFUNCTION("""COMPUTED_VALUE"""),2026) -> 2026 | F47: =IFERROR(__xludf.DUMMYFUNCTION("""COMPUTED_VALUE"""),1) -> 1 | G47: =IFERROR(__xludf.DUMMYFUNCTION("""COMPUTED_VALUE"""),"Zaragoza- León XIII") -> Zaragoza- León XIII | H47: =IFERROR(__xludf.DUMMYFUNCTION("""COMPUTED_VALUE"""),"C202512129125747718") -> C202512129125747718 | I47: =IFERROR(__xludf.DUMMYFUNCTION("""COMPUTED_VALUE"""),"TOMÁS JAVIER MARTÍNEZ MORENO") -> TOMÁS JAVIER MARTÍNEZ MORENO | J47: =IFERROR(__xludf.DUMMYFUNCTION("""COMPUTED_VALUE"""),46003) -> 46003 | K47: =IFERROR(__xludf.DUMMYFUNCTION("""COMPUTED_VALUE"""),"Factura audífonos") -> Factura audífonos | L47: =IFERROR(__xludf.DUMMYFUNCTION("""COMPUTED_VALUE"""),46042) -> 46042 | M47: =IFERROR(__xludf.DUMMYFUNCTION("""COMPUTED_VALUE"""),"NO") -> NO | N47: =IFERROR(__xludf.DUMMYFUNCTION("""COMPUTED_VALUE"""),2) -> 2 | O47: =IFERROR(__xludf.DUMMYFUNCTION("""COMPUTED_VALUE"""),"CONFORT") -> CONFORT | P47: =IFERROR(__xludf.DUMMYFUNCTION("""COMPUTED_VALUE"""),3618.27) -> 3618.27 | Q47: =IFERROR(__xludf.DUMMYFUNCTION("""COMPUTED_VALUE"""),"Ignacio Berdejo") -> Ignacio Berdejo | R47: =IFERROR(__xludf.DUMMYFUNCTION("""COMPUTED_VALUE"""),"Pedro Gil Paraíso") -> Pedro Gil Paraíso | S47: =IFERROR(__xludf.DUMMYFUNCTION("""COMPUTED_VALUE"""),"03 ORL") -> 03 ORL | T47: =IFERROR(__xludf.DUMMYFUNCTION("""COMPUTED_VALUE"""),"06 ORL") -> 06 ORL
B48: =IF($C48="","",LEFT(C48,3)) -> MBM | C48: =IFERROR(__xludf.DUMMYFUNCTION("""COMPUTED_VALUE"""),"MBM34") -> MBM34 | D48: =IFERROR(__xludf.DUMMYFUNCTION("""COMPUTED_VALUE"""),"PROPIOS") -> PROPIOS | E48: =IFERROR(__xludf.DUMMYFUNCTION("""COMPUTED_VALUE"""),2026) -> 2026 | F48: =IFERROR(__xludf.DUMMYFUNCTION("""COMPUTED_VALUE"""),1) -> 1 | G48: =IFERROR(__xludf.DUMMYFUNCTION("""COMPUTED_VALUE"""),"Madrid- Moratalaz") -> Madrid- Moratalaz | H48: =IFERROR(__xludf.DUMMYFUNCTION("""COMPUTED_VALUE"""),"C202512511444323836") -> C202512511444323836 | I48: =IFERROR(__xludf.DUMMYFUNCTION("""COMPUTED_VALUE"""),"ANTONIA MUÑOZ DURAN") -> ANTONIA MUÑOZ DURAN | J48: =IFERROR(__xludf.DUMMYFUNCTION("""COMPUTED_VALUE"""),45996) -> 45996 | K48: =IFERROR(__xludf.DUMMYFUNCTION("""COMPUTED_VALUE"""),"Factura audífonos") -> Factura audífonos | L48: =IFERROR(__xludf.DUMMYFUNCTION("""COMPUTED_VALUE"""),46042) -> 46042 | M48: =IFERROR(__xludf.DUMMYFUNCTION("""COMPUTED_VALUE"""),"NO") -> NO | N48: =IFERROR(__xludf.DUMMYFUNCTION("""COMPUTED_VALUE"""),2) -> 2 | O48: =IFERROR(__xludf.DUMMYFUNCTION("""COMPUTED_VALUE"""),"ADVANCED") -> ADVANCED | P48: =IFERROR(__xludf.DUMMYFUNCTION("""COMPUTED_VALUE"""),4136.36) -> 4136.36 | Q48: =IFERROR(__xludf.DUMMYFUNCTION("""COMPUTED_VALUE"""),"Maika Blázquez") -> Maika Blázquez | R48: =IFERROR(__xludf.DUMMYFUNCTION("""COMPUTED_VALUE"""),"Ignacio Aristegui Torrano") -> Ignacio Aristegui Torrano | S48: =IFERROR(__xludf.DUMMYFUNCTION("""COMPUTED_VALUE"""),"03 ORL") -> 03 ORL | T48: =IFERROR(__xludf.DUMMYFUNCTION("""COMPUTED_VALUE"""),"06 ORL") -> 06 ORL
B49: =IF($C49="","",LEFT(C49,3)) -> LAA | C49: =IFERROR(__xludf.DUMMYFUNCTION("""COMPUTED_VALUE"""),"LAA47") -> LAA47 | D49: =IFERROR(__xludf.DUMMYFUNCTION("""COMPUTED_VALUE"""),"PROPIOS") -> PROPIOS | E49: =IFERROR(__xludf.DUMMYFUNCTION("""COMPUTED_VALUE"""),2026) -> 2026 | F49: =IFERROR(__xludf.DUMMYFUNCTION("""COMPUTED_VALUE"""),1) -> 1 | G49: =IFERROR(__xludf.DUMMYFUNCTION("""COMPUTED_VALUE"""),"Sevilla- Montoto") -> Sevilla- Montoto | H49: =IFERROR(__xludf.DUMMYFUNCTION("""COMPUTED_VALUE"""),"C202511271216474526") -> C202511271216474526 | I49: =IFERROR(__xludf.DUMMYFUNCTION("""COMPUTED_VALUE"""),"JAVIER ALGABA GIL") -> JAVIER ALGABA GIL | J49: =IFERROR(__xludf.DUMMYFUNCTION("""COMPUTED_VALUE"""),45988) -> 45988 | K49: =IFERROR(__xludf.DUMMYFUNCTION("""COMPUTED_VALUE"""),"Factura audífonos") -> Factura audífonos | L49: =IFERROR(__xludf.DUMMYFUNCTION("""COMPUTED_VALUE"""),46042) -> 46042 | M49: =IFERROR(__xludf.DUMMYFUNCTION("""COMPUTED_VALUE"""),"NO") -> NO | N49: =IFERROR(__xludf.DUMMYFUNCTION("""COMPUTED_VALUE"""),2) -> 2 | O49: =IFERROR(__xludf.DUMMYFUNCTION("""COMPUTED_VALUE"""),"CONFORT") -> CONFORT | P49: =IFERROR(__xludf.DUMMYFUNCTION("""COMPUTED_VALUE"""),3630.77) -> 3630.77 | Q49: =IFERROR(__xludf.DUMMYFUNCTION("""COMPUTED_VALUE"""),"Luis Alberto Rodríguez") -> Luis Alberto Rodríguez | R49: =IFERROR(__xludf.DUMMYFUNCTION("""COMPUTED_VALUE"""),"Estefanía Berrocal Postigo") -> Estefanía Berrocal Postigo | S49: =IFERROR(__xludf.DUMMYFUNCTION("""COMPUTED_VALUE"""),"03 ORL") -> 03 ORL | T49: =IFERROR(__xludf.DUMMYFUNCTION("""COMPUTED_VALUE"""),"06 ORL") -> 06 ORL
B50: =IF($C50="","",LEFT(C50,3)) -> MBM | C50: =IFERROR(__xludf.DUMMYFUNCTION("""COMPUTED_VALUE"""),"MBM149") -> MBM149 | D50: =IFERROR(__xludf.DUMMYFUNCTION("""COMPUTED_VALUE"""),"PROPIOS") -> PROPIOS | E50: =IFERROR(__xludf.DUMMYFUNCTION("""COMPUTED_VALUE"""),2026) -> 2026 | F50: =IFERROR(__xludf.DUMMYFUNCTION("""COMPUTED_VALUE"""),1) -> 1 | G50: =IFERROR(__xludf.DUMMYFUNCTION("""COMPUTED_VALUE"""),"Toledo") -> Toledo | H50: =IFERROR(__xludf.DUMMYFUNCTION("""COMPUTED_VALUE"""),"C202512418122957997") -> C202512418122957997 | I50: =IFERROR(__xludf.DUMMYFUNCTION("""COMPUTED_VALUE"""),"Maria Isabel Espinosa Martinez") -> Maria Isabel Espinosa Martinez | J50: =IFERROR(__xludf.DUMMYFUNCTION("""COMPUTED_VALUE"""),45995) -> 45995 | K50: =IFERROR(__xludf.DUMMYFUNCTION("""COMPUTED_VALUE"""),"Factura audífonos") -> Factura audífonos | L50: =IFERROR(__xludf.DUMMYFUNCTION("""COMPUTED_VALUE"""),46042) -> 46042 | M50: =IFERROR(__xludf.DUMMYFUNCTION("""COMPUTED_VALUE"""),"NO") -> NO | N50: =IFERROR(__xludf.DUMMYFUNCTION("""COMPUTED_VALUE"""),2) -> 2 | O50: =IFERROR(__xludf.DUMMYFUNCTION("""COMPUTED_VALUE"""),"CONFORT") -> CONFORT | P50: =IFERROR(__xludf.DUMMYFUNCTION("""COMPUTED_VALUE"""),3631.82) -> 3631.82 | Q50: =IFERROR(__xludf.DUMMYFUNCTION("""COMPUTED_VALUE"""),"Maika Blázquez") -> Maika Blázquez | R50: =IFERROR(__xludf.DUMMYFUNCTION("""COMPUTED_VALUE"""),"María Garrote Garrote") -> María Garrote Garrote | S50: =IFERROR(__xludf.DUMMYFUNCTION("""COMPUTED_VALUE"""),"03 ORL") -> 03 ORL | T50: =IFERROR(__xludf.DUMMYFUNCTION("""COMPUTED_VALUE"""),"06 ORL") -> 06 ORL
B51: =IF($C51="","",LEFT(C51,3)) -> ISL | C51: =IFERROR(__xludf.DUMMYFUNCTION("""COMPUTED_VALUE"""),"ISL37") -> ISL37 | D51: =IFERROR(__xludf.DUMMYFUNCTION("""COMPUTED_VALUE"""),"PROPIOS") -> PROPIOS | E51: =IFERROR(__xludf.DUMMYFUNCTION("""COMPUTED_VALUE"""),2026) -> 2026 | F51: =IFERROR(__xludf.DUMMYFUNCTION("""COMPUTED_VALUE"""),1) -> 1 | G51: =IFERROR(__xludf.DUMMYFUNCTION("""COMPUTED_VALUE"""),"Alicante") -> Alicante | H51: =IFERROR(__xludf.DUMMYFUNCTION("""COMPUTED_VALUE"""),"C202512910126436073") -> C202512910126436073 | I51: =IFERROR(__xludf.DUMMYFUNCTION("""COMPUTED_VALUE"""),"JERONIMO MACIA MAS") -> JERONIMO MACIA MAS | J51: =IFERROR(__xludf.DUMMYFUNCTION("""COMPUTED_VALUE"""),46000) -> 46000 | K51: =IFERROR(__xludf.DUMMYFUNCTION("""COMPUTED_VALUE"""),"Factura audífonos") -> Factura audífonos | L51: =IFERROR(__xludf.DUMMYFUNCTION("""COMPUTED_VALUE"""),46042) -> 46042 | M51: =IFERROR(__xludf.DUMMYFUNCTION("""COMPUTED_VALUE"""),"NO") -> NO | N51: =IFERROR(__xludf.DUMMYFUNCTION("""COMPUTED_VALUE"""),2) -> 2 | O51: =IFERROR(__xludf.DUMMYFUNCTION("""COMPUTED_VALUE"""),"PRO") -> PRO | P51: =IFERROR(__xludf.DUMMYFUNCTION("""COMPUTED_VALUE"""),4536.36) -> 4536.36 | Q51: =IFERROR(__xludf.DUMMYFUNCTION("""COMPUTED_VALUE"""),"Iván Sánchez") -> Iván Sánchez | R51: =IFERROR(__xludf.DUMMYFUNCTION("""COMPUTED_VALUE"""),"Guillermo Severá Ferrándiz") -> Guillermo Severá Ferrándiz | S51: =IFERROR(__xludf.DUMMYFUNCTION("""COMPUTED_VALUE"""),"03 ORL") -> 03 ORL | T51: =IFERROR(__xludf.DUMMYFUNCTION("""COMPUTED_VALUE"""),"06 ORL") -> 06 ORL
B52: =IF($C52="","",LEFT(C52,3)) -> ISL | C52: =IFERROR(__xludf.DUMMYFUNCTION("""COMPUTED_VALUE"""),"ISL91") -> ISL91 | D52: =IFERROR(__xludf.DUMMYFUNCTION("""COMPUTED_VALUE"""),"PROPIOS") -> PROPIOS | E52: =IFERROR(__xludf.DUMMYFUNCTION("""COMPUTED_VALUE"""),2026) -> 2026 | F52: =IFERROR(__xludf.DUMMYFUNCTION("""COMPUTED_VALUE"""),1) -> 1 | G52: =IFERROR(__xludf.DUMMYFUNCTION("""COMPUTED_VALUE"""),"Albacete") -> Albacete | H52: =IFERROR(__xludf.DUMMYFUNCTION("""COMPUTED_VALUE"""),"C202512121711459148") -> C202512121711459148 | I52: =IFERROR(__xludf.DUMMYFUNCTION("""COMPUTED_VALUE"""),"JOSE JUAN AROCA PEREZ") -> JOSE JUAN AROCA PEREZ | J52: =IFERROR(__xludf.DUMMYFUNCTION("""COMPUTED_VALUE"""),46003) -> 46003 | K52: =IFERROR(__xludf.DUMMYFUNCTION("""COMPUTED_VALUE"""),"Factura audífonos") -> Factura audífonos | L52: =IFERROR(__xludf.DUMMYFUNCTION("""COMPUTED_VALUE"""),46042) -> 46042 | M52: =IFERROR(__xludf.DUMMYFUNCTION("""COMPUTED_VALUE"""),"NO") -> NO | N52: =IFERROR(__xludf.DUMMYFUNCTION("""COMPUTED_VALUE"""),2) -> 2 | O52: =IFERROR(__xludf.DUMMYFUNCTION("""COMPUTED_VALUE"""),"QUIET") -> QUIET | P52: =IFERROR(__xludf.DUMMYFUNCTION("""COMPUTED_VALUE"""),2718.18) -> 2718.18 | Q52: =IFERROR(__xludf.DUMMYFUNCTION("""COMPUTED_VALUE"""),"Iván Sánchez") -> Iván Sánchez | R52: =IFERROR(__xludf.DUMMYFUNCTION("""COMPUTED_VALUE"""),"Alejandra Jara Maquilón") -> Alejandra Jara Maquilón | S52: =IFERROR(__xludf.DUMMYFUNCTION("""COMPUTED_VALUE"""),"03 ORL") -> 03 ORL | T52: =IFERROR(__xludf.DUMMYFUNCTION("""COMPUTED_VALUE"""),"06 ORL") -> 06 ORL
B53: =IF($C53="","",LEFT(C53,3)) -> LAA | C53: =IFERROR(__xludf.DUMMYFUNCTION("""COMPUTED_VALUE"""),"LAA13") -> LAA13 | D53: =IFERROR(__xludf.DUMMYFUNCTION("""COMPUTED_VALUE"""),"PROPIOS") -> PROPIOS | E53: =IFERROR(__xludf.DUMMYFUNCTION("""COMPUTED_VALUE"""),2026) -> 2026 | F53: =IFERROR(__xludf.DUMMYFUNCTION("""COMPUTED_VALUE"""),1) -> 1 | G53: =IFERROR(__xludf.DUMMYFUNCTION("""COMPUTED_VALUE"""),"Sevilla- Montoto") -> Sevilla- Montoto | H53: =IFERROR(__xludf.DUMMYFUNCTION("""COMPUTED_VALUE"""),"C202510311713966723") -> C202510311713966723 | I53: =IFERROR(__xludf.DUMMYFUNCTION("""COMPUTED_VALUE"""),"MANUEL LOZANO PADILLA") -> MANUEL LOZANO PADILLA | J53: =IFERROR(__xludf.DUMMYFUNCTION("""COMPUTED_VALUE"""),45961) -> 45961 | K53: =IFERROR(__xludf.DUMMYFUNCTION("""COMPUTED_VALUE"""),"Factura audífonos") -> Factura audífonos | L53: =IFERROR(__xludf.DUMMYFUNCTION("""COMPUTED_VALUE"""),46043) -> 46043 | M53: =IFERROR(__xludf.DUMMYFUNCTION("""COMPUTED_VALUE"""),"NO") -> NO | N53: =IFERROR(__xludf.DUMMYFUNCTION("""COMPUTED_VALUE"""),2) -> 2 | O53: =IFERROR(__xludf.DUMMYFUNCTION("""COMPUTED_VALUE"""),"CONFORT") -> CONFORT | P53: =IFERROR(__xludf.DUMMYFUNCTION("""COMPUTED_VALUE"""),3631.82) -> 3631.82 | Q53: =IFERROR(__xludf.DUMMYFUNCTION("""COMPUTED_VALUE"""),"Luis Alberto Rodríguez") -> Luis Alberto Rodríguez | R53: =IFERROR(__xludf.DUMMYFUNCTION("""COMPUTED_VALUE"""),"Francisco Javier Aguilar Vera") -> Francisco Javier Aguilar Vera | S53: =IFERROR(__xludf.DUMMYFUNCTION("""COMPUTED_VALUE"""),"03 ORL") -> 03 ORL | T53: =IFERROR(__xludf.DUMMYFUNCTION("""COMPUTED_VALUE"""),"06 ORL") -> 06 ORL
B54: =IF($C54="","",LEFT(C54,3)) -> ISL | C54: =IFERROR(__xludf.DUMMYFUNCTION("""COMPUTED_VALUE"""),"ISL58") -> ISL58 | D54: =IFERROR(__xludf.DUMMYFUNCTION("""COMPUTED_VALUE"""),"PROPIOS") -> PROPIOS | E54: =IFERROR(__xludf.DUMMYFUNCTION("""COMPUTED_VALUE"""),2026) -> 2026 | F54: =IFERROR(__xludf.DUMMYFUNCTION("""COMPUTED_VALUE"""),1) -> 1 | G54: =IFERROR(__xludf.DUMMYFUNCTION("""COMPUTED_VALUE"""),"Orihuela") -> Orihuela | H54: =IFERROR(__xludf.DUMMYFUNCTION("""COMPUTED_VALUE"""),"C202512311581610869") -> C202512311581610869 | I54: =IFERROR(__xludf.DUMMYFUNCTION("""COMPUTED_VALUE"""),"JOSÉ EDUARDO DE LA FUENTE FERNANDEZ") -> JOSÉ EDUARDO DE LA FUENTE FERNANDEZ | J54: =IFERROR(__xludf.DUMMYFUNCTION("""COMPUTED_VALUE"""),45994) -> 45994 | K54: =IFERROR(__xludf.DUMMYFUNCTION("""COMPUTED_VALUE"""),"Factura audífonos") -> Factura audífonos | L54: =IFERROR(__xludf.DUMMYFUNCTION("""COMPUTED_VALUE"""),46043) -> 46043 | M54: =IFERROR(__xludf.DUMMYFUNCTION("""COMPUTED_VALUE"""),"NO") -> NO | N54: =IFERROR(__xludf.DUMMYFUNCTION("""COMPUTED_VALUE"""),2) -> 2 | O54: =IFERROR(__xludf.DUMMYFUNCTION("""COMPUTED_VALUE"""),"CONFORT") -> CONFORT | P54: =IFERROR(__xludf.DUMMYFUNCTION("""COMPUTED_VALUE"""),3631.73) -> 3631.73 | Q54: =IFERROR(__xludf.DUMMYFUNCTION("""COMPUTED_VALUE"""),"Iván Sánchez") -> Iván Sánchez | R54: =IFERROR(__xludf.DUMMYFUNCTION("""COMPUTED_VALUE"""),"Juan Javier Álvarez López") -> Juan Javier Álvarez López | S54: =IFERROR(__xludf.DUMMYFUNCTION("""COMPUTED_VALUE"""),"03 ORL") -> 03 ORL | T54: =IFERROR(__xludf.DUMMYFUNCTION("""COMPUTED_VALUE"""),"06 ORL") -> 06 ORL
B55: =IF($C55="","",LEFT(C55,3)) -> MBM | C55: =IFERROR(__xludf.DUMMYFUNCTION("""COMPUTED_VALUE"""),"MBM149") -> MBM149 | D55: =IFERROR(__xludf.DUMMYFUNCTION("""COMPUTED_VALUE"""),"PROPIOS") -> PROPIOS | E55: =IFERROR(__xludf.DUMMYFUNCTION("""COMPUTED_VALUE"""),2026) -> 2026 | F55: =IFERROR(__xludf.DUMMYFUNCTION("""COMPUTED_VALUE"""),1) -> 1 | G55: =IFERROR(__xludf.DUMMYFUNCTION("""COMPUTED_VALUE"""),"Getafe") -> Getafe | H55: =IFERROR(__xludf.DUMMYFUNCTION("""COMPUTED_VALUE"""),"C202512595841880689") -> C202512595841880689 | I55: =IFERROR(__xludf.DUMMYFUNCTION("""COMPUTED_VALUE"""),"MARIA ROSA FELIU CASADO") -> MARIA ROSA FELIU CASADO | J55: =IFERROR(__xludf.DUMMYFUNCTION("""COMPUTED_VALUE"""),45996) -> 45996 | K55: =IFERROR(__xludf.DUMMYFUNCTION("""COMPUTED_VALUE"""),"Factura audífonos") -> Factura audífonos | L55: =IFERROR(__xludf.DUMMYFUNCTION("""COMPUTED_VALUE"""),46043) -> 46043 | M55: =IFERROR(__xludf.DUMMYFUNCTION("""COMPUTED_VALUE"""),"NO") -> NO | N55: =IFERROR(__xludf.DUMMYFUNCTION("""COMPUTED_VALUE"""),2) -> 2 | O55: =IFERROR(__xludf.DUMMYFUNCTION("""COMPUTED_VALUE"""),"QUIET") -> QUIET | P55: =IFERROR(__xludf.DUMMYFUNCTION("""COMPUTED_VALUE"""),2445.45) -> 2445.45 | Q55: =IFERROR(__xludf.DUMMYFUNCTION("""COMPUTED_VALUE"""),"Maika Blázquez") -> Maika Blázquez | R55: =IFERROR(__xludf.DUMMYFUNCTION("""COMPUTED_VALUE"""),"María Garrote Garrote") -> María Garrote Garrote | S55: =IFERROR(__xludf.DUMMYFUNCTION("""COMPUTED_VALUE"""),"03 ORL") -> 03 ORL | T55: =IFERROR(__xludf.DUMMYFUNCTION("""COMPUTED_VALUE"""),"06 ORL") -> 06 ORL
B56: =IF($C56="","",LEFT(C56,3)) -> ISL | C56: =IFERROR(__xludf.DUMMYFUNCTION("""COMPUTED_VALUE"""),"ISL14") -> ISL14 | D56: =IFERROR(__xludf.DUMMYFUNCTION("""COMPUTED_VALUE"""),"PROPIOS") -> PROPIOS | E56: =IFERROR(__xludf.DUMMYFUNCTION("""COMPUTED_VALUE"""),2026) -> 2026 | F56: =IFERROR(__xludf.DUMMYFUNCTION("""COMPUTED_VALUE"""),1) -> 1 | G56: =IFERROR(__xludf.DUMMYFUNCTION("""COMPUTED_VALUE"""),"Alicante") -> Alicante | H56: =IFERROR(__xludf.DUMMYFUNCTION("""COMPUTED_VALUE"""),"C202512169525324632") -> C202512169525324632 | I56: =IFERROR(__xludf.DUMMYFUNCTION("""COMPUTED_VALUE"""),"MAURIZIO CENCIARELLI") -> MAURIZIO CENCIARELLI | J56: =IFERROR(__xludf.DUMMYFUNCTION("""COMPUTED_VALUE"""),46007) -> 46007 | K56: =IFERROR(__xludf.DUMMYFUNCTION("""COMPUTED_VALUE"""),"Factura audífonos") -> Factura audífonos | L56: =IFERROR(__xludf.DUMMYFUNCTION("""COMPUTED_VALUE"""),46044) -> 46044 | M56: =IFERROR(__xludf.DUMMYFUNCTION("""COMPUTED_VALUE"""),"NO") -> NO | N56: =IFERROR(__xludf.DUMMYFUNCTION("""COMPUTED_VALUE"""),2) -> 2 | O56: =IFERROR(__xludf.DUMMYFUNCTION("""COMPUTED_VALUE"""),"ADVANCED") -> ADVANCED | P56: =IFERROR(__xludf.DUMMYFUNCTION("""COMPUTED_VALUE"""),4136.36) -> 4136.36 | Q56: =IFERROR(__xludf.DUMMYFUNCTION("""COMPUTED_VALUE"""),"Iván Sánchez") -> Iván Sánchez | R56: =IFERROR(__xludf.DUMMYFUNCTION("""COMPUTED_VALUE"""),"Carlos Velásquez Fermín") -> Carlos Velásquez Fermín | S56: =IFERROR(__xludf.DUMMYFUNCTION("""COMPUTED_VALUE"""),"03 ORL") -> 03 ORL | T56: =IFERROR(__xludf.DUMMYFUNCTION("""COMPUTED_VALUE"""),"06 ORL") -> 06 ORL
B57: =IF($C57="","",LEFT(C57,3)) -> LRM | C57: =IFERROR(__xludf.DUMMYFUNCTION("""COMPUTED_VALUE"""),"LRM153") -> LRM153 | D57: =IFERROR(__xludf.DUMMYFUNCTION("""COMPUTED_VALUE"""),"ASOCIADOS") -> ASOCIADOS | E57: =IFERROR(__xludf.DUMMYFUNCTION("""COMPUTED_VALUE"""),2026) -> 2026 | F57: =IFERROR(__xludf.DUMMYFUNCTION("""COMPUTED_VALUE"""),1) -> 1 | G57: =IFERROR(__xludf.DUMMYFUNCTION("""COMPUTED_VALUE"""),"Cáceres") -> Cáceres | H57: =IFERROR(__xludf.DUMMYFUNCTION("""COMPUTED_VALUE"""),"C202512268393761744") -> C202512268393761744 | I57: =IFERROR(__xludf.DUMMYFUNCTION("""COMPUTED_VALUE"""),"DAVID SOCORRO FERRER") -> DAVID SOCORRO FERRER | J57: =IFERROR(__xludf.DUMMYFUNCTION("""COMPUTED_VALUE"""),46017) -> 46017 | K57: =IFERROR(__xludf.DUMMYFUNCTION("""COMPUTED_VALUE"""),"Factura audífonos") -> Factura audífonos | L57: =IFERROR(__xludf.DUMMYFUNCTION("""COMPUTED_VALUE"""),46044) -> 46044 | M57: =IFERROR(__xludf.DUMMYFUNCTION("""COMPUTED_VALUE"""),"NO") -> NO | N57: =IFERROR(__xludf.DUMMYFUNCTION("""COMPUTED_VALUE"""),2) -> 2 | O57: =IFERROR(__xludf.DUMMYFUNCTION("""COMPUTED_VALUE"""),"QUIET") -> QUIET | P57: =IFERROR(__xludf.DUMMYFUNCTION("""COMPUTED_VALUE"""),3163.64) -> 3163.64 | Q57: =IFERROR(__xludf.DUMMYFUNCTION("""COMPUTED_VALUE"""),"Lisandro Russian") -> Lisandro Russian | R57: =IFERROR(__xludf.DUMMYFUNCTION("""COMPUTED_VALUE"""),"Daniela Carolina Laguado Bulgheroni") -> Daniela Carolina Laguado Bulgheroni | S57: =IFERROR(__xludf.DUMMYFUNCTION("""COMPUTED_VALUE"""),"03 ORL") -> 03 ORL | T57: =IFERROR(__xludf.DUMMYFUNCTION("""COMPUTED_VALUE"""),"06 ORL") -> 06 ORL
B58: =IF($C58="","",LEFT(C58,3)) -> RPG | C58: =IFERROR(__xludf.DUMMYFUNCTION("""COMPUTED_VALUE"""),"RPG37") -> RPG37 | D58: =IFERROR(__xludf.DUMMYFUNCTION("""COMPUTED_VALUE"""),"PARTICIPADOS") -> PARTICIPADOS | E58: =IFERROR(__xludf.DUMMYFUNCTION("""COMPUTED_VALUE"""),2026) -> 2026 | F58: =IFERROR(__xludf.DUMMYFUNCTION("""COMPUTED_VALUE"""),1) -> 1 | G58: =IFERROR(__xludf.DUMMYFUNCTION("""COMPUTED_VALUE"""),"Ourense") -> Ourense | H58: =IFERROR(__xludf.DUMMYFUNCTION("""COMPUTED_VALUE"""),"C202512392737668984") -> C202512392737668984 | I58: =IFERROR(__xludf.DUMMYFUNCTION("""COMPUTED_VALUE"""),"PABLO GOMEZ SEOANE") -> PABLO GOMEZ SEOANE | J58: =IFERROR(__xludf.DUMMYFUNCTION("""COMPUTED_VALUE"""),45994) -> 45994 | K58: =IFERROR(__xludf.DUMMYFUNCTION("""COMPUTED_VALUE"""),"Factura audífonos") -> Factura audífonos | L58: =IFERROR(__xludf.DUMMYFUNCTION("""COMPUTED_VALUE"""),46044) -> 46044 | M58: =IFERROR(__xludf.DUMMYFUNCTION("""COMPUTED_VALUE"""),"NO") -> NO | N58: =IFERROR(__xludf.DUMMYFUNCTION("""COMPUTED_VALUE"""),1) -> 1 | O58: =IFERROR(__xludf.DUMMYFUNCTION("""COMPUTED_VALUE"""),"CONFORT") -> CONFORT | P58: =IFERROR(__xludf.DUMMYFUNCTION("""COMPUTED_VALUE"""),2180.91) -> 2180.91 | Q58: =IFERROR(__xludf.DUMMYFUNCTION("""COMPUTED_VALUE"""),"Alberto Moreno") -> Alberto Moreno | R58: =IFERROR(__xludf.DUMMYFUNCTION("""COMPUTED_VALUE"""),"Ana Quintana Sanjuan") -> Ana Quintana Sanjuan | S58: =IFERROR(__xludf.DUMMYFUNCTION("""COMPUTED_VALUE"""),"03 ORL") -> 03 ORL | T58: =IFERROR(__xludf.DUMMYFUNCTION("""COMPUTED_VALUE"""),"06 ORL") -> 06 ORL
B59: =IF($C59="","",LEFT(C59,3)) -> MBM | C59: =IFERROR(__xludf.DUMMYFUNCTION("""COMPUTED_VALUE"""),"MBM115") -> MBM115 | D59: =IFERROR(__xludf.DUMMYFUNCTION("""COMPUTED_VALUE"""),"PARTICIPADOS") -> PARTICIPADOS | E59: =IFERROR(__xludf.DUMMYFUNCTION("""COMPUTED_VALUE"""),2026) -> 2026 | F59: =IFERROR(__xludf.DUMMYFUNCTION("""COMPUTED_VALUE"""),1) -> 1 | G59: =IFERROR(__xludf.DUMMYFUNCTION("""COMPUTED_VALUE"""),"Madrid- La Oca") -> Madrid- La Oca | H59: =IFERROR(__xludf.DUMMYFUNCTION("""COMPUTED_VALUE"""),"C20251210112255528") -> C20251210112255528 | I59: =IFERROR(__xludf.DUMMYFUNCTION("""COMPUTED_VALUE"""),"EMILIO RUIZ-ROSO CASTAÑO") -> EMILIO RUIZ-ROSO CASTAÑO | J59: =IFERROR(__xludf.DUMMYFUNCTION("""COMPUTED_VALUE"""),45973) -> 45973 | K59: =IFERROR(__xludf.DUMMYFUNCTION("""COMPUTED_VALUE"""),"Factura audífonos") -> Factura audífonos | L59: =IFERROR(__xludf.DUMMYFUNCTION("""COMPUTED_VALUE"""),46044) -> 46044 | M59: =IFERROR(__xludf.DUMMYFUNCTION("""COMPUTED_VALUE"""),"NO") -> NO | N59: =IFERROR(__xludf.DUMMYFUNCTION("""COMPUTED_VALUE"""),2) -> 2 | O59: =IFERROR(__xludf.DUMMYFUNCTION("""COMPUTED_VALUE"""),"QUIET") -> QUIET | P59: =IFERROR(__xludf.DUMMYFUNCTION("""COMPUTED_VALUE"""),2545.45) -> 2545.45 | Q59: =IFERROR(__xludf.DUMMYFUNCTION("""COMPUTED_VALUE"""),"Maika Blázquez") -> Maika Blázquez | R59: =IFERROR(__xludf.DUMMYFUNCTION("""COMPUTED_VALUE"""),"Esther Macon Liquete") -> Esther Macon Liquete | S59: =IFERROR(__xludf.DUMMYFUNCTION("""COMPUTED_VALUE"""),"03 ORL") -> 03 ORL | T59: =IFERROR(__xludf.DUMMYFUNCTION("""COMPUTED_VALUE"""),"06 ORL") -> 06 ORL
B60: =IF($C60="","",LEFT(C60,3)) | D60: =IFERROR(__xludf.DUMMYFUNCTION("""COMPUTED_VALUE"""),"ASOCIADOS") -> ASOCIADOS | E60: =IFERROR(__xludf.DUMMYFUNCTION("""COMPUTED_VALUE"""),2026) -> 2026 | F60: =IFERROR(__xludf.DUMMYFUNCTION("""COMPUTED_VALUE"""),1) -> 1 | G60: =IFERROR(__xludf.DUMMYFUNCTION("""COMPUTED_VALUE"""),"Badajoz") -> Badajoz | H60: =IFERROR(__xludf.DUMMYFUNCTION("""COMPUTED_VALUE"""),"BJZE-2540") -> BJZE-2540 | I60: =IFERROR(__xludf.DUMMYFUNCTION("""COMPUTED_VALUE"""),"MARIA INMACULADA BENAVENTE POZO") -> MARIA INMACULADA BENAVENTE POZO | J60: =IFERROR(__xludf.DUMMYFUNCTION("""COMPUTED_VALUE"""),45964) -> 45964 | K60: =IFERROR(__xludf.DUMMYFUNCTION("""COMPUTED_VALUE"""),"Factura audífonos") -> Factura audífonos | L60: =IFERROR(__xludf.DUMMYFUNCTION("""COMPUTED_VALUE"""),46044) -> 46044 | M60: =IFERROR(__xludf.DUMMYFUNCTION("""COMPUTED_VALUE"""),"NO") -> NO | N60: =IFERROR(__xludf.DUMMYFUNCTION("""COMPUTED_VALUE"""),2) -> 2 | O60: =IFERROR(__xludf.DUMMYFUNCTION("""COMPUTED_VALUE"""),"QUIET") -> QUIET | P60: =IFERROR(__xludf.DUMMYFUNCTION("""COMPUTED_VALUE"""),3263.64) -> 3263.64 | Q60: =IFERROR(__xludf.DUMMYFUNCTION("""COMPUTED_VALUE"""),"Luis Alberto Rodríguez") -> Luis Alberto Rodríguez | R60: =IFERROR(__xludf.DUMMYFUNCTION("""COMPUTED_VALUE"""),"No recuerda ORL") -> No recuerda ORL | S60: =IFERROR(__xludf.DUMMYFUNCTION("""COMPUTED_VALUE"""),"03 ORL") -> 03 ORL | T60: =IFERROR(__xludf.DUMMYFUNCTION("""COMPUTED_VALUE"""),"06 ORL") -> 06 ORL
B61: =IF($C61="","",LEFT(C61,3)) -> RFV | C61: =IFERROR(__xludf.DUMMYFUNCTION("""COMPUTED_VALUE"""),"RFV47") -> RFV47 | D61: =IFERROR(__xludf.DUMMYFUNCTION("""COMPUTED_VALUE"""),"PROPIOS") -> PROPIOS | E61: =IFERROR(__xludf.DUMMYFUNCTION("""COMPUTED_VALUE"""),2026) -> 2026 | F61: =IFERROR(__xludf.DUMMYFUNCTION("""COMPUTED_VALUE"""),1) -> 1 | G61: =IFERROR(__xludf.DUMMYFUNCTION("""COMPUTED_VALUE"""),"Almería") -> Almería | H61: =IFERROR(__xludf.DUMMYFUNCTION("""COMPUTED_VALUE"""),"C202512161837483546") -> C202512161837483546 | I61: =IFERROR(__xludf.DUMMYFUNCTION("""COMPUTED_VALUE"""),"DIEGO LOPEZ CAYUELA") -> DIEGO LOPEZ CAYUELA | J61: =IFERROR(__xludf.DUMMYFUNCTION("""COMPUTED_VALUE"""),46007) -> 46007 | K61: =IFERROR(__xludf.DUMMYFUNCTION("""COMPUTED_VALUE"""),"Factura audífonos") -> Factura audífonos | L61: =IFERROR(__xludf.DUMMYFUNCTION("""COMPUTED_VALUE"""),46044) -> 46044 | M61: =IFERROR(__xludf.DUMMYFUNCTION("""COMPUTED_VALUE"""),"NO") -> NO | N61: =IFERROR(__xludf.DUMMYFUNCTION("""COMPUTED_VALUE"""),2) -> 2 | O61: =IFERROR(__xludf.DUMMYFUNCTION("""COMPUTED_VALUE"""),"QUIET") -> QUIET | P61: =IFERROR(__xludf.DUMMYFUNCTION("""COMPUTED_VALUE"""),2718.18) -> 2718.18 | Q61: =IFERROR(__xludf.DUMMYFUNCTION("""COMPUTED_VALUE"""),"Ramon Ferrando") -> Ramon Ferrando | R61: =IFERROR(__xludf.DUMMYFUNCTION("""COMPUTED_VALUE"""),"Elisheba Haro Hernández") -> Elisheba Haro Hernández | S61: =IFERROR(__xludf.DUMMYFUNCTION("""COMPUTED_VALUE"""),"03 ORL") -> 03 ORL | T61: =IFERROR(__xludf.DUMMYFUNCTION("""COMPUTED_VALUE"""),"06 ORL") -> 06 ORL
B62: =IF($C62="","",LEFT(C62,3)) -> LRM | C62: =IFERROR(__xludf.DUMMYFUNCTION("""COMPUTED_VALUE"""),"LRM253") -> LRM253 | D62: =IFERROR(__xludf.DUMMYFUNCTION("""COMPUTED_VALUE"""),"ASOCIADOS") -> ASOCIADOS | E62: =IFERROR(__xludf.DUMMYFUNCTION("""COMPUTED_VALUE"""),2026) -> 2026 | F62: =IFERROR(__xludf.DUMMYFUNCTION("""COMPUTED_VALUE"""),1) -> 1 | G62: =IFERROR(__xludf.DUMMYFUNCTION("""COMPUTED_VALUE"""),"Cáceres") -> Cáceres | H62: =IFERROR(__xludf.DUMMYFUNCTION("""COMPUTED_VALUE"""),"C202512151640123719") -> C202512151640123719 | I62: =IFERROR(__xludf.DUMMYFUNCTION("""COMPUTED_VALUE"""),"MARIA DOLORES PIMIENTA ROJAS") -> MARIA DOLORES PIMIENTA ROJAS | J62: =IFERROR(__xludf.DUMMYFUNCTION("""COMPUTED_VALUE"""),46006) -> 46006 | K62: =IFERROR(__xludf.DUMMYFUNCTION("""COMPUTED_VALUE"""),"Factura audífonos") -> Factura audífonos | L62: =IFERROR(__xludf.DUMMYFUNCTION("""COMPUTED_VALUE"""),46044) -> 46044 | M62: =IFERROR(__xludf.DUMMYFUNCTION("""COMPUTED_VALUE"""),"NO") -> NO | N62: =IFERROR(__xludf.DUMMYFUNCTION("""COMPUTED_VALUE"""),2) -> 2 | O62: =IFERROR(__xludf.DUMMYFUNCTION("""COMPUTED_VALUE"""),"ADVANCED") -> ADVANCED | P62: =IFERROR(__xludf.DUMMYFUNCTION("""COMPUTED_VALUE"""),4227.27) -> 4227.27 | Q62: =IFERROR(__xludf.DUMMYFUNCTION("""COMPUTED_VALUE"""),"Lisandro Russian") -> Lisandro Russian | R62: =IFERROR(__xludf.DUMMYFUNCTION("""COMPUTED_VALUE"""),"Marta García Jiménez") -> Marta García Jiménez | S62: =IFERROR(__xludf.DUMMYFUNCTION("""COMPUTED_VALUE"""),"03 ORL") -> 03 ORL | T62: =IFERROR(__xludf.DUMMYFUNCTION("""COMPUTED_VALUE"""),"06 ORL") -> 06 ORL
B63: =IF($C63="","",LEFT(C63,3)) -> LRM | C63: =IFERROR(__xludf.DUMMYFUNCTION("""COMPUTED_VALUE"""),"LRM07") -> LRM07 | D63: =IFERROR(__xludf.DUMMYFUNCTION("""COMPUTED_VALUE"""),"PROPIOS") -> PROPIOS | E63: =IFERROR(__xludf.DUMMYFUNCTION("""COMPUTED_VALUE"""),2026) -> 2026 | F63: =IFERROR(__xludf.DUMMYFUNCTION("""COMPUTED_VALUE"""),1) -> 1 | G63: =IFERROR(__xludf.DUMMYFUNCTION("""COMPUTED_VALUE"""),"Alcorcón") -> Alcorcón | H63: =IFERROR(__xludf.DUMMYFUNCTION("""COMPUTED_VALUE"""),"C202510131556115741") -> C202510131556115741 | I63: =IFERROR(__xludf.DUMMYFUNCTION("""COMPUTED_VALUE"""),"AMADOR FRIAS GONZALEZ") -> AMADOR FRIAS GONZALEZ | J63: =IFERROR(__xludf.DUMMYFUNCTION("""COMPUTED_VALUE"""),45943) -> 45943 | K63: =IFERROR(__xludf.DUMMYFUNCTION("""COMPUTED_VALUE"""),"Factura audífonos") -> Factura audífonos | L63: =IFERROR(__xludf.DUMMYFUNCTION("""COMPUTED_VALUE"""),46044) -> 46044 | M63: =IFERROR(__xludf.DUMMYFUNCTION("""COMPUTED_VALUE"""),"NO") -> NO | N63: =IFERROR(__xludf.DUMMYFUNCTION("""COMPUTED_VALUE"""),2) -> 2 | O63: =IFERROR(__xludf.DUMMYFUNCTION("""COMPUTED_VALUE"""),"QUIET") -> QUIET | P63: =IFERROR(__xludf.DUMMYFUNCTION("""COMPUTED_VALUE"""),2718.18) -> 2718.18 | Q63: =IFERROR(__xludf.DUMMYFUNCTION("""COMPUTED_VALUE"""),"Lisandro Russian") -> Lisandro Russian | R63: =IFERROR(__xludf.DUMMYFUNCTION("""COMPUTED_VALUE"""),"Álvaro Sánchez Álvarez") -> Álvaro Sánchez Álvarez | S63: =IFERROR(__xludf.DUMMYFUNCTION("""COMPUTED_VALUE"""),"03 ORL") -> 03 ORL | T63: =IFERROR(__xludf.DUMMYFUNCTION("""COMPUTED_VALUE"""),"06 ORL") -> 06 ORL
B64: =IF($C64="","",LEFT(C64,3)) -> LAA | C64: =IFERROR(__xludf.DUMMYFUNCTION("""COMPUTED_VALUE"""),"LAA16") -> LAA16 | D64: =IFERROR(__xludf.DUMMYFUNCTION("""COMPUTED_VALUE"""),"PROPIOS") -> PROPIOS | E64: =IFERROR(__xludf.DUMMYFUNCTION("""COMPUTED_VALUE"""),2026) -> 2026 | F64: =IFERROR(__xludf.DUMMYFUNCTION("""COMPUTED_VALUE"""),1) -> 1 | G64: =IFERROR(__xludf.DUMMYFUNCTION("""COMPUTED_VALUE"""),"Sevilla- Montoto") -> Sevilla- Montoto | H64: =IFERROR(__xludf.DUMMYFUNCTION("""COMPUTED_VALUE"""),"C202512111353317097") -> C202512111353317097 | I64: =IFERROR(__xludf.DUMMYFUNCTION("""COMPUTED_VALUE"""),"CARMEN MANCHA MACIAS") -> CARMEN MANCHA MACIAS | J64: =IFERROR(__xludf.DUMMYFUNCTION("""COMPUTED_VALUE"""),46002) -> 46002 | K64: =IFERROR(__xludf.DUMMYFUNCTION("""COMPUTED_VALUE"""),"Factura audífonos") -> Factura audífonos | L64: =IFERROR(__xludf.DUMMYFUNCTION("""COMPUTED_VALUE"""),46044) -> 46044 | M64: =IFERROR(__xludf.DUMMYFUNCTION("""COMPUTED_VALUE"""),"NO") -> NO | N64: =IFERROR(__xludf.DUMMYFUNCTION("""COMPUTED_VALUE"""),1) -> 1 | O64: =IFERROR(__xludf.DUMMYFUNCTION("""COMPUTED_VALUE"""),"ADVANCED") -> ADVANCED | P64: =IFERROR(__xludf.DUMMYFUNCTION("""COMPUTED_VALUE"""),2357.73) -> 2357.73 | Q64: =IFERROR(__xludf.DUMMYFUNCTION("""COMPUTED_VALUE"""),"Luis Alberto Rodríguez") -> Luis Alberto Rodríguez | R64: =IFERROR(__xludf.DUMMYFUNCTION("""COMPUTED_VALUE"""),"Francisco López Navas") -> Francisco López Navas | S64: =IFERROR(__xludf.DUMMYFUNCTION("""COMPUTED_VALUE"""),"03 ORL") -> 03 ORL | T64: =IFERROR(__xludf.DUMMYFUNCTION("""COMPUTED_VALUE"""),"06 ORL") -> 06 ORL
B65: =IF($C65="","",LEFT(C65,3)) -> ISL | C65: =IFERROR(__xludf.DUMMYFUNCTION("""COMPUTED_VALUE"""),"ISL14") -> ISL14 | D65: =IFERROR(__xludf.DUMMYFUNCTION("""COMPUTED_VALUE"""),"PROPIOS") -> PROPIOS | E65: =IFERROR(__xludf.DUMMYFUNCTION("""COMPUTED_VALUE"""),2026) -> 2026 | F65: =IFERROR(__xludf.DUMMYFUNCTION("""COMPUTED_VALUE"""),1) -> 1 | G65: =IFERROR(__xludf.DUMMYFUNCTION("""COMPUTED_VALUE"""),"Orihuela") -> Orihuela | H65: =IFERROR(__xludf.DUMMYFUNCTION("""COMPUTED_VALUE"""),"C202511201113975005") -> C202511201113975005 | I65: =IFERROR(__xludf.DUMMYFUNCTION("""COMPUTED_VALUE"""),"KAREN GHANDALYAN") -> KAREN GHANDALYAN | J65: =IFERROR(__xludf.DUMMYFUNCTION("""COMPUTED_VALUE"""),45981) -> 45981 | K65: =IFERROR(__xludf.DUMMYFUNCTION("""COMPUTED_VALUE"""),"Factura audífonos") -> Factura audífonos | L65: =IFERROR(__xludf.DUMMYFUNCTION("""COMPUTED_VALUE"""),46044) -> 46044 | M65: =IFERROR(__xludf.DUMMYFUNCTION("""COMPUTED_VALUE"""),"NO") -> NO | N65: =IFERROR(__xludf.DUMMYFUNCTION("""COMPUTED_VALUE"""),1) -> 1 | O65: =IFERROR(__xludf.DUMMYFUNCTION("""COMPUTED_VALUE"""),"ADVANCED") -> ADVANCED | P65: =IFERROR(__xludf.DUMMYFUNCTION("""COMPUTED_VALUE"""),2481.82) -> 2481.82 | Q65: =IFERROR(__xludf.DUMMYFUNCTION("""COMPUTED_VALUE"""),"Iván Sánchez") -> Iván Sánchez | R65: =IFERROR(__xludf.DUMMYFUNCTION("""COMPUTED_VALUE"""),"Carlos Velásquez Fermín") -> Carlos Velásquez Fermín | S65: =IFERROR(__xludf.DUMMYFUNCTION("""COMPUTED_VALUE"""),"03 ORL") -> 03 ORL | T65: =IFERROR(__xludf.DUMMYFUNCTION("""COMPUTED_VALUE"""),"06 ORL") -> 06 ORL
B66: =IF($C66="","",LEFT(C66,3)) -> MBM | C66: =IFERROR(__xludf.DUMMYFUNCTION("""COMPUTED_VALUE"""),"MBM184") -> MBM184 | D66: =IFERROR(__xludf.DUMMYFUNCTION("""COMPUTED_VALUE"""),"PROPIOS") -> PROPIOS | E66: =IFERROR(__xludf.DUMMYFUNCTION("""COMPUTED_VALUE"""),2026) -> 2026 | F66: =IFERROR(__xludf.DUMMYFUNCTION("""COMPUTED_VALUE"""),1) -> 1 | G66: =IFERROR(__xludf.DUMMYFUNCTION("""COMPUTED_VALUE"""),"Madrid- Monforte de Lemos") -> Madrid- Monforte de Lemos | H66: =IFERROR(__xludf.DUMMYFUNCTION("""COMPUTED_VALUE"""),"C202512159363301430") -> C202512159363301430 | I66: =IFERROR(__xludf.DUMMYFUNCTION("""COMPUTED_VALUE"""),"MARIA SAGRARIO TARANCON DE DIEGO") -> MARIA SAGRARIO TARANCON DE DIEGO | J66: =IFERROR(__xludf.DUMMYFUNCTION("""COMPUTED_VALUE"""),46006) -> 46006 | K66: =IFERROR(__xludf.DUMMYFUNCTION("""COMPUTED_VALUE"""),"Factura audífonos") -> Factura audífonos | L66: =IFERROR(__xludf.DUMMYFUNCTION("""COMPUTED_VALUE"""),46044) -> 46044 | M66: =IFERROR(__xludf.DUMMYFUNCTION("""COMPUTED_VALUE"""),"NO") -> NO | N66: =IFERROR(__xludf.DUMMYFUNCTION("""COMPUTED_VALUE"""),1) -> 1 | O66: =IFERROR(__xludf.DUMMYFUNCTION("""COMPUTED_VALUE"""),"CONFORT") -> CONFORT | P66: =IFERROR(__xludf.DUMMYFUNCTION("""COMPUTED_VALUE"""),2180.91) -> 2180.91 | Q66: =IFERROR(__xludf.DUMMYFUNCTION("""COMPUTED_VALUE"""),"Maika Blázquez") -> Maika Blázquez | R66: =IFERROR(__xludf.DUMMYFUNCTION("""COMPUTED_VALUE"""),"Victoria García Peces") -> Victoria García Peces | S66: =IFERROR(__xludf.DUMMYFUNCTION("""COMPUTED_VALUE"""),"03 ORL") -> 03 ORL | T66: =IFERROR(__xludf.DUMMYFUNCTION("""COMPUTED_VALUE"""),"06 ORL") -> 06 ORL
B67: =IF($C67="","",LEFT(C67,3)) -> ISL | C67: =IFERROR(__xludf.DUMMYFUNCTION("""COMPUTED_VALUE"""),"ISL113") -> ISL113 | D67: =IFERROR(__xludf.DUMMYFUNCTION("""COMPUTED_VALUE"""),"PROPIOS") -> PROPIOS | E67: =IFERROR(__xludf.DUMMYFUNCTION("""COMPUTED_VALUE"""),2026) -> 2026 | F67: =IFERROR(__xludf.DUMMYFUNCTION("""COMPUTED_VALUE"""),1) -> 1 | G67: =IFERROR(__xludf.DUMMYFUNCTION("""COMPUTED_VALUE"""),"Alicante") -> Alicante | H67: =IFERROR(__xludf.DUMMYFUNCTION("""COMPUTED_VALUE"""),"C202512221119249267") -> C202512221119249267 | I67: =IFERROR(__xludf.DUMMYFUNCTION("""COMPUTED_VALUE"""),"ANTONIA LOPEZ NIETO") -> ANTONIA LOPEZ NIETO | J67: =IFERROR(__xludf.DUMMYFUNCTION("""COMPUTED_VALUE"""),46013) -> 46013 | K67: =IFERROR(__xludf.DUMMYFUNCTION("""COMPUTED_VALUE"""),"Factura audífonos") -> Factura audífonos | L67: =IFERROR(__xludf.DUMMYFUNCTION("""COMPUTED_VALUE"""),46044) -> 46044 | M67: =IFERROR(__xludf.DUMMYFUNCTION("""COMPUTED_VALUE"""),"NO") -> NO | N67: =IFERROR(__xludf.DUMMYFUNCTION("""COMPUTED_VALUE"""),1) -> 1 | O67: =IFERROR(__xludf.DUMMYFUNCTION("""COMPUTED_VALUE"""),"CONFORT") -> CONFORT | P67: =IFERROR(__xludf.DUMMYFUNCTION("""COMPUTED_VALUE"""),2180.91) -> 2180.91 | Q67: =IFERROR(__xludf.DUMMYFUNCTION("""COMPUTED_VALUE"""),"Iván Sánchez") -> Iván Sánchez | R67: =IFERROR(__xludf.DUMMYFUNCTION("""COMPUTED_VALUE"""),"Luisa Payá Pérez") -> Luisa Payá Pérez | S67: =IFERROR(__xludf.DUMMYFUNCTION("""COMPUTED_VALUE"""),"03 ORL") -> 03 ORL | T67: =IFERROR(__xludf.DUMMYFUNCTION("""COMPUTED_VALUE"""),"06 ORL") -> 06 ORL
B68: =IF($C68="","",LEFT(C68,3)) -> ISL | C68: =IFERROR(__xludf.DUMMYFUNCTION("""COMPUTED_VALUE"""),"ISL65") -> ISL65 | D68: =IFERROR(__xludf.DUMMYFUNCTION("""COMPUTED_VALUE"""),"PROPIOS") -> PROPIOS | E68: =IFERROR(__xludf.DUMMYFUNCTION("""COMPUTED_VALUE"""),2026) -> 2026 | F68: =IFERROR(__xludf.DUMMYFUNCTION("""COMPUTED_VALUE"""),1) -> 1 | G68: =IFERROR(__xludf.DUMMYFUNCTION("""COMPUTED_VALUE"""),"Albacete") -> Albacete | H68: =IFERROR(__xludf.DUMMYFUNCTION("""COMPUTED_VALUE"""),"C202511271222372314") -> C202511271222372314 | I68: =IFERROR(__xludf.DUMMYFUNCTION("""COMPUTED_VALUE"""),"JOSE PLAZA BLAZQUEZ") -> JOSE PLAZA BLAZQUEZ | J68: =IFERROR(__xludf.DUMMYFUNCTION("""COMPUTED_VALUE"""),45988) -> 45988 | K68: =IFERROR(__xludf.DUMMYFUNCTION("""COMPUTED_VALUE"""),"Factura audífonos") -> Factura audífonos | L68: =IFERROR(__xludf.DUMMYFUNCTION("""COMPUTED_VALUE"""),46045) -> 46045 | M68: =IFERROR(__xludf.DUMMYFUNCTION("""COMPUTED_VALUE"""),"NO") -> NO | N68: =IFERROR(__xludf.DUMMYFUNCTION("""COMPUTED_VALUE"""),1) -> 1 | O68: =IFERROR(__xludf.DUMMYFUNCTION("""COMPUTED_VALUE"""),"ADVANCED") -> ADVANCED | P68: =IFERROR(__xludf.DUMMYFUNCTION("""COMPUTED_VALUE"""),2372.73) -> 2372.73 | Q68: =IFERROR(__xludf.DUMMYFUNCTION("""COMPUTED_VALUE"""),"Iván Sánchez") -> Iván Sánchez | R68: =IFERROR(__xludf.DUMMYFUNCTION("""COMPUTED_VALUE"""),"Manuel García López") -> Manuel García López | S68: =IFERROR(__xludf.DUMMYFUNCTION("""COMPUTED_VALUE"""),"03 ORL") -> 03 ORL | T68: =IFERROR(__xludf.DUMMYFUNCTION("""COMPUTED_VALUE"""),"22 AUDIOMETRIA CLINICA") -> 22 AUDIOMETRIA CLINICA
B69: =IF($C69="","",LEFT(C69,3)) -> RFV | C69: =IFERROR(__xludf.DUMMYFUNCTION("""COMPUTED_VALUE"""),"RFV38") -> RFV38 | D69: =IFERROR(__xludf.DUMMYFUNCTION("""COMPUTED_VALUE"""),"PROPIOS") -> PROPIOS | E69: =IFERROR(__xludf.DUMMYFUNCTION("""COMPUTED_VALUE"""),2026) -> 2026 | F69: =IFERROR(__xludf.DUMMYFUNCTION("""COMPUTED_VALUE"""),1) -> 1 | G69: =IFERROR(__xludf.DUMMYFUNCTION("""COMPUTED_VALUE"""),"El Albir (Benidorm)") -> El Albir (Benidorm) | H69: =IFERROR(__xludf.DUMMYFUNCTION("""COMPUTED_VALUE"""),"C202512183015487201") -> C202512183015487201 | I69: =IFERROR(__xludf.DUMMYFUNCTION("""COMPUTED_VALUE"""),"BERNABE SANCHIS SANZ") -> BERNABE SANCHIS SANZ | J69: =IFERROR(__xludf.DUMMYFUNCTION("""COMPUTED_VALUE"""),45992) -> 45992 | K69: =IFERROR(__xludf.DUMMYFUNCTION("""COMPUTED_VALUE"""),"Factura audífonos") -> Factura audífonos | L69: =IFERROR(__xludf.DUMMYFUNCTION("""COMPUTED_VALUE"""),46045) -> 46045 | M69: =IFERROR(__xludf.DUMMYFUNCTION("""COMPUTED_VALUE"""),"NO") -> NO | N69: =IFERROR(__xludf.DUMMYFUNCTION("""COMPUTED_VALUE"""),2) -> 2 | O69: =IFERROR(__xludf.DUMMYFUNCTION("""COMPUTED_VALUE"""),"CONFORT") -> CONFORT | P69: =IFERROR(__xludf.DUMMYFUNCTION("""COMPUTED_VALUE"""),3631.82) -> 3631.82 | Q69: =IFERROR(__xludf.DUMMYFUNCTION("""COMPUTED_VALUE"""),"Ramon Ferrando") -> Ramon Ferrando | R69: =IFERROR(__xludf.DUMMYFUNCTION("""COMPUTED_VALUE"""),"María Emilia García Ruiz") -> María Emilia García Ruiz | S69: =IFERROR(__xludf.DUMMYFUNCTION("""COMPUTED_VALUE"""),"03 ORL") -> 03 ORL | T69: =IFERROR(__xludf.DUMMYFUNCTION("""COMPUTED_VALUE"""),"06 ORL") -> 06 ORL
B70: =IF($C70="","",LEFT(C70,3)) -> RFV | C70: =IFERROR(__xludf.DUMMYFUNCTION("""COMPUTED_VALUE"""),"RFV49") -> RFV49 | D70: =IFERROR(__xludf.DUMMYFUNCTION("""COMPUTED_VALUE"""),"PROPIOS") -> PROPIOS | E70: =IFERROR(__xludf.DUMMYFUNCTION("""COMPUTED_VALUE"""),2026) -> 2026 | F70: =IFERROR(__xludf.DUMMYFUNCTION("""COMPUTED_VALUE"""),1) -> 1 | G70: =IFERROR(__xludf.DUMMYFUNCTION("""COMPUTED_VALUE"""),"Valencia- Parra") -> Valencia- Parra | H70: =IFERROR(__xludf.DUMMYFUNCTION("""COMPUTED_VALUE"""),"C202511251235490541") -> C202511251235490541 | I70: =IFERROR(__xludf.DUMMYFUNCTION("""COMPUTED_VALUE"""),"CRISTOBAL SOBREVELA LOPEZ") -> CRISTOBAL SOBREVELA LOPEZ | J70: =IFERROR(__xludf.DUMMYFUNCTION("""COMPUTED_VALUE"""),45986) -> 45986 | K70: =IFERROR(__xludf.DUMMYFUNCTION("""COMPUTED_VALUE"""),"Factura audífonos") -> Factura audífonos | L70: =IFERROR(__xludf.DUMMYFUNCTION("""COMPUTED_VALUE"""),46045) -> 46045 | M70: =IFERROR(__xludf.DUMMYFUNCTION("""COMPUTED_VALUE"""),"NO") -> NO | N70: =IFERROR(__xludf.DUMMYFUNCTION("""COMPUTED_VALUE"""),2) -> 2 | O70: =IFERROR(__xludf.DUMMYFUNCTION("""COMPUTED_VALUE"""),"CONFORT") -> CONFORT | P70: =IFERROR(__xludf.DUMMYFUNCTION("""COMPUTED_VALUE"""),3631.82) -> 3631.82 | Q70: =IFERROR(__xludf.DUMMYFUNCTION("""COMPUTED_VALUE"""),"Ramon Ferrando") -> Ramon Ferrando | R70: =IFERROR(__xludf.DUMMYFUNCTION("""COMPUTED_VALUE"""),"Vladimir Rubio Segarra") -> Vladimir Rubio Segarra | S70: =IFERROR(__xludf.DUMMYFUNCTION("""COMPUTED_VALUE"""),"03 ORL") -> 03 ORL | T70: =IFERROR(__xludf.DUMMYFUNCTION("""COMPUTED_VALUE"""),"06 ORL") -> 06 ORL
B71: =IF($C71="","",LEFT(C71,3)) -> RFV | C71: =IFERROR(__xludf.DUMMYFUNCTION("""COMPUTED_VALUE"""),"RFV39") -> RFV39 | D71: =IFERROR(__xludf.DUMMYFUNCTION("""COMPUTED_VALUE"""),"PROPIOS") -> PROPIOS | E71: =IFERROR(__xludf.DUMMYFUNCTION("""COMPUTED_VALUE"""),2026) -> 2026 | F71: =IFERROR(__xludf.DUMMYFUNCTION("""COMPUTED_VALUE"""),1) -> 1 | G71: =IFERROR(__xludf.DUMMYFUNCTION("""COMPUTED_VALUE"""),"Valencia- Parra") -> Valencia- Parra | H71: =IFERROR(__xludf.DUMMYFUNCTION("""COMPUTED_VALUE"""),"C202510201139577779") -> C202510201139577779 | I71: =IFERROR(__xludf.DUMMYFUNCTION("""COMPUTED_VALUE"""),"MARCOS JUSTO ROMAGUERA") -> MARCOS JUSTO ROMAGUERA | J71: =IFERROR(__xludf.DUMMYFUNCTION("""COMPUTED_VALUE"""),45950) -> 45950 | K71: =IFERROR(__xludf.DUMMYFUNCTION("""COMPUTED_VALUE"""),"Factura audífonos") -> Factura audífonos | L71: =IFERROR(__xludf.DUMMYFUNCTION("""COMPUTED_VALUE"""),46045) -> 46045 | M71: =IFERROR(__xludf.DUMMYFUNCTION("""COMPUTED_VALUE"""),"NO") -> NO | N71: =IFERROR(__xludf.DUMMYFUNCTION("""COMPUTED_VALUE"""),1) -> 1 | O71: =IFERROR(__xludf.DUMMYFUNCTION("""COMPUTED_VALUE"""),"CONFORT") -> CONFORT | P71: =IFERROR(__xludf.DUMMYFUNCTION("""COMPUTED_VALUE"""),2162.73) -> 2162.73 | Q71: =IFERROR(__xludf.DUMMYFUNCTION("""COMPUTED_VALUE"""),"Ramon Ferrando") -> Ramon Ferrando | R71: =IFERROR(__xludf.DUMMYFUNCTION("""COMPUTED_VALUE"""),"Carlos de Paula Vernetta") -> Carlos de Paula Vernetta | S71: =IFERROR(__xludf.DUMMYFUNCTION("""COMPUTED_VALUE"""),"03 ORL") -> 03 ORL | T71: =IFERROR(__xludf.DUMMYFUNCTION("""COMPUTED_VALUE"""),"06 ORL") -> 06 ORL
B72: =IF($C72="","",LEFT(C72,3)) -> LRM | C72: =IFERROR(__xludf.DUMMYFUNCTION("""COMPUTED_VALUE"""),"LRM240") -> LRM240 | D72: =IFERROR(__xludf.DUMMYFUNCTION("""COMPUTED_VALUE"""),"ASOCIADOS") -> ASOCIADOS | E72: =IFERROR(__xludf.DUMMYFUNCTION("""COMPUTED_VALUE"""),2026) -> 2026 | F72: =IFERROR(__xludf.DUMMYFUNCTION("""COMPUTED_VALUE"""),1) -> 1 | G72: =IFERROR(__xludf.DUMMYFUNCTION("""COMPUTED_VALUE"""),"Cáceres") -> Cáceres | H72: =IFERROR(__xludf.DUMMYFUNCTION("""COMPUTED_VALUE"""),"C202512231713186578") -> C202512231713186578 | I72: =IFERROR(__xludf.DUMMYFUNCTION("""COMPUTED_VALUE"""),"DAMIAN DIAZ DOMINGUEZ") -> DAMIAN DIAZ DOMINGUEZ | J72: =IFERROR(__xludf.DUMMYFUNCTION("""COMPUTED_VALUE"""),46014) -> 46014 | K72: =IFERROR(__xludf.DUMMYFUNCTION("""COMPUTED_VALUE"""),"Factura audífonos") -> Factura audífonos | L72: =IFERROR(__xludf.DUMMYFUNCTION("""COMPUTED_VALUE"""),46045) -> 46045 | M72: =IFERROR(__xludf.DUMMYFUNCTION("""COMPUTED_VALUE"""),"NO") -> NO | N72: =IFERROR(__xludf.DUMMYFUNCTION("""COMPUTED_VALUE"""),2) -> 2 | O72: =IFERROR(__xludf.DUMMYFUNCTION("""COMPUTED_VALUE"""),"ADVANCED") -> ADVANCED | P72: =IFERROR(__xludf.DUMMYFUNCTION("""COMPUTED_VALUE"""),4500) -> 4500 | Q72: =IFERROR(__xludf.DUMMYFUNCTION("""COMPUTED_VALUE"""),"Lisandro Russian") -> Lisandro Russian | R72: =IFERROR(__xludf.DUMMYFUNCTION("""COMPUTED_VALUE"""),"Andrés Paulino Herrera") -> Andrés Paulino Herrera | S72: =IFERROR(__xludf.DUMMYFUNCTION("""COMPUTED_VALUE"""),"03 ORL") -> 03 ORL | T72: =IFERROR(__xludf.DUMMYFUNCTION("""COMPUTED_VALUE"""),"06 ORL") -> 06 ORL
B73: =IF($C73="","",LEFT(C73,3)) -> LRM | C73: =IFERROR(__xludf.DUMMYFUNCTION("""COMPUTED_VALUE"""),"LRM114") -> LRM114 | D73: =IFERROR(__xludf.DUMMYFUNCTION("""COMPUTED_VALUE"""),"ASOCIADOS") -> ASOCIADOS | E73: =IFERROR(__xludf.DUMMYFUNCTION("""COMPUTED_VALUE"""),2026) -> 2026 | F73: =IFERROR(__xludf.DUMMYFUNCTION("""COMPUTED_VALUE"""),1) -> 1 | G73: =IFERROR(__xludf.DUMMYFUNCTION("""COMPUTED_VALUE"""),"Zaragoza- León XIII") -> Zaragoza- León XIII | H73: =IFERROR(__xludf.DUMMYFUNCTION("""COMPUTED_VALUE"""),"C202512121148341527") -> C202512121148341527 | I73: =IFERROR(__xludf.DUMMYFUNCTION("""COMPUTED_VALUE"""),"MARIA MERCEDES LÓPEZ CANTOS") -> MARIA MERCEDES LÓPEZ CANTOS | J73: =IFERROR(__xludf.DUMMYFUNCTION("""COMPUTED_VALUE"""),46003) -> 46003 | K73: =IFERROR(__xludf.DUMMYFUNCTION("""COMPUTED_VALUE"""),"Factura audífonos") -> Factura audífonos | L73: =IFERROR(__xludf.DUMMYFUNCTION("""COMPUTED_VALUE"""),46046) -> 46046 | M73: =IFERROR(__xludf.DUMMYFUNCTION("""COMPUTED_VALUE"""),"NO") -> NO | N73: =IFERROR(__xludf.DUMMYFUNCTION("""COMPUTED_VALUE"""),2) -> 2 | O73: =IFERROR(__xludf.DUMMYFUNCTION("""COMPUTED_VALUE"""),"CONFORT") -> CONFORT | P73: =IFERROR(__xludf.DUMMYFUNCTION("""COMPUTED_VALUE"""),3365.38) -> 3365.38 | Q73: =IFERROR(__xludf.DUMMYFUNCTION("""COMPUTED_VALUE"""),"Ignacio Berdejo") -> Ignacio Berdejo | R73: =IFERROR(__xludf.DUMMYFUNCTION("""COMPUTED_VALUE"""),"Rafael Fernández Liesa") -> Rafael Fernández Liesa | S73: =IFERROR(__xludf.DUMMYFUNCTION("""COMPUTED_VALUE"""),"03 ORL") -> 03 ORL | T73: =IFERROR(__xludf.DUMMYFUNCTION("""COMPUTED_VALUE"""),"06 ORL") -> 06 ORL
B74: =IF($C74="","",LEFT(C74,3)) -> MCC | C74: =IFERROR(__xludf.DUMMYFUNCTION("""COMPUTED_VALUE"""),"MCC18") -> MCC18 | D74: =IFERROR(__xludf.DUMMYFUNCTION("""COMPUTED_VALUE"""),"PARTICIPADOS") -> PARTICIPADOS | E74: =IFERROR(__xludf.DUMMYFUNCTION("""COMPUTED_VALUE"""),2026) -> 2026 | F74: =IFERROR(__xludf.DUMMYFUNCTION("""COMPUTED_VALUE"""),1) -> 1 | G74: =IFERROR(__xludf.DUMMYFUNCTION("""COMPUTED_VALUE"""),"Barcelona- Córcega") -> Barcelona- Córcega | H74: =IFERROR(__xludf.DUMMYFUNCTION("""COMPUTED_VALUE"""),"C202511261218486321") -> C202511261218486321 | I74: =IFERROR(__xludf.DUMMYFUNCTION("""COMPUTED_VALUE"""),"Maria Pilar Sanchez Sanchez") -> Maria Pilar Sanchez Sanchez | J74: =IFERROR(__xludf.DUMMYFUNCTION("""COMPUTED_VALUE"""),45987) -> 45987 | K74: =IFERROR(__xludf.DUMMYFUNCTION("""COMPUTED_VALUE"""),"Factura audífonos") -> Factura audífonos | L74: =IFERROR(__xludf.DUMMYFUNCTION("""COMPUTED_VALUE"""),46048) -> 46048 | M74: =IFERROR(__xludf.DUMMYFUNCTION("""COMPUTED_VALUE"""),"NO") -> NO | N74: =IFERROR(__xludf.DUMMYFUNCTION("""COMPUTED_VALUE"""),2) -> 2 | O74: =IFERROR(__xludf.DUMMYFUNCTION("""COMPUTED_VALUE"""),"CONFORT") -> CONFORT | P74: =IFERROR(__xludf.DUMMYFUNCTION("""COMPUTED_VALUE"""),3631.82) -> 3631.82 | Q74: =IFERROR(__xludf.DUMMYFUNCTION("""COMPUTED_VALUE"""),"Mercè Cabrera") -> Mercè Cabrera | R74: =IFERROR(__xludf.DUMMYFUNCTION("""COMPUTED_VALUE"""),"Jesus-Maria Grasa Pérez") -> Jesus-Maria Grasa Pérez | S74: =IFERROR(__xludf.DUMMYFUNCTION("""COMPUTED_VALUE"""),"03 ORL") -> 03 ORL | T74: =IFERROR(__xludf.DUMMYFUNCTION("""COMPUTED_VALUE"""),"06 ORL") -> 06 ORL
B75: =IF($C75="","",LEFT(C75,3)) -> ISL | C75: =IFERROR(__xludf.DUMMYFUNCTION("""COMPUTED_VALUE"""),"ISL06") -> ISL06 | D75: =IFERROR(__xludf.DUMMYFUNCTION("""COMPUTED_VALUE"""),"PROPIOS") -> PROPIOS | E75: =IFERROR(__xludf.DUMMYFUNCTION("""COMPUTED_VALUE"""),2026) -> 2026 | F75: =IFERROR(__xludf.DUMMYFUNCTION("""COMPUTED_VALUE"""),1) -> 1 | G75: =IFERROR(__xludf.DUMMYFUNCTION("""COMPUTED_VALUE"""),"San Javier") -> San Javier | H75: =IFERROR(__xludf.DUMMYFUNCTION("""COMPUTED_VALUE"""),"C202512171228417197") -> C202512171228417197 | I75: =IFERROR(__xludf.DUMMYFUNCTION("""COMPUTED_VALUE"""),"EVA VARELA TOJO") -> EVA VARELA TOJO | J75: =IFERROR(__xludf.DUMMYFUNCTION("""COMPUTED_VALUE"""),46008) -> 46008 | K75: =IFERROR(__xludf.DUMMYFUNCTION("""COMPUTED_VALUE"""),"Factura audífonos") -> Factura audífonos | L75: =IFERROR(__xludf.DUMMYFUNCTION("""COMPUTED_VALUE"""),46048) -> 46048 | M75: =IFERROR(__xludf.DUMMYFUNCTION("""COMPUTED_VALUE"""),"NO") -> NO | N75: =IFERROR(__xludf.DUMMYFUNCTION("""COMPUTED_VALUE"""),2) -> 2 | O75: =IFERROR(__xludf.DUMMYFUNCTION("""COMPUTED_VALUE"""),"CONFORT") -> CONFORT | P75: =IFERROR(__xludf.DUMMYFUNCTION("""COMPUTED_VALUE"""),3631.82) -> 3631.82 | Q75: =IFERROR(__xludf.DUMMYFUNCTION("""COMPUTED_VALUE"""),"Iván Sánchez") -> Iván Sánchez | R75: =IFERROR(__xludf.DUMMYFUNCTION("""COMPUTED_VALUE"""),"Andrés Barrios Recio") -> Andrés Barrios Recio | S75: =IFERROR(__xludf.DUMMYFUNCTION("""COMPUTED_VALUE"""),"03 ORL") -> 03 ORL | T75: =IFERROR(__xludf.DUMMYFUNCTION("""COMPUTED_VALUE"""),"06 ORL") -> 06 ORL
B76: =IF($C76="","",LEFT(C76,3)) -> ISL | C76: =IFERROR(__xludf.DUMMYFUNCTION("""COMPUTED_VALUE"""),"ISL94") -> ISL94 | D76: =IFERROR(__xludf.DUMMYFUNCTION("""COMPUTED_VALUE"""),"PROPIOS") -> PROPIOS | E76: =IFERROR(__xludf.DUMMYFUNCTION("""COMPUTED_VALUE"""),2026) -> 2026 | F76: =IFERROR(__xludf.DUMMYFUNCTION("""COMPUTED_VALUE"""),1) -> 1 | G76: =IFERROR(__xludf.DUMMYFUNCTION("""COMPUTED_VALUE"""),"Murcia") -> Murcia | H76: =IFERROR(__xludf.DUMMYFUNCTION("""COMPUTED_VALUE"""),"C202512410121341481") -> C202512410121341481 | I76: =IFERROR(__xludf.DUMMYFUNCTION("""COMPUTED_VALUE"""),"JULIA MARIA ARQUEROS AMAT") -> JULIA MARIA ARQUEROS AMAT | J76: =IFERROR(__xludf.DUMMYFUNCTION("""COMPUTED_VALUE"""),45995) -> 45995 | K76: =IFERROR(__xludf.DUMMYFUNCTION("""COMPUTED_VALUE"""),"Factura audífonos") -> Factura audífonos | L76: =IFERROR(__xludf.DUMMYFUNCTION("""COMPUTED_VALUE"""),46048) -> 46048 | M76: =IFERROR(__xludf.DUMMYFUNCTION("""COMPUTED_VALUE"""),"NO") -> NO | N76: =IFERROR(__xludf.DUMMYFUNCTION("""COMPUTED_VALUE"""),2) -> 2 | O76: =IFERROR(__xludf.DUMMYFUNCTION("""COMPUTED_VALUE"""),"CONFORT") -> CONFORT | P76: =IFERROR(__xludf.DUMMYFUNCTION("""COMPUTED_VALUE"""),3631.83) -> 3631.83 | Q76: =IFERROR(__xludf.DUMMYFUNCTION("""COMPUTED_VALUE"""),"Iván Sánchez") -> Iván Sánchez | R76: =IFERROR(__xludf.DUMMYFUNCTION("""COMPUTED_VALUE"""),"Beatriz Rodríguez González Herrero") -> Beatriz Rodríguez González Herrero | S76: =IFERROR(__xludf.DUMMYFUNCTION("""COMPUTED_VALUE"""),"03 ORL") -> 03 ORL | T76: =IFERROR(__xludf.DUMMYFUNCTION("""COMPUTED_VALUE"""),"06 ORL") -> 06 ORL
B77: =IF($C77="","",LEFT(C77,3)) -> ISL | C77: =IFERROR(__xludf.DUMMYFUNCTION("""COMPUTED_VALUE"""),"ISL62") -> ISL62 | D77: =IFERROR(__xludf.DUMMYFUNCTION("""COMPUTED_VALUE"""),"PROPIOS") -> PROPIOS | E77: =IFERROR(__xludf.DUMMYFUNCTION("""COMPUTED_VALUE"""),2026) -> 2026 | F77: =IFERROR(__xludf.DUMMYFUNCTION("""COMPUTED_VALUE"""),1) -> 1 | G77: =IFERROR(__xludf.DUMMYFUNCTION("""COMPUTED_VALUE"""),"El Albir (Benidorm)") -> El Albir (Benidorm) | H77: =IFERROR(__xludf.DUMMYFUNCTION("""COMPUTED_VALUE"""),"C202512121026113021") -> C202512121026113021 | I77: =IFERROR(__xludf.DUMMYFUNCTION("""COMPUTED_VALUE"""),"FRANCISCA MATA PEREZ") -> FRANCISCA MATA PEREZ | J77: =IFERROR(__xludf.DUMMYFUNCTION("""COMPUTED_VALUE"""),46003) -> 46003 | K77: =IFERROR(__xludf.DUMMYFUNCTION("""COMPUTED_VALUE"""),"Factura audífonos") -> Factura audífonos | L77: =IFERROR(__xludf.DUMMYFUNCTION("""COMPUTED_VALUE"""),46048) -> 46048 | M77: =IFERROR(__xludf.DUMMYFUNCTION("""COMPUTED_VALUE"""),"NO") -> NO | N77: =IFERROR(__xludf.DUMMYFUNCTION("""COMPUTED_VALUE"""),2) -> 2 | O77: =IFERROR(__xludf.DUMMYFUNCTION("""COMPUTED_VALUE"""),"QUIET") -> QUIET | P77: =IFERROR(__xludf.DUMMYFUNCTION("""COMPUTED_VALUE"""),2718.18) -> 2718.18 | Q77: =IFERROR(__xludf.DUMMYFUNCTION("""COMPUTED_VALUE"""),"Ramon Ferrando") -> Ramon Ferrando | R77: =IFERROR(__xludf.DUMMYFUNCTION("""COMPUTED_VALUE"""),"Lino Enguidanos Hernandorena") -> Lino Enguidanos Hernandorena | S77: =IFERROR(__xludf.DUMMYFUNCTION("""COMPUTED_VALUE"""),"03 ORL") -> 03 ORL | T77: =IFERROR(__xludf.DUMMYFUNCTION("""COMPUTED_VALUE"""),"06 ORL") -> 06 ORL
B78: =IF($C78="","",LEFT(C78,3)) -> MBM | C78: =IFERROR(__xludf.DUMMYFUNCTION("""COMPUTED_VALUE"""),"MBM149") -> MBM149 | D78: =IFERROR(__xludf.DUMMYFUNCTION("""COMPUTED_VALUE"""),"PROPIOS") -> PROPIOS | E78: =IFERROR(__xludf.DUMMYFUNCTION("""COMPUTED_VALUE"""),2026) -> 2026 | F78: =IFERROR(__xludf.DUMMYFUNCTION("""COMPUTED_VALUE"""),1) -> 1 | G78: =IFERROR(__xludf.DUMMYFUNCTION("""COMPUTED_VALUE"""),"Toledo") -> Toledo | H78: =IFERROR(__xludf.DUMMYFUNCTION("""COMPUTED_VALUE"""),"C202511269485787430") -> C202511269485787430 | I78: =IFERROR(__xludf.DUMMYFUNCTION("""COMPUTED_VALUE"""),"Primitivo Garcia Ruiz") -> Primitivo Garcia Ruiz | J78: =IFERROR(__xludf.DUMMYFUNCTION("""COMPUTED_VALUE"""),45987) -> 45987 | K78: =IFERROR(__xludf.DUMMYFUNCTION("""COMPUTED_VALUE"""),"Factura audífonos") -> Factura audífonos | L78: =IFERROR(__xludf.DUMMYFUNCTION("""COMPUTED_VALUE"""),46048) -> 46048 | M78: =IFERROR(__xludf.DUMMYFUNCTION("""COMPUTED_VALUE"""),"NO") -> NO | N78: =IFERROR(__xludf.DUMMYFUNCTION("""COMPUTED_VALUE"""),2) -> 2 | O78: =IFERROR(__xludf.DUMMYFUNCTION("""COMPUTED_VALUE"""),"QUIET") -> QUIET | P78: =IFERROR(__xludf.DUMMYFUNCTION("""COMPUTED_VALUE"""),2718.18) -> 2718.18 | Q78: =IFERROR(__xludf.DUMMYFUNCTION("""COMPUTED_VALUE"""),"Maika Blázquez") -> Maika Blázquez | R78: =IFERROR(__xludf.DUMMYFUNCTION("""COMPUTED_VALUE"""),"María Garrote Garrote") -> María Garrote Garrote | S78: =IFERROR(__xludf.DUMMYFUNCTION("""COMPUTED_VALUE"""),"03 ORL") -> 03 ORL | T78: =IFERROR(__xludf.DUMMYFUNCTION("""COMPUTED_VALUE"""),"06 ORL") -> 06 ORL
B79: =IF($C79="","",LEFT(C79,3)) -> MCC | C79: =IFERROR(__xludf.DUMMYFUNCTION("""COMPUTED_VALUE"""),"MCC70") -> MCC70 | D79: =IFERROR(__xludf.DUMMYFUNCTION("""COMPUTED_VALUE"""),"PARTICIPADOS") -> PARTICIPADOS | E79: =IFERROR(__xludf.DUMMYFUNCTION("""COMPUTED_VALUE"""),2026) -> 2026 | F79: =IFERROR(__xludf.DUMMYFUNCTION("""COMPUTED_VALUE"""),1) -> 1 | G79: =IFERROR(__xludf.DUMMYFUNCTION("""COMPUTED_VALUE"""),"Barcelona- Córcega") -> Barcelona- Córcega | H79: =IFERROR(__xludf.DUMMYFUNCTION("""COMPUTED_VALUE"""),"C202617113410376988") -> C202617113410376988 | I79: =IFERROR(__xludf.DUMMYFUNCTION("""COMPUTED_VALUE"""),"Ana Maria Cano Rafael") -> Ana Maria Cano Rafael | J79: =IFERROR(__xludf.DUMMYFUNCTION("""COMPUTED_VALUE"""),46029) -> 46029 | K79: =IFERROR(__xludf.DUMMYFUNCTION("""COMPUTED_VALUE"""),"Factura audífonos") -> Factura audífonos | L79: =IFERROR(__xludf.DUMMYFUNCTION("""COMPUTED_VALUE"""),46048) -> 46048 | M79: =IFERROR(__xludf.DUMMYFUNCTION("""COMPUTED_VALUE"""),"NO") -> NO | N79: =IFERROR(__xludf.DUMMYFUNCTION("""COMPUTED_VALUE"""),2) -> 2 | O79: =IFERROR(__xludf.DUMMYFUNCTION("""COMPUTED_VALUE"""),"PRO") -> PRO | P79: =IFERROR(__xludf.DUMMYFUNCTION("""COMPUTED_VALUE"""),4536.36) -> 4536.36 | Q79: =IFERROR(__xludf.DUMMYFUNCTION("""COMPUTED_VALUE"""),"Mercè Cabrera") -> Mercè Cabrera | R79: =IFERROR(__xludf.DUMMYFUNCTION("""COMPUTED_VALUE"""),"Nesly Illely González Sánchez") -> Nesly Illely González Sánchez | S79: =IFERROR(__xludf.DUMMYFUNCTION("""COMPUTED_VALUE"""),"03 ORL") -> 03 ORL | T79: =IFERROR(__xludf.DUMMYFUNCTION("""COMPUTED_VALUE"""),"06 ORL") -> 06 ORL
B80: =IF($C80="","",LEFT(C80,3)) -> LAA | C80: =IFERROR(__xludf.DUMMYFUNCTION("""COMPUTED_VALUE"""),"LAA24") -> LAA24 | D80: =IFERROR(__xludf.DUMMYFUNCTION("""COMPUTED_VALUE"""),"PROPIOS") -> PROPIOS | E80: =IFERROR(__xludf.DUMMYFUNCTION("""COMPUTED_VALUE"""),2026) -> 2026 | F80: =IFERROR(__xludf.DUMMYFUNCTION("""COMPUTED_VALUE"""),1) -> 1 | G80: =IFERROR(__xludf.DUMMYFUNCTION("""COMPUTED_VALUE"""),"Sevilla- Montoto") -> Sevilla- Montoto | H80: =IFERROR(__xludf.DUMMYFUNCTION("""COMPUTED_VALUE"""),"C202511121127351007") -> C202511121127351007 | I80: =IFERROR(__xludf.DUMMYFUNCTION("""COMPUTED_VALUE"""),"MARIA LUISA GRANADOS MAGUILLA") -> MARIA LUISA GRANADOS MAGUILLA | J80: =IFERROR(__xludf.DUMMYFUNCTION("""COMPUTED_VALUE"""),45973) -> 45973 | K80: =IFERROR(__xludf.DUMMYFUNCTION("""COMPUTED_VALUE"""),"Factura audífonos") -> Factura audífonos | L80: =IFERROR(__xludf.DUMMYFUNCTION("""COMPUTED_VALUE"""),46048) -> 46048 | M80: =IFERROR(__xludf.DUMMYFUNCTION("""COMPUTED_VALUE"""),"NO") -> NO | N80: =IFERROR(__xludf.DUMMYFUNCTION("""COMPUTED_VALUE"""),2) -> 2 | O80: =IFERROR(__xludf.DUMMYFUNCTION("""COMPUTED_VALUE"""),"CONFORT") -> CONFORT | P80: =IFERROR(__xludf.DUMMYFUNCTION("""COMPUTED_VALUE"""),3631.82) -> 3631.82 | Q80: =IFERROR(__xludf.DUMMYFUNCTION("""COMPUTED_VALUE"""),"Luis Alberto Rodríguez") -> Luis Alberto Rodríguez | R80: =IFERROR(__xludf.DUMMYFUNCTION("""COMPUTED_VALUE"""),"Jesús Crovato Rojas") -> Jesús Crovato Rojas | S80: =IFERROR(__xludf.DUMMYFUNCTION("""COMPUTED_VALUE"""),"03 ORL") -> 03 ORL | T80: =IFERROR(__xludf.DUMMYFUNCTION("""COMPUTED_VALUE"""),"06 ORL") -> 06 ORL
B81: =IF($C81="","",LEFT(C81,3)) -> ISL | C81: =IFERROR(__xludf.DUMMYFUNCTION("""COMPUTED_VALUE"""),"ISL105") -> ISL105 | D81: =IFERROR(__xludf.DUMMYFUNCTION("""COMPUTED_VALUE"""),"PROPIOS") -> PROPIOS | E81: =IFERROR(__xludf.DUMMYFUNCTION("""COMPUTED_VALUE"""),2026) -> 2026 | F81: =IFERROR(__xludf.DUMMYFUNCTION("""COMPUTED_VALUE"""),1) -> 1 | G81: =IFERROR(__xludf.DUMMYFUNCTION("""COMPUTED_VALUE"""),"Alicante") -> Alicante | H81: =IFERROR(__xludf.DUMMYFUNCTION("""COMPUTED_VALUE"""),"C202512261157304222") -> C202512261157304222 | I81: =IFERROR(__xludf.DUMMYFUNCTION("""COMPUTED_VALUE"""),"PEDRO ESPINOSA SAN NICOLAS") -> PEDRO ESPINOSA SAN NICOLAS | J81: =IFERROR(__xludf.DUMMYFUNCTION("""COMPUTED_VALUE"""),46017) -> 46017 | K81: =IFERROR(__xludf.DUMMYFUNCTION("""COMPUTED_VALUE"""),"Factura audífonos") -> Factura audífonos | L81: =IFERROR(__xludf.DUMMYFUNCTION("""COMPUTED_VALUE"""),46049) -> 46049 | M81: =IFERROR(__xludf.DUMMYFUNCTION("""COMPUTED_VALUE"""),"NO") -> NO | N81: =IFERROR(__xludf.DUMMYFUNCTION("""COMPUTED_VALUE"""),2) -> 2 | O81: =IFERROR(__xludf.DUMMYFUNCTION("""COMPUTED_VALUE"""),"QUIET") -> QUIET | P81: =IFERROR(__xludf.DUMMYFUNCTION("""COMPUTED_VALUE"""),2718.18) -> 2718.18 | Q81: =IFERROR(__xludf.DUMMYFUNCTION("""COMPUTED_VALUE"""),"Iván Sánchez") -> Iván Sánchez | R81: =IFERROR(__xludf.DUMMYFUNCTION("""COMPUTED_VALUE"""),"Karen Rojas Crespo") -> Karen Rojas Crespo | S81: =IFERROR(__xludf.DUMMYFUNCTION("""COMPUTED_VALUE"""),"03 ORL") -> 03 ORL | T81: =IFERROR(__xludf.DUMMYFUNCTION("""COMPUTED_VALUE"""),"06 ORL") -> 06 ORL
B82: =IF($C82="","",LEFT(C82,3)) -> MBM | C82: =IFERROR(__xludf.DUMMYFUNCTION("""COMPUTED_VALUE"""),"MBM195") -> MBM195 | D82: =IFERROR(__xludf.DUMMYFUNCTION("""COMPUTED_VALUE"""),"PROPIOS") -> PROPIOS | E82: =IFERROR(__xludf.DUMMYFUNCTION("""COMPUTED_VALUE"""),2026) -> 2026 | F82: =IFERROR(__xludf.DUMMYFUNCTION("""COMPUTED_VALUE"""),1) -> 1 | G82: =IFERROR(__xludf.DUMMYFUNCTION("""COMPUTED_VALUE"""),"Fuenlabrada") -> Fuenlabrada | H82: =IFERROR(__xludf.DUMMYFUNCTION("""COMPUTED_VALUE"""),"C202512121025258882") -> C202512121025258882 | I82: =IFERROR(__xludf.DUMMYFUNCTION("""COMPUTED_VALUE"""),"TERESA CASTILLO GARCIA") -> TERESA CASTILLO GARCIA | J82: =IFERROR(__xludf.DUMMYFUNCTION("""COMPUTED_VALUE"""),46003) -> 46003 | K82: =IFERROR(__xludf.DUMMYFUNCTION("""COMPUTED_VALUE"""),"Factura audífonos") -> Factura audífonos | L82: =IFERROR(__xludf.DUMMYFUNCTION("""COMPUTED_VALUE"""),46049) -> 46049 | M82: =IFERROR(__xludf.DUMMYFUNCTION("""COMPUTED_VALUE"""),"NO") -> NO | N82: =IFERROR(__xludf.DUMMYFUNCTION("""COMPUTED_VALUE"""),1) -> 1 | O82: =IFERROR(__xludf.DUMMYFUNCTION("""COMPUTED_VALUE"""),"QUIET") -> QUIET | P82: =IFERROR(__xludf.DUMMYFUNCTION("""COMPUTED_VALUE"""),1631.82) -> 1631.82 | Q82: =IFERROR(__xludf.DUMMYFUNCTION("""COMPUTED_VALUE"""),"Maika Blázquez") -> Maika Blázquez | R82: =IFERROR(__xludf.DUMMYFUNCTION("""COMPUTED_VALUE"""),"Anastasiya Audiyuk Martynyuk") -> Anastasiya Audiyuk Martynyuk | S82: =IFERROR(__xludf.DUMMYFUNCTION("""COMPUTED_VALUE"""),"03 ORL") -> 03 ORL | T82: =IFERROR(__xludf.DUMMYFUNCTION("""COMPUTED_VALUE"""),"06 ORL") -> 06 ORL
B83: =IF($C83="","",LEFT(C83,3)) -> MCC | C83: =IFERROR(__xludf.DUMMYFUNCTION("""COMPUTED_VALUE"""),"MCC76") -> MCC76 | D83: =IFERROR(__xludf.DUMMYFUNCTION("""COMPUTED_VALUE"""),"PARTICIPADOS") -> PARTICIPADOS | E83: =IFERROR(__xludf.DUMMYFUNCTION("""COMPUTED_VALUE"""),2026) -> 2026 | F83: =IFERROR(__xludf.DUMMYFUNCTION("""COMPUTED_VALUE"""),1) -> 1 | G83: =IFERROR(__xludf.DUMMYFUNCTION("""COMPUTED_VALUE"""),"Hospitalet de Llobregat") -> Hospitalet de Llobregat | H83: =IFERROR(__xludf.DUMMYFUNCTION("""COMPUTED_VALUE"""),"C202511181545320772") -> C202511181545320772 | I83: =IFERROR(__xludf.DUMMYFUNCTION("""COMPUTED_VALUE"""),"PAULA RUIZ ORTEGA") -> PAULA RUIZ ORTEGA | J83: =IFERROR(__xludf.DUMMYFUNCTION("""COMPUTED_VALUE"""),45979) -> 45979 | K83: =IFERROR(__xludf.DUMMYFUNCTION("""COMPUTED_VALUE"""),"Factura audífonos") -> Factura audífonos | L83: =IFERROR(__xludf.DUMMYFUNCTION("""COMPUTED_VALUE"""),46049) -> 46049 | M83: =IFERROR(__xludf.DUMMYFUNCTION("""COMPUTED_VALUE"""),"NO") -> NO | N83: =IFERROR(__xludf.DUMMYFUNCTION("""COMPUTED_VALUE"""),1) -> 1 | O83: =IFERROR(__xludf.DUMMYFUNCTION("""COMPUTED_VALUE"""),"ADVANCED") -> ADVANCED | P83: =IFERROR(__xludf.DUMMYFUNCTION("""COMPUTED_VALUE"""),2481.82) -> 2481.82 | Q83: =IFERROR(__xludf.DUMMYFUNCTION("""COMPUTED_VALUE"""),"Mercè Cabrera") -> Mercè Cabrera | R83: =IFERROR(__xludf.DUMMYFUNCTION("""COMPUTED_VALUE"""),"Albert Pla Esperanzi") -> Albert Pla Esperanzi | S83: =IFERROR(__xludf.DUMMYFUNCTION("""COMPUTED_VALUE"""),"03 ORL") -> 03 ORL | T83: =IFERROR(__xludf.DUMMYFUNCTION("""COMPUTED_VALUE"""),"06 ORL") -> 06 ORL
B84: =IF($C84="","",LEFT(C84,3)) -> MBM | C84: =IFERROR(__xludf.DUMMYFUNCTION("""COMPUTED_VALUE"""),"MBM39") -> MBM39 | D84: =IFERROR(__xludf.DUMMYFUNCTION("""COMPUTED_VALUE"""),"PROPIOS") -> PROPIOS | E84: =IFERROR(__xludf.DUMMYFUNCTION("""COMPUTED_VALUE"""),2026) -> 2026 | F84: =IFERROR(__xludf.DUMMYFUNCTION("""COMPUTED_VALUE"""),1) -> 1 | G84: =IFERROR(__xludf.DUMMYFUNCTION("""COMPUTED_VALUE"""),"Madrid- Juan Bravo") -> Madrid- Juan Bravo | H84: =IFERROR(__xludf.DUMMYFUNCTION("""COMPUTED_VALUE"""),"C20261292625074298") -> C20261292625074298 | I84: =IFERROR(__xludf.DUMMYFUNCTION("""COMPUTED_VALUE"""),"JOSEFA GOMEZ DE ENTERRIA SANCHEZ") -> JOSEFA GOMEZ DE ENTERRIA SANCHEZ | J84: =IFERROR(__xludf.DUMMYFUNCTION("""COMPUTED_VALUE"""),46024) -> 46024 | K84: =IFERROR(__xludf.DUMMYFUNCTION("""COMPUTED_VALUE"""),"Factura audífonos") -> Factura audífonos | L84: =IFERROR(__xludf.DUMMYFUNCTION("""COMPUTED_VALUE"""),46049) -> 46049 | M84: =IFERROR(__xludf.DUMMYFUNCTION("""COMPUTED_VALUE"""),"NO") -> NO | N84: =IFERROR(__xludf.DUMMYFUNCTION("""COMPUTED_VALUE"""),2) -> 2 | O84: =IFERROR(__xludf.DUMMYFUNCTION("""COMPUTED_VALUE"""),"PRO") -> PRO | P84: =IFERROR(__xludf.DUMMYFUNCTION("""COMPUTED_VALUE"""),4536.36) -> 4536.36 | Q84: =IFERROR(__xludf.DUMMYFUNCTION("""COMPUTED_VALUE"""),"Maika Blázquez") -> Maika Blázquez | R84: =IFERROR(__xludf.DUMMYFUNCTION("""COMPUTED_VALUE"""),"Javier García Domínguez") -> Javier García Domínguez | S84: =IFERROR(__xludf.DUMMYFUNCTION("""COMPUTED_VALUE"""),"03 ORL") -> 03 ORL | T84: =IFERROR(__xludf.DUMMYFUNCTION("""COMPUTED_VALUE"""),"06 ORL") -> 06 ORL
B85: =IF($C85="","",LEFT(C85,3)) -> MBM | C85: =IFERROR(__xludf.DUMMYFUNCTION("""COMPUTED_VALUE"""),"MBM74") -> MBM74 | D85: =IFERROR(__xludf.DUMMYFUNCTION("""COMPUTED_VALUE"""),"PROPIOS") -> PROPIOS | E85: =IFERROR(__xludf.DUMMYFUNCTION("""COMPUTED_VALUE"""),2026) -> 2026 | F85: =IFERROR(__xludf.DUMMYFUNCTION("""COMPUTED_VALUE"""),1) -> 1 | G85: =IFERROR(__xludf.DUMMYFUNCTION("""COMPUTED_VALUE"""),"Fuenlabrada") -> Fuenlabrada | H85: =IFERROR(__xludf.DUMMYFUNCTION("""COMPUTED_VALUE"""),"C202511279152147211") -> C202511279152147211 | I85: =IFERROR(__xludf.DUMMYFUNCTION("""COMPUTED_VALUE"""),"MARGARITA CORTAZAR VIANCO") -> MARGARITA CORTAZAR VIANCO | J85: =IFERROR(__xludf.DUMMYFUNCTION("""COMPUTED_VALUE"""),45988) -> 45988 | K85: =IFERROR(__xludf.DUMMYFUNCTION("""COMPUTED_VALUE"""),"Factura audífonos") -> Factura audífonos | L85: =IFERROR(__xludf.DUMMYFUNCTION("""COMPUTED_VALUE"""),46049) -> 46049 | M85: =IFERROR(__xludf.DUMMYFUNCTION("""COMPUTED_VALUE"""),"NO") -> NO | N85: =IFERROR(__xludf.DUMMYFUNCTION("""COMPUTED_VALUE"""),1) -> 1 | O85: =IFERROR(__xludf.DUMMYFUNCTION("""COMPUTED_VALUE"""),"PRO") -> PRO | P85: =IFERROR(__xludf.DUMMYFUNCTION("""COMPUTED_VALUE"""),2722.73) -> 2722.73 | Q85: =IFERROR(__xludf.DUMMYFUNCTION("""COMPUTED_VALUE"""),"Maika Blázquez") -> Maika Blázquez | R85: =IFERROR(__xludf.DUMMYFUNCTION("""COMPUTED_VALUE"""),"Raimundo Andres Navarro Mediano") -> Raimundo Andres Navarro Mediano | S85: =IFERROR(__xludf.DUMMYFUNCTION("""COMPUTED_VALUE"""),"03 ORL") -> 03 ORL | T85: =IFERROR(__xludf.DUMMYFUNCTION("""COMPUTED_VALUE"""),"06 ORL") -> 06 ORL
B86: =IF($C86="","",LEFT(C86,3)) -> LRM | C86: =IFERROR(__xludf.DUMMYFUNCTION("""COMPUTED_VALUE"""),"LRM39") -> LRM39 | D86: =IFERROR(__xludf.DUMMYFUNCTION("""COMPUTED_VALUE"""),"PROPIOS") -> PROPIOS | E86: =IFERROR(__xludf.DUMMYFUNCTION("""COMPUTED_VALUE"""),2026) -> 2026 | F86: =IFERROR(__xludf.DUMMYFUNCTION("""COMPUTED_VALUE"""),1) -> 1 | G86: =IFERROR(__xludf.DUMMYFUNCTION("""COMPUTED_VALUE"""),"Logroño") -> Logroño | H86: =IFERROR(__xludf.DUMMYFUNCTION("""COMPUTED_VALUE"""),"C202512158202709477") -> C202512158202709477 | I86: =IFERROR(__xludf.DUMMYFUNCTION("""COMPUTED_VALUE"""),"JOSE LUIS MARQUINEZ IBAÑEZ") -> JOSE LUIS MARQUINEZ IBAÑEZ | J86: =IFERROR(__xludf.DUMMYFUNCTION("""COMPUTED_VALUE"""),46006) -> 46006 | K86: =IFERROR(__xludf.DUMMYFUNCTION("""COMPUTED_VALUE"""),"Factura audífonos") -> Factura audífonos | L86: =IFERROR(__xludf.DUMMYFUNCTION("""COMPUTED_VALUE"""),46049) -> 46049 | M86: =IFERROR(__xludf.DUMMYFUNCTION("""COMPUTED_VALUE"""),"NO") -> NO | N86: =IFERROR(__xludf.DUMMYFUNCTION("""COMPUTED_VALUE"""),2) -> 2 | O86: =IFERROR(__xludf.DUMMYFUNCTION("""COMPUTED_VALUE"""),"PRO") -> PRO | P86: =IFERROR(__xludf.DUMMYFUNCTION("""COMPUTED_VALUE"""),4536.36) -> 4536.36 | Q86: =IFERROR(__xludf.DUMMYFUNCTION("""COMPUTED_VALUE"""),"Lisandro Russian") -> Lisandro Russian | R86: =IFERROR(__xludf.DUMMYFUNCTION("""COMPUTED_VALUE"""),"Fernando Salazar Barcelona") -> Fernando Salazar Barcelona | S86: =IFERROR(__xludf.DUMMYFUNCTION("""COMPUTED_VALUE"""),"03 ORL") -> 03 ORL | T86: =IFERROR(__xludf.DUMMYFUNCTION("""COMPUTED_VALUE"""),"06 ORL") -> 06 ORL
B87: =IF($C87="","",LEFT(C87,3)) -> LRM | C87: =IFERROR(__xludf.DUMMYFUNCTION("""COMPUTED_VALUE"""),"LRM48") -> LRM48 | D87: =IFERROR(__xludf.DUMMYFUNCTION("""COMPUTED_VALUE"""),"PROPIOS") -> PROPIOS | E87: =IFERROR(__xludf.DUMMYFUNCTION("""COMPUTED_VALUE"""),2026) -> 2026 | F87: =IFERROR(__xludf.DUMMYFUNCTION("""COMPUTED_VALUE"""),1) -> 1 | G87: =IFERROR(__xludf.DUMMYFUNCTION("""COMPUTED_VALUE"""),"Logroño") -> Logroño | H87: =IFERROR(__xludf.DUMMYFUNCTION("""COMPUTED_VALUE"""),"C202615112933324246") -> C202615112933324246 | I87: =IFERROR(__xludf.DUMMYFUNCTION("""COMPUTED_VALUE"""),"GREGORIO ANDRES MURILLO BARTOLOME") -> GREGORIO ANDRES MURILLO BARTOLOME | J87: =IFERROR(__xludf.DUMMYFUNCTION("""COMPUTED_VALUE"""),46027) -> 46027 | K87: =IFERROR(__xludf.DUMMYFUNCTION("""COMPUTED_VALUE"""),"Factura audífonos") -> Factura audífonos | L87: =IFERROR(__xludf.DUMMYFUNCTION("""COMPUTED_VALUE"""),46049) -> 46049 | M87: =IFERROR(__xludf.DUMMYFUNCTION("""COMPUTED_VALUE"""),"NO") -> NO | N87: =IFERROR(__xludf.DUMMYFUNCTION("""COMPUTED_VALUE"""),2) -> 2 | O87: =IFERROR(__xludf.DUMMYFUNCTION("""COMPUTED_VALUE"""),"QUIET") -> QUIET | P87: =IFERROR(__xludf.DUMMYFUNCTION("""COMPUTED_VALUE"""),2582.27) -> 2582.27 | Q87: =IFERROR(__xludf.DUMMYFUNCTION("""COMPUTED_VALUE"""),"Lisandro Russian") -> Lisandro Russian | R87: =IFERROR(__xludf.DUMMYFUNCTION("""COMPUTED_VALUE"""),"Garikoitz Calzada Uriondo") -> Garikoitz Calzada Uriondo | S87: =IFERROR(__xludf.DUMMYFUNCTION("""COMPUTED_VALUE"""),"03 ORL") -> 03 ORL | T87: =IFERROR(__xludf.DUMMYFUNCTION("""COMPUTED_VALUE"""),"06 ORL") -> 06 ORL
B88: =IF($C88="","",LEFT(C88,3)) -> ISL | C88: =IFERROR(__xludf.DUMMYFUNCTION("""COMPUTED_VALUE"""),"ISL104") -> ISL104 | D88: =IFERROR(__xludf.DUMMYFUNCTION("""COMPUTED_VALUE"""),"PROPIOS") -> PROPIOS | E88: =IFERROR(__xludf.DUMMYFUNCTION("""COMPUTED_VALUE"""),2026) -> 2026 | F88: =IFERROR(__xludf.DUMMYFUNCTION("""COMPUTED_VALUE"""),1) -> 1 | G88: =IFERROR(__xludf.DUMMYFUNCTION("""COMPUTED_VALUE"""),"El Albir (Benidorm)") -> El Albir (Benidorm) | H88: =IFERROR(__xludf.DUMMYFUNCTION("""COMPUTED_VALUE"""),"C20261785351356795") -> C20261785351356795 | I88: =IFERROR(__xludf.DUMMYFUNCTION("""COMPUTED_VALUE"""),"FRANCISCO DOMINGUEZ DONADO") -> FRANCISCO DOMINGUEZ DONADO | J88: =IFERROR(__xludf.DUMMYFUNCTION("""COMPUTED_VALUE"""),46029) -> 46029 | K88: =IFERROR(__xludf.DUMMYFUNCTION("""COMPUTED_VALUE"""),"Factura audífonos") -> Factura audífonos | L88: =IFERROR(__xludf.DUMMYFUNCTION("""COMPUTED_VALUE"""),46049) -> 46049 | M88: =IFERROR(__xludf.DUMMYFUNCTION("""COMPUTED_VALUE"""),"NO") -> NO | N88: =IFERROR(__xludf.DUMMYFUNCTION("""COMPUTED_VALUE"""),2) -> 2 | O88: =IFERROR(__xludf.DUMMYFUNCTION("""COMPUTED_VALUE"""),"CONFORT") -> CONFORT | P88: =IFERROR(__xludf.DUMMYFUNCTION("""COMPUTED_VALUE"""),3631.81) -> 3631.81 | Q88: =IFERROR(__xludf.DUMMYFUNCTION("""COMPUTED_VALUE"""),"Ramon Ferrando") -> Ramon Ferrando | R88: =IFERROR(__xludf.DUMMYFUNCTION("""COMPUTED_VALUE"""),"Isabel Polo Tomás") -> Isabel Polo Tomás | S88: =IFERROR(__xludf.DUMMYFUNCTION("""COMPUTED_VALUE"""),"03 ORL") -> 03 ORL | T88: =IFERROR(__xludf.DUMMYFUNCTION("""COMPUTED_VALUE"""),"06 ORL") -> 06 ORL
B89: =IF($C89="","",LEFT(C89,3)) -> ISL | C89: =IFERROR(__xludf.DUMMYFUNCTION("""COMPUTED_VALUE"""),"ISL91") -> ISL91 | D89: =IFERROR(__xludf.DUMMYFUNCTION("""COMPUTED_VALUE"""),"PROPIOS") -> PROPIOS | E89: =IFERROR(__xludf.DUMMYFUNCTION("""COMPUTED_VALUE"""),2026) -> 2026 | F89: =IFERROR(__xludf.DUMMYFUNCTION("""COMPUTED_VALUE"""),1) -> 1 | G89: =IFERROR(__xludf.DUMMYFUNCTION("""COMPUTED_VALUE"""),"Murcia") -> Murcia | H89: =IFERROR(__xludf.DUMMYFUNCTION("""COMPUTED_VALUE"""),"C202512191124560708") -> C202512191124560708 | I89: =IFERROR(__xludf.DUMMYFUNCTION("""COMPUTED_VALUE"""),"RAMON ANDREU ANDREU") -> RAMON ANDREU ANDREU | J89: =IFERROR(__xludf.DUMMYFUNCTION("""COMPUTED_VALUE"""),46010) -> 46010 | K89: =IFERROR(__xludf.DUMMYFUNCTION("""COMPUTED_VALUE"""),"Factura audífonos") -> Factura audífonos | L89: =IFERROR(__xludf.DUMMYFUNCTION("""COMPUTED_VALUE"""),46049) -> 46049 | M89: =IFERROR(__xludf.DUMMYFUNCTION("""COMPUTED_VALUE"""),"NO") -> NO | N89: =IFERROR(__xludf.DUMMYFUNCTION("""COMPUTED_VALUE"""),2) -> 2 | O89: =IFERROR(__xludf.DUMMYFUNCTION("""COMPUTED_VALUE"""),"QUIET") -> QUIET | P89: =IFERROR(__xludf.DUMMYFUNCTION("""COMPUTED_VALUE"""),2718.18) -> 2718.18 | Q89: =IFERROR(__xludf.DUMMYFUNCTION("""COMPUTED_VALUE"""),"Iván Sánchez") -> Iván Sánchez | R89: =IFERROR(__xludf.DUMMYFUNCTION("""COMPUTED_VALUE"""),"Alejandra Jara Maquilón") -> Alejandra Jara Maquilón | S89: =IFERROR(__xludf.DUMMYFUNCTION("""COMPUTED_VALUE"""),"03 ORL") -> 03 ORL | T89: =IFERROR(__xludf.DUMMYFUNCTION("""COMPUTED_VALUE"""),"06 ORL") -> 06 ORL
B90: =IF($C90="","",LEFT(C90,3)) -> MCC | C90: =IFERROR(__xludf.DUMMYFUNCTION("""COMPUTED_VALUE"""),"MCC10") -> MCC10 | D90: =IFERROR(__xludf.DUMMYFUNCTION("""COMPUTED_VALUE"""),"PARTICIPADOS") -> PARTICIPADOS | E90: =IFERROR(__xludf.DUMMYFUNCTION("""COMPUTED_VALUE"""),2026) -> 2026 | F90: =IFERROR(__xludf.DUMMYFUNCTION("""COMPUTED_VALUE"""),1) -> 1 | G90: =IFERROR(__xludf.DUMMYFUNCTION("""COMPUTED_VALUE"""),"Barcelona- Córcega") -> Barcelona- Córcega | H90: =IFERROR(__xludf.DUMMYFUNCTION("""COMPUTED_VALUE"""),"C202511141556043637") -> C202511141556043637 | I90: =IFERROR(__xludf.DUMMYFUNCTION("""COMPUTED_VALUE"""),"MANEL ALCAIDE VILLANUEVA") -> MANEL ALCAIDE VILLANUEVA | J90: =IFERROR(__xludf.DUMMYFUNCTION("""COMPUTED_VALUE"""),45975) -> 45975 | K90: =IFERROR(__xludf.DUMMYFUNCTION("""COMPUTED_VALUE"""),"Factura audífonos") -> Factura audífonos | L90: =IFERROR(__xludf.DUMMYFUNCTION("""COMPUTED_VALUE"""),46049) -> 46049 | M90: =IFERROR(__xludf.DUMMYFUNCTION("""COMPUTED_VALUE"""),"NO") -> NO | N90: =IFERROR(__xludf.DUMMYFUNCTION("""COMPUTED_VALUE"""),2) -> 2 | O90: =IFERROR(__xludf.DUMMYFUNCTION("""COMPUTED_VALUE"""),"PRO") -> PRO | P90: =IFERROR(__xludf.DUMMYFUNCTION("""COMPUTED_VALUE"""),4536.37) -> 4536.37 | Q90: =IFERROR(__xludf.DUMMYFUNCTION("""COMPUTED_VALUE"""),"Mercè Cabrera") -> Mercè Cabrera | R90: =IFERROR(__xludf.DUMMYFUNCTION("""COMPUTED_VALUE"""),"Enrique Romero Van Abeleen") -> Enrique Romero Van Abeleen | S90: =IFERROR(__xludf.DUMMYFUNCTION("""COMPUTED_VALUE"""),"03 ORL") -> 03 ORL | T90: =IFERROR(__xludf.DUMMYFUNCTION("""COMPUTED_VALUE"""),"06 ORL") -> 06 ORL
B91: =IF($C91="","",LEFT(C91,3)) -> MBM | C91: =IFERROR(__xludf.DUMMYFUNCTION("""COMPUTED_VALUE"""),"MBM132") -> MBM132 | D91: =IFERROR(__xludf.DUMMYFUNCTION("""COMPUTED_VALUE"""),"PARTICIPADOS") -> PARTICIPADOS | E91: =IFERROR(__xludf.DUMMYFUNCTION("""COMPUTED_VALUE"""),2026) -> 2026 | F91: =IFERROR(__xludf.DUMMYFUNCTION("""COMPUTED_VALUE"""),1) -> 1 | G91: =IFERROR(__xludf.DUMMYFUNCTION("""COMPUTED_VALUE"""),"Madrid- La Oca") -> Madrid- La Oca | H91: =IFERROR(__xludf.DUMMYFUNCTION("""COMPUTED_VALUE"""),"C202511315038757150") -> C202511315038757150 | I91: =IFERROR(__xludf.DUMMYFUNCTION("""COMPUTED_VALUE"""),"NIEVES ORDAS FIDALGO") -> NIEVES ORDAS FIDALGO | J91: =IFERROR(__xludf.DUMMYFUNCTION("""COMPUTED_VALUE"""),45964) -> 45964 | K91: =IFERROR(__xludf.DUMMYFUNCTION("""COMPUTED_VALUE"""),"Factura audífonos") -> Factura audífonos | L91: =IFERROR(__xludf.DUMMYFUNCTION("""COMPUTED_VALUE"""),46049) -> 46049 | M91: =IFERROR(__xludf.DUMMYFUNCTION("""COMPUTED_VALUE"""),"NO") -> NO | N91: =IFERROR(__xludf.DUMMYFUNCTION("""COMPUTED_VALUE"""),2) -> 2 | O91: =IFERROR(__xludf.DUMMYFUNCTION("""COMPUTED_VALUE"""),"QUIET") -> QUIET | P91: =IFERROR(__xludf.DUMMYFUNCTION("""COMPUTED_VALUE"""),2718.18) -> 2718.18 | Q91: =IFERROR(__xludf.DUMMYFUNCTION("""COMPUTED_VALUE"""),"Maika Blázquez") -> Maika Blázquez | R91: =IFERROR(__xludf.DUMMYFUNCTION("""COMPUTED_VALUE"""),"Laura Ruano De Pablo") -> Laura Ruano De Pablo | S91: =IFERROR(__xludf.DUMMYFUNCTION("""COMPUTED_VALUE"""),"03 ORL") -> 03 ORL | T91: =IFERROR(__xludf.DUMMYFUNCTION("""COMPUTED_VALUE"""),"06 ORL") -> 06 ORL
B92: =IF($C92="","",LEFT(C92,3)) -> LRM | C92: =IFERROR(__xludf.DUMMYFUNCTION("""COMPUTED_VALUE"""),"LRM13") -> LRM13 | D92: =IFERROR(__xludf.DUMMYFUNCTION("""COMPUTED_VALUE"""),"PARTICIPADOS") -> PARTICIPADOS | E92: =IFERROR(__xludf.DUMMYFUNCTION("""COMPUTED_VALUE"""),2026) -> 2026 | F92: =IFERROR(__xludf.DUMMYFUNCTION("""COMPUTED_VALUE"""),1) -> 1 | G92: =IFERROR(__xludf.DUMMYFUNCTION("""COMPUTED_VALUE"""),"Madrid- Costa Rica") -> Madrid- Costa Rica | H92: =IFERROR(__xludf.DUMMYFUNCTION("""COMPUTED_VALUE"""),"C202512512211094875") -> C202512512211094875 | I92: =IFERROR(__xludf.DUMMYFUNCTION("""COMPUTED_VALUE"""),"MICHELE CUNY") -> MICHELE CUNY | J92: =IFERROR(__xludf.DUMMYFUNCTION("""COMPUTED_VALUE"""),45996) -> 45996 | K92: =IFERROR(__xludf.DUMMYFUNCTION("""COMPUTED_VALUE"""),"Factura audífonos") -> Factura audífonos | L92: =IFERROR(__xludf.DUMMYFUNCTION("""COMPUTED_VALUE"""),46049) -> 46049 | M92: =IFERROR(__xludf.DUMMYFUNCTION("""COMPUTED_VALUE"""),"NO") -> NO | N92: =IFERROR(__xludf.DUMMYFUNCTION("""COMPUTED_VALUE"""),2) -> 2 | O92: =IFERROR(__xludf.DUMMYFUNCTION("""COMPUTED_VALUE"""),"QUIET") -> QUIET | P92: =IFERROR(__xludf.DUMMYFUNCTION("""COMPUTED_VALUE"""),2718.18) -> 2718.18 | Q92: =IFERROR(__xludf.DUMMYFUNCTION("""COMPUTED_VALUE"""),"Lisandro Russian") -> Lisandro Russian | R92: =IFERROR(__xludf.DUMMYFUNCTION("""COMPUTED_VALUE"""),"Antonio Bueno Ríos") -> Antonio Bueno Ríos | S92: =IFERROR(__xludf.DUMMYFUNCTION("""COMPUTED_VALUE"""),"03 ORL") -> 03 ORL | T92: =IFERROR(__xludf.DUMMYFUNCTION("""COMPUTED_VALUE"""),"06 ORL") -> 06 ORL
B93: =IF($C93="","",LEFT(C93,3)) -> RPG | C93: =IFERROR(__xludf.DUMMYFUNCTION("""COMPUTED_VALUE"""),"RPG51") -> RPG51 | D93: =IFERROR(__xludf.DUMMYFUNCTION("""COMPUTED_VALUE"""),"PARTICIPADOS") -> PARTICIPADOS | E93: =IFERROR(__xludf.DUMMYFUNCTION("""COMPUTED_VALUE"""),2026) -> 2026 | F93: =IFERROR(__xludf.DUMMYFUNCTION("""COMPUTED_VALUE"""),1) -> 1 | G93: =IFERROR(__xludf.DUMMYFUNCTION("""COMPUTED_VALUE"""),"Ourense") -> Ourense | H93: =IFERROR(__xludf.DUMMYFUNCTION("""COMPUTED_VALUE"""),"C202512111122089926") -> C202512111122089926 | I93: =IFERROR(__xludf.DUMMYFUNCTION("""COMPUTED_VALUE"""),"MARCELINO QUINTAS SUAREZ") -> MARCELINO QUINTAS SUAREZ | J93: =IFERROR(__xludf.DUMMYFUNCTION("""COMPUTED_VALUE"""),46002) -> 46002 | K93: =IFERROR(__xludf.DUMMYFUNCTION("""COMPUTED_VALUE"""),"Factura audífonos") -> Factura audífonos | L93: =IFERROR(__xludf.DUMMYFUNCTION("""COMPUTED_VALUE"""),46049) -> 46049 | M93: =IFERROR(__xludf.DUMMYFUNCTION("""COMPUTED_VALUE"""),"NO") -> NO | N93: =IFERROR(__xludf.DUMMYFUNCTION("""COMPUTED_VALUE"""),1) -> 1 | O93: =IFERROR(__xludf.DUMMYFUNCTION("""COMPUTED_VALUE"""),"CONFORT") -> CONFORT | P93: =IFERROR(__xludf.DUMMYFUNCTION("""COMPUTED_VALUE"""),2180.91) -> 2180.91 | Q93: =IFERROR(__xludf.DUMMYFUNCTION("""COMPUTED_VALUE"""),"Alberto Moreno") -> Alberto Moreno | R93: =IFERROR(__xludf.DUMMYFUNCTION("""COMPUTED_VALUE"""),"María Rey Marcos") -> María Rey Marcos | S93: =IFERROR(__xludf.DUMMYFUNCTION("""COMPUTED_VALUE"""),"03 ORL") -> 03 ORL | T93: =IFERROR(__xludf.DUMMYFUNCTION("""COMPUTED_VALUE"""),"06 ORL") -> 06 ORL
B94: =IF($C94="","",LEFT(C94,3)) -> ISL | C94: =IFERROR(__xludf.DUMMYFUNCTION("""COMPUTED_VALUE"""),"ISL94") -> ISL94 | D94: =IFERROR(__xludf.DUMMYFUNCTION("""COMPUTED_VALUE"""),"PROPIOS") -> PROPIOS | E94: =IFERROR(__xludf.DUMMYFUNCTION("""COMPUTED_VALUE"""),2026) -> 2026 | F94: =IFERROR(__xludf.DUMMYFUNCTION("""COMPUTED_VALUE"""),1) -> 1 | G94: =IFERROR(__xludf.DUMMYFUNCTION("""COMPUTED_VALUE"""),"Murcia") -> Murcia | H94: =IFERROR(__xludf.DUMMYFUNCTION("""COMPUTED_VALUE"""),"C202615105031143656") -> C202615105031143656 | I94: =IFERROR(__xludf.DUMMYFUNCTION("""COMPUTED_VALUE"""),"MARIA ANGELES HERNANDEZ VAZQUEZ") -> MARIA ANGELES HERNANDEZ VAZQUEZ | J94: =IFERROR(__xludf.DUMMYFUNCTION("""COMPUTED_VALUE"""),46027) -> 46027 | K94: =IFERROR(__xludf.DUMMYFUNCTION("""COMPUTED_VALUE"""),"Factura audífonos") -> Factura audífonos | L94: =IFERROR(__xludf.DUMMYFUNCTION("""COMPUTED_VALUE"""),46049) -> 46049 | M94: =IFERROR(__xludf.DUMMYFUNCTION("""COMPUTED_VALUE"""),"NO") -> NO | N94: =IFERROR(__xludf.DUMMYFUNCTION("""COMPUTED_VALUE"""),2) -> 2 | O94: =IFERROR(__xludf.DUMMYFUNCTION("""COMPUTED_VALUE"""),"QUIET") -> QUIET | P94: =IFERROR(__xludf.DUMMYFUNCTION("""COMPUTED_VALUE"""),2718.18) -> 2718.18 | Q94: =IFERROR(__xludf.DUMMYFUNCTION("""COMPUTED_VALUE"""),"Iván Sánchez") -> Iván Sánchez | R94: =IFERROR(__xludf.DUMMYFUNCTION("""COMPUTED_VALUE"""),"Beatriz Rodríguez González Herrero") -> Beatriz Rodríguez González Herrero | S94: =IFERROR(__xludf.DUMMYFUNCTION("""COMPUTED_VALUE"""),"03 ORL") -> 03 ORL | T94: =IFERROR(__xludf.DUMMYFUNCTION("""COMPUTED_VALUE"""),"06 ORL") -> 06 ORL
B95: =IF($C95="","",LEFT(C95,3)) -> LAA | C95: =IFERROR(__xludf.DUMMYFUNCTION("""COMPUTED_VALUE"""),"LAA78") -> LAA78 | D95: =IFERROR(__xludf.DUMMYFUNCTION("""COMPUTED_VALUE"""),"PROPIOS") -> PROPIOS | E95: =IFERROR(__xludf.DUMMYFUNCTION("""COMPUTED_VALUE"""),2026) -> 2026 | F95: =IFERROR(__xludf.DUMMYFUNCTION("""COMPUTED_VALUE"""),1) -> 1 | G95: =IFERROR(__xludf.DUMMYFUNCTION("""COMPUTED_VALUE"""),"Jerez de la Frontera") -> Jerez de la Frontera | H95: =IFERROR(__xludf.DUMMYFUNCTION("""COMPUTED_VALUE"""),"C202617145953074840") -> C202617145953074840 | I95: =IFERROR(__xludf.DUMMYFUNCTION("""COMPUTED_VALUE"""),"herminia CORDERO RODRIGUEZ") -> herminia CORDERO RODRIGUEZ | J95: =IFERROR(__xludf.DUMMYFUNCTION("""COMPUTED_VALUE"""),46029) -> 46029 | K95: =IFERROR(__xludf.DUMMYFUNCTION("""COMPUTED_VALUE"""),"Factura audífonos") -> Factura audífonos | L95: =IFERROR(__xludf.DUMMYFUNCTION("""COMPUTED_VALUE"""),46050) -> 46050 | M95: =IFERROR(__xludf.DUMMYFUNCTION("""COMPUTED_VALUE"""),"NO") -> NO | N95: =IFERROR(__xludf.DUMMYFUNCTION("""COMPUTED_VALUE"""),2) -> 2 | O95: =IFERROR(__xludf.DUMMYFUNCTION("""COMPUTED_VALUE"""),"QUIET") -> QUIET | P95: =IFERROR(__xludf.DUMMYFUNCTION("""COMPUTED_VALUE"""),2718.18) -> 2718.18 | Q95: =IFERROR(__xludf.DUMMYFUNCTION("""COMPUTED_VALUE"""),"Luis Alberto Rodríguez") -> Luis Alberto Rodríguez | R95: =IFERROR(__xludf.DUMMYFUNCTION("""COMPUTED_VALUE"""),"Maria Del Carmen Salom Coveñas") -> Maria Del Carmen Salom Coveñas | S95: =IFERROR(__xludf.DUMMYFUNCTION("""COMPUTED_VALUE"""),"03 ORL") -> 03 ORL | T95: =IFERROR(__xludf.DUMMYFUNCTION("""COMPUTED_VALUE"""),"06 ORL") -> 06 ORL
