Workbook

Sheet TOTAL2026
A1: CONTRATO | B1: MES | C1: VISITADOR | D1: CENTRO | E1: COD.CONTRATO | F1: ORL | G1: ACCION MKT | H1: CATEGORÍAS | I1: FECHA P/ | J1: FECHA PAGO | K1: IMPORTE | L1: EMPRESA | M1: OBSERVACIONES | N1: Codigo medico
A2: =IF(C2="","",IFERROR(VLOOKUP($E2,códigos!$R:$R,1,FALSE),"NO")) -> NO | B2: =IFERROR(__xludf.DUMMYFUNCTION("{FILTER(ENERO!A4:K1001,ENERO!C4:C1001<>"""");FILTER(FEBRERO!A4:K1001,FEBRERO!C4:C1001<>"""");FILTER(MARZO!A4:K1001,MARZO!C4:C1001<>"""");FILTER(ABRIL!A4:K1001,ABRIL!C4:C1001<>"""");FILTER(MAYO!A4:K1001,MAYO!C4:C1001<>"""");FILTER(JUNIO!A4:K1001,JUNIO!C4:C"&"1001<>"""");FILTER(JULIO!A4:K1001,JULIO!C4:C1001<>"""");FILTER(AGOSTO!A4:K1001,AGOSTO!C4:C1001<>"""");FILTER(SEPTIEMBRE!A4:K1001,SEPTIEMBRE!C4:C1001<>"""");FILTER(OCTUBRE!A4:K1001,OCTUBRE!C4:C1001<>"""");FILTER(NOVIEMBRE!A4:K1001,NOVIEMBRE!C4:C1001<>"""")"&";FILTER(DICIEMBRE!A4:K1001,DICIEMBRE!C4:C1001<>"""")}"),1) -> 1 | C2: =IFERROR(__xludf.DUMMYFUNCTION("""COMPUTED_VALUE"""),"Luis Alberto Rodríguez") -> Luis Alberto Rodríguez | D2: =IFERROR(__xludf.DUMMYFUNCTION("""COMPUTED_VALUE"""),"Jerez de la Frontera") -> Jerez de la Frontera | E2: =IFERROR(__xludf.DUMMYFUNCTION("""COMPUTED_VALUE"""),"LAA78") -> LAA78 | F2: =IFERROR(__xludf.DUMMYFUNCTION("""COMPUTED_VALUE"""),"Maria Del Carmen Salom Coveñas") -> Maria Del Carmen Salom Coveñas | G2: =IFERROR(__xludf.DUMMYFUNCTION("""COMPUTED_VALUE"""),"PATROCINIO") -> PATROCINIO | H2: =IFERROR(__xludf.DUMMYFUNCTION("""COMPUTED_VALUE"""),"Publicidad") -> Publicidad | J2: =IFERROR(__xludf.DUMMYFUNCTION("""COMPUTED_VALUE"""),46034) -> 46034 | K2: =IFERROR(__xludf.DUMMYFUNCTION("""COMPUTED_VALUE"""),-4432) -> -4432 | L2: =IFERROR(__xludf.DUMMYFUNCTION("""COMPUTED_VALUE"""),"AUDICOST, S.L.U") -> AUDICOST, S.L.U
A3: =IF(C3="","",IFERROR(VLOOKUP($E3,códigos!$R:$R,1,FALSE),"NO")) -> NO | B3: =IFERROR(__xludf.DUMMYFUNCTION("""COMPUTED_VALUE"""),1) -> 1 | C3: =IFERROR(__xludf.DUMMYFUNCTION("""COMPUTED_VALUE"""),"Maika Blázquez") -> Maika Blázquez | D3: =IFERROR(__xludf.DUMMYFUNCTION("""COMPUTED_VALUE"""),"Getafe") -> Getafe | E3: =IFERROR(__xludf.DUMMYFUNCTION("""COMPUTED_VALUE"""),"MBM149") -> MBM149 | F3: =IFERROR(__xludf.DUMMYFUNCTION("""COMPUTED_VALUE"""),"María Garrote Garrote") -> María Garrote Garrote | G3: =IFERROR(__xludf.DUMMYFUNCTION("""COMPUTED_VALUE"""),"AIRBNB") -> AIRBNB | H3: =IFERROR(__xludf.DUMMYFUNCTION("""COMPUTED_VALUE"""),"Alojamiento") -> Alojamiento | I3: =IFERROR(__xludf.DUMMYFUNCTION("""COMPUTED_VALUE"""),46036) -> 46036 | J3: =IFERROR(__xludf.DUMMYFUNCTION("""COMPUTED_VALUE"""),46034) -> 46034 | K3: =IFERROR(__xludf.DUMMYFUNCTION("""COMPUTED_VALUE"""),-1700) -> -1700 | L3: =IFERROR(__xludf.DUMMYFUNCTION("""COMPUTED_VALUE"""),"AUDIBRADA") -> AUDIBRADA
A4: =IF(C4="","",IFERROR(VLOOKUP($E4,códigos!$R:$R,1,FALSE),"NO")) -> NO | B4: =IFERROR(__xludf.DUMMYFUNCTION("""COMPUTED_VALUE"""),1) -> 1 | C4: =IFERROR(__xludf.DUMMYFUNCTION("""COMPUTED_VALUE"""),"Maika Blázquez") -> Maika Blázquez | D4: =IFERROR(__xludf.DUMMYFUNCTION("""COMPUTED_VALUE"""),"Fuenlabrada") -> Fuenlabrada | E4: =IFERROR(__xludf.DUMMYFUNCTION("""COMPUTED_VALUE"""),"MBM164") -> MBM164 | F4: =IFERROR(__xludf.DUMMYFUNCTION("""COMPUTED_VALUE"""),"Paloma Martín-Aragón Martín") -> Paloma Martín-Aragón Martín | G4: =IFERROR(__xludf.DUMMYFUNCTION("""COMPUTED_VALUE"""),"INSCRIPCION CURSO MICROCIRUGIA") -> INSCRIPCION CURSO MICROCIRUGIA | H4: =IFERROR(__xludf.DUMMYFUNCTION("""COMPUTED_VALUE"""),"Inscripción") -> Inscripción | J4: =IFERROR(__xludf.DUMMYFUNCTION("""COMPUTED_VALUE"""),46035) -> 46035 | K4: =IFERROR(__xludf.DUMMYFUNCTION("""COMPUTED_VALUE"""),-1663.35) -> -1663.35 | L4: =IFERROR(__xludf.DUMMYFUNCTION("""COMPUTED_VALUE"""),"AUDIBRADA") -> AUDIBRADA
A5: =IF(C5="","",IFERROR(VLOOKUP($E5,códigos!$R:$R,1,FALSE),"NO")) -> NO | B5: =IFERROR(__xludf.DUMMYFUNCTION("""COMPUTED_VALUE"""),1) -> 1 | C5: =IFERROR(__xludf.DUMMYFUNCTION("""COMPUTED_VALUE"""),"Maika Blázquez") -> Maika Blázquez | D5: =IFERROR(__xludf.DUMMYFUNCTION("""COMPUTED_VALUE"""),"Fuenlabrada") -> Fuenlabrada | E5: =IFERROR(__xludf.DUMMYFUNCTION("""COMPUTED_VALUE"""),"MBM111") -> MBM111 | F5: =IFERROR(__xludf.DUMMYFUNCTION("""COMPUTED_VALUE"""),"Elisabeth Amarillo Espitia") -> Elisabeth Amarillo Espitia | G5: =IFERROR(__xludf.DUMMYFUNCTION("""COMPUTED_VALUE"""),"INSCRIPCION CURSO MICROCIRUGIA") -> INSCRIPCION CURSO MICROCIRUGIA | H5: =IFERROR(__xludf.DUMMYFUNCTION("""COMPUTED_VALUE"""),"Inscripción") -> Inscripción | J5: =IFERROR(__xludf.DUMMYFUNCTION("""COMPUTED_VALUE"""),46035) -> 46035 | K5: =IFERROR(__xludf.DUMMYFUNCTION("""COMPUTED_VALUE"""),-1663.35) -> -1663.35 | L5: =IFERROR(__xludf.DUMMYFUNCTION("""COMPUTED_VALUE"""),"AUDIBRADA") -> AUDIBRADA
A6: =IF(C6="","",IFERROR(VLOOKUP($E6,códigos!$R:$R,1,FALSE),"NO")) -> NO | B6: =IFERROR(__xludf.DUMMYFUNCTION("""COMPUTED_VALUE"""),1) -> 1 | C6: =IFERROR(__xludf.DUMMYFUNCTION("""COMPUTED_VALUE"""),"Maika Blázquez") -> Maika Blázquez | D6: =IFERROR(__xludf.DUMMYFUNCTION("""COMPUTED_VALUE"""),"Madrid- Canillas") -> Madrid- Canillas | E6: =IFERROR(__xludf.DUMMYFUNCTION("""COMPUTED_VALUE"""),"MBM50") -> MBM50 | F6: =IFERROR(__xludf.DUMMYFUNCTION("""COMPUTED_VALUE"""),"José Gustavo Barroso Braojos") -> José Gustavo Barroso Braojos | G6: =IFERROR(__xludf.DUMMYFUNCTION("""COMPUTED_VALUE"""),"2 SMARTWATCH") -> 2 SMARTWATCH | H6: =IFERROR(__xludf.DUMMYFUNCTION("""COMPUTED_VALUE"""),"Material para centro") -> Material para centro | I6: =IFERROR(__xludf.DUMMYFUNCTION("""COMPUTED_VALUE"""),46036) -> 46036 | J6: =IFERROR(__xludf.DUMMYFUNCTION("""COMPUTED_VALUE"""),46035) -> 46035 | K6: =IFERROR(__xludf.DUMMYFUNCTION("""COMPUTED_VALUE"""),-899.98) -> -899.98 | L6: =IFERROR(__xludf.DUMMYFUNCTION("""COMPUTED_VALUE"""),"AUDICOST, S.L.U") -> AUDICOST, S.L.U
A7: =IF(C7="","",IFERROR(VLOOKUP($E7,códigos!$R:$R,1,FALSE),"NO")) -> NO | B7: =IFERROR(__xludf.DUMMYFUNCTION("""COMPUTED_VALUE"""),1) -> 1 | C7: =IFERROR(__xludf.DUMMYFUNCTION("""COMPUTED_VALUE"""),"Luis Alberto Rodríguez") -> Luis Alberto Rodríguez | D7: =IFERROR(__xludf.DUMMYFUNCTION("""COMPUTED_VALUE"""),"Sevilla- Montoto") -> Sevilla- Montoto | E7: =IFERROR(__xludf.DUMMYFUNCTION("""COMPUTED_VALUE"""),"LAA08") -> LAA08 | F7: =IFERROR(__xludf.DUMMYFUNCTION("""COMPUTED_VALUE"""),"David Castro Gutiérrez de Agüero") -> David Castro Gutiérrez de Agüero | G7: =IFERROR(__xludf.DUMMYFUNCTION("""COMPUTED_VALUE"""),"IPHONE17 PRO") -> IPHONE17 PRO | H7: =IFERROR(__xludf.DUMMYFUNCTION("""COMPUTED_VALUE"""),"Material para centro") -> Material para centro | I7: =IFERROR(__xludf.DUMMYFUNCTION("""COMPUTED_VALUE"""),46042) -> 46042 | J7: =IFERROR(__xludf.DUMMYFUNCTION("""COMPUTED_VALUE"""),46037) -> 46037 | K7: =IFERROR(__xludf.DUMMYFUNCTION("""COMPUTED_VALUE"""),-1289) -> -1289 | L7: =IFERROR(__xludf.DUMMYFUNCTION("""COMPUTED_VALUE"""),"OIR VITAL CENTROS AUDITIVOS ") -> OIR VITAL CENTROS AUDITIVOS
A8: =IF(C8="","",IFERROR(VLOOKUP($E8,códigos!$R:$R,1,FALSE),"NO")) -> NO | B8: =IFERROR(__xludf.DUMMYFUNCTION("""COMPUTED_VALUE"""),1) -> 1 | C8: =IFERROR(__xludf.DUMMYFUNCTION("""COMPUTED_VALUE"""),"Maika Blázquez") -> Maika Blázquez | D8: =IFERROR(__xludf.DUMMYFUNCTION("""COMPUTED_VALUE"""),"Torrejón De Ardoz") -> Torrejón De Ardoz | E8: =IFERROR(__xludf.DUMMYFUNCTION("""COMPUTED_VALUE"""),"MBM136") -> MBM136 | F8: =IFERROR(__xludf.DUMMYFUNCTION("""COMPUTED_VALUE"""),"Lorena Sanz López") -> Lorena Sanz López | G8: =IFERROR(__xludf.DUMMYFUNCTION("""COMPUTED_VALUE"""),"INSCRIPCION, VUELO Y HOTEL-MAYOR IMPORTE DICBRE.") -> INSCRIPCION, VUELO Y HOTEL-MAYOR IMPORTE DICBRE. | H8: =IFERROR(__xludf.DUMMYFUNCTION("""COMPUTED_VALUE"""),"Inscripción") -> Inscripción | I8: =IFERROR(__xludf.DUMMYFUNCTION("""COMPUTED_VALUE"""),46042) -> 46042 | J8: =IFERROR(__xludf.DUMMYFUNCTION("""COMPUTED_VALUE"""),46041) -> 46041 | K8: =IFERROR(__xludf.DUMMYFUNCTION("""COMPUTED_VALUE"""),-205.75) -> -205.75 | L8: =IFERROR(__xludf.DUMMYFUNCTION("""COMPUTED_VALUE"""),"AUDICOST LEGANES") -> AUDICOST LEGANES
A9: =IF(C9="","",IFERROR(VLOOKUP($E9,códigos!$R:$R,1,FALSE),"NO")) -> NO | B9: =IFERROR(__xludf.DUMMYFUNCTION("""COMPUTED_VALUE"""),1) -> 1 | C9: =IFERROR(__xludf.DUMMYFUNCTION("""COMPUTED_VALUE"""),"Maika Blázquez") -> Maika Blázquez | D9: =IFERROR(__xludf.DUMMYFUNCTION("""COMPUTED_VALUE"""),"Madrid- La Oca") -> Madrid- La Oca | E9: =IFERROR(__xludf.DUMMYFUNCTION("""COMPUTED_VALUE"""),"MBM52") -> MBM52 | F9: =IFERROR(__xludf.DUMMYFUNCTION("""COMPUTED_VALUE"""),"José Joaquín Gutiérrez Barquín") -> José Joaquín Gutiérrez Barquín | G9: =IFERROR(__xludf.DUMMYFUNCTION("""COMPUTED_VALUE"""),"MESA") -> MESA | H9: =IFERROR(__xludf.DUMMYFUNCTION("""COMPUTED_VALUE"""),"Mobiliario") -> Mobiliario | I9: =IFERROR(__xludf.DUMMYFUNCTION("""COMPUTED_VALUE"""),46044) -> 46044 | J9: =IFERROR(__xludf.DUMMYFUNCTION("""COMPUTED_VALUE"""),46042) -> 46042 | K9: =IFERROR(__xludf.DUMMYFUNCTION("""COMPUTED_VALUE"""),-973) -> -973 | L9: =IFERROR(__xludf.DUMMYFUNCTION("""COMPUTED_VALUE"""),"SIEMA BLINK, S.L") -> SIEMA BLINK, S.L
A10: =IF(C10="","",IFERROR(VLOOKUP($E10,códigos!$R:$R,1,FALSE),"NO")) -> NO | B10: =IFERROR(__xludf.DUMMYFUNCTION("""COMPUTED_VALUE"""),1) -> 1 | C10: =IFERROR(__xludf.DUMMYFUNCTION("""COMPUTED_VALUE"""),"Maika Blázquez") -> Maika Blázquez | D10: =IFERROR(__xludf.DUMMYFUNCTION("""COMPUTED_VALUE"""),"Fuenlabrada") -> Fuenlabrada | E10: =IFERROR(__xludf.DUMMYFUNCTION("""COMPUTED_VALUE"""),"MBM190") -> MBM190 | F10: =IFERROR(__xludf.DUMMYFUNCTION("""COMPUTED_VALUE"""),"Cristina García García") -> Cristina García García | G10: =IFERROR(__xludf.DUMMYFUNCTION("""COMPUTED_VALUE"""),"CURSO 2") -> CURSO 2 | H10: =IFERROR(__xludf.DUMMYFUNCTION("""COMPUTED_VALUE"""),"Inscripción") -> Inscripción | I10: =IFERROR(__xludf.DUMMYFUNCTION("""COMPUTED_VALUE""")," ") | J10: =IFERROR(__xludf.DUMMYFUNCTION("""COMPUTED_VALUE"""),46043) -> 46043 | K10: =IFERROR(__xludf.DUMMYFUNCTION("""COMPUTED_VALUE"""),-1386.13) -> -1386.13 | L10: =IFERROR(__xludf.DUMMYFUNCTION("""COMPUTED_VALUE"""),"AUDIBRADA") -> AUDIBRADA
A11: =IF(C11="","",IFERROR(VLOOKUP($E11,códigos!$R:$R,1,FALSE),"NO")) -> NO | B11: =IFERROR(__xludf.DUMMYFUNCTION("""COMPUTED_VALUE"""),1) -> 1 | C11: =IFERROR(__xludf.DUMMYFUNCTION("""COMPUTED_VALUE"""),"Maika Blázquez") -> Maika Blázquez | D11: =IFERROR(__xludf.DUMMYFUNCTION("""COMPUTED_VALUE"""),"Fuenlabrada") -> Fuenlabrada | E11: =IFERROR(__xludf.DUMMYFUNCTION("""COMPUTED_VALUE"""),"MBM190") -> MBM190 | F11: =IFERROR(__xludf.DUMMYFUNCTION("""COMPUTED_VALUE"""),"Cristina García García") -> Cristina García García | G11: =IFERROR(__xludf.DUMMYFUNCTION("""COMPUTED_VALUE"""),"CURSO 1") -> CURSO 1 | H11: =IFERROR(__xludf.DUMMYFUNCTION("""COMPUTED_VALUE"""),"Inscripción") -> Inscripción | I11: =IFERROR(__xludf.DUMMYFUNCTION("""COMPUTED_VALUE""")," ") | J11: =IFERROR(__xludf.DUMMYFUNCTION("""COMPUTED_VALUE"""),46043) -> 46043 | K11: =IFERROR(__xludf.DUMMYFUNCTION("""COMPUTED_VALUE"""),-1386.13) -> -1386.13 | L11: =IFERROR(__xludf.DUMMYFUNCTION("""COMPUTED_VALUE"""),"AUDIBRADA") -> AUDIBRADA
A12: =IF(C12="","",IFERROR(VLOOKUP($E12,códigos!$R:$R,1,FALSE),"NO")) -> NO | B12: =IFERROR(__xludf.DUMMYFUNCTION("""COMPUTED_VALUE"""),1) -> 1 | C12: =IFERROR(__xludf.DUMMYFUNCTION("""COMPUTED_VALUE"""),"Maika Blázquez") -> Maika Blázquez | D12: =IFERROR(__xludf.DUMMYFUNCTION("""COMPUTED_VALUE"""),"Madrid- Juan Bravo") -> Madrid- Juan Bravo | E12: =IFERROR(__xludf.DUMMYFUNCTION("""COMPUTED_VALUE"""),"MBM224") -> MBM224 | F12: =IFERROR(__xludf.DUMMYFUNCTION("""COMPUTED_VALUE"""),"Roberto Sanz Garzón") -> Roberto Sanz Garzón | G12: =IFERROR(__xludf.DUMMYFUNCTION("""COMPUTED_VALUE"""),"CURSO") -> CURSO | H12: =IFERROR(__xludf.DUMMYFUNCTION("""COMPUTED_VALUE"""),"Inscripción") -> Inscripción | I12: =IFERROR(__xludf.DUMMYFUNCTION("""COMPUTED_VALUE"""),46043) -> 46043 | J12: =IFERROR(__xludf.DUMMYFUNCTION("""COMPUTED_VALUE"""),46043) -> 46043 | K12: =IFERROR(__xludf.DUMMYFUNCTION("""COMPUTED_VALUE"""),-600) -> -600 | L12: =IFERROR(__xludf.DUMMYFUNCTION("""COMPUTED_VALUE"""),"AUDICOST, S.L.U") -> AUDICOST, S.L.U
A13: =IF(C13="","",IFERROR(VLOOKUP($E13,códigos!$R:$R,1,FALSE),"NO")) -> NO | B13: =IFERROR(__xludf.DUMMYFUNCTION("""COMPUTED_VALUE"""),1) -> 1 | C13: =IFERROR(__xludf.DUMMYFUNCTION("""COMPUTED_VALUE"""),"Lisandro Russian") -> Lisandro Russian | D13: =IFERROR(__xludf.DUMMYFUNCTION("""COMPUTED_VALUE"""),"Logroño") -> Logroño | E13: =IFERROR(__xludf.DUMMYFUNCTION("""COMPUTED_VALUE"""),"LRM151") -> LRM151 | F13: =IFERROR(__xludf.DUMMYFUNCTION("""COMPUTED_VALUE"""),"Cristina Ibañez Muñoz") -> Cristina Ibañez Muñoz | G13: =IFERROR(__xludf.DUMMYFUNCTION("""COMPUTED_VALUE"""),"CONGRESO ATENAS") -> CONGRESO ATENAS | H13: =IFERROR(__xludf.DUMMYFUNCTION("""COMPUTED_VALUE"""),"Congreso internacional personal") -> Congreso internacional personal | I13: =IFERROR(__xludf.DUMMYFUNCTION("""COMPUTED_VALUE"""),46058) -> 46058 | J13: =IFERROR(__xludf.DUMMYFUNCTION("""COMPUTED_VALUE"""),46044) -> 46044 | K13: =IFERROR(__xludf.DUMMYFUNCTION("""COMPUTED_VALUE"""),-4701.07) -> -4701.07 | L13: =IFERROR(__xludf.DUMMYFUNCTION("""COMPUTED_VALUE"""),"AUDICOST LOGROÑO ") -> AUDICOST LOGROÑO
A14: =IF(C14="","",IFERROR(VLOOKUP($E14,códigos!$R:$R,1,FALSE),"NO")) -> NO | B14: =IFERROR(__xludf.DUMMYFUNCTION("""COMPUTED_VALUE"""),1) -> 1 | C14: =IFERROR(__xludf.DUMMYFUNCTION("""COMPUTED_VALUE"""),"Ramon Ferrando") -> Ramon Ferrando | D14: =IFERROR(__xludf.DUMMYFUNCTION("""COMPUTED_VALUE"""),"El Albir (Benidorm)") -> El Albir (Benidorm) | E14: =IFERROR(__xludf.DUMMYFUNCTION("""COMPUTED_VALUE"""),"RFV38") -> RFV38 | F14: =IFERROR(__xludf.DUMMYFUNCTION("""COMPUTED_VALUE"""),"María Emilia García Ruiz") -> María Emilia García Ruiz | G14: =IFERROR(__xludf.DUMMYFUNCTION("""COMPUTED_VALUE"""),"IPHONE17 ") -> IPHONE17 | H14: =IFERROR(__xludf.DUMMYFUNCTION("""COMPUTED_VALUE"""),"Material para centro") -> Material para centro | J14: =IFERROR(__xludf.DUMMYFUNCTION("""COMPUTED_VALUE"""),46045) -> 46045 | K14: =IFERROR(__xludf.DUMMYFUNCTION("""COMPUTED_VALUE"""),-1500) -> -1500 | L14: =IFERROR(__xludf.DUMMYFUNCTION("""COMPUTED_VALUE"""),"AUDICANTE") -> AUDICANTE
A15: =IF(C15="","",IFERROR(VLOOKUP($E15,códigos!$R:$R,1,FALSE),"NO")) -> NO | B15: =IFERROR(__xludf.DUMMYFUNCTION("""COMPUTED_VALUE"""),1) -> 1 | C15: =IFERROR(__xludf.DUMMYFUNCTION("""COMPUTED_VALUE"""),"Maika Blázquez") -> Maika Blázquez | D15: =IFERROR(__xludf.DUMMYFUNCTION("""COMPUTED_VALUE"""),"Torrejón De Ardoz") -> Torrejón De Ardoz | E15: =IFERROR(__xludf.DUMMYFUNCTION("""COMPUTED_VALUE"""),"MBM187") -> MBM187 | F15: =IFERROR(__xludf.DUMMYFUNCTION("""COMPUTED_VALUE"""),"Abel Bogoya Castaño") -> Abel Bogoya Castaño | G15: =IFERROR(__xludf.DUMMYFUNCTION("""COMPUTED_VALUE"""),"CURSO") -> CURSO | H15: =IFERROR(__xludf.DUMMYFUNCTION("""COMPUTED_VALUE"""),"Inscripción") -> Inscripción | L15: =IFERROR(__xludf.DUMMYFUNCTION("""COMPUTED_VALUE"""),"AUDICOST LEGANES") -> AUDICOST LEGANES
A16: =IF(C16="","",IFERROR(VLOOKUP($E16,códigos!$R:$R,1,FALSE),"NO")) -> NO | B16: =IFERROR(__xludf.DUMMYFUNCTION("""COMPUTED_VALUE"""),1) -> 1 | C16: =IFERROR(__xludf.DUMMYFUNCTION("""COMPUTED_VALUE"""),"Ramon Ferrando") -> Ramon Ferrando | D16: =IFERROR(__xludf.DUMMYFUNCTION("""COMPUTED_VALUE"""),"Valencia- Cadiz") -> Valencia- Cadiz | E16: =IFERROR(__xludf.DUMMYFUNCTION("""COMPUTED_VALUE"""),"RFV48") -> RFV48 | F16: =IFERROR(__xludf.DUMMYFUNCTION("""COMPUTED_VALUE"""),"Elena González Turienzo") -> Elena González Turienzo | G16: =IFERROR(__xludf.DUMMYFUNCTION("""COMPUTED_VALUE"""),"CURSO") -> CURSO | H16: =IFERROR(__xludf.DUMMYFUNCTION("""COMPUTED_VALUE"""),"Inscripción") -> Inscripción | I16: =IFERROR(__xludf.DUMMYFUNCTION("""COMPUTED_VALUE"""),46058) -> 46058 | J16: =IFERROR(__xludf.DUMMYFUNCTION("""COMPUTED_VALUE"""),46049) -> 46049 | K16: =IFERROR(__xludf.DUMMYFUNCTION("""COMPUTED_VALUE"""),-133.07) -> -133.07 | L16: =IFERROR(__xludf.DUMMYFUNCTION("""COMPUTED_VALUE"""),"AUDICANTE") -> AUDICANTE
A17: =IF(C17="","",IFERROR(VLOOKUP($E17,códigos!$R:$R,1,FALSE),"NO")) -> NO | B17: =IFERROR(__xludf.DUMMYFUNCTION("""COMPUTED_VALUE"""),2) -> 2 | C17: =IFERROR(__xludf.DUMMYFUNCTION("""COMPUTED_VALUE"""),"Maika Blázquez") -> Maika Blázquez | D17: =IFERROR(__xludf.DUMMYFUNCTION("""COMPUTED_VALUE"""),"Torrejón De Ardoz") -> Torrejón De Ardoz | E17: =IFERROR(__xludf.DUMMYFUNCTION("""COMPUTED_VALUE"""),"MBM61") -> MBM61 | F17: =IFERROR(__xludf.DUMMYFUNCTION("""COMPUTED_VALUE"""),"Julie Múñoz Freitez") -> Julie Múñoz Freitez | G17: =IFERROR(__xludf.DUMMYFUNCTION("""COMPUTED_VALUE"""),"CURSO") -> CURSO | H17: =IFERROR(__xludf.DUMMYFUNCTION("""COMPUTED_VALUE"""),"Inscripción") -> Inscripción | I17: =IFERROR(__xludf.DUMMYFUNCTION("""COMPUTED_VALUE"""),46062) -> 46062 | J17: =IFERROR(__xludf.DUMMYFUNCTION("""COMPUTED_VALUE"""),46056) -> 46056 | K17: =IFERROR(__xludf.DUMMYFUNCTION("""COMPUTED_VALUE"""),-2772.25) -> -2772.25 | L17: =IFERROR(__xludf.DUMMYFUNCTION("""COMPUTED_VALUE"""),"AUDICOST LEGANES") -> AUDICOST LEGANES
A18: =IF(C18="","",IFERROR(VLOOKUP($E18,códigos!$R:$R,1,FALSE),"NO")) -> NO | B18: =IFERROR(__xludf.DUMMYFUNCTION("""COMPUTED_VALUE"""),2) -> 2 | C18: =IFERROR(__xludf.DUMMYFUNCTION("""COMPUTED_VALUE"""),"Maika Blázquez") -> Maika Blázquez | D18: =IFERROR(__xludf.DUMMYFUNCTION("""COMPUTED_VALUE"""),"Fuenlabrada") -> Fuenlabrada | E18: =IFERROR(__xludf.DUMMYFUNCTION("""COMPUTED_VALUE"""),"MBM147") -> MBM147 | F18: =IFERROR(__xludf.DUMMYFUNCTION("""COMPUTED_VALUE"""),"María Estefanía Hernández García") -> María Estefanía Hernández García | G18: =IFERROR(__xludf.DUMMYFUNCTION("""COMPUTED_VALUE"""),"CURSO") -> CURSO | H18: =IFERROR(__xludf.DUMMYFUNCTION("""COMPUTED_VALUE"""),"Inscripción") -> Inscripción | I18: =IFERROR(__xludf.DUMMYFUNCTION("""COMPUTED_VALUE"""),46064) -> 46064 | J18: =IFERROR(__xludf.DUMMYFUNCTION("""COMPUTED_VALUE"""),46056) -> 46056 | K18: =IFERROR(__xludf.DUMMYFUNCTION("""COMPUTED_VALUE"""),-443.56) -> -443.56 | L18: =IFERROR(__xludf.DUMMYFUNCTION("""COMPUTED_VALUE"""),"AUDIBRADA") -> AUDIBRADA
A19: =IF(C19="","",IFERROR(VLOOKUP($E19,códigos!$R:$R,1,FALSE),"NO")) -> NO | B19: =IFERROR(__xludf.DUMMYFUNCTION("""COMPUTED_VALUE"""),2) -> 2 | C19: =IFERROR(__xludf.DUMMYFUNCTION("""COMPUTED_VALUE"""),"Ramon Ferrando") -> Ramon Ferrando | D19: =IFERROR(__xludf.DUMMYFUNCTION("""COMPUTED_VALUE"""),"Valencia- Parra") -> Valencia- Parra | E19: =IFERROR(__xludf.DUMMYFUNCTION("""COMPUTED_VALUE"""),"RFV15") -> RFV15 | F19: =IFERROR(__xludf.DUMMYFUNCTION("""COMPUTED_VALUE"""),"Jean Franco Intraprendente Martini") -> Jean Franco Intraprendente Martini | G19: =IFERROR(__xludf.DUMMYFUNCTION("""COMPUTED_VALUE"""),"APPLEWATCH") -> APPLEWATCH | H19: =IFERROR(__xludf.DUMMYFUNCTION("""COMPUTED_VALUE"""),"Material para centro") -> Material para centro | J19: =IFERROR(__xludf.DUMMYFUNCTION("""COMPUTED_VALUE"""),46055) -> 46055 | K19: =IFERROR(__xludf.DUMMYFUNCTION("""COMPUTED_VALUE"""),-899) -> -899 | L19: =IFERROR(__xludf.DUMMYFUNCTION("""COMPUTED_VALUE"""),"AUDICOST, S.L.U") -> AUDICOST, S.L.U
A20: =IF(C20="","",IFERROR(VLOOKUP($E20,códigos!$R:$R,1,FALSE),"NO")) -> NO | B20: =IFERROR(__xludf.DUMMYFUNCTION("""COMPUTED_VALUE"""),2) -> 2 | C20: =IFERROR(__xludf.DUMMYFUNCTION("""COMPUTED_VALUE"""),"Iván Sánchez") -> Iván Sánchez | D20: =IFERROR(__xludf.DUMMYFUNCTION("""COMPUTED_VALUE"""),"El Albir (Benidorm)") -> El Albir (Benidorm) | E20: =IFERROR(__xludf.DUMMYFUNCTION("""COMPUTED_VALUE"""),"ISL54") -> ISL54 | F20: =IFERROR(__xludf.DUMMYFUNCTION("""COMPUTED_VALUE"""),"José María Laborda Margolles") -> José María Laborda Margolles | G20: =IFERROR(__xludf.DUMMYFUNCTION("""COMPUTED_VALUE"""),"VIAJE A TANZANIA") -> VIAJE A TANZANIA | H20: =IFERROR(__xludf.DUMMYFUNCTION("""COMPUTED_VALUE"""),"Congreso internacional") -> Congreso internacional | I20: =IFERROR(__xludf.DUMMYFUNCTION("""COMPUTED_VALUE"""),46059) -> 46059 | J20: =IFERROR(__xludf.DUMMYFUNCTION("""COMPUTED_VALUE"""),46059) -> 46059 | K20: =IFERROR(__xludf.DUMMYFUNCTION("""COMPUTED_VALUE"""),-4000) -> -4000 | L20: =IFERROR(__xludf.DUMMYFUNCTION("""COMPUTED_VALUE"""),"AUDICANTE") -> AUDICANTE
A21: =IF(C21="","",IFERROR(VLOOKUP($E21,códigos!$R:$R,1,FALSE),"NO")) -> NO | B21: =IFERROR(__xludf.DUMMYFUNCTION("""COMPUTED_VALUE"""),2) -> 2 | C21: =IFERROR(__xludf.DUMMYFUNCTION("""COMPUTED_VALUE"""),"Lisandro Russian") -> Lisandro Russian | D21: =IFERROR(__xludf.DUMMYFUNCTION("""COMPUTED_VALUE"""),"Logroño") -> Logroño | E21: =IFERROR(__xludf.DUMMYFUNCTION("""COMPUTED_VALUE"""),"LRM264") -> LRM264 | F21: =IFERROR(__xludf.DUMMYFUNCTION("""COMPUTED_VALUE"""),"Carmen Delgado Muñoz") -> Carmen Delgado Muñoz | G21: =IFERROR(__xludf.DUMMYFUNCTION("""COMPUTED_VALUE"""),"IPHONE15") -> IPHONE15 | H21: =IFERROR(__xludf.DUMMYFUNCTION("""COMPUTED_VALUE"""),"Material para centro") -> Material para centro | J21: =IFERROR(__xludf.DUMMYFUNCTION("""COMPUTED_VALUE"""),46049) -> 46049 | K21: =IFERROR(__xludf.DUMMYFUNCTION("""COMPUTED_VALUE"""),-626.99) -> -626.99 | L21: =IFERROR(__xludf.DUMMYFUNCTION("""COMPUTED_VALUE"""),"AUDICOST LOGROÑO ") -> AUDICOST LOGROÑO
A22: =IF(C22="","",IFERROR(VLOOKUP($E22,códigos!$R:$R,1,FALSE),"NO")) -> NO | B22: =IFERROR(__xludf.DUMMYFUNCTION("""COMPUTED_VALUE"""),1) -> 1 | C22: =IFERROR(__xludf.DUMMYFUNCTION("""COMPUTED_VALUE"""),"Lisandro Russian") -> Lisandro Russian | D22: =IFERROR(__xludf.DUMMYFUNCTION("""COMPUTED_VALUE"""),"Alcorcón") -> Alcorcón | E22: =IFERROR(__xludf.DUMMYFUNCTION("""COMPUTED_VALUE"""),"LRM82") -> LRM82 | F22: =IFERROR(__xludf.DUMMYFUNCTION("""COMPUTED_VALUE"""),"José Miguel Aparicio Fernández") -> José Miguel Aparicio Fernández | G22: =IFERROR(__xludf.DUMMYFUNCTION("""COMPUTED_VALUE"""),"CURSO PARA R4 TERESA CONDE GOMEZ-MENOR") -> CURSO PARA R4 TERESA CONDE GOMEZ-MENOR | H22: =IFERROR(__xludf.DUMMYFUNCTION("""COMPUTED_VALUE"""),"Inscripción") -> Inscripción | I22: =IFERROR(__xludf.DUMMYFUNCTION("""COMPUTED_VALUE"""),46062) -> 46062 | J22: =IFERROR(__xludf.DUMMYFUNCTION("""COMPUTED_VALUE"""),46036) -> 46036 | K22: =IFERROR(__xludf.DUMMYFUNCTION("""COMPUTED_VALUE"""),-310.5) -> -310.5 | L22: =IFERROR(__xludf.DUMMYFUNCTION("""COMPUTED_VALUE"""),"CLINICA DOS DE MAYO ") -> CLINICA DOS DE MAYO
A23: =IF(C23="","",IFERROR(VLOOKUP($E23,códigos!$R:$R,1,FALSE),"NO")) -> ISL104 | B23: =IFERROR(__xludf.DUMMYFUNCTION("""COMPUTED_VALUE"""),2) -> 2 | C23: =IFERROR(__xludf.DUMMYFUNCTION("""COMPUTED_VALUE"""),"Ramon Ferrando") -> Ramon Ferrando | D23: =IFERROR(__xludf.DUMMYFUNCTION("""COMPUTED_VALUE"""),"El Albir (Benidorm)") -> El Albir (Benidorm) | E23: =IFERROR(__xludf.DUMMYFUNCTION("""COMPUTED_VALUE"""),"ISL104") -> ISL104 | F23: =IFERROR(__xludf.DUMMYFUNCTION("""COMPUTED_VALUE"""),"Isabel Polo Tomás") -> Isabel Polo Tomás | G23: =IFERROR(__xludf.DUMMYFUNCTION("""COMPUTED_VALUE"""),"TRASLADO TREN") -> TRASLADO TREN | H23: =IFERROR(__xludf.DUMMYFUNCTION("""COMPUTED_VALUE"""),"Traslado") -> Traslado | I23: =IFERROR(__xludf.DUMMYFUNCTION("""COMPUTED_VALUE"""),46063) -> 46063 | J23: =IFERROR(__xludf.DUMMYFUNCTION("""COMPUTED_VALUE"""),46062) -> 46062 | K23: =IFERROR(__xludf.DUMMYFUNCTION("""COMPUTED_VALUE"""),-84.52) -> -84.52 | L23: =IFERROR(__xludf.DUMMYFUNCTION("""COMPUTED_VALUE"""),"AUDICANTE") -> AUDICANTE
A24: =IF(C24="","",IFERROR(VLOOKUP($E24,códigos!$R:$R,1,FALSE),"NO")) -> NO | B24: =IFERROR(__xludf.DUMMYFUNCTION("""COMPUTED_VALUE"""),2) -> 2 | C24: =IFERROR(__xludf.DUMMYFUNCTION("""COMPUTED_VALUE"""),"Maika Blázquez") -> Maika Blázquez | D24: =IFERROR(__xludf.DUMMYFUNCTION("""COMPUTED_VALUE"""),"Getafe") -> Getafe | E24: =IFERROR(__xludf.DUMMYFUNCTION("""COMPUTED_VALUE"""),"MBM26") -> MBM26 | F24: =IFERROR(__xludf.DUMMYFUNCTION("""COMPUTED_VALUE"""),"Gerardo Monedero Rodrigo") -> Gerardo Monedero Rodrigo | G24: =IFERROR(__xludf.DUMMYFUNCTION("""COMPUTED_VALUE"""),"CURSO") -> CURSO | H24: =IFERROR(__xludf.DUMMYFUNCTION("""COMPUTED_VALUE"""),"Inscripción") -> Inscripción | J24: =IFERROR(__xludf.DUMMYFUNCTION("""COMPUTED_VALUE"""),46062) -> 46062 | K24: =IFERROR(__xludf.DUMMYFUNCTION("""COMPUTED_VALUE"""),-609.9) -> -609.9 | L24: =IFERROR(__xludf.DUMMYFUNCTION("""COMPUTED_VALUE"""),"AUDIBRADA") -> AUDIBRADA
A25: =IF(C25="","",IFERROR(VLOOKUP($E25,códigos!$R:$R,1,FALSE),"NO")) -> NO | B25: =IFERROR(__xludf.DUMMYFUNCTION("""COMPUTED_VALUE"""),2) -> 2 | C25: =IFERROR(__xludf.DUMMYFUNCTION("""COMPUTED_VALUE"""),"Maika Blázquez") -> Maika Blázquez | D25: =IFERROR(__xludf.DUMMYFUNCTION("""COMPUTED_VALUE"""),"Getafe") -> Getafe | E25: =IFERROR(__xludf.DUMMYFUNCTION("""COMPUTED_VALUE"""),"MBM96") -> MBM96 | F25: =IFERROR(__xludf.DUMMYFUNCTION("""COMPUTED_VALUE"""),"Beatriz Santos Duque") -> Beatriz Santos Duque | G25: =IFERROR(__xludf.DUMMYFUNCTION("""COMPUTED_VALUE"""),"CURSO") -> CURSO | H25: =IFERROR(__xludf.DUMMYFUNCTION("""COMPUTED_VALUE"""),"Inscripción") -> Inscripción | J25: =IFERROR(__xludf.DUMMYFUNCTION("""COMPUTED_VALUE"""),46062) -> 46062 | K25: =IFERROR(__xludf.DUMMYFUNCTION("""COMPUTED_VALUE"""),-609.9) -> -609.9 | L25: =IFERROR(__xludf.DUMMYFUNCTION("""COMPUTED_VALUE"""),"AUDIBRADA") -> AUDIBRADA
A26: =IF(C26="","",IFERROR(VLOOKUP($E26,códigos!$R:$R,1,FALSE),"NO")) -> NO | B26: =IFERROR(__xludf.DUMMYFUNCTION("""COMPUTED_VALUE"""),2) -> 2 | C26: =IFERROR(__xludf.DUMMYFUNCTION("""COMPUTED_VALUE"""),"Luis Alberto Rodríguez") -> Luis Alberto Rodríguez | D26: =IFERROR(__xludf.DUMMYFUNCTION("""COMPUTED_VALUE"""),"Sevilla- Montoto") -> Sevilla- Montoto | E26: =IFERROR(__xludf.DUMMYFUNCTION("""COMPUTED_VALUE"""),"LAA37") -> LAA37 | F26: =IFERROR(__xludf.DUMMYFUNCTION("""COMPUTED_VALUE"""),"Miguel Rodriguez Pérez") -> Miguel Rodriguez Pérez | G26: =IFERROR(__xludf.DUMMYFUNCTION("""COMPUTED_VALUE"""),"ESTANCIA HOTEL") -> ESTANCIA HOTEL | H26: =IFERROR(__xludf.DUMMYFUNCTION("""COMPUTED_VALUE"""),"Alojamiento") -> Alojamiento | J26: =IFERROR(__xludf.DUMMYFUNCTION("""COMPUTED_VALUE"""),46062) -> 46062 | K26: =IFERROR(__xludf.DUMMYFUNCTION("""COMPUTED_VALUE"""),-980.85) -> -980.85 | L26: =IFERROR(__xludf.DUMMYFUNCTION("""COMPUTED_VALUE"""),"OIR VITAL CENTROS AUDITIVOS ") -> OIR VITAL CENTROS AUDITIVOS
A27: =IF(C27="","",IFERROR(VLOOKUP($E27,códigos!$R:$R,1,FALSE),"NO")) -> ISL104 | B27: =IFERROR(__xludf.DUMMYFUNCTION("""COMPUTED_VALUE"""),2) -> 2 | C27: =IFERROR(__xludf.DUMMYFUNCTION("""COMPUTED_VALUE"""),"Ramon Ferrando") -> Ramon Ferrando | D27: =IFERROR(__xludf.DUMMYFUNCTION("""COMPUTED_VALUE"""),"El Albir (Benidorm)") -> El Albir (Benidorm) | E27: =IFERROR(__xludf.DUMMYFUNCTION("""COMPUTED_VALUE"""),"ISL104") -> ISL104 | F27: =IFERROR(__xludf.DUMMYFUNCTION("""COMPUTED_VALUE"""),"Isabel Polo Tomás") -> Isabel Polo Tomás | G27: =IFERROR(__xludf.DUMMYFUNCTION("""COMPUTED_VALUE"""),"TRASLADO ") -> TRASLADO | H27: =IFERROR(__xludf.DUMMYFUNCTION("""COMPUTED_VALUE"""),"Traslado") -> Traslado | J27: =IFERROR(__xludf.DUMMYFUNCTION("""COMPUTED_VALUE"""),46035) -> 46035 | K27: =IFERROR(__xludf.DUMMYFUNCTION("""COMPUTED_VALUE"""),-68.75) -> -68.75 | L27: =IFERROR(__xludf.DUMMYFUNCTION("""COMPUTED_VALUE"""),"AUDICANTE") -> AUDICANTE
A28: =IF(C28="","",IFERROR(VLOOKUP($E28,códigos!$R:$R,1,FALSE),"NO")) -> ISL104 | B28: =IFERROR(__xludf.DUMMYFUNCTION("""COMPUTED_VALUE"""),2) -> 2 | C28: =IFERROR(__xludf.DUMMYFUNCTION("""COMPUTED_VALUE"""),"Ramon Ferrando") -> Ramon Ferrando | D28: =IFERROR(__xludf.DUMMYFUNCTION("""COMPUTED_VALUE"""),"El Albir (Benidorm)") -> El Albir (Benidorm) | E28: =IFERROR(__xludf.DUMMYFUNCTION("""COMPUTED_VALUE"""),"ISL104") -> ISL104 | F28: =IFERROR(__xludf.DUMMYFUNCTION("""COMPUTED_VALUE"""),"Isabel Polo Tomás") -> Isabel Polo Tomás | G28: =IFERROR(__xludf.DUMMYFUNCTION("""COMPUTED_VALUE"""),"TRASLADO ") -> TRASLADO | H28: =IFERROR(__xludf.DUMMYFUNCTION("""COMPUTED_VALUE"""),"Traslado") -> Traslado | J28: =IFERROR(__xludf.DUMMYFUNCTION("""COMPUTED_VALUE"""),46035) -> 46035 | K28: =IFERROR(__xludf.DUMMYFUNCTION("""COMPUTED_VALUE"""),-630.47) -> -630.47 | L28: =IFERROR(__xludf.DUMMYFUNCTION("""COMPUTED_VALUE"""),"AUDICANTE") -> AUDICANTE
A29: =IF(C29="","",IFERROR(VLOOKUP($E29,códigos!$R:$R,1,FALSE),"NO")) -> NO | B29: =IFERROR(__xludf.DUMMYFUNCTION("""COMPUTED_VALUE"""),2) -> 2 | C29: =IFERROR(__xludf.DUMMYFUNCTION("""COMPUTED_VALUE"""),"Maika Blázquez") -> Maika Blázquez | D29: =IFERROR(__xludf.DUMMYFUNCTION("""COMPUTED_VALUE"""),"Madrid- La Oca") -> Madrid- La Oca | E29: =IFERROR(__xludf.DUMMYFUNCTION("""COMPUTED_VALUE"""),"MBM69") -> MBM69 | F29: =IFERROR(__xludf.DUMMYFUNCTION("""COMPUTED_VALUE"""),"Oscar A, Sánchez Valenzuela") -> Oscar A, Sánchez Valenzuela | G29: =IFERROR(__xludf.DUMMYFUNCTION("""COMPUTED_VALUE"""),"MACBOOK PRO") -> MACBOOK PRO | H29: =IFERROR(__xludf.DUMMYFUNCTION("""COMPUTED_VALUE"""),"Material para centro") -> Material para centro | J29: =IFERROR(__xludf.DUMMYFUNCTION("""COMPUTED_VALUE"""),46065) -> 46065 | K29: =IFERROR(__xludf.DUMMYFUNCTION("""COMPUTED_VALUE"""),-3353.99) -> -3353.99 | L29: =IFERROR(__xludf.DUMMYFUNCTION("""COMPUTED_VALUE"""),"SIEMA BLINK, S.L") -> SIEMA BLINK, S.L
A30: =IF(C30="","",IFERROR(VLOOKUP($E30,códigos!$R:$R,1,FALSE),"NO")) -> NO | B30: =IFERROR(__xludf.DUMMYFUNCTION("""COMPUTED_VALUE"""),2) -> 2 | C30: =IFERROR(__xludf.DUMMYFUNCTION("""COMPUTED_VALUE"""),"Maika Blázquez") -> Maika Blázquez | D30: =IFERROR(__xludf.DUMMYFUNCTION("""COMPUTED_VALUE"""),"Madrid- Canillas") -> Madrid- Canillas | E30: =IFERROR(__xludf.DUMMYFUNCTION("""COMPUTED_VALUE"""),"MBM50") -> MBM50 | F30: =IFERROR(__xludf.DUMMYFUNCTION("""COMPUTED_VALUE"""),"José Gustavo Barroso Braojos") -> José Gustavo Barroso Braojos | G30: =IFERROR(__xludf.DUMMYFUNCTION("""COMPUTED_VALUE"""),"PATROCINIO-VIAJE ISLANDIA") -> PATROCINIO-VIAJE ISLANDIA | H30: =IFERROR(__xludf.DUMMYFUNCTION("""COMPUTED_VALUE"""),"Publicidad") -> Publicidad | I30: =IFERROR(__xludf.DUMMYFUNCTION("""COMPUTED_VALUE"""),46065) -> 46065 | J30: =IFERROR(__xludf.DUMMYFUNCTION("""COMPUTED_VALUE"""),46065) -> 46065 | K30: =IFERROR(__xludf.DUMMYFUNCTION("""COMPUTED_VALUE"""),5025) -> 5025 | L30: =IFERROR(__xludf.DUMMYFUNCTION("""COMPUTED_VALUE"""),"AUDICOST, S.L.U") -> AUDICOST, S.L.U
A31: =IF(C31="","",IFERROR(VLOOKUP($E31,códigos!$R:$R,1,FALSE),"NO")) -> NO | B31: =IFERROR(__xludf.DUMMYFUNCTION("""COMPUTED_VALUE"""),2) -> 2 | C31: =IFERROR(__xludf.DUMMYFUNCTION("""COMPUTED_VALUE"""),"Maika Blázquez") -> Maika Blázquez | D31: =IFERROR(__xludf.DUMMYFUNCTION("""COMPUTED_VALUE"""),"Fuenlabrada") -> Fuenlabrada | E31: =IFERROR(__xludf.DUMMYFUNCTION("""COMPUTED_VALUE"""),"MBM228") -> MBM228 | F31: =IFERROR(__xludf.DUMMYFUNCTION("""COMPUTED_VALUE"""),"Daniel Rodríguez Ocaña") -> Daniel Rodríguez Ocaña | G31: =IFERROR(__xludf.DUMMYFUNCTION("""COMPUTED_VALUE"""),"CURSO") -> CURSO | H31: =IFERROR(__xludf.DUMMYFUNCTION("""COMPUTED_VALUE"""),"Inscripción") -> Inscripción | J31: =IFERROR(__xludf.DUMMYFUNCTION("""COMPUTED_VALUE"""),46066) -> 46066 | K31: =IFERROR(__xludf.DUMMYFUNCTION("""COMPUTED_VALUE"""),-1000) -> -1000 | L31: =IFERROR(__xludf.DUMMYFUNCTION("""COMPUTED_VALUE"""),"AUDIBRADA") -> AUDIBRADA
A32: =IF(C32="","",IFERROR(VLOOKUP($E32,códigos!$R:$R,1,FALSE),"NO")) -> NO | B32: =IFERROR(__xludf.DUMMYFUNCTION("""COMPUTED_VALUE"""),2) -> 2 | C32: =IFERROR(__xludf.DUMMYFUNCTION("""COMPUTED_VALUE"""),"Maika Blázquez") -> Maika Blázquez | D32: =IFERROR(__xludf.DUMMYFUNCTION("""COMPUTED_VALUE"""),"Madrid- Juan Bravo") -> Madrid- Juan Bravo | E32: =IFERROR(__xludf.DUMMYFUNCTION("""COMPUTED_VALUE"""),"MBM229") -> MBM229 | F32: =IFERROR(__xludf.DUMMYFUNCTION("""COMPUTED_VALUE"""),"Raquel de Lama Bermejo") -> Raquel de Lama Bermejo | G32: =IFERROR(__xludf.DUMMYFUNCTION("""COMPUTED_VALUE"""),"CURSO") -> CURSO | H32: =IFERROR(__xludf.DUMMYFUNCTION("""COMPUTED_VALUE"""),"Inscripción") -> Inscripción | J32: =IFERROR(__xludf.DUMMYFUNCTION("""COMPUTED_VALUE"""),46071) -> 46071 | K32: =IFERROR(__xludf.DUMMYFUNCTION("""COMPUTED_VALUE"""),-900) -> -900 | L32: =IFERROR(__xludf.DUMMYFUNCTION("""COMPUTED_VALUE"""),"AUDICOST, S.L.U") -> AUDICOST, S.L.U
A33: =IF(C33="","",IFERROR(VLOOKUP($E33,códigos!$R:$R,1,FALSE),"NO")) -> ISL104 | B33: =IFERROR(__xludf.DUMMYFUNCTION("""COMPUTED_VALUE"""),2) -> 2 | C33: =IFERROR(__xludf.DUMMYFUNCTION("""COMPUTED_VALUE"""),"Ramon Ferrando") -> Ramon Ferrando | D33: =IFERROR(__xludf.DUMMYFUNCTION("""COMPUTED_VALUE"""),"El Albir (Benidorm)") -> El Albir (Benidorm) | E33: =IFERROR(__xludf.DUMMYFUNCTION("""COMPUTED_VALUE"""),"ISL104") -> ISL104 | F33: =IFERROR(__xludf.DUMMYFUNCTION("""COMPUTED_VALUE"""),"Isabel Polo Tomás") -> Isabel Polo Tomás | G33: =IFERROR(__xludf.DUMMYFUNCTION("""COMPUTED_VALUE"""),"VIAJE A JAPON") -> VIAJE A JAPON | H33: =IFERROR(__xludf.DUMMYFUNCTION("""COMPUTED_VALUE"""),"Congreso internacional personal") -> Congreso internacional personal | I33: =IFERROR(__xludf.DUMMYFUNCTION("""COMPUTED_VALUE"""),46078) -> 46078 | J33: =IFERROR(__xludf.DUMMYFUNCTION("""COMPUTED_VALUE"""),46073) -> 46073 | K33: =IFERROR(__xludf.DUMMYFUNCTION("""COMPUTED_VALUE"""),-4957.1) -> -4957.1 | L33: =IFERROR(__xludf.DUMMYFUNCTION("""COMPUTED_VALUE"""),"AUDICANTE") -> AUDICANTE
A34: =IF(C34="","",IFERROR(VLOOKUP($E34,códigos!$R:$R,1,FALSE),"NO")) -> NO | B34: =IFERROR(__xludf.DUMMYFUNCTION("""COMPUTED_VALUE"""),2) -> 2 | C34: =IFERROR(__xludf.DUMMYFUNCTION("""COMPUTED_VALUE"""),"Maika Blázquez") -> Maika Blázquez | D34: =IFERROR(__xludf.DUMMYFUNCTION("""COMPUTED_VALUE"""),"Getafe") -> Getafe | E34: =IFERROR(__xludf.DUMMYFUNCTION("""COMPUTED_VALUE"""),"MBM230") -> MBM230 | F34: =IFERROR(__xludf.DUMMYFUNCTION("""COMPUTED_VALUE"""),"Daniela Carrillo Moreno") -> Daniela Carrillo Moreno | G34: =IFERROR(__xludf.DUMMYFUNCTION("""COMPUTED_VALUE"""),"CURSO") -> CURSO | H34: =IFERROR(__xludf.DUMMYFUNCTION("""COMPUTED_VALUE"""),"Inscripción") -> Inscripción | J34: =IFERROR(__xludf.DUMMYFUNCTION("""COMPUTED_VALUE"""),46078) -> 46078 | K34: =IFERROR(__xludf.DUMMYFUNCTION("""COMPUTED_VALUE"""),-600) -> -600 | L34: =IFERROR(__xludf.DUMMYFUNCTION("""COMPUTED_VALUE"""),"AUDIBRADA") -> AUDIBRADA
A35: =IF(C35="","",IFERROR(VLOOKUP($E35,códigos!$R:$R,1,FALSE),"NO")) -> ISL14 | B35: =IFERROR(__xludf.DUMMYFUNCTION("""COMPUTED_VALUE"""),2) -> 2 | C35: =IFERROR(__xludf.DUMMYFUNCTION("""COMPUTED_VALUE"""),"Iván Sánchez") -> Iván Sánchez | D35: =IFERROR(__xludf.DUMMYFUNCTION("""COMPUTED_VALUE"""),"Orihuela") -> Orihuela | E35: =IFERROR(__xludf.DUMMYFUNCTION("""COMPUTED_VALUE"""),"ISL14") -> ISL14 | F35: =IFERROR(__xludf.DUMMYFUNCTION("""COMPUTED_VALUE"""),"Carlos Velásquez Fermín") -> Carlos Velásquez Fermín | G35: =IFERROR(__xludf.DUMMYFUNCTION("""COMPUTED_VALUE"""),"CERRAMIENTO") -> CERRAMIENTO | H35: =IFERROR(__xludf.DUMMYFUNCTION("""COMPUTED_VALUE"""),"Obras acondicionamiento centro") -> Obras acondicionamiento centro | I35: =IFERROR(__xludf.DUMMYFUNCTION("""COMPUTED_VALUE"""),46063) -> 46063 | K35: =IFERROR(__xludf.DUMMYFUNCTION("""COMPUTED_VALUE"""),-2085.24) -> -2085.24 | L35: =IFERROR(__xludf.DUMMYFUNCTION("""COMPUTED_VALUE"""),"AUDICOST, S.L.U") -> AUDICOST, S.L.U
A36: =IF(C36="","",IFERROR(VLOOKUP($E36,códigos!$R:$R,1,FALSE),"NO")) -> NO | B36: =IFERROR(__xludf.DUMMYFUNCTION("""COMPUTED_VALUE"""),2) -> 2 | C36: =IFERROR(__xludf.DUMMYFUNCTION("""COMPUTED_VALUE"""),"Iván Sánchez") -> Iván Sánchez | D36: =IFERROR(__xludf.DUMMYFUNCTION("""COMPUTED_VALUE"""),"Murcia") -> Murcia | E36: =IFERROR(__xludf.DUMMYFUNCTION("""COMPUTED_VALUE"""),"ISL24") -> ISL24 | F36: =IFERROR(__xludf.DUMMYFUNCTION("""COMPUTED_VALUE"""),"Enrique López Meseguer") -> Enrique López Meseguer | G36: =IFERROR(__xludf.DUMMYFUNCTION("""COMPUTED_VALUE"""),"VIAJE A JORDANIA") -> VIAJE A JORDANIA | H36: =IFERROR(__xludf.DUMMYFUNCTION("""COMPUTED_VALUE"""),"Congreso internacional personal") -> Congreso internacional personal | I36: =IFERROR(__xludf.DUMMYFUNCTION("""COMPUTED_VALUE"""),46056) -> 46056 | K36: =IFERROR(__xludf.DUMMYFUNCTION("""COMPUTED_VALUE"""),-3098) -> -3098 | L36: =IFERROR(__xludf.DUMMYFUNCTION("""COMPUTED_VALUE"""),"AUDICANTE") -> AUDICANTE
A37: =IF(C37="","",IFERROR(VLOOKUP($E37,códigos!$R:$R,1,FALSE),"NO")) -> ISL104 | B37: =IFERROR(__xludf.DUMMYFUNCTION("""COMPUTED_VALUE"""),3) -> 3 | C37: =IFERROR(__xludf.DUMMYFUNCTION("""COMPUTED_VALUE"""),"Ramon Ferrando") -> Ramon Ferrando | D37: =IFERROR(__xludf.DUMMYFUNCTION("""COMPUTED_VALUE"""),"El Albir (Benidorm)") -> El Albir (Benidorm) | E37: =IFERROR(__xludf.DUMMYFUNCTION("""COMPUTED_VALUE"""),"ISL104") -> ISL104 | F37: =IFERROR(__xludf.DUMMYFUNCTION("""COMPUTED_VALUE"""),"Isabel Polo Tomás") -> Isabel Polo Tomás | G37: =IFERROR(__xludf.DUMMYFUNCTION("""COMPUTED_VALUE"""),"HOTEL EN MADRID") -> HOTEL EN MADRID | H37: =IFERROR(__xludf.DUMMYFUNCTION("""COMPUTED_VALUE"""),"Alojamiento") -> Alojamiento | I37: =IFERROR(__xludf.DUMMYFUNCTION("""COMPUTED_VALUE"""),46085) -> 46085 | J37: =IFERROR(__xludf.DUMMYFUNCTION("""COMPUTED_VALUE"""),46084) -> 46084 | K37: =IFERROR(__xludf.DUMMYFUNCTION("""COMPUTED_VALUE"""),-285.73) -> -285.73 | L37: =IFERROR(__xludf.DUMMYFUNCTION("""COMPUTED_VALUE"""),"AUDICANTE") -> AUDICANTE
A38: =IF(C38="","",IFERROR(VLOOKUP($E38,códigos!$R:$R,1,FALSE),"NO")) -> NO | B38: =IFERROR(__xludf.DUMMYFUNCTION("""COMPUTED_VALUE"""),3) -> 3 | C38: =IFERROR(__xludf.DUMMYFUNCTION("""COMPUTED_VALUE"""),"Iván Sánchez") -> Iván Sánchez | D38: =IFERROR(__xludf.DUMMYFUNCTION("""COMPUTED_VALUE"""),"San Javier") -> San Javier | E38: =IFERROR(__xludf.DUMMYFUNCTION("""COMPUTED_VALUE"""),"ISL149") -> ISL149 | F38: =IFERROR(__xludf.DUMMYFUNCTION("""COMPUTED_VALUE"""),"Ángel Onofre Pérez Coll") -> Ángel Onofre Pérez Coll | G38: =IFERROR(__xludf.DUMMYFUNCTION("""COMPUTED_VALUE"""),"INSCRIPCION CURSO RINOPLASTIA") -> INSCRIPCION CURSO RINOPLASTIA | H38: =IFERROR(__xludf.DUMMYFUNCTION("""COMPUTED_VALUE"""),"Inscripción") -> Inscripción | J38: =IFERROR(__xludf.DUMMYFUNCTION("""COMPUTED_VALUE"""),46086) -> 46086 | K38: =IFERROR(__xludf.DUMMYFUNCTION("""COMPUTED_VALUE"""),2176.19) -> 2176.19 | L38: =IFERROR(__xludf.DUMMYFUNCTION("""COMPUTED_VALUE"""),"AUDICOST, S.L.U") -> AUDICOST, S.L.U
A39: =IF(C39="","",IFERROR(VLOOKUP($E39,códigos!$R:$R,1,FALSE),"NO")) -> NO | B39: =IFERROR(__xludf.DUMMYFUNCTION("""COMPUTED_VALUE"""),3) -> 3 | C39: =IFERROR(__xludf.DUMMYFUNCTION("""COMPUTED_VALUE"""),"Lisandro Russian") -> Lisandro Russian | D39: =IFERROR(__xludf.DUMMYFUNCTION("""COMPUTED_VALUE"""),"Logroño") -> Logroño | E39: =IFERROR(__xludf.DUMMYFUNCTION("""COMPUTED_VALUE"""),"LRM249") -> LRM249 | F39: =IFERROR(__xludf.DUMMYFUNCTION("""COMPUTED_VALUE"""),"Daniel Briones Crespo") -> Daniel Briones Crespo | G39: =IFERROR(__xludf.DUMMYFUNCTION("""COMPUTED_VALUE"""),"VIAJE CONGRESO ATENAS") -> VIAJE CONGRESO ATENAS | H39: =IFERROR(__xludf.DUMMYFUNCTION("""COMPUTED_VALUE"""),"Alojamiento y traslado") -> Alojamiento y traslado | I39: =IFERROR(__xludf.DUMMYFUNCTION("""COMPUTED_VALUE"""),46094) -> 46094 | J39: =IFERROR(__xludf.DUMMYFUNCTION("""COMPUTED_VALUE"""),46093) -> 46093 | K39: =IFERROR(__xludf.DUMMYFUNCTION("""COMPUTED_VALUE"""),-4215.86) -> -4215.86 | L39: =IFERROR(__xludf.DUMMYFUNCTION("""COMPUTED_VALUE"""),"AUDICOST LOGROÑO ") -> AUDICOST LOGROÑO
A40: =IF(C40="","",IFERROR(VLOOKUP($E40,códigos!$R:$R,1,FALSE),"NO")) -> NO | B40: =IFERROR(__xludf.DUMMYFUNCTION("""COMPUTED_VALUE"""),3) -> 3 | C40: =IFERROR(__xludf.DUMMYFUNCTION("""COMPUTED_VALUE"""),"Maika Blázquez") -> Maika Blázquez | D40: =IFERROR(__xludf.DUMMYFUNCTION("""COMPUTED_VALUE"""),"Madrid- Canillas") -> Madrid- Canillas | E40: =IFERROR(__xludf.DUMMYFUNCTION("""COMPUTED_VALUE"""),"MBM50") -> MBM50 | F40: =IFERROR(__xludf.DUMMYFUNCTION("""COMPUTED_VALUE"""),"José Gustavo Barroso Braojos") -> José Gustavo Barroso Braojos | G40: =IFERROR(__xludf.DUMMYFUNCTION("""COMPUTED_VALUE"""),"CAMARA ACCION PARA ISLANDIA") -> CAMARA ACCION PARA ISLANDIA | H40: =IFERROR(__xludf.DUMMYFUNCTION("""COMPUTED_VALUE"""),"Publicidad") -> Publicidad | J40: =IFERROR(__xludf.DUMMYFUNCTION("""COMPUTED_VALUE"""),46090) -> 46090 | K40: =IFERROR(__xludf.DUMMYFUNCTION("""COMPUTED_VALUE"""),-699.99) -> -699.99 | L40: =IFERROR(__xludf.DUMMYFUNCTION("""COMPUTED_VALUE"""),"AUDICOST, S.L.U") -> AUDICOST, S.L.U
A41: =IF(C41="","",IFERROR(VLOOKUP($E41,códigos!$R:$R,1,FALSE),"NO")) -> NO | B41: =IFERROR(__xludf.DUMMYFUNCTION("""COMPUTED_VALUE"""),3) -> 3 | C41: =IFERROR(__xludf.DUMMYFUNCTION("""COMPUTED_VALUE"""),"Maika Blázquez") -> Maika Blázquez | D41: =IFERROR(__xludf.DUMMYFUNCTION("""COMPUTED_VALUE"""),"Madrid- Canillas") -> Madrid- Canillas | E41: =IFERROR(__xludf.DUMMYFUNCTION("""COMPUTED_VALUE"""),"MBM50") -> MBM50 | F41: =IFERROR(__xludf.DUMMYFUNCTION("""COMPUTED_VALUE"""),"José Gustavo Barroso Braojos") -> José Gustavo Barroso Braojos | G41: =IFERROR(__xludf.DUMMYFUNCTION("""COMPUTED_VALUE"""),"KIT BICICLETA PARA ISLANDIA") -> KIT BICICLETA PARA ISLANDIA | H41: =IFERROR(__xludf.DUMMYFUNCTION("""COMPUTED_VALUE"""),"Publicidad") -> Publicidad | J41: =IFERROR(__xludf.DUMMYFUNCTION("""COMPUTED_VALUE"""),46090) -> 46090 | K41: =IFERROR(__xludf.DUMMYFUNCTION("""COMPUTED_VALUE"""),-62.99) -> -62.99 | L41: =IFERROR(__xludf.DUMMYFUNCTION("""COMPUTED_VALUE"""),"AUDICOST, S.L.U") -> AUDICOST, S.L.U
A42: =IF(C42="","",IFERROR(VLOOKUP($E42,códigos!$R:$R,1,FALSE),"NO")) -> NO | B42: =IFERROR(__xludf.DUMMYFUNCTION("""COMPUTED_VALUE"""),3) -> 3 | C42: =IFERROR(__xludf.DUMMYFUNCTION("""COMPUTED_VALUE"""),"Maika Blázquez") -> Maika Blázquez | D42: =IFERROR(__xludf.DUMMYFUNCTION("""COMPUTED_VALUE"""),"Madrid- Canillas") -> Madrid- Canillas | E42: =IFERROR(__xludf.DUMMYFUNCTION("""COMPUTED_VALUE"""),"MBM50") -> MBM50 | F42: =IFERROR(__xludf.DUMMYFUNCTION("""COMPUTED_VALUE"""),"José Gustavo Barroso Braojos") -> José Gustavo Barroso Braojos | G42: =IFERROR(__xludf.DUMMYFUNCTION("""COMPUTED_VALUE"""),"CARCASA BUCEO PARA ISLANDIA") -> CARCASA BUCEO PARA ISLANDIA | H42: =IFERROR(__xludf.DUMMYFUNCTION("""COMPUTED_VALUE"""),"Publicidad") -> Publicidad | J42: =IFERROR(__xludf.DUMMYFUNCTION("""COMPUTED_VALUE"""),46090) -> 46090 | K42: =IFERROR(__xludf.DUMMYFUNCTION("""COMPUTED_VALUE"""),-119.99) -> -119.99 | L42: =IFERROR(__xludf.DUMMYFUNCTION("""COMPUTED_VALUE"""),"AUDICOST, S.L.U") -> AUDICOST, S.L.U
A43: =IF(C43="","",IFERROR(VLOOKUP($E43,códigos!$R:$R,1,FALSE),"NO")) -> NO | B43: =IFERROR(__xludf.DUMMYFUNCTION("""COMPUTED_VALUE"""),3) -> 3 | C43: =IFERROR(__xludf.DUMMYFUNCTION("""COMPUTED_VALUE"""),"Maika Blázquez") -> Maika Blázquez | D43: =IFERROR(__xludf.DUMMYFUNCTION("""COMPUTED_VALUE"""),"Madrid- Canillas") -> Madrid- Canillas | E43: =IFERROR(__xludf.DUMMYFUNCTION("""COMPUTED_VALUE"""),"MBM50") -> MBM50 | F43: =IFERROR(__xludf.DUMMYFUNCTION("""COMPUTED_VALUE"""),"José Gustavo Barroso Braojos") -> José Gustavo Barroso Braojos | G43: =IFERROR(__xludf.DUMMYFUNCTION("""COMPUTED_VALUE"""),"PRISMATICOS PARA ISLANDIA") -> PRISMATICOS PARA ISLANDIA | H43: =IFERROR(__xludf.DUMMYFUNCTION("""COMPUTED_VALUE"""),"Publicidad") -> Publicidad | J43: =IFERROR(__xludf.DUMMYFUNCTION("""COMPUTED_VALUE"""),46090) -> 46090 | K43: =IFERROR(__xludf.DUMMYFUNCTION("""COMPUTED_VALUE"""),-399) -> -399 | L43: =IFERROR(__xludf.DUMMYFUNCTION("""COMPUTED_VALUE"""),"AUDICOST, S.L.U") -> AUDICOST, S.L.U
A44: =IF(C44="","",IFERROR(VLOOKUP($E44,códigos!$R:$R,1,FALSE),"NO")) -> NO | B44: =IFERROR(__xludf.DUMMYFUNCTION("""COMPUTED_VALUE"""),3) -> 3 | C44: =IFERROR(__xludf.DUMMYFUNCTION("""COMPUTED_VALUE"""),"Maika Blázquez") -> Maika Blázquez | D44: =IFERROR(__xludf.DUMMYFUNCTION("""COMPUTED_VALUE"""),"Madrid- Canillas") -> Madrid- Canillas | E44: =IFERROR(__xludf.DUMMYFUNCTION("""COMPUTED_VALUE"""),"MBM50") -> MBM50 | F44: =IFERROR(__xludf.DUMMYFUNCTION("""COMPUTED_VALUE"""),"José Gustavo Barroso Braojos") -> José Gustavo Barroso Braojos | G44: =IFERROR(__xludf.DUMMYFUNCTION("""COMPUTED_VALUE"""),"LINTERNA PARA ISLANDIA") -> LINTERNA PARA ISLANDIA | H44: =IFERROR(__xludf.DUMMYFUNCTION("""COMPUTED_VALUE"""),"Publicidad") -> Publicidad | J44: =IFERROR(__xludf.DUMMYFUNCTION("""COMPUTED_VALUE"""),46090) -> 46090 | K44: =IFERROR(__xludf.DUMMYFUNCTION("""COMPUTED_VALUE"""),-153.97) -> -153.97 | L44: =IFERROR(__xludf.DUMMYFUNCTION("""COMPUTED_VALUE"""),"AUDICOST, S.L.U") -> AUDICOST, S.L.U
A45: =IF(C45="","",IFERROR(VLOOKUP($E45,códigos!$R:$R,1,FALSE),"NO")) -> NO | B45: =IFERROR(__xludf.DUMMYFUNCTION("""COMPUTED_VALUE"""),3) -> 3 | C45: =IFERROR(__xludf.DUMMYFUNCTION("""COMPUTED_VALUE"""),"Maika Blázquez") -> Maika Blázquez | D45: =IFERROR(__xludf.DUMMYFUNCTION("""COMPUTED_VALUE"""),"Madrid- Canillas") -> Madrid- Canillas | E45: =IFERROR(__xludf.DUMMYFUNCTION("""COMPUTED_VALUE"""),"MBM50") -> MBM50 | F45: =IFERROR(__xludf.DUMMYFUNCTION("""COMPUTED_VALUE"""),"José Gustavo Barroso Braojos") -> José Gustavo Barroso Braojos | G45: =IFERROR(__xludf.DUMMYFUNCTION("""COMPUTED_VALUE"""),"ESTUCHE LAPICES COLORES X 2") -> ESTUCHE LAPICES COLORES X 2 | H45: =IFERROR(__xludf.DUMMYFUNCTION("""COMPUTED_VALUE"""),"Publicidad") -> Publicidad | J45: =IFERROR(__xludf.DUMMYFUNCTION("""COMPUTED_VALUE"""),46090) -> 46090 | K45: =IFERROR(__xludf.DUMMYFUNCTION("""COMPUTED_VALUE"""),-930) -> -930 | L45: =IFERROR(__xludf.DUMMYFUNCTION("""COMPUTED_VALUE"""),"AUDICOST, S.L.U") -> AUDICOST, S.L.U
A46: =IF(C46="","",IFERROR(VLOOKUP($E46,códigos!$R:$R,1,FALSE),"NO")) -> NO | B46: =IFERROR(__xludf.DUMMYFUNCTION("""COMPUTED_VALUE"""),3) -> 3 | C46: =IFERROR(__xludf.DUMMYFUNCTION("""COMPUTED_VALUE"""),"Maika Blázquez") -> Maika Blázquez | D46: =IFERROR(__xludf.DUMMYFUNCTION("""COMPUTED_VALUE"""),"Getafe") -> Getafe | E46: =IFERROR(__xludf.DUMMYFUNCTION("""COMPUTED_VALUE"""),"MBM223") -> MBM223 | F46: =IFERROR(__xludf.DUMMYFUNCTION("""COMPUTED_VALUE"""),"Cristina Vaduva") -> Cristina Vaduva | G46: =IFERROR(__xludf.DUMMYFUNCTION("""COMPUTED_VALUE"""),"ALQUILER PIEZO ELECTRICO") -> ALQUILER PIEZO ELECTRICO | H46: =IFERROR(__xludf.DUMMYFUNCTION("""COMPUTED_VALUE"""),"Material para centro") -> Material para centro | I46: =IFERROR(__xludf.DUMMYFUNCTION("""COMPUTED_VALUE"""),46092) -> 46092 | J46: =IFERROR(__xludf.DUMMYFUNCTION("""COMPUTED_VALUE"""),46090) -> 46090 | K46: =IFERROR(__xludf.DUMMYFUNCTION("""COMPUTED_VALUE"""),-2268.6) -> -2268.6 | L46: =IFERROR(__xludf.DUMMYFUNCTION("""COMPUTED_VALUE"""),"AUDIBRADA") -> AUDIBRADA
A47: =IF(C47="","",IFERROR(VLOOKUP($E47,códigos!$R:$R,1,FALSE),"NO")) -> ISL14 | B47: =IFERROR(__xludf.DUMMYFUNCTION("""COMPUTED_VALUE"""),3) -> 3 | C47: =IFERROR(__xludf.DUMMYFUNCTION("""COMPUTED_VALUE"""),"Iván Sánchez") -> Iván Sánchez | D47: =IFERROR(__xludf.DUMMYFUNCTION("""COMPUTED_VALUE"""),"Orihuela") -> Orihuela | E47: =IFERROR(__xludf.DUMMYFUNCTION("""COMPUTED_VALUE"""),"ISL14") -> ISL14 | F47: =IFERROR(__xludf.DUMMYFUNCTION("""COMPUTED_VALUE"""),"Carlos Velásquez Fermín") -> Carlos Velásquez Fermín | G47: =IFERROR(__xludf.DUMMYFUNCTION("""COMPUTED_VALUE"""),"CURSO") -> CURSO | H47: =IFERROR(__xludf.DUMMYFUNCTION("""COMPUTED_VALUE"""),"Inscripción") -> Inscripción | I47: =IFERROR(__xludf.DUMMYFUNCTION("""COMPUTED_VALUE"""),46094) -> 46094 | J47: =IFERROR(__xludf.DUMMYFUNCTION("""COMPUTED_VALUE"""),46090) -> 46090 | K47: =IFERROR(__xludf.DUMMYFUNCTION("""COMPUTED_VALUE"""),-568.7) -> -568.7 | L47: =IFERROR(__xludf.DUMMYFUNCTION("""COMPUTED_VALUE"""),"AUDICOST, S.L.U") -> AUDICOST, S.L.U
A48: =IF(C48="","",IFERROR(VLOOKUP($E48,códigos!$R:$R,1,FALSE),"NO")) -> NO | B48: =IFERROR(__xludf.DUMMYFUNCTION("""COMPUTED_VALUE"""),3) -> 3 | C48: =IFERROR(__xludf.DUMMYFUNCTION("""COMPUTED_VALUE"""),"Iván Sánchez") -> Iván Sánchez | D48: =IFERROR(__xludf.DUMMYFUNCTION("""COMPUTED_VALUE"""),"Orihuela") -> Orihuela | E48: =IFERROR(__xludf.DUMMYFUNCTION("""COMPUTED_VALUE"""),"ISL58") -> ISL58 | F48: =IFERROR(__xludf.DUMMYFUNCTION("""COMPUTED_VALUE"""),"Juan Javier Álvarez López") -> Juan Javier Álvarez López | G48: =IFERROR(__xludf.DUMMYFUNCTION("""COMPUTED_VALUE"""),"IPHONE 17 PRO MAX 512 GB AZUL OSCURO") -> IPHONE 17 PRO MAX 512 GB AZUL OSCURO | H48: =IFERROR(__xludf.DUMMYFUNCTION("""COMPUTED_VALUE"""),"Material para centro") -> Material para centro | J48: =IFERROR(__xludf.DUMMYFUNCTION("""COMPUTED_VALUE"""),46090) -> 46090 | K48: =IFERROR(__xludf.DUMMYFUNCTION("""COMPUTED_VALUE"""),-1719) -> -1719 | L48: =IFERROR(__xludf.DUMMYFUNCTION("""COMPUTED_VALUE"""),"AUDICOST, S.L.U") -> AUDICOST, S.L.U
A49: =IF(C49="","",IFERROR(VLOOKUP($E49,códigos!$R:$R,1,FALSE),"NO")) -> NO | B49: =IFERROR(__xludf.DUMMYFUNCTION("""COMPUTED_VALUE"""),3) -> 3 | C49: =IFERROR(__xludf.DUMMYFUNCTION("""COMPUTED_VALUE"""),"Iván Sánchez") -> Iván Sánchez | D49: =IFERROR(__xludf.DUMMYFUNCTION("""COMPUTED_VALUE"""),"Orihuela") -> Orihuela | E49: =IFERROR(__xludf.DUMMYFUNCTION("""COMPUTED_VALUE"""),"ISL58") -> ISL58 | F49: =IFERROR(__xludf.DUMMYFUNCTION("""COMPUTED_VALUE"""),"Juan Javier Álvarez López") -> Juan Javier Álvarez López | G49: =IFERROR(__xludf.DUMMYFUNCTION("""COMPUTED_VALUE"""),"ASPIRADOR ESCOBA") -> ASPIRADOR ESCOBA | H49: =IFERROR(__xludf.DUMMYFUNCTION("""COMPUTED_VALUE"""),"Material para centro") -> Material para centro | J49: =IFERROR(__xludf.DUMMYFUNCTION("""COMPUTED_VALUE"""),46090) -> 46090 | K49: =IFERROR(__xludf.DUMMYFUNCTION("""COMPUTED_VALUE"""),-849) -> -849 | L49: =IFERROR(__xludf.DUMMYFUNCTION("""COMPUTED_VALUE"""),"AUDICOST, S.L.U") -> AUDICOST, S.L.U
A50: =IF(C50="","",IFERROR(VLOOKUP($E50,códigos!$R:$R,1,FALSE),"NO")) -> NO | B50: =IFERROR(__xludf.DUMMYFUNCTION("""COMPUTED_VALUE"""),3) -> 3 | C50: =IFERROR(__xludf.DUMMYFUNCTION("""COMPUTED_VALUE"""),"Luis Alberto Rodríguez") -> Luis Alberto Rodríguez | D50: =IFERROR(__xludf.DUMMYFUNCTION("""COMPUTED_VALUE"""),"Jerez de la Frontera") -> Jerez de la Frontera | E50: =IFERROR(__xludf.DUMMYFUNCTION("""COMPUTED_VALUE"""),"LAA81") -> LAA81 | F50: =IFERROR(__xludf.DUMMYFUNCTION("""COMPUTED_VALUE"""),"Manuel Tucciarone") -> Manuel Tucciarone | G50: =IFERROR(__xludf.DUMMYFUNCTION("""COMPUTED_VALUE"""),"HOTEL EN MADRID") -> HOTEL EN MADRID | H50: =IFERROR(__xludf.DUMMYFUNCTION("""COMPUTED_VALUE"""),"Alojamiento") -> Alojamiento | J50: =IFERROR(__xludf.DUMMYFUNCTION("""COMPUTED_VALUE"""),46091) -> 46091 | K50: =IFERROR(__xludf.DUMMYFUNCTION("""COMPUTED_VALUE"""),-1171.53) -> -1171.53 | L50: =IFERROR(__xludf.DUMMYFUNCTION("""COMPUTED_VALUE"""),"AUDICOST, S.L.U") -> AUDICOST, S.L.U
A51: =IF(C51="","",IFERROR(VLOOKUP($E51,códigos!$R:$R,1,FALSE),"NO")) -> NO | B51: =IFERROR(__xludf.DUMMYFUNCTION("""COMPUTED_VALUE"""),3) -> 3 | C51: =IFERROR(__xludf.DUMMYFUNCTION("""COMPUTED_VALUE"""),"Iván Sánchez") -> Iván Sánchez | D51: =IFERROR(__xludf.DUMMYFUNCTION("""COMPUTED_VALUE"""),"Orihuela") -> Orihuela | E51: =IFERROR(__xludf.DUMMYFUNCTION("""COMPUTED_VALUE"""),"ISL142") -> ISL142 | F51: =IFERROR(__xludf.DUMMYFUNCTION("""COMPUTED_VALUE"""),"Marina Pérez Grau") -> Marina Pérez Grau | G51: =IFERROR(__xludf.DUMMYFUNCTION("""COMPUTED_VALUE"""),"CURSO RINOPLASTIA") -> CURSO RINOPLASTIA | H51: =IFERROR(__xludf.DUMMYFUNCTION("""COMPUTED_VALUE"""),"Inscripción") -> Inscripción | I51: =IFERROR(__xludf.DUMMYFUNCTION("""COMPUTED_VALUE"""),46094) -> 46094 | J51: =IFERROR(__xludf.DUMMYFUNCTION("""COMPUTED_VALUE"""),46092) -> 46092 | K51: =IFERROR(__xludf.DUMMYFUNCTION("""COMPUTED_VALUE"""),-2176.19) -> -2176.19 | L51: =IFERROR(__xludf.DUMMYFUNCTION("""COMPUTED_VALUE"""),"AUDICOST, S.L.U") -> AUDICOST, S.L.U
A52: =IF(C52="","",IFERROR(VLOOKUP($E52,códigos!$R:$R,1,FALSE),"NO")) -> NO | B52: =IFERROR(__xludf.DUMMYFUNCTION("""COMPUTED_VALUE"""),3) -> 3 | C52: =IFERROR(__xludf.DUMMYFUNCTION("""COMPUTED_VALUE"""),"Iván Sánchez") -> Iván Sánchez | D52: =IFERROR(__xludf.DUMMYFUNCTION("""COMPUTED_VALUE"""),"Alicante") -> Alicante | E52: =IFERROR(__xludf.DUMMYFUNCTION("""COMPUTED_VALUE"""),"ISL105") -> ISL105 | F52: =IFERROR(__xludf.DUMMYFUNCTION("""COMPUTED_VALUE"""),"Karen Rojas Crespo") -> Karen Rojas Crespo | G52: =IFERROR(__xludf.DUMMYFUNCTION("""COMPUTED_VALUE"""),"CURSO") -> CURSO | H52: =IFERROR(__xludf.DUMMYFUNCTION("""COMPUTED_VALUE"""),"Inscripción") -> Inscripción | I52: =IFERROR(__xludf.DUMMYFUNCTION("""COMPUTED_VALUE"""),46106) -> 46106 | J52: =IFERROR(__xludf.DUMMYFUNCTION("""COMPUTED_VALUE"""),46099) -> 46099 | K52: =IFERROR(__xludf.DUMMYFUNCTION("""COMPUTED_VALUE"""),-599.52) -> -599.52 | L52: =IFERROR(__xludf.DUMMYFUNCTION("""COMPUTED_VALUE"""),"AUDICANTE") -> AUDICANTE
A53: =IF(C53="","",IFERROR(VLOOKUP($E53,códigos!$R:$R,1,FALSE),"NO")) -> NO | B53: =IFERROR(__xludf.DUMMYFUNCTION("""COMPUTED_VALUE"""),3) -> 3 | C53: =IFERROR(__xludf.DUMMYFUNCTION("""COMPUTED_VALUE"""),"Lisandro Russian") -> Lisandro Russian | D53: =IFERROR(__xludf.DUMMYFUNCTION("""COMPUTED_VALUE"""),"Logroño") -> Logroño | E53: =IFERROR(__xludf.DUMMYFUNCTION("""COMPUTED_VALUE"""),"LRM261") -> LRM261 | F53: =IFERROR(__xludf.DUMMYFUNCTION("""COMPUTED_VALUE"""),"Miguel Garikoitz Calzada Uriondo") -> Miguel Garikoitz Calzada Uriondo | G53: =IFERROR(__xludf.DUMMYFUNCTION("""COMPUTED_VALUE"""),"ESTANCIA EN CHICLANA") -> ESTANCIA EN CHICLANA | H53: =IFERROR(__xludf.DUMMYFUNCTION("""COMPUTED_VALUE"""),"Alojamiento") -> Alojamiento | I53: =IFERROR(__xludf.DUMMYFUNCTION("""COMPUTED_VALUE"""),46099) -> 46099 | L53: =IFERROR(__xludf.DUMMYFUNCTION("""COMPUTED_VALUE"""),"AUDICOST LOGROÑO ") -> AUDICOST LOGROÑO
A54: =IF(C54="","",IFERROR(VLOOKUP($E54,códigos!$R:$R,1,FALSE),"NO")) -> NO | B54: =IFERROR(__xludf.DUMMYFUNCTION("""COMPUTED_VALUE"""),3) -> 3 | C54: =IFERROR(__xludf.DUMMYFUNCTION("""COMPUTED_VALUE"""),"Maika Blázquez") -> Maika Blázquez | D54: =IFERROR(__xludf.DUMMYFUNCTION("""COMPUTED_VALUE"""),"Madrid- Canillas") -> Madrid- Canillas | E54: =IFERROR(__xludf.DUMMYFUNCTION("""COMPUTED_VALUE"""),"MBM50") -> MBM50 | F54: =IFERROR(__xludf.DUMMYFUNCTION("""COMPUTED_VALUE"""),"José Gustavo Barroso Braojos") -> José Gustavo Barroso Braojos | G54: =IFERROR(__xludf.DUMMYFUNCTION("""COMPUTED_VALUE"""),"ENTRADAS CIRCO SOL") -> ENTRADAS CIRCO SOL | H54: =IFERROR(__xludf.DUMMYFUNCTION("""COMPUTED_VALUE"""),"Publicidad") -> Publicidad | I54: =IFERROR(__xludf.DUMMYFUNCTION("""COMPUTED_VALUE"""),46099) -> 46099 | L54: =IFERROR(__xludf.DUMMYFUNCTION("""COMPUTED_VALUE"""),"AUDICOST, S.L.U") -> AUDICOST, S.L.U
A55: =IF(C55="","",IFERROR(VLOOKUP($E55,códigos!$R:$R,1,FALSE),"NO")) -> ISL14 | B55: =IFERROR(__xludf.DUMMYFUNCTION("""COMPUTED_VALUE"""),3) -> 3 | C55: =IFERROR(__xludf.DUMMYFUNCTION("""COMPUTED_VALUE"""),"Iván Sánchez") -> Iván Sánchez | D55: =IFERROR(__xludf.DUMMYFUNCTION("""COMPUTED_VALUE"""),"Orihuela") -> Orihuela | E55: =IFERROR(__xludf.DUMMYFUNCTION("""COMPUTED_VALUE"""),"ISL14") -> ISL14 | F55: =IFERROR(__xludf.DUMMYFUNCTION("""COMPUTED_VALUE"""),"Carlos Velásquez Fermín") -> Carlos Velásquez Fermín | G55: =IFERROR(__xludf.DUMMYFUNCTION("""COMPUTED_VALUE"""),"HOTEL Y AVION") -> HOTEL Y AVION | H55: =IFERROR(__xludf.DUMMYFUNCTION("""COMPUTED_VALUE"""),"Alojamiento y traslado") -> Alojamiento y traslado | I55: =IFERROR(__xludf.DUMMYFUNCTION("""COMPUTED_VALUE"""),46106) -> 46106 | J55: =IFERROR(__xludf.DUMMYFUNCTION("""COMPUTED_VALUE"""),46105) -> 46105 | K55: =IFERROR(__xludf.DUMMYFUNCTION("""COMPUTED_VALUE"""),-2286.1) -> -2286.1 | L55: =IFERROR(__xludf.DUMMYFUNCTION("""COMPUTED_VALUE"""),"AUDICOST, S.L.U") -> AUDICOST, S.L.U
A56: =IF(C56="","",IFERROR(VLOOKUP($E56,códigos!$R:$R,1,FALSE),"NO")) -> NO | B56: =IFERROR(__xludf.DUMMYFUNCTION("""COMPUTED_VALUE"""),3) -> 3 | C56: =IFERROR(__xludf.DUMMYFUNCTION("""COMPUTED_VALUE"""),"Luis Alberto Rodríguez") -> Luis Alberto Rodríguez | D56: =IFERROR(__xludf.DUMMYFUNCTION("""COMPUTED_VALUE"""),"Sevilla- Montoto") -> Sevilla- Montoto | E56: =IFERROR(__xludf.DUMMYFUNCTION("""COMPUTED_VALUE"""),"LAA47") -> LAA47 | F56: =IFERROR(__xludf.DUMMYFUNCTION("""COMPUTED_VALUE"""),"Estefanía Berrocal Postigo") -> Estefanía Berrocal Postigo | G56: =IFERROR(__xludf.DUMMYFUNCTION("""COMPUTED_VALUE"""),"REUNION OTORRINOS EN REPUBLICA DOMINICANA") -> REUNION OTORRINOS EN REPUBLICA DOMINICANA | H56: =IFERROR(__xludf.DUMMYFUNCTION("""COMPUTED_VALUE"""),"Congreso internacional personal") -> Congreso internacional personal | I56: =IFERROR(__xludf.DUMMYFUNCTION("""COMPUTED_VALUE"""),46108) -> 46108 | J56: =IFERROR(__xludf.DUMMYFUNCTION("""COMPUTED_VALUE"""),46107) -> 46107 | K56: =IFERROR(__xludf.DUMMYFUNCTION("""COMPUTED_VALUE"""),-13700) -> -13700 | L56: =IFERROR(__xludf.DUMMYFUNCTION("""COMPUTED_VALUE"""),"OIR VITAL CENTROS AUDITIVOS ") -> OIR VITAL CENTROS AUDITIVOS
A57: =IF(C57="","",IFERROR(VLOOKUP($E57,códigos!$R:$R,1,FALSE),"NO")) -> NO | B57: =IFERROR(__xludf.DUMMYFUNCTION("""COMPUTED_VALUE"""),3) -> 3 | C57: =IFERROR(__xludf.DUMMYFUNCTION("""COMPUTED_VALUE"""),"Ramon Ferrando") -> Ramon Ferrando | D57: =IFERROR(__xludf.DUMMYFUNCTION("""COMPUTED_VALUE"""),"Valencia- Cadiz") -> Valencia- Cadiz | E57: =IFERROR(__xludf.DUMMYFUNCTION("""COMPUTED_VALUE"""),"RFV26") -> RFV26 | F57: =IFERROR(__xludf.DUMMYFUNCTION("""COMPUTED_VALUE"""),"Ainhoa García-Lliberos de Miguel") -> Ainhoa García-Lliberos de Miguel | G57: =IFERROR(__xludf.DUMMYFUNCTION("""COMPUTED_VALUE"""),"INSCRIPION CONGRESO") -> INSCRIPION CONGRESO | H57: =IFERROR(__xludf.DUMMYFUNCTION("""COMPUTED_VALUE"""),"Inscripción") -> Inscripción | I57: =IFERROR(__xludf.DUMMYFUNCTION("""COMPUTED_VALUE"""),46108) -> 46108 | J57: =IFERROR(__xludf.DUMMYFUNCTION("""COMPUTED_VALUE"""),46107) -> 46107 | K57: =IFERROR(__xludf.DUMMYFUNCTION("""COMPUTED_VALUE"""),-490.51) -> -490.51 | L57: =IFERROR(__xludf.DUMMYFUNCTION("""COMPUTED_VALUE"""),"AUDICANTE") -> AUDICANTE
A58: =IF(C58="","",IFERROR(VLOOKUP($E58,códigos!$R:$R,1,FALSE),"NO")) -> ISL14 | B58: =IFERROR(__xludf.DUMMYFUNCTION("""COMPUTED_VALUE"""),3) -> 3 | C58: =IFERROR(__xludf.DUMMYFUNCTION("""COMPUTED_VALUE"""),"Iván Sánchez") -> Iván Sánchez | D58: =IFERROR(__xludf.DUMMYFUNCTION("""COMPUTED_VALUE"""),"Alicante") -> Alicante | E58: =IFERROR(__xludf.DUMMYFUNCTION("""COMPUTED_VALUE"""),"ISL14") -> ISL14 | F58: =IFERROR(__xludf.DUMMYFUNCTION("""COMPUTED_VALUE"""),"Carlos Velásquez Fermín") -> Carlos Velásquez Fermín | G58: =IFERROR(__xludf.DUMMYFUNCTION("""COMPUTED_VALUE"""),"TRASLADO") -> TRASLADO | H58: =IFERROR(__xludf.DUMMYFUNCTION("""COMPUTED_VALUE"""),"Traslado") -> Traslado | I58: =IFERROR(__xludf.DUMMYFUNCTION("""COMPUTED_VALUE"""),46112) -> 46112 | J58: =IFERROR(__xludf.DUMMYFUNCTION("""COMPUTED_VALUE"""),46111) -> 46111 | K58: =IFERROR(__xludf.DUMMYFUNCTION("""COMPUTED_VALUE"""),-856.98) -> -856.98 | L58: =IFERROR(__xludf.DUMMYFUNCTION("""COMPUTED_VALUE"""),"AUDICANTE") -> AUDICANTE
A59: =IF(C59="","",IFERROR(VLOOKUP($E59,códigos!$R:$R,1,FALSE),"NO")) -> NO | B59: =IFERROR(__xludf.DUMMYFUNCTION("""COMPUTED_VALUE"""),3) -> 3 | C59: =IFERROR(__xludf.DUMMYFUNCTION("""COMPUTED_VALUE"""),"Iván Sánchez") -> Iván Sánchez | D59: =IFERROR(__xludf.DUMMYFUNCTION("""COMPUTED_VALUE"""),"Murcia") -> Murcia | E59: =IFERROR(__xludf.DUMMYFUNCTION("""COMPUTED_VALUE"""),"ISL24") -> ISL24 | F59: =IFERROR(__xludf.DUMMYFUNCTION("""COMPUTED_VALUE"""),"Enrique López Meseguer") -> Enrique López Meseguer | G59: =IFERROR(__xludf.DUMMYFUNCTION("""COMPUTED_VALUE"""),"VIAJE CAMINO SANTIAGO-DEPOSITO DEL 20%") -> VIAJE CAMINO SANTIAGO-DEPOSITO DEL 20% | H59: =IFERROR(__xludf.DUMMYFUNCTION("""COMPUTED_VALUE"""),"Congreso nacional personal") -> Congreso nacional personal | I59: =IFERROR(__xludf.DUMMYFUNCTION("""COMPUTED_VALUE"""),46112) -> 46112 | J59: =IFERROR(__xludf.DUMMYFUNCTION("""COMPUTED_VALUE"""),46112) -> 46112 | K59: =IFERROR(__xludf.DUMMYFUNCTION("""COMPUTED_VALUE"""),-318) -> -318 | L59: =IFERROR(__xludf.DUMMYFUNCTION("""COMPUTED_VALUE"""),"AUDICANTE") -> AUDICANTE
A60: =IF(C60="","",IFERROR(VLOOKUP($E60,códigos!$R:$R,1,FALSE),"NO")) -> NO | B60: =IFERROR(__xludf.DUMMYFUNCTION("""COMPUTED_VALUE"""),3) -> 3 | C60: =IFERROR(__xludf.DUMMYFUNCTION("""COMPUTED_VALUE"""),"Maika Blázquez") -> Maika Blázquez | D60: =IFERROR(__xludf.DUMMYFUNCTION("""COMPUTED_VALUE"""),"Madrid- La Oca") -> Madrid- La Oca | E60: =IFERROR(__xludf.DUMMYFUNCTION("""COMPUTED_VALUE"""),"MBM231") -> MBM231 | F60: =IFERROR(__xludf.DUMMYFUNCTION("""COMPUTED_VALUE"""),"Itziar Jimenez Gomez") -> Itziar Jimenez Gomez | G60: =IFERROR(__xludf.DUMMYFUNCTION("""COMPUTED_VALUE"""),"CURSO") -> CURSO | H60: =IFERROR(__xludf.DUMMYFUNCTION("""COMPUTED_VALUE"""),"Inscripción") -> Inscripción | J60: =IFERROR(__xludf.DUMMYFUNCTION("""COMPUTED_VALUE"""),46111) -> 46111 | K60: =IFERROR(__xludf.DUMMYFUNCTION("""COMPUTED_VALUE"""),-600) -> -600 | L60: =IFERROR(__xludf.DUMMYFUNCTION("""COMPUTED_VALUE"""),"SIEMA BLINK, S.L") -> SIEMA BLINK, S.L
A61: =IF(C61="","",IFERROR(VLOOKUP($E61,códigos!$R:$R,1,FALSE),"NO")) -> NO | B61: =IFERROR(__xludf.DUMMYFUNCTION("""COMPUTED_VALUE"""),1) -> 1 | C61: =IFERROR(__xludf.DUMMYFUNCTION("""COMPUTED_VALUE"""),"Lisandro Russian") -> Lisandro Russian | D61: =IFERROR(__xludf.DUMMYFUNCTION("""COMPUTED_VALUE"""),"Madrid- Juan Bravo") -> Madrid- Juan Bravo | E61: =IFERROR(__xludf.DUMMYFUNCTION("""COMPUTED_VALUE"""),"LRM239") -> LRM239 | F61: =IFERROR(__xludf.DUMMYFUNCTION("""COMPUTED_VALUE"""),"Carlos Barajas Del Rosal") -> Carlos Barajas Del Rosal | G61: =IFERROR(__xludf.DUMMYFUNCTION("""COMPUTED_VALUE"""),"COSTES DE EMPLEADA-ENERO") -> COSTES DE EMPLEADA-ENERO | H61: =IFERROR(__xludf.DUMMYFUNCTION("""COMPUTED_VALUE"""),"Gastos de personal") -> Gastos de personal | I61: =IFERROR(__xludf.DUMMYFUNCTION("""COMPUTED_VALUE""")," ") | K61: =IFERROR(__xludf.DUMMYFUNCTION("""COMPUTED_VALUE"""),-1398.88) -> -1398.88 | L61: =IFERROR(__xludf.DUMMYFUNCTION("""COMPUTED_VALUE"""),"AUDICOST, S.L.U") -> AUDICOST, S.L.U
A62: =IF(C62="","",IFERROR(VLOOKUP($E62,códigos!$R:$R,1,FALSE),"NO")) -> NO | B62: =IFERROR(__xludf.DUMMYFUNCTION("""COMPUTED_VALUE"""),2) -> 2 | C62: =IFERROR(__xludf.DUMMYFUNCTION("""COMPUTED_VALUE"""),"Lisandro Russian") -> Lisandro Russian | D62: =IFERROR(__xludf.DUMMYFUNCTION("""COMPUTED_VALUE"""),"Madrid- Juan Bravo") -> Madrid- Juan Bravo | E62: =IFERROR(__xludf.DUMMYFUNCTION("""COMPUTED_VALUE"""),"LRM239") -> LRM239 | F62: =IFERROR(__xludf.DUMMYFUNCTION("""COMPUTED_VALUE"""),"Carlos Barajas Del Rosal") -> Carlos Barajas Del Rosal | G62: =IFERROR(__xludf.DUMMYFUNCTION("""COMPUTED_VALUE"""),"COSTES DE EMPLEADA-FEBRERO") -> COSTES DE EMPLEADA-FEBRERO | H62: =IFERROR(__xludf.DUMMYFUNCTION("""COMPUTED_VALUE"""),"Gastos de personal") -> Gastos de personal | I62: =IFERROR(__xludf.DUMMYFUNCTION("""COMPUTED_VALUE""")," ") | K62: =IFERROR(__xludf.DUMMYFUNCTION("""COMPUTED_VALUE"""),-1398.88) -> -1398.88 | L62: =IFERROR(__xludf.DUMMYFUNCTION("""COMPUTED_VALUE"""),"AUDICOST, S.L.U") -> AUDICOST, S.L.U
A63: =IF(C63="","",IFERROR(VLOOKUP($E63,códigos!$R:$R,1,FALSE),"NO")) -> NO | B63: =IFERROR(__xludf.DUMMYFUNCTION("""COMPUTED_VALUE"""),3) -> 3 | C63: =IFERROR(__xludf.DUMMYFUNCTION("""COMPUTED_VALUE"""),"Lisandro Russian") -> Lisandro Russian | D63: =IFERROR(__xludf.DUMMYFUNCTION("""COMPUTED_VALUE"""),"Madrid- Juan Bravo") -> Madrid- Juan Bravo | E63: =IFERROR(__xludf.DUMMYFUNCTION("""COMPUTED_VALUE"""),"LRM239") -> LRM239 | F63: =IFERROR(__xludf.DUMMYFUNCTION("""COMPUTED_VALUE"""),"Carlos Barajas Del Rosal") -> Carlos Barajas Del Rosal | G63: =IFERROR(__xludf.DUMMYFUNCTION("""COMPUTED_VALUE"""),"COSTES DE EMPLEADA-MARZO") -> COSTES DE EMPLEADA-MARZO | H63: =IFERROR(__xludf.DUMMYFUNCTION("""COMPUTED_VALUE"""),"Gastos de personal") -> Gastos de personal | I63: =IFERROR(__xludf.DUMMYFUNCTION("""COMPUTED_VALUE""")," ") | K63: =IFERROR(__xludf.DUMMYFUNCTION("""COMPUTED_VALUE"""),-1398.88) -> -1398.88 | L63: =IFERROR(__xludf.DUMMYFUNCTION("""COMPUTED_VALUE"""),"AUDICOST, S.L.U") -> AUDICOST, S.L.U
A64: =IF(C64="","",IFERROR(VLOOKUP($E64,códigos!$R:$R,1,FALSE),"NO")) -> NO | B64: =IFERROR(__xludf.DUMMYFUNCTION("""COMPUTED_VALUE"""),4) -> 4 | C64: =IFERROR(__xludf.DUMMYFUNCTION("""COMPUTED_VALUE"""),"Iván Sánchez") -> Iván Sánchez | D64: =IFERROR(__xludf.DUMMYFUNCTION("""COMPUTED_VALUE"""),"Orihuela") -> Orihuela | E64: =IFERROR(__xludf.DUMMYFUNCTION("""COMPUTED_VALUE"""),"ISL58") -> ISL58 | F64: =IFERROR(__xludf.DUMMYFUNCTION("""COMPUTED_VALUE"""),"Juan Javier Álvarez López") -> Juan Javier Álvarez López | G64: =IFERROR(__xludf.DUMMYFUNCTION("""COMPUTED_VALUE"""),"TV+SOPORTE") -> TV+SOPORTE | H64: =IFERROR(__xludf.DUMMYFUNCTION("""COMPUTED_VALUE"""),"Material para centro") -> Material para centro | I64: =IFERROR(__xludf.DUMMYFUNCTION("""COMPUTED_VALUE"""),46119) -> 46119 | J64: =IFERROR(__xludf.DUMMYFUNCTION("""COMPUTED_VALUE"""),46118) -> 46118 | K64: =IFERROR(__xludf.DUMMYFUNCTION("""COMPUTED_VALUE"""),-1400.42) -> -1400.42 | L64: =IFERROR(__xludf.DUMMYFUNCTION("""COMPUTED_VALUE"""),"AUDICOST, S.L.U") -> AUDICOST, S.L.U
A65: =IF(C65="","",IFERROR(VLOOKUP($E65,códigos!$R:$R,1,FALSE),"NO")) -> NO | B65: =IFERROR(__xludf.DUMMYFUNCTION("""COMPUTED_VALUE"""),4) -> 4 | C65: =IFERROR(__xludf.DUMMYFUNCTION("""COMPUTED_VALUE"""),"Luis Alberto Rodríguez") -> Luis Alberto Rodríguez | D65: =IFERROR(__xludf.DUMMYFUNCTION("""COMPUTED_VALUE"""),"Sevilla- Montoto") -> Sevilla- Montoto | E65: =IFERROR(__xludf.DUMMYFUNCTION("""COMPUTED_VALUE"""),"LAA08") -> LAA08 | F65: =IFERROR(__xludf.DUMMYFUNCTION("""COMPUTED_VALUE"""),"David Castro Gutiérrez de Agüero") -> David Castro Gutiérrez de Agüero | G65: =IFERROR(__xludf.DUMMYFUNCTION("""COMPUTED_VALUE"""),"PORTATIL MEDIA MARKT") -> PORTATIL MEDIA MARKT | H65: =IFERROR(__xludf.DUMMYFUNCTION("""COMPUTED_VALUE"""),"Material para centro") -> Material para centro | I65: =IFERROR(__xludf.DUMMYFUNCTION("""COMPUTED_VALUE"""),46120) -> 46120 | J65: =IFERROR(__xludf.DUMMYFUNCTION("""COMPUTED_VALUE"""),46120) -> 46120 | K65: =IFERROR(__xludf.DUMMYFUNCTION("""COMPUTED_VALUE"""),-899) -> -899 | L65: =IFERROR(__xludf.DUMMYFUNCTION("""COMPUTED_VALUE"""),"OIR VITAL CENTROS AUDITIVOS ") -> OIR VITAL CENTROS AUDITIVOS
A66: =IF(C66="","",IFERROR(VLOOKUP($E66,códigos!$R:$R,1,FALSE),"NO")) | B66: =IFERROR(__xludf.DUMMYFUNCTION("""COMPUTED_VALUE"""),5) -> 5 | C66: =IFERROR(__xludf.DUMMYFUNCTION("""COMPUTED_VALUE"""),"") | D66: =IFERROR(__xludf.DUMMYFUNCTION("""COMPUTED_VALUE"""),"Clínica") -> Clínica | E66: =IFERROR(__xludf.DUMMYFUNCTION("""COMPUTED_VALUE"""),"") | L66: =IFERROR(__xludf.DUMMYFUNCTION("""COMPUTED_VALUE"""),"Empresa") -> Empresa
A67: =IF(C67="","",IFERROR(VLOOKUP($E67,códigos!$R:$R,1,FALSE),"NO")) | B67: =IFERROR(__xludf.DUMMYFUNCTION("""COMPUTED_VALUE"""),6) -> 6 | C67: =IFERROR(__xludf.DUMMYFUNCTION("""COMPUTED_VALUE"""),"") | D67: =IFERROR(__xludf.DUMMYFUNCTION("""COMPUTED_VALUE"""),"Clínica") -> Clínica | E67: =IFERROR(__xludf.DUMMYFUNCTION("""COMPUTED_VALUE"""),"") | L67: =IFERROR(__xludf.DUMMYFUNCTION("""COMPUTED_VALUE"""),"Empresa") -> Empresa
A68: =IF(C68="","",IFERROR(VLOOKUP($E68,códigos!$R:$R,1,FALSE),"NO")) | B68: =IFERROR(__xludf.DUMMYFUNCTION("""COMPUTED_VALUE"""),7) -> 7 | C68: =IFERROR(__xludf.DUMMYFUNCTION("""COMPUTED_VALUE"""),"") | D68: =IFERROR(__xludf.DUMMYFUNCTION("""COMPUTED_VALUE"""),"Clínica") -> Clínica | E68: =IFERROR(__xludf.DUMMYFUNCTION("""COMPUTED_VALUE"""),"") | L68: =IFERROR(__xludf.DUMMYFUNCTION("""COMPUTED_VALUE"""),"Empresa") -> Empresa
A69: =IF(C69="","",IFERROR(VLOOKUP($E69,códigos!$R:$R,1,FALSE),"NO")) | B69: =IFERROR(__xludf.DUMMYFUNCTION("""COMPUTED_VALUE"""),8) -> 8 | C69: =IFERROR(__xludf.DUMMYFUNCTION("""COMPUTED_VALUE"""),"") | D69: =IFERROR(__xludf.DUMMYFUNCTION("""COMPUTED_VALUE"""),"Clínica") -> Clínica | E69: =IFERROR(__xludf.DUMMYFUNCTION("""COMPUTED_VALUE"""),"") | L69: =IFERROR(__xludf.DUMMYFUNCTION("""COMPUTED_VALUE"""),"Empresa") -> Empresa
A70: =IF(C70="","",IFERROR(VLOOKUP($E70,códigos!$R:$R,1,FALSE),"NO")) | B70: =IFERROR(__xludf.DUMMYFUNCTION("""COMPUTED_VALUE"""),9) -> 9 | C70: =IFERROR(__xludf.DUMMYFUNCTION("""COMPUTED_VALUE"""),"") | D70: =IFERROR(__xludf.DUMMYFUNCTION("""COMPUTED_VALUE"""),"Clínica") -> Clínica | E70: =IFERROR(__xludf.DUMMYFUNCTION("""COMPUTED_VALUE"""),"") | L70: =IFERROR(__xludf.DUMMYFUNCTION("""COMPUTED_VALUE"""),"Empresa") -> Empresa
A71: =IF(C71="","",IFERROR(VLOOKUP($E71,códigos!$R:$R,1,FALSE),"NO")) | B71: =IFERROR(__xludf.DUMMYFUNCTION("""COMPUTED_VALUE"""),10) -> 10 | C71: =IFERROR(__xludf.DUMMYFUNCTION("""COMPUTED_VALUE"""),"") | D71: =IFERROR(__xludf.DUMMYFUNCTION("""COMPUTED_VALUE"""),"Clínica") -> Clínica | E71: =IFERROR(__xludf.DUMMYFUNCTION("""COMPUTED_VALUE"""),"") | L71: =IFERROR(__xludf.DUMMYFUNCTION("""COMPUTED_VALUE"""),"Empresa") -> Empresa
A72: =IF(C72="","",IFERROR(VLOOKUP($E72,códigos!$R:$R,1,FALSE),"NO")) | B72: =IFERROR(__xludf.DUMMYFUNCTION("""COMPUTED_VALUE"""),11) -> 11 | C72: =IFERROR(__xludf.DUMMYFUNCTION("""COMPUTED_VALUE"""),"") | D72: =IFERROR(__xludf.DUMMYFUNCTION("""COMPUTED_VALUE"""),"Clínica") -> Clínica | E72: =IFERROR(__xludf.DUMMYFUNCTION("""COMPUTED_VALUE"""),"") | L72: =IFERROR(__xludf.DUMMYFUNCTION("""COMPUTED_VALUE"""),"Empresa") -> Empresa
A73: =IF(C73="","",IFERROR(VLOOKUP($E73,códigos!$R:$R,1,FALSE),"NO")) | B73: =IFERROR(__xludf.DUMMYFUNCTION("""COMPUTED_VALUE"""),12) -> 12 | C73: =IFERROR(__xludf.DUMMYFUNCTION("""COMPUTED_VALUE"""),"") | D73: =IFERROR(__xludf.DUMMYFUNCTION("""COMPUTED_VALUE"""),"Clínica") -> Clínica | E73: =IFERROR(__xludf.DUMMYFUNCTION("""COMPUTED_VALUE"""),"") | L73: =IFERROR(__xludf.DUMMYFUNCTION("""COMPUTED_VALUE"""),"Empresa") -> Empresa
A74: =IF(C74="","",IFERROR(VLOOKUP($E74,códigos!$R:$R,1,FALSE),"NO"))
A75: =IF(C75="","",IFERROR(VLOOKUP($E75,códigos!$R:$R,1,FALSE),"NO"))
A76: =IF(C76="","",IFERROR(VLOOKUP($E76,códigos!$R:$R,1,FALSE),"NO"))
A77: =IF(C77="","",IFERROR(VLOOKUP($E77,códigos!$R:$R,1,FALSE),"NO"))
A78: =IF(C78="","",IFERROR(VLOOKUP($E78,códigos!$R:$R,1,FALSE),"NO"))
A79: =IF(C79="","",IFERROR(VLOOKUP($E79,códigos!$R:$R,1,FALSE),"NO"))
A80: =IF(C80="","",IFERROR(VLOOKUP($E80,códigos!$R:$R,1,FALSE),"NO"))
A81: =IF(C81="","",IFERROR(VLOOKUP($E81,códigos!$R:$R,1,FALSE),"NO"))
A82: =IF(C82="","",IFERROR(VLOOKUP($E82,códigos!$R:$R,1,FALSE),"NO"))
A83: =IF(C83="","",IFERROR(VLOOKUP($E83,códigos!$R:$R,1,FALSE),"NO"))
A84: =IF(C84="","",IFERROR(VLOOKUP($E84,códigos!$R:$R,1,FALSE),"NO"))
A85: =IF(C85="","",IFERROR(VLOOKUP($E85,códigos!$R:$R,1,FALSE),"NO"))
... A267: =IF(C267="","",IFERROR(VLOOKUP($E267,códigos!$R:$R,1,FALSE),"NO"))

Sheet ENERO
B1: PETICIONES ORL 2026
A3: MES | B3: VISITADOR | C3: CENTRO | D3: COD.CONTRATO | E3: ORL | F3: ACCION MKT | G3: CATEGORÍAS | H3: FECHA P/ | I3: FECHA PETICION | J3: IMPORTE | K3: EMPRESA | L3: OBSERVACIONES
A4: 1 | B4: =IF($E4="","",VLOOKUP(D4,códigos!$F:$G,2,FALSE)) -> Luis Alberto Rodríguez | C4: Jerez de la Frontera | D4: =IF(E4="","",VLOOKUP($E4,códigos!$E:$F,2,FALSE)) -> LAA78 | E4: Maria Del Carmen Salom Coveñas | F4: PATROCINIO | G4: Publicidad | I4: 46034 | J4: -4432 | K4: =IF($C4="","",VLOOKUP(C4,códigos!$B:$C,2,FALSE)) -> AUDICOST, S.L.U | N4: {=INDEX(códigos!E:E,MATCH(D4,códigos!F:F,0))} -> Maria Del Carmen Salom Coveñas
A5: 1 | B5: =IF($E5="","",VLOOKUP(D5,códigos!$F:$G,2,FALSE)) -> Maika Blázquez | C5: Getafe | D5: =IF(E5="","",VLOOKUP($E5,códigos!$E:$F,2,FALSE)) -> MBM149 | E5: María Garrote Garrote | F5: AIRBNB | G5: Alojamiento | H5: 46036 | I5: 46034 | J5: -1700 | K5: =IF($C5="","",VLOOKUP(C5,códigos!$B:$C,2,FALSE)) -> AUDIBRADA | N5: {=INDEX(códigos!E:E,MATCH(D5,códigos!F:F,0))} -> María Garrote Garrote
A6: 1 | B6: =IF($E6="","",VLOOKUP(D6,códigos!$F:$G,2,FALSE)) -> Maika Blázquez | C6: Fuenlabrada | D6: =IF(E6="","",VLOOKUP($E6,códigos!$E:$F,2,FALSE)) -> MBM164 | E6: Paloma Martín-Aragón Martín | F6: INSCRIPCION CURSO MICROCIRUGIA | G6: Inscripción | I6: 46035 | J6: -1663.35 | K6: =IF($C6="","",VLOOKUP(C6,códigos!$B:$C,2,FALSE)) -> AUDIBRADA | N6: {=INDEX(códigos!E:E,MATCH(D6,códigos!F:F,0))} -> Paloma Martín-Aragón Martín
A7: 1 | B7: =IF($E7="","",VLOOKUP(D7,códigos!$F:$G,2,FALSE)) -> Maika Blázquez | C7: Fuenlabrada | D7: =IF(E7="","",VLOOKUP($E7,códigos!$E:$F,2,FALSE)) -> MBM111 | E7: Elisabeth Amarillo Espitia | F7: INSCRIPCION CURSO MICROCIRUGIA | G7: Inscripción | I7: 46035 | J7: -1663.35 | K7: =IF($C7="","",VLOOKUP(C7,códigos!$B:$C,2,FALSE)) -> AUDIBRADA | N7: {=INDEX(códigos!E:E,MATCH(D7,códigos!F:F,0))} -> Elisabeth Amarillo Espitia
A8: 1 | B8: =IF($E8="","",VLOOKUP(D8,códigos!$F:$G,2,FALSE)) -> Maika Blázquez | C8: Madrid- Canillas | D8: =IF(E8="","",VLOOKUP($E8,códigos!$E:$F,2,FALSE)) -> MBM50 | E8: José Gustavo Barroso Braojos | F8: 2 SMARTWATCH | G8: Material para centro | H8: 46036 | I8: 46035 | J8: =-449.99*2 -> -899.98 | K8: =IF($C8="","",VLOOKUP(C8,códigos!$B:$C,2,FALSE)) -> AUDICOST, S.L.U | N8: {=INDEX(códigos!E:E,MATCH(D8,códigos!F:F,0))} -> José Gustavo Barroso Braojos
A9: 1 | B9: =IF($E9="","",VLOOKUP(D9,códigos!$F:$G,2,FALSE)) -> Luis Alberto Rodríguez | C9: Sevilla- Montoto | D9: =IF(E9="","",VLOOKUP($E9,códigos!$E:$F,2,FALSE)) -> LAA08 | E9: David Castro Gutiérrez de Agüero | F9: IPHONE17 PRO | G9: Material para centro | H9: 46042 | I9: 46037 | J9: -1289 | K9: =IF($C9="","",VLOOKUP(C9,códigos!$B:$C,2,FALSE)) -> OIR VITAL CENTROS AUDITIVOS | N9: {=INDEX(códigos!E:E,MATCH(D9,códigos!F:F,0))} -> David Castro Gutiérrez de Agüero
A10: 1 | B10: =IF($E10="","",VLOOKUP(D10,códigos!$F:$G,2,FALSE)) -> Maika Blázquez | C10: Torrejón De Ardoz | D10: =IF(E10="","",VLOOKUP($E10,códigos!$E:$F,2,FALSE)) -> MBM136 | E10: Lorena Sanz López | F10: INSCRIPCION, VUELO Y HOTEL-MAYOR IMPORTE DICBRE. | G10: Inscripción | H10: 46042 | I10: 46041 | J10: -205.75 | K10: =IF($C10="","",VLOOKUP(C10,códigos!$B:$C,2,FALSE)) -> AUDICOST LEGANES | M10: 46003 | N10: {=INDEX(códigos!E:E,MATCH(D10,códigos!F:F,0))} -> Lorena Sanz López
A11: 1 | B11: =IF($E11="","",VLOOKUP(D11,códigos!$F:$G,2,FALSE)) -> Maika Blázquez | C11: Madrid- La Oca | D11: =IF(E11="","",VLOOKUP($E11,códigos!$E:$F,2,FALSE)) -> MBM52 | E11: José Joaquín Gutiérrez Barquín | F11: MESA | G11: Mobiliario | H11: 46044 | I11: 46042 | J11: -973 | K11: =IF($C11="","",VLOOKUP(C11,códigos!$B:$C,2,FALSE)) -> SIEMA BLINK, S.L | N11: {=INDEX(códigos!E:E,MATCH(D11,códigos!F:F,0))} -> José Joaquín Gutiérrez Barquín
A12: 1 | B12: =IF($E12="","",VLOOKUP(D12,códigos!$F:$G,2,FALSE)) -> Maika Blázquez | C12: Fuenlabrada | D12: =IF(E12="","",VLOOKUP($E12,códigos!$E:$F,2,FALSE)) -> MBM190 | E12: Cristina García García | F12: CURSO 2 | G12: Inscripción | I12: 46043 | J12: =-2772.26/2 -> -1386.13 | K12: =IF($C12="","",VLOOKUP(C12,códigos!$B:$C,2,FALSE)) -> AUDIBRADA | N12: {=INDEX(códigos!E:E,MATCH(D12,códigos!F:F,0))} -> Cristina García García
A13: 1 | B13: =IF($E13="","",VLOOKUP(D13,códigos!$F:$G,2,FALSE)) -> Maika Blázquez | C13: Fuenlabrada | D13: =IF(E13="","",VLOOKUP($E13,códigos!$E:$F,2,FALSE)) -> MBM190 | E13: Cristina García García | F13: CURSO 1 | G13: Inscripción | I13: 46043 | J13: =-2772.26/2 -> -1386.13 | K13: =IF($C13="","",VLOOKUP(C13,códigos!$B:$C,2,FALSE)) -> AUDIBRADA | N13: {=INDEX(códigos!E:E,MATCH(D13,códigos!F:F,0))} -> Cristina García García
A14: 1 | B14: =IF($E14="","",VLOOKUP(D14,códigos!$F:$G,2,FALSE)) -> Maika Blázquez | C14: Madrid- Juan Bravo | D14: =IF(E14="","",VLOOKUP($E14,códigos!$E:$F,2,FALSE)) -> MBM224 | E14: Roberto Sanz Garzón | F14: CURSO | G14: Inscripción | H14: 46043 | I14: 46043 | J14: -600 | K14: =IF($C14="","",VLOOKUP(C14,códigos!$B:$C,2,FALSE)) -> AUDICOST, S.L.U | N14: {=INDEX(códigos!E:E,MATCH(D14,códigos!F:F,0))} -> Roberto Sanz Garzón
A15: 1 | B15: =IF($E15="","",VLOOKUP(D15,códigos!$F:$G,2,FALSE)) -> Lisandro Russian | C15: Logroño | D15: =IF(E15="","",VLOOKUP($E15,códigos!$E:$F,2,FALSE)) -> LRM151 | E15: Cristina Ibañez Muñoz | F15: CONGRESO ATENAS | G15: Congreso internacional personal | H15: 46058 | I15: 46044 | J15: -4701.07 | K15: =IF($C15="","",VLOOKUP(C15,códigos!$B:$C,2,FALSE)) -> AUDICOST LOGROÑO | N15: {=INDEX(códigos!E:E,MATCH(D15,códigos!F:F,0))} -> Cristina Ibañez Muñoz
A16: 1 | B16: =IF($E16="","",VLOOKUP(D16,códigos!$F:$G,2,FALSE)) -> Ramon Ferrando | C16: El Albir (Benidorm) | D16: =IF(E16="","",VLOOKUP($E16,códigos!$E:$F,2,FALSE)) -> RFV38 | E16: María Emilia García Ruiz | F16: IPHONE17 | G16: Material para centro | I16: 46045 | J16: -1500 | K16: =IF($C16="","",VLOOKUP(C16,códigos!$B:$C,2,FALSE)) -> AUDICANTE | N16: {=INDEX(códigos!E:E,MATCH(D16,códigos!F:F,0))} -> María Emilia García Ruiz
A17: 1 | B17: =IF($E17="","",VLOOKUP(D17,códigos!$F:$G,2,FALSE)) -> Maika Blázquez | C17: Torrejón De Ardoz | D17: =IF(E17="","",VLOOKUP($E17,códigos!$E:$F,2,FALSE)) -> MBM187 | E17: Abel Bogoya Castaño | F17: CURSO | G17: Inscripción | K17: =IF($C17="","",VLOOKUP(C17,códigos!$B:$C,2,FALSE)) -> AUDICOST LEGANES | N17: {=INDEX(códigos!E:E,MATCH(D17,códigos!F:F,0))} -> Abel Bogoya Castaño
A18: 1 | B18: =IF($E18="","",VLOOKUP(D18,códigos!$F:$G,2,FALSE)) -> Ramon Ferrando | C18: Valencia- Cadiz | D18: =IF(E18="","",VLOOKUP($E18,códigos!$E:$F,2,FALSE)) -> RFV48 | E18: Elena González Turienzo | F18: CURSO | G18: Inscripción | H18: 46058 | I18: 46049 | J18: -133.07 | K18: =IF($C18="","",VLOOKUP(C18,códigos!$B:$C,2,FALSE)) -> AUDICANTE | N18: {=INDEX(códigos!E:E,MATCH(D18,códigos!F:F,0))} -> Elena González Turienzo
A19: 1 | B19: =IF($E19="","",VLOOKUP(D19,códigos!$F:$G,2,FALSE)) | D19: =IF(E19="","",VLOOKUP($E19,códigos!$E:$F,2,FALSE)) | K19: =IF($C19="","",VLOOKUP(C19,códigos!$B:$C,2,FALSE)) | N19: {=INDEX(códigos!E:E,MATCH(D19,códigos!F:F,0))} -> #N/A
A20: 1 | B20: =IF($E20="","",VLOOKUP(D20,códigos!$F:$G,2,FALSE)) | D20: =IF(E20="","",VLOOKUP($E20,códigos!$E:$F,2,FALSE)) | K20: =IF($C20="","",VLOOKUP(C20,códigos!$B:$C,2,FALSE)) | N20: {=INDEX(códigos!E:E,MATCH(D20,códigos!F:F,0))} -> #N/A
A21: 1 | B21: =IF($E21="","",VLOOKUP(D21,códigos!$F:$G,2,FALSE)) | D21: =IF(E21="","",VLOOKUP($E21,códigos!$E:$F,2,FALSE)) | K21: =IF($C21="","",VLOOKUP(C21,códigos!$B:$C,2,FALSE)) | N21: {=INDEX(códigos!E:E,MATCH(D21,códigos!F:F,0))} -> #N/A
A22: 1 | B22: =IF($E22="","",VLOOKUP(D22,códigos!$F:$G,2,FALSE)) | D22: =IF(E22="","",VLOOKUP($E22,códigos!$E:$F,2,FALSE)) | K22: =IF($C22="","",VLOOKUP(C22,códigos!$B:$C,2,FALSE)) | N22: {=INDEX(códigos!E:E,MATCH(D22,códigos!F:F,0))} -> #N/A
A23: 1 | B23: =IF($E23="","",VLOOKUP(D23,códigos!$F:$G,2,FALSE)) | D23: =IF(E23="","",VLOOKUP($E23,códigos!$E:$F,2,FALSE)) | K23: =IF($C23="","",VLOOKUP(C23,códigos!$B:$C,2,FALSE)) | N23: {=INDEX(códigos!E:E,MATCH(D23,códigos!F:F,0))} -> #N/A
A24: 1 | B24: =IF($E24="","",VLOOKUP(D24,códigos!$F:$G,2,FALSE)) | D24: =IF(E24="","",VLOOKUP($E24,códigos!$E:$F,2,FALSE)) | K24: =IF($C24="","",VLOOKUP(C24,códigos!$B:$C,2,FALSE)) | N24: {=INDEX(códigos!E:E,MATCH(D24,códigos!F:F,0))} -> #N/A
A25: 1 | B25: =IF($E25="","",VLOOKUP(D25,códigos!$F:$G,2,FALSE)) | D25: =IF(E25="","",VLOOKUP($E25,códigos!$E:$F,2,FALSE)) | K25: =IF($C25="","",VLOOKUP(C25,códigos!$B:$C,2,FALSE)) | N25: {=INDEX(códigos!E:E,MATCH(D25,códigos!F:F,0))} -> #N/A
E48: ORL
E98: ORL
E148: ORL
E198: ORL
E248: ORL
E298: ORL
E348: ORL
E398: ORL
E448: ORL
E498: ORL
E548: ORL
E598: ORL
... E898: ORL

Sheet FEBRERO
B1: PETICIONES ORL 2026
A3: MES | B3: VISITADOR | C3: CENTRO | D3: COD.CONTRATO | E3: ORL | F3: ACCION MKT | G3: CATEGORÍAS | H3: FECHA P/ | I3: FECHA PETICION | J3: IMPORTE | K3: EMPRESA | L3: OBSERVACIONES
A4: 2 | B4: =IF($E4="","",VLOOKUP(D4,códigos!$F:$G,2,FALSE)) -> Maika Blázquez | C4: Torrejón De Ardoz | D4: =IF(E4="","",VLOOKUP($E4,códigos!$E:$F,2,FALSE)) -> MBM61 | E4: Julie Múñoz Freitez | F4: CURSO | G4: Inscripción | H4: 46062 | I4: 46056 | J4: -2772.25 | K4: =IF($C4="","",VLOOKUP(C4,códigos!$B:$C,2,FALSE)) -> AUDICOST LEGANES | N4: {=INDEX(códigos!E:E,MATCH(D4,códigos!F:F,0))} -> Julie Múñoz Freitez
A5: 2 | B5: =IF($E5="","",VLOOKUP(D5,códigos!$F:$G,2,FALSE)) -> Maika Blázquez | C5: Fuenlabrada | D5: =IF(E5="","",VLOOKUP($E5,códigos!$E:$F,2,FALSE)) -> MBM147 | E5: María Estefanía Hernández García | F5: CURSO | G5: Inscripción | H5: 46064 | I5: 46056 | J5: -443.56 | K5: =IF($C5="","",VLOOKUP(C5,códigos!$B:$C,2,FALSE)) -> AUDIBRADA | N5: {=INDEX(códigos!E:E,MATCH(D5,códigos!F:F,0))} -> María Estefanía Hernández García
A6: 2 | B6: =IF($E6="","",VLOOKUP(D6,códigos!$F:$G,2,FALSE)) -> Ramon Ferrando | C6: Valencia- Parra | D6: =IF(E6="","",VLOOKUP($E6,códigos!$E:$F,2,FALSE)) -> RFV15 | E6: Jean Franco Intraprendente Martini | F6: APPLEWATCH | G6: Material para centro | I6: 46055 | J6: -899 | K6: =IF($C6="","",VLOOKUP(C6,códigos!$B:$C,2,FALSE)) -> AUDICOST, S.L.U | N6: {=INDEX(códigos!E:E,MATCH(D6,códigos!F:F,0))} -> Jean Franco Intraprendente Martini
A7: 2 | B7: =IF($E7="","",VLOOKUP(D7,códigos!$F:$G,2,FALSE)) -> Iván Sánchez | C7: El Albir (Benidorm) | D7: =IF(E7="","",VLOOKUP($E7,códigos!$E:$F,2,FALSE)) -> ISL54 | E7: José María Laborda Margolles | F7: VIAJE A TANZANIA | G7: Congreso internacional | H7: 46059 | I7: 46059 | J7: -4000 | K7: =IF($C7="","",VLOOKUP(C7,códigos!$B:$C,2,FALSE)) -> AUDICANTE | N7: {=INDEX(códigos!E:E,MATCH(D7,códigos!F:F,0))} -> José María Laborda Margolles | P7: PAGADO POR EL
A8: 2 | B8: =IF($E8="","",VLOOKUP(D8,códigos!$F:$G,2,FALSE)) -> Lisandro Russian | C8: Logroño | D8: =IF(E8="","",VLOOKUP($E8,códigos!$E:$F,2,FALSE)) -> LRM264 | E8: Carmen Delgado Muñoz | F8: IPHONE15 | G8: Material para centro | I8: 46049 | J8: -626.99 | K8: =IF($C8="","",VLOOKUP(C8,códigos!$B:$C,2,FALSE)) -> AUDICOST LOGROÑO | N8: {=INDEX(códigos!E:E,MATCH(D8,códigos!F:F,0))} -> Carmen Delgado Muñoz
A9: 1 | B9: =IF($E9="","",VLOOKUP(D9,códigos!$F:$G,2,FALSE)) -> Lisandro Russian | C9: Alcorcón | D9: =IF(E9="","",VLOOKUP($E9,códigos!$E:$F,2,FALSE)) -> LRM82 | E9: José Miguel Aparicio Fernández | F9: CURSO PARA R4 TERESA CONDE GOMEZ-MENOR | G9: Inscripción | H9: 46062 | I9: 46036 | J9: -310.5 | K9: =IF($C9="","",VLOOKUP(C9,códigos!$B:$C,2,FALSE)) -> CLINICA DOS DE MAYO | N9: {=INDEX(códigos!E:E,MATCH(D9,códigos!F:F,0))} -> José Miguel Aparicio Fernández
A10: 2 | B10: =IF($E10="","",VLOOKUP(D10,códigos!$F:$G,2,FALSE)) -> Ramon Ferrando | C10: El Albir (Benidorm) | D10: =IF(E10="","",VLOOKUP($E10,códigos!$E:$F,2,FALSE)) -> ISL104 | E10: Isabel Polo Tomás | F10: TRASLADO TREN | G10: Traslado | H10: 46063 | I10: 46062 | J10: -84.52 | K10: =IF($C10="","",VLOOKUP(C10,códigos!$B:$C,2,FALSE)) -> AUDICANTE | N10: {=INDEX(códigos!E:E,MATCH(D10,códigos!F:F,0))} -> Isabel Polo Tomás
A11: 2 | B11: =IF($E11="","",VLOOKUP(D11,códigos!$F:$G,2,FALSE)) -> Maika Blázquez | C11: Getafe | D11: =IF(E11="","",VLOOKUP($E11,códigos!$E:$F,2,FALSE)) -> MBM26 | E11: Gerardo Monedero Rodrigo | F11: CURSO | G11: Inscripción | I11: 46062 | J11: =-1219.8/2 -> -609.9 | K11: =IF($C11="","",VLOOKUP(C11,códigos!$B:$C,2,FALSE)) -> AUDIBRADA | N11: {=INDEX(códigos!E:E,MATCH(D11,códigos!F:F,0))} -> Gerardo Monedero Rodrigo
A12: 2 | B12: =IF($E12="","",VLOOKUP(D12,códigos!$F:$G,2,FALSE)) -> Maika Blázquez | C12: Getafe | D12: =IF(E12="","",VLOOKUP($E12,códigos!$E:$F,2,FALSE)) -> MBM96 | E12: Beatriz Santos Duque | F12: CURSO | G12: Inscripción | I12: 46062 | J12: =J11 -> -609.9 | K12: =IF($C12="","",VLOOKUP(C12,códigos!$B:$C,2,FALSE)) -> AUDIBRADA | N12: {=INDEX(códigos!E:E,MATCH(D12,códigos!F:F,0))} -> Beatriz Santos Duque
A13: 2 | B13: =IF($E13="","",VLOOKUP(D13,códigos!$F:$G,2,FALSE)) -> Luis Alberto Rodríguez | C13: Sevilla- Montoto | D13: =IF(E13="","",VLOOKUP($E13,códigos!$E:$F,2,FALSE)) -> LAA37 | E13: Miguel Rodriguez Pérez | F13: ESTANCIA HOTEL | G13: Alojamiento | I13: 46062 | J13: -980.85 | K13: =IF($C13="","",VLOOKUP(C13,códigos!$B:$C,2,FALSE)) -> OIR VITAL CENTROS AUDITIVOS | N13: {=INDEX(códigos!E:E,MATCH(D13,códigos!F:F,0))} -> Miguel Rodriguez Pérez
A14: 2 | B14: =IF($E14="","",VLOOKUP(D14,códigos!$F:$G,2,FALSE)) -> Ramon Ferrando | C14: El Albir (Benidorm) | D14: =IF(E14="","",VLOOKUP($E14,códigos!$E:$F,2,FALSE)) -> ISL104 | E14: Isabel Polo Tomás | F14: TRASLADO | G14: Traslado | I14: 46035 | J14: -68.75 | K14: =IF($C14="","",VLOOKUP(C14,códigos!$B:$C,2,FALSE)) -> AUDICANTE | N14: {=INDEX(códigos!E:E,MATCH(D14,códigos!F:F,0))} -> Isabel Polo Tomás
A15: 2 | B15: =IF($E15="","",VLOOKUP(D15,códigos!$F:$G,2,FALSE)) -> Ramon Ferrando | C15: El Albir (Benidorm) | D15: =IF(E15="","",VLOOKUP($E15,códigos!$E:$F,2,FALSE)) -> ISL104 | E15: Isabel Polo Tomás | F15: TRASLADO | G15: Traslado | I15: 46035 | J15: -630.47 | K15: =IF($C15="","",VLOOKUP(C15,códigos!$B:$C,2,FALSE)) -> AUDICANTE | N15: {=INDEX(códigos!E:E,MATCH(D15,códigos!F:F,0))} -> Isabel Polo Tomás
A16: 2 | B16: =IF($E16="","",VLOOKUP(D16,códigos!$F:$G,2,FALSE)) -> Maika Blázquez | C16: Madrid- La Oca | D16: =IF(E16="","",VLOOKUP($E16,códigos!$E:$F,2,FALSE)) -> MBM69 | E16: Oscar A, Sánchez Valenzuela | F16: MACBOOK PRO | G16: Material para centro | I16: 46065 | J16: -3353.99 | K16: =IF($C16="","",VLOOKUP(C16,códigos!$B:$C,2,FALSE)) -> SIEMA BLINK, S.L | N16: {=INDEX(códigos!E:E,MATCH(D16,códigos!F:F,0))} -> Oscar A, Sánchez Valenzuela
A17: 2 | B17: =IF($E17="","",VLOOKUP(D17,códigos!$F:$G,2,FALSE)) -> Maika Blázquez | C17: Madrid- Canillas | D17: =IF(E17="","",VLOOKUP($E17,códigos!$E:$F,2,FALSE)) -> MBM50 | E17: José Gustavo Barroso Braojos | F17: PATROCINIO-VIAJE ISLANDIA | G17: Publicidad | H17: 46065 | I17: 46065 | J17: 5025 | K17: =IF($C17="","",VLOOKUP(C17,códigos!$B:$C,2,FALSE)) -> AUDICOST, S.L.U | N17: {=INDEX(códigos!E:E,MATCH(D17,códigos!F:F,0))} -> José Gustavo Barroso Braojos
A18: 2 | B18: =IF($E18="","",VLOOKUP(D18,códigos!$F:$G,2,FALSE)) -> Maika Blázquez | C18: Fuenlabrada | D18: =IF(E18="","",VLOOKUP($E18,códigos!$E:$F,2,FALSE)) -> MBM228 | E18: Daniel Rodríguez Ocaña | F18: CURSO | G18: Inscripción | I18: 46066 | J18: -1000 | K18: =IF($C18="","",VLOOKUP(C18,códigos!$B:$C,2,FALSE)) -> AUDIBRADA | N18: {=INDEX(códigos!E:E,MATCH(D18,códigos!F:F,0))} -> Daniel Rodríguez Ocaña
A19: 2 | B19: =IF($E19="","",VLOOKUP(D19,códigos!$F:$G,2,FALSE)) -> Maika Blázquez | C19: Madrid- Juan Bravo | D19: =IF(E19="","",VLOOKUP($E19,códigos!$E:$F,2,FALSE)) -> MBM229 | E19: Raquel de Lama Bermejo | F19: CURSO | G19: Inscripción | I19: 46071 | J19: -900 | K19: =IF($C19="","",VLOOKUP(C19,códigos!$B:$C,2,FALSE)) -> AUDICOST, S.L.U | N19: {=INDEX(códigos!E:E,MATCH(D19,códigos!F:F,0))} -> Raquel de Lama Bermejo
A20: 2 | B20: =IF($E20="","",VLOOKUP(D20,códigos!$F:$G,2,FALSE)) -> Ramon Ferrando | C20: El Albir (Benidorm) | D20: =IF(E20="","",VLOOKUP($E20,códigos!$E:$F,2,FALSE)) -> ISL104 | E20: Isabel Polo Tomás | F20: VIAJE A JAPON | G20: Congreso internacional personal | H20: 46078 | I20: 46073 | J20: -4957.1 | K20: =IF($C20="","",VLOOKUP(C20,códigos!$B:$C,2,FALSE)) -> AUDICANTE | N20: {=INDEX(códigos!E:E,MATCH(D20,códigos!F:F,0))} -> Isabel Polo Tomás
A21: 2 | B21: =IF($E21="","",VLOOKUP(D21,códigos!$F:$G,2,FALSE)) -> Maika Blázquez | C21: Getafe | D21: =IF(E21="","",VLOOKUP($E21,códigos!$E:$F,2,FALSE)) -> MBM230 | E21: Daniela Carrillo Moreno | F21: CURSO | G21: Inscripción | I21: 46078 | J21: -600 | K21: =IF($C21="","",VLOOKUP(C21,códigos!$B:$C,2,FALSE)) -> AUDIBRADA | N21: {=INDEX(códigos!E:E,MATCH(D21,códigos!F:F,0))} -> Daniela Carrillo Moreno
A22: 2 | B22: =IF($E22="","",VLOOKUP(D22,códigos!$F:$G,2,FALSE)) -> Iván Sánchez | C22: Orihuela | D22: =IF(E22="","",VLOOKUP($E22,códigos!$E:$F,2,FALSE)) -> ISL14 | E22: Carlos Velásquez Fermín | F22: CERRAMIENTO | G22: Obras acondicionamiento centro | H22: 46063 | J22: -2085.24 | K22: =IF($C22="","",VLOOKUP(C22,códigos!$B:$C,2,FALSE)) -> AUDICOST, S.L.U | N22: {=INDEX(códigos!E:E,MATCH(D22,códigos!F:F,0))} -> Carlos Velásquez Fermín
A23: 2 | B23: =IF($E23="","",VLOOKUP(D23,códigos!$F:$G,2,FALSE)) -> Iván Sánchez | C23: Murcia | D23: =IF(E23="","",VLOOKUP($E23,códigos!$E:$F,2,FALSE)) -> ISL24 | E23: Enrique López Meseguer | F23: VIAJE A JORDANIA | G23: Congreso internacional personal | H23: 46056 | J23: -3098 | K23: =IF($C23="","",VLOOKUP(C23,códigos!$B:$C,2,FALSE)) -> AUDICANTE | M23: 46009 | N23: {=INDEX(códigos!E:E,MATCH(D23,códigos!F:F,0))} -> Enrique López Meseguer
A24: 2 | B24: =IF($E24="","",VLOOKUP(D24,códigos!$F:$G,2,FALSE)) | D24: =IF(E24="","",VLOOKUP($E24,códigos!$E:$F,2,FALSE)) | K24: =IF($C24="","",VLOOKUP(C24,códigos!$B:$C,2,FALSE)) | N24: {=INDEX(códigos!E:E,MATCH(D24,códigos!F:F,0))} -> #N/A
A25: 2 | B25: =IF($E25="","",VLOOKUP(D25,códigos!$F:$G,2,FALSE)) | D25: =IF(E25="","",VLOOKUP($E25,códigos!$E:$F,2,FALSE)) | K25: =IF($C25="","",VLOOKUP(C25,códigos!$B:$C,2,FALSE)) | N25: {=INDEX(códigos!E:E,MATCH(D25,códigos!F:F,0))} -> #N/A
A26: 2 | B26: =IF($E26="","",VLOOKUP(D26,códigos!$F:$G,2,FALSE)) | D26: =IF(E26="","",VLOOKUP($E26,códigos!$E:$F,2,FALSE)) | K26: =IF($C26="","",VLOOKUP(C26,códigos!$B:$C,2,FALSE)) | N26: {=INDEX(códigos!E:E,MATCH(D26,códigos!F:F,0))} -> #N/A
A27: 2 | B27: =IF($E27="","",VLOOKUP(D27,códigos!$F:$G,2,FALSE)) | D27: =IF(E27="","",VLOOKUP($E27,códigos!$E:$F,2,FALSE)) | K27: =IF($C27="","",VLOOKUP(C27,códigos!$B:$C,2,FALSE)) | N27: {=INDEX(códigos!E:E,MATCH(D27,códigos!F:F,0))} -> #N/A
B28: =IF($E28="","",VLOOKUP(D28,códigos!$F:$G,2,FALSE)) | D28: =IF(E28="","",VLOOKUP($E28,códigos!$E:$F,2,FALSE)) | K28: =IF($C28="","",VLOOKUP(C28,códigos!$B:$C,2,FALSE))
B29: =IF($E29="","",VLOOKUP(D29,códigos!$F:$G,2,FALSE)) | D29: =IF(E29="","",VLOOKUP($E29,códigos!$E:$F,2,FALSE)) | K29: =IF($C29="","",VLOOKUP(C29,códigos!$B:$C,2,FALSE))
B30: =IF($E30="","",VLOOKUP(D30,códigos!$F:$G,2,FALSE)) | D30: =IF(E30="","",VLOOKUP($E30,códigos!$E:$F,2,FALSE)) | K30: =IF($C30="","",VLOOKUP(C30,códigos!$B:$C,2,FALSE))

Sheet MARZO
B1: PETICIONES ORL 2026
A3: MES | B3: VISITADOR | C3: CENTRO | D3: COD.CONTRATO | E3: ORL | F3: ACCION MKT | G3: CATEGORÍAS | H3: FECHA P/ | I3: FECHA PETICION | J3: IMPORTE | K3: EMPRESA | L3: OBSERVACIONES
A4: 3 | B4: =IF($E4="","",VLOOKUP(D4,códigos!$F:$G,2,FALSE)) -> Ramon Ferrando | C4: El Albir (Benidorm) | D4: =IF(E4="","",VLOOKUP($E4,códigos!$E:$F,2,FALSE)) -> ISL104 | E4: Isabel Polo Tomás | F4: HOTEL EN MADRID | G4: Alojamiento | H4: 46085 | I4: 46084 | J4: -285.73 | K4: =IF($C4="","",VLOOKUP(C4,códigos!$B:$C,2,FALSE)) -> AUDICANTE | N4: {=INDEX(códigos!E:E,MATCH(D4,códigos!F:F,0))} -> Isabel Polo Tomás
A5: 3 | B5: =IF($E5="","",VLOOKUP(D5,códigos!$F:$G,2,FALSE)) -> Iván Sánchez | C5: San Javier | D5: =IF(E5="","",VLOOKUP($E5,códigos!$E:$F,2,FALSE)) -> ISL149 | E5: Ángel Onofre Pérez Coll | F5: INSCRIPCION CURSO RINOPLASTIA | G5: Inscripción | I5: 46086 | J5: 2176.19 | K5: =IF($C5="","",VLOOKUP(C5,códigos!$B:$C,2,FALSE)) -> AUDICOST, S.L.U | N5: {=INDEX(códigos!E:E,MATCH(D5,códigos!F:F,0))} -> Ángel Onofre Pérez Coll
A6: 3 | B6: =IF($E6="","",VLOOKUP(D6,códigos!$F:$G,2,FALSE)) -> Lisandro Russian | C6: Logroño | D6: =IF(E6="","",VLOOKUP($E6,códigos!$E:$F,2,FALSE)) -> LRM249 | E6: Daniel Briones Crespo | F6: VIAJE CONGRESO ATENAS | G6: Alojamiento y traslado | H6: 46094 | I6: 46093 | J6: -4215.86 | K6: =IF($C6="","",VLOOKUP(C6,códigos!$B:$C,2,FALSE)) -> AUDICOST LOGROÑO | N6: {=INDEX(códigos!E:E,MATCH(D6,códigos!F:F,0))} -> Daniel Briones Crespo
A7: 3 | B7: =IF($E7="","",VLOOKUP(D7,códigos!$F:$G,2,FALSE)) -> Maika Blázquez | C7: Madrid- Canillas | D7: =IF(E7="","",VLOOKUP($E7,códigos!$E:$F,2,FALSE)) -> MBM50 | E7: José Gustavo Barroso Braojos | F7: CAMARA ACCION PARA ISLANDIA | G7: Publicidad | I7: 46090 | J7: -699.99 | K7: =IF($C7="","",VLOOKUP(C7,códigos!$B:$C,2,FALSE)) -> AUDICOST, S.L.U | N7: {=INDEX(códigos!E:E,MATCH(D7,códigos!F:F,0))} -> José Gustavo Barroso Braojos
A8: 3 | B8: =IF($E8="","",VLOOKUP(D8,códigos!$F:$G,2,FALSE)) -> Maika Blázquez | C8: Madrid- Canillas | D8: =IF(E8="","",VLOOKUP($E8,códigos!$E:$F,2,FALSE)) -> MBM50 | E8: José Gustavo Barroso Braojos | F8: KIT BICICLETA PARA ISLANDIA | G8: Publicidad | I8: 46090 | J8: -62.99 | K8: =IF($C8="","",VLOOKUP(C8,códigos!$B:$C,2,FALSE)) -> AUDICOST, S.L.U | N8: {=INDEX(códigos!E:E,MATCH(D8,códigos!F:F,0))} -> José Gustavo Barroso Braojos
A9: 3 | B9: =IF($E9="","",VLOOKUP(D9,códigos!$F:$G,2,FALSE)) -> Maika Blázquez | C9: Madrid- Canillas | D9: =IF(E9="","",VLOOKUP($E9,códigos!$E:$F,2,FALSE)) -> MBM50 | E9: José Gustavo Barroso Braojos | F9: CARCASA BUCEO PARA ISLANDIA | G9: Publicidad | I9: 46090 | J9: -119.99 | K9: =IF($C9="","",VLOOKUP(C9,códigos!$B:$C,2,FALSE)) -> AUDICOST, S.L.U | N9: {=INDEX(códigos!E:E,MATCH(D9,códigos!F:F,0))} -> José Gustavo Barroso Braojos
A10: 3 | B10: =IF($E10="","",VLOOKUP(D10,códigos!$F:$G,2,FALSE)) -> Maika Blázquez | C10: Madrid- Canillas | D10: =IF(E10="","",VLOOKUP($E10,códigos!$E:$F,2,FALSE)) -> MBM50 | E10: José Gustavo Barroso Braojos | F10: PRISMATICOS PARA ISLANDIA | G10: Publicidad | I10: 46090 | J10: -399 | K10: =IF($C10="","",VLOOKUP(C10,códigos!$B:$C,2,FALSE)) -> AUDICOST, S.L.U | N10: {=INDEX(códigos!E:E,MATCH(D10,códigos!F:F,0))} -> José Gustavo Barroso Braojos
A11: 3 | B11: =IF($E11="","",VLOOKUP(D11,códigos!$F:$G,2,FALSE)) -> Maika Blázquez | C11: Madrid- Canillas | D11: =IF(E11="","",VLOOKUP($E11,códigos!$E:$F,2,FALSE)) -> MBM50 | E11: José Gustavo Barroso Braojos | F11: LINTERNA PARA ISLANDIA | G11: Publicidad | I11: 46090 | J11: -153.97 | K11: =IF($C11="","",VLOOKUP(C11,códigos!$B:$C,2,FALSE)) -> AUDICOST, S.L.U | N11: {=INDEX(códigos!E:E,MATCH(D11,códigos!F:F,0))} -> José Gustavo Barroso Braojos
A12: 3 | B12: =IF($E12="","",VLOOKUP(D12,códigos!$F:$G,2,FALSE)) -> Maika Blázquez | C12: Madrid- Canillas | D12: =IF(E12="","",VLOOKUP($E12,códigos!$E:$F,2,FALSE)) -> MBM50 | E12: José Gustavo Barroso Braojos | F12: ESTUCHE LAPICES COLORES X 2 | G12: Publicidad | I12: 46090 | J12: =-465*2 -> -930 | K12: =IF($C12="","",VLOOKUP(C12,códigos!$B:$C,2,FALSE)) -> AUDICOST, S.L.U | N12: {=INDEX(códigos!E:E,MATCH(D12,códigos!F:F,0))} -> José Gustavo Barroso Braojos
A13: 3 | B13: =IF($E13="","",VLOOKUP(D13,códigos!$F:$G,2,FALSE)) -> Maika Blázquez | C13: Getafe | D13: =IF(E13="","",VLOOKUP($E13,códigos!$E:$F,2,FALSE)) -> MBM223 | E13: Cristina Vaduva | F13: ALQUILER PIEZO ELECTRICO | G13: Material para centro | H13: 46092 | I13: 46090 | J13: -2268.6 | K13: =IF($C13="","",VLOOKUP(C13,códigos!$B:$C,2,FALSE)) -> AUDIBRADA | N13: {=INDEX(códigos!E:E,MATCH(D13,códigos!F:F,0))} -> Cristina Vaduva
A14: 3 | B14: =IF($E14="","",VLOOKUP(D14,códigos!$F:$G,2,FALSE)) -> Iván Sánchez | C14: Orihuela | D14: =IF(E14="","",VLOOKUP($E14,códigos!$E:$F,2,FALSE)) -> ISL14 | E14: Carlos Velásquez Fermín | F14: CURSO | G14: Inscripción | H14: 46094 | I14: 46090 | J14: -568.7 | K14: =IF($C14="","",VLOOKUP(C14,códigos!$B:$C,2,FALSE)) -> AUDICOST, S.L.U | N14: {=INDEX(códigos!E:E,MATCH(D14,códigos!F:F,0))} -> Carlos Velásquez Fermín
A15: 3 | B15: =IF($E15="","",VLOOKUP(D15,códigos!$F:$G,2,FALSE)) -> Iván Sánchez | C15: Orihuela | D15: =IF(E15="","",VLOOKUP($E15,códigos!$E:$F,2,FALSE)) -> ISL58 | E15: Juan Javier Álvarez López | F15: IPHONE 17 PRO MAX 512 GB AZUL OSCURO | G15: Material para centro | I15: 46090 | J15: -1719 | K15: =IF($C15="","",VLOOKUP(C15,códigos!$B:$C,2,FALSE)) -> AUDICOST, S.L.U | N15: {=INDEX(códigos!E:E,MATCH(D15,códigos!F:F,0))} -> Juan Javier Álvarez López
A16: 3 | B16: =IF($E16="","",VLOOKUP(D16,códigos!$F:$G,2,FALSE)) -> Iván Sánchez | C16: Orihuela | D16: =IF(E16="","",VLOOKUP($E16,códigos!$E:$F,2,FALSE)) -> ISL58 | E16: Juan Javier Álvarez López | F16: ASPIRADOR ESCOBA | G16: Material para centro | I16: 46090 | J16: -849 | K16: =IF($C16="","",VLOOKUP(C16,códigos!$B:$C,2,FALSE)) -> AUDICOST, S.L.U | N16: {=INDEX(códigos!E:E,MATCH(D16,códigos!F:F,0))} -> Juan Javier Álvarez López
A17: 3 | B17: =IF($E17="","",VLOOKUP(D17,códigos!$F:$G,2,FALSE)) -> Luis Alberto Rodríguez | C17: Jerez de la Frontera | D17: =IF(E17="","",VLOOKUP($E17,códigos!$E:$F,2,FALSE)) -> LAA81 | E17: Manuel Tucciarone | F17: HOTEL EN MADRID | G17: Alojamiento | I17: 46091 | J17: -1171.53 | K17: =IF($C17="","",VLOOKUP(C17,códigos!$B:$C,2,FALSE)) -> AUDICOST, S.L.U | N17: {=INDEX(códigos!E:E,MATCH(D17,códigos!F:F,0))} -> Manuel Tucciarone
A18: 3 | B18: =IF($E18="","",VLOOKUP(D18,códigos!$F:$G,2,FALSE)) -> Iván Sánchez | C18: Orihuela | D18: =IF(E18="","",VLOOKUP($E18,códigos!$E:$F,2,FALSE)) -> ISL142 | E18: Marina Pérez Grau | F18: CURSO RINOPLASTIA | G18: Inscripción | H18: 46094 | I18: 46092 | J18: -2176.19 | K18: =IF($C18="","",VLOOKUP(C18,códigos!$B:$C,2,FALSE)) -> AUDICOST, S.L.U
A19: 3 | B19: =IF($E19="","",VLOOKUP(D19,códigos!$F:$G,2,FALSE)) -> Iván Sánchez | C19: Alicante | D19: =IF(E19="","",VLOOKUP($E19,códigos!$E:$F,2,FALSE)) -> ISL105 | E19: Karen Rojas Crespo | F19: CURSO | G19: Inscripción | H19: 46106 | I19: 46099 | J19: -599.52 | K19: =IF($C19="","",VLOOKUP(C19,códigos!$B:$C,2,FALSE)) -> AUDICANTE
A20: 3 | B20: =IF($E20="","",VLOOKUP(D20,códigos!$F:$G,2,FALSE)) -> Lisandro Russian | C20: Logroño | D20: =IF(E20="","",VLOOKUP($E20,códigos!$E:$F,2,FALSE)) -> LRM261 | E20: Miguel Garikoitz Calzada Uriondo | F20: ESTANCIA EN CHICLANA | G20: Alojamiento | H20: 46099 | K20: =IF($C20="","",VLOOKUP(C20,códigos!$B:$C,2,FALSE)) -> AUDICOST LOGROÑO
A21: 3 | B21: =IF($E21="","",VLOOKUP(D21,códigos!$F:$G,2,FALSE)) -> Maika Blázquez | C21: Madrid- Canillas | D21: =IF(E21="","",VLOOKUP($E21,códigos!$E:$F,2,FALSE)) -> MBM50 | E21: José Gustavo Barroso Braojos | F21: ENTRADAS CIRCO SOL | G21: Publicidad | H21: 46099 | K21: =IF($C21="","",VLOOKUP(C21,códigos!$B:$C,2,FALSE)) -> AUDICOST, S.L.U
A22: 3 | B22: =IF($E22="","",VLOOKUP(D22,códigos!$F:$G,2,FALSE)) -> Iván Sánchez | C22: Orihuela | D22: =IF(E22="","",VLOOKUP($E22,códigos!$E:$F,2,FALSE)) -> ISL14 | E22: Carlos Velásquez Fermín | F22: HOTEL Y AVION | G22: Alojamiento y traslado | H22: 46106 | I22: 46105 | J22: -2286.1 | K22: =IF($C22="","",VLOOKUP(C22,códigos!$B:$C,2,FALSE)) -> AUDICOST, S.L.U
A23: 3 | B23: =IF($E23="","",VLOOKUP(D23,códigos!$F:$G,2,FALSE)) -> Luis Alberto Rodríguez | C23: Sevilla- Montoto | D23: =IF(E23="","",VLOOKUP($E23,códigos!$E:$F,2,FALSE)) -> LAA47 | E23: Estefanía Berrocal Postigo | F23: REUNION OTORRINOS EN REPUBLICA DOMINICANA | G23: Congreso internacional personal | H23: 46108 | I23: 46107 | J23: -13700 | K23: =IF($C23="","",VLOOKUP(C23,códigos!$B:$C,2,FALSE)) -> OIR VITAL CENTROS AUDITIVOS
A24: 3 | B24: =IF($E24="","",VLOOKUP(D24,códigos!$F:$G,2,FALSE)) -> Ramon Ferrando | C24: Valencia- Cadiz | D24: =IF(E24="","",VLOOKUP($E24,códigos!$E:$F,2,FALSE)) -> RFV26 | E24: Ainhoa García-Lliberos de Miguel | F24: INSCRIPION CONGRESO | G24: Inscripción | H24: 46108 | I24: 46107 | J24: -490.51 | K24: =IF($C24="","",VLOOKUP(C24,códigos!$B:$C,2,FALSE)) -> AUDICANTE
A25: 3 | B25: =IF($E25="","",VLOOKUP(D25,códigos!$F:$G,2,FALSE)) -> Iván Sánchez | C25: Alicante | D25: =IF(E25="","",VLOOKUP($E25,códigos!$E:$F,2,FALSE)) -> ISL14 | E25: Carlos Velásquez Fermín | F25: TRASLADO | G25: Traslado | H25: 46112 | I25: 46111 | J25: -856.98 | K25: =IF($C25="","",VLOOKUP(C25,códigos!$B:$C,2,FALSE)) -> AUDICANTE
A26: 3 | B26: =IF($E26="","",VLOOKUP(D26,códigos!$F:$G,2,FALSE)) -> Iván Sánchez | C26: Murcia | D26: =IF(E26="","",VLOOKUP($E26,códigos!$E:$F,2,FALSE)) -> ISL24 | E26: Enrique López Meseguer | F26: VIAJE CAMINO SANTIAGO-DEPOSITO DEL 20% | G26: Congreso nacional personal | H26: 46112 | I26: 46112 | J26: -318 | K26: =IF($C26="","",VLOOKUP(C26,códigos!$B:$C,2,FALSE)) -> AUDICANTE
A27: 3 | B27: =IF($E27="","",VLOOKUP(D27,códigos!$F:$G,2,FALSE)) -> Maika Blázquez | C27: Madrid- La Oca | D27: MBM231 | E27: Itziar Jimenez Gomez | F27: CURSO | G27: Inscripción | I27: 46111 | J27: -600 | K27: =IF($C27="","",VLOOKUP(C27,códigos!$B:$C,2,FALSE)) -> SIEMA BLINK, S.L
A28: 1 | B28: =IF($E28="","",VLOOKUP(D28,códigos!$F:$G,2,FALSE)) -> Lisandro Russian | C28: Madrid- Juan Bravo | D28: =IF(E28="","",VLOOKUP($E28,códigos!$E:$F,2,FALSE)) -> LRM239 | E28: Carlos Barajas Del Rosal | F28: COSTES DE EMPLEADA-ENERO | G28: Gastos de personal | J28: -1398.88 | K28: =IF($C28="","",VLOOKUP($C28,códigos!$B:$C,2,FALSE)) -> AUDICOST, S.L.U | M28: {=INDEX(códigos!E:E,MATCH(D28,códigos!F:F,0))} -> Carlos Barajas Del Rosal
A29: 2 | B29: =IF($E29="","",VLOOKUP(D29,códigos!$F:$G,2,FALSE)) -> Lisandro Russian | C29: Madrid- Juan Bravo | D29: =IF(E29="","",VLOOKUP($E29,códigos!$E:$F,2,FALSE)) -> LRM239 | E29: Carlos Barajas Del Rosal | F29: COSTES DE EMPLEADA-FEBRERO | G29: Gastos de personal | J29: -1398.88 | K29: =IF($C29="","",VLOOKUP($C29,códigos!$B:$C,2,FALSE)) -> AUDICOST, S.L.U | M29: {=INDEX(códigos!E:E,MATCH(D29,códigos!F:F,0))} -> Carlos Barajas Del Rosal
A30: 3 | B30: =IF($E30="","",VLOOKUP(D30,códigos!$F:$G,2,FALSE)) -> Lisandro Russian | C30: Madrid- Juan Bravo | D30: =IF(E30="","",VLOOKUP($E30,códigos!$E:$F,2,FALSE)) -> LRM239 | E30: Carlos Barajas Del Rosal | F30: COSTES DE EMPLEADA-MARZO | G30: Gastos de personal | J30: -1398.88 | K30: =IF($C30="","",VLOOKUP($C30,códigos!$B:$C,2,FALSE)) -> AUDICOST, S.L.U | M30: {=INDEX(códigos!E:E,MATCH(D30,códigos!F:F,0))} -> Carlos Barajas Del Rosal
E52: ORL
E102: ORL
E152: ORL
E202: ORL
E252: ORL
E302: ORL
E352: ORL
E402: ORL
E452: ORL
E502: ORL
E552: ORL
E602: ORL
... E902: ORL

Sheet ABRIL
B1: PETICIONES ORL 2026
B3: VISITADOR | C3: CENTRO | D3: COD.CONTRATO | E3: ORL | F3: ACCION MKT | G3: CATEGORÍAS | H3: FECHA P/ | I3: FECHA PETICION | J3: IMPORTE | K3: EMPRESA | L3: OBSERVACIONES
A4: 4 | B4: =IF($E4="","",VLOOKUP(D4,códigos!$F:$G,2,FALSE)) -> Iván Sánchez | C4: Orihuela | D4: =IF(E4="","",VLOOKUP($E4,códigos!$E:$F,2,FALSE)) -> ISL58 | E4: Juan Javier Álvarez López | F4: TV+SOPORTE | G4: Material para centro | H4: 46119 | I4: 46118 | J4: -1400.42 | K4: =IF($C4="","",VLOOKUP(C4,códigos!$B:$C,2,FALSE)) -> AUDICOST, S.L.U | N4: {=INDEX(códigos!E:E,MATCH(D4,códigos!F:F,0))} -> Juan Javier Álvarez López
A5: 4 | B5: =IF($E5="","",VLOOKUP(D5,códigos!$F:$G,2,FALSE)) -> Luis Alberto Rodríguez | C5: Sevilla- Montoto | D5: =IF(E5="","",VLOOKUP($E5,códigos!$E:$F,2,FALSE)) -> LAA08 | E5: David Castro Gutiérrez de Agüero | F5: PORTATIL MEDIA MARKT | G5: Material para centro | H5: 46120 | I5: 46120 | J5: -899 | K5: =IF($C5="","",VLOOKUP(C5,códigos!$B:$C,2,FALSE)) -> OIR VITAL CENTROS AUDITIVOS | N5: {=INDEX(códigos!E:E,MATCH(D5,códigos!F:F,0))} -> David Castro Gutiérrez de Agüero
A6: 4 | B6: =IF($E6="","",VLOOKUP(D6,códigos!$F:$G,2,FALSE)) | D6: =IF(E6="","",VLOOKUP($E6,códigos!$E:$F,2,FALSE)) | K6: =IF($C6="","",VLOOKUP(C6,códigos!$B:$C,2,FALSE)) | N6: {=INDEX(códigos!E:E,MATCH(D6,códigos!F:F,0))} -> #N/A
A7: 4 | B7: =IF($E7="","",VLOOKUP(D7,códigos!$F:$G,2,FALSE)) | D7: =IF(E7="","",VLOOKUP($E7,códigos!$E:$F,2,FALSE)) | K7: =IF($C7="","",VLOOKUP(C7,códigos!$B:$C,2,FALSE)) | N7: {=INDEX(códigos!E:E,MATCH(D7,códigos!F:F,0))} -> #N/A
A8: 4 | B8: =IF($E8="","",VLOOKUP(D8,códigos!$F:$G,2,FALSE)) | D8: =IF(E8="","",VLOOKUP($E8,códigos!$E:$F,2,FALSE)) | K8: =IF($C8="","",VLOOKUP(C8,códigos!$B:$C,2,FALSE)) | N8: {=INDEX(códigos!E:E,MATCH(D8,códigos!F:F,0))} -> #N/A
A9: 4 | B9: =IF($E9="","",VLOOKUP(D9,códigos!$F:$G,2,FALSE)) | D9: =IF(E9="","",VLOOKUP($E9,códigos!$E:$F,2,FALSE)) | K9: =IF($C9="","",VLOOKUP(C9,códigos!$B:$C,2,FALSE)) | N9: {=INDEX(códigos!E:E,MATCH(D9,códigos!F:F,0))} -> #N/A
A10: 4 | B10: =IF($E10="","",VLOOKUP(D10,códigos!$F:$G,2,FALSE)) | D10: =IF(E10="","",VLOOKUP($E10,códigos!$E:$F,2,FALSE)) | K10: =IF($C10="","",VLOOKUP(C10,códigos!$B:$C,2,FALSE)) | N10: {=INDEX(códigos!E:E,MATCH(D10,códigos!F:F,0))} -> #N/A
A11: 4 | B11: =IF($E11="","",VLOOKUP(D11,códigos!$F:$G,2,FALSE)) | D11: =IF(E11="","",VLOOKUP($E11,códigos!$E:$F,2,FALSE)) | K11: =IF($C11="","",VLOOKUP(C11,códigos!$B:$C,2,FALSE)) | N11: {=INDEX(códigos!E:E,MATCH(D11,códigos!F:F,0))} -> #N/A
A12: 4 | B12: =IF($E12="","",VLOOKUP(D12,códigos!$F:$G,2,FALSE)) | D12: =IF(E12="","",VLOOKUP($E12,códigos!$E:$F,2,FALSE)) | K12: =IF($C12="","",VLOOKUP(C12,códigos!$B:$C,2,FALSE)) | N12: {=INDEX(códigos!E:E,MATCH(D12,códigos!F:F,0))} -> #N/A
A13: 4 | B13: =IF($E13="","",VLOOKUP(D13,códigos!$F:$G,2,FALSE)) | D13: =IF(E13="","",VLOOKUP($E13,códigos!$E:$F,2,FALSE)) | K13: =IF($C13="","",VLOOKUP(C13,códigos!$B:$C,2,FALSE)) | N13: {=INDEX(códigos!E:E,MATCH(D13,códigos!F:F,0))} -> #N/A
A14: 4 | B14: =IF($E14="","",VLOOKUP(D14,códigos!$F:$G,2,FALSE)) | D14: =IF(E14="","",VLOOKUP($E14,códigos!$E:$F,2,FALSE)) | K14: =IF($C14="","",VLOOKUP(C14,códigos!$B:$C,2,FALSE)) | N14: {=INDEX(códigos!E:E,MATCH(D14,códigos!F:F,0))} -> #N/A
A15: 4 | B15: =IF($E15="","",VLOOKUP(D15,códigos!$F:$G,2,FALSE)) | D15: =IF(E15="","",VLOOKUP($E15,códigos!$E:$F,2,FALSE)) | K15: =IF($C15="","",VLOOKUP(C15,códigos!$B:$C,2,FALSE)) | N15: {=INDEX(códigos!E:E,MATCH(D15,códigos!F:F,0))} -> #N/A
A16: 4 | B16: =IF($E16="","",VLOOKUP(D16,códigos!$F:$G,2,FALSE)) | D16: =IF(E16="","",VLOOKUP($E16,códigos!$E:$F,2,FALSE)) | K16: =IF($C16="","",VLOOKUP(C16,códigos!$B:$C,2,FALSE)) | N16: {=INDEX(códigos!E:E,MATCH(D16,códigos!F:F,0))} -> #N/A
A17: 4 | B17: =IF($E17="","",VLOOKUP(D17,códigos!$F:$G,2,FALSE)) | D17: =IF(E17="","",VLOOKUP($E17,códigos!$E:$F,2,FALSE)) | K17: =IF($C17="","",VLOOKUP(C17,códigos!$B:$C,2,FALSE)) | N17: {=INDEX(códigos!E:E,MATCH(D17,códigos!F:F,0))} -> #N/A
... A29: 4 | B29: =IF($E29="","",VLOOKUP(D29,códigos!$F:$G,2,FALSE)) | D29: =IF(E29="","",VLOOKUP($E29,códigos!$E:$F,2,FALSE)) | K29: =IF($C29="","",VLOOKUP(C29,códigos!$B:$C,2,FALSE)) | N29: {=INDEX(códigos!E:E,MATCH(D29,códigos!F:F,0))} -> #N/A
A30: 4 | B30: =IF($E30="","",VLOOKUP(D30,códigos!$F:$G,2,FALSE)) | D30: =IF(E30="","",VLOOKUP($E30,códigos!$E:$F,2,FALSE)) | K30: =IF($C30="","",VLOOKUP(C30,códigos!$B:$C,2,FALSE))
E53: ORL
E103: ORL
E153: ORL
E203: ORL
E253: ORL
E303: ORL
E353: ORL
E403: ORL
E453: ORL
E503: ORL
E553: ORL
E603: ORL
... E853: ORL

Sheet MAYO
B1: PETICIONES ORL 2026
A3: MES | B3: VISITADOR | C3: CENTRO | D3: COD.CONTRATO | E3: ORL | F3: ACCION MKT | G3: CATEGORÍAS | H3: FECHA P/ | I3: FECHA PETICION | J3: IMPORTE | K3: EMPRESA | L3: OBSERVACIONES
A4: 5 | B4: =IF($E4="","",VLOOKUP(D4,códigos!$F:$G,2,FALSE)) | C4: Clínica | D4: =IF(E4="","",VLOOKUP($E4,códigos!$E:$F,2,FALSE)) | K4: =IF($C4="","",VLOOKUP(C4,códigos!$B:$C,2,FALSE)) -> Empresa | N4: {=INDEX(códigos!E:E,MATCH(D4,códigos!F:F,0))} -> #N/A
A5: 5 | B5: =IF($E5="","",VLOOKUP(D5,códigos!$F:$G,2,FALSE)) | D5: =IF(E5="","",VLOOKUP($E5,códigos!$E:$F,2,FALSE)) | K5: =IF($C5="","",VLOOKUP(C5,códigos!$B:$C,2,FALSE)) | N5: {=INDEX(códigos!E:E,MATCH(D5,códigos!F:F,0))} -> #N/A
A6: 5 | B6: =IF($E6="","",VLOOKUP(D6,códigos!$F:$G,2,FALSE)) | D6: =IF(E6="","",VLOOKUP($E6,códigos!$E:$F,2,FALSE)) | K6: =IF($C6="","",VLOOKUP(C6,códigos!$B:$C,2,FALSE)) | N6: {=INDEX(códigos!E:E,MATCH(D6,códigos!F:F,0))} -> #N/A
A7: 5 | B7: =IF($E7="","",VLOOKUP(D7,códigos!$F:$G,2,FALSE)) | D7: =IF(E7="","",VLOOKUP($E7,códigos!$E:$F,2,FALSE)) | K7: =IF($C7="","",VLOOKUP(C7,códigos!$B:$C,2,FALSE)) | N7: {=INDEX(códigos!E:E,MATCH(D7,códigos!F:F,0))} -> #N/A
A8: 5 | B8: =IF($E8="","",VLOOKUP(D8,códigos!$F:$G,2,FALSE)) | D8: =IF(E8="","",VLOOKUP($E8,códigos!$E:$F,2,FALSE)) | K8: =IF($C8="","",VLOOKUP(C8,códigos!$B:$C,2,FALSE)) | N8: {=INDEX(códigos!E:E,MATCH(D8,códigos!F:F,0))} -> #N/A
A9: 5 | B9: =IF($E9="","",VLOOKUP(D9,códigos!$F:$G,2,FALSE)) | D9: =IF(E9="","",VLOOKUP($E9,códigos!$E:$F,2,FALSE)) | K9: =IF($C9="","",VLOOKUP(C9,códigos!$B:$C,2,FALSE)) | N9: {=INDEX(códigos!E:E,MATCH(D9,códigos!F:F,0))} -> #N/A
A10: 5 | B10: =IF($E10="","",VLOOKUP(D10,códigos!$F:$G,2,FALSE)) | D10: =IF(E10="","",VLOOKUP($E10,códigos!$E:$F,2,FALSE)) | K10: =IF($C10="","",VLOOKUP(C10,códigos!$B:$C,2,FALSE)) | N10: {=INDEX(códigos!E:E,MATCH(D10,códigos!F:F,0))} -> #N/A
A11: 5 | B11: =IF($E11="","",VLOOKUP(D11,códigos!$F:$G,2,FALSE)) | D11: =IF(E11="","",VLOOKUP($E11,códigos!$E:$F,2,FALSE)) | K11: =IF($C11="","",VLOOKUP(C11,códigos!$B:$C,2,FALSE)) | N11: {=INDEX(códigos!E:E,MATCH(D11,códigos!F:F,0))} -> #N/A
A12: 5 | B12: =IF($E12="","",VLOOKUP(D12,códigos!$F:$G,2,FALSE)) | D12: =IF(E12="","",VLOOKUP($E12,códigos!$E:$F,2,FALSE)) | K12: =IF($C12="","",VLOOKUP(C12,códigos!$B:$C,2,FALSE)) | N12: {=INDEX(códigos!E:E,MATCH(D12,códigos!F:F,0))} -> #N/A
A13: 5 | B13: =IF($E13="","",VLOOKUP(D13,códigos!$F:$G,2,FALSE)) | D13: =IF(E13="","",VLOOKUP($E13,códigos!$E:$F,2,FALSE)) | K13: =IF($C13="","",VLOOKUP(C13,códigos!$B:$C,2,FALSE)) | N13: {=INDEX(códigos!E:E,MATCH(D13,códigos!F:F,0))} -> #N/A
A14: 5 | B14: =IF($E14="","",VLOOKUP(D14,códigos!$F:$G,2,FALSE)) | D14: =IF(E14="","",VLOOKUP($E14,códigos!$E:$F,2,FALSE)) | K14: =IF($C14="","",VLOOKUP(C14,códigos!$B:$C,2,FALSE)) | N14: {=INDEX(códigos!E:E,MATCH(D14,códigos!F:F,0))} -> #N/A
A15: 5 | B15: =IF($E15="","",VLOOKUP(D15,códigos!$F:$G,2,FALSE)) | D15: =IF(E15="","",VLOOKUP($E15,códigos!$E:$F,2,FALSE)) | K15: =IF($C15="","",VLOOKUP(C15,códigos!$B:$C,2,FALSE)) | N15: {=INDEX(códigos!E:E,MATCH(D15,códigos!F:F,0))} -> #N/A
A16: 5 | B16: =IF($E16="","",VLOOKUP(D16,códigos!$F:$G,2,FALSE)) | D16: =IF(E16="","",VLOOKUP($E16,códigos!$E:$F,2,FALSE)) | K16: =IF($C16="","",VLOOKUP(C16,códigos!$B:$C,2,FALSE)) | N16: {=INDEX(códigos!E:E,MATCH(D16,códigos!F:F,0))} -> #N/A
... A27: 5 | B27: =IF($E27="","",VLOOKUP(D27,códigos!$F:$G,2,FALSE)) | D27: =IF(E27="","",VLOOKUP($E27,códigos!$E:$F,2,FALSE)) | K27: =IF($C27="","",VLOOKUP(C27,códigos!$B:$C,2,FALSE)) | N27: {=INDEX(códigos!E:E,MATCH(D27,códigos!F:F,0))} -> #N/A
A28: 5 | B28: =IF($E28="","",VLOOKUP(D28,códigos!$F:$G,2,FALSE)) | D28: =IF(E28="","",VLOOKUP($E28,códigos!$E:$F,2,FALSE)) | K28: =IF($C28="","",VLOOKUP(C28,códigos!$B:$C,2,FALSE))
A29: 5 | B29: =IF($E29="","",VLOOKUP(D29,códigos!$F:$G,2,FALSE)) | D29: =IF(E29="","",VLOOKUP($E29,códigos!$E:$F,2,FALSE)) | K29: =IF($C29="","",VLOOKUP(C29,códigos!$B:$C,2,FALSE))
A30: 5 | B30: =IF($E30="","",VLOOKUP(D30,códigos!$F:$G,2,FALSE)) | D30: =IF(E30="","",VLOOKUP($E30,códigos!$E:$F,2,FALSE)) | K30: =IF($C30="","",VLOOKUP(C30,códigos!$B:$C,2,FALSE))
E53: ORL
E103: ORL
E153: ORL
E203: ORL
E253: ORL
E303: ORL
E353: ORL
E403: ORL
E453: ORL
E503: ORL
E553: ORL
E603: ORL
... E903: ORL

Sheet JUNIO
B1: PETICIONES ORL 2026
A3: MES | B3: VISITADOR | C3: CENTRO | D3: COD.CONTRATO | E3: ORL | F3: ACCION MKT | G3: CATEGORÍAS | H3: FECHA P/ | I3: FECHA PETICION | J3: IMPORTE | K3: EMPRESA | L3: OBSERVACIONES
A4: 6 | B4: =IF($E4="","",VLOOKUP(D4,códigos!$F:$G,2,FALSE)) | C4: Clínica | D4: =IF(E4="","",VLOOKUP($E4,códigos!$E:$F,2,FALSE)) | K4: =IF($C4="","",VLOOKUP(C4,códigos!$B:$C,2,FALSE)) -> Empresa | N4: {=INDEX(códigos!E:E,MATCH(D4,códigos!F:F,0))} -> #N/A
A5: 6 | B5: =IF($E5="","",VLOOKUP(D5,códigos!$F:$G,2,FALSE)) | D5: =IF(E5="","",VLOOKUP($E5,códigos!$E:$F,2,FALSE)) | K5: =IF($C5="","",VLOOKUP(C5,códigos!$B:$C,2,FALSE)) | N5: {=INDEX(códigos!E:E,MATCH(D5,códigos!F:F,0))} -> #N/A
A6: 6 | B6: =IF($E6="","",VLOOKUP(D6,códigos!$F:$G,2,FALSE)) | D6: =IF(E6="","",VLOOKUP($E6,códigos!$E:$F,2,FALSE)) | K6: =IF($C6="","",VLOOKUP(C6,códigos!$B:$C,2,FALSE)) | N6: {=INDEX(códigos!E:E,MATCH(D6,códigos!F:F,0))} -> #N/A
A7: 6 | B7: =IF($E7="","",VLOOKUP(D7,códigos!$F:$G,2,FALSE)) | D7: =IF(E7="","",VLOOKUP($E7,códigos!$E:$F,2,FALSE)) | K7: =IF($C7="","",VLOOKUP(C7,códigos!$B:$C,2,FALSE)) | N7: {=INDEX(códigos!E:E,MATCH(D7,códigos!F:F,0))} -> #N/A
A8: 6 | B8: =IF($E8="","",VLOOKUP(D8,códigos!$F:$G,2,FALSE)) | D8: =IF(E8="","",VLOOKUP($E8,códigos!$E:$F,2,FALSE)) | K8: =IF($C8="","",VLOOKUP(C8,códigos!$B:$C,2,FALSE)) | N8: {=INDEX(códigos!E:E,MATCH(D8,códigos!F:F,0))} -> #N/A
A9: 6 | B9: =IF($E9="","",VLOOKUP(D9,códigos!$F:$G,2,FALSE)) | D9: =IF(E9="","",VLOOKUP($E9,códigos!$E:$F,2,FALSE)) | K9: =IF($C9="","",VLOOKUP(C9,códigos!$B:$C,2,FALSE)) | N9: {=INDEX(códigos!E:E,MATCH(D9,códigos!F:F,0))} -> #N/A
A10: 6 | B10: =IF($E10="","",VLOOKUP(D10,códigos!$F:$G,2,FALSE)) | D10: =IF(E10="","",VLOOKUP($E10,códigos!$E:$F,2,FALSE)) | K10: =IF($C10="","",VLOOKUP(C10,códigos!$B:$C,2,FALSE)) | N10: {=INDEX(códigos!E:E,MATCH(D10,códigos!F:F,0))} -> #N/A
A11: 6 | B11: =IF($E11="","",VLOOKUP(D11,códigos!$F:$G,2,FALSE)) | D11: =IF(E11="","",VLOOKUP($E11,códigos!$E:$F,2,FALSE)) | K11: =IF($C11="","",VLOOKUP(C11,códigos!$B:$C,2,FALSE)) | N11: {=INDEX(códigos!E:E,MATCH(D11,códigos!F:F,0))} -> #N/A
A12: 6 | B12: =IF($E12="","",VLOOKUP(D12,códigos!$F:$G,2,FALSE)) | D12: =IF(E12="","",VLOOKUP($E12,códigos!$E:$F,2,FALSE)) | K12: =IF($C12="","",VLOOKUP(C12,códigos!$B:$C,2,FALSE)) | N12: {=INDEX(códigos!E:E,MATCH(D12,códigos!F:F,0))} -> #N/A
A13: 6 | B13: =IF($E13="","",VLOOKUP(D13,códigos!$F:$G,2,FALSE)) | D13: =IF(E13="","",VLOOKUP($E13,códigos!$E:$F,2,FALSE)) | K13: =IF($C13="","",VLOOKUP(C13,códigos!$B:$C,2,FALSE)) | N13: {=INDEX(códigos!E:E,MATCH(D13,códigos!F:F,0))} -> #N/A
A14: 6 | B14: =IF($E14="","",VLOOKUP(D14,códigos!$F:$G,2,FALSE)) | D14: =IF(E14="","",VLOOKUP($E14,códigos!$E:$F,2,FALSE)) | K14: =IF($C14="","",VLOOKUP(C14,códigos!$B:$C,2,FALSE)) | N14: {=INDEX(códigos!E:E,MATCH(D14,códigos!F:F,0))} -> #N/A
A15: 6 | B15: =IF($E15="","",VLOOKUP(D15,códigos!$F:$G,2,FALSE)) | D15: =IF(E15="","",VLOOKUP($E15,códigos!$E:$F,2,FALSE)) | K15: =IF($C15="","",VLOOKUP(C15,códigos!$B:$C,2,FALSE)) | N15: {=INDEX(códigos!E:E,MATCH(D15,códigos!F:F,0))} -> #N/A
A16: 6 | B16: =IF($E16="","",VLOOKUP(D16,códigos!$F:$G,2,FALSE)) | D16: =IF(E16="","",VLOOKUP($E16,códigos!$E:$F,2,FALSE)) | K16: =IF($C16="","",VLOOKUP(C16,códigos!$B:$C,2,FALSE)) | N16: {=INDEX(códigos!E:E,MATCH(D16,códigos!F:F,0))} -> #N/A
... A30: 6 | B30: =IF($E30="","",VLOOKUP(D30,códigos!$F:$G,2,FALSE)) | D30: =IF(E30="","",VLOOKUP($E30,códigos!$E:$F,2,FALSE)) | K30: =IF($C30="","",VLOOKUP(C30,códigos!$B:$C,2,FALSE)) | N30: {=INDEX(códigos!E:E,MATCH(D30,códigos!F:F,0))} -> #N/A
E53: ORL
E103: ORL
E153: ORL
E203: ORL
E253: ORL
E303: ORL
E353: ORL
E403: ORL
E453: ORL
E503: ORL
E553: ORL
E603: ORL
... E853: ORL

Sheet JULIO
B1: PETICIONES ORL 2026
A3: MES | B3: VISITADOR | C3: CENTRO | D3: COD.CONTRATO | E3: ORL | F3: ACCION MKT | G3: CATEGORÍAS | H3: FECHA P/ | I3: FECHA PETICION | J3: IMPORTE | K3: EMPRESA | L3: OBSERVACIONES
A4: 7 | B4: =IF($E4="","",VLOOKUP(D4,códigos!$F:$G,2,FALSE)) | C4: Clínica | D4: =IF(E4="","",VLOOKUP($E4,códigos!$E:$F,2,FALSE)) | K4: =IF($C4="","",VLOOKUP(C4,códigos!$B:$C,2,FALSE)) -> Empresa | N4: {=INDEX(códigos!E:E,MATCH(D4,códigos!F:F,0))} -> #N/A
A5: 7 | B5: =IF($E5="","",VLOOKUP(D5,códigos!$F:$G,2,FALSE)) | D5: =IF(E5="","",VLOOKUP($E5,códigos!$E:$F,2,FALSE)) | K5: =IF($C5="","",VLOOKUP(C5,códigos!$B:$C,2,FALSE)) | N5: {=INDEX(códigos!E:E,MATCH(D5,códigos!F:F,0))} -> #N/A
A6: 7 | B6: =IF($E6="","",VLOOKUP(D6,códigos!$F:$G,2,FALSE)) | D6: =IF(E6="","",VLOOKUP($E6,códigos!$E:$F,2,FALSE)) | K6: =IF($C6="","",VLOOKUP(C6,códigos!$B:$C,2,FALSE)) | N6: {=INDEX(códigos!E:E,MATCH(D6,códigos!F:F,0))} -> #N/A
A7: 7 | B7: =IF($E7="","",VLOOKUP(D7,códigos!$F:$G,2,FALSE)) | D7: =IF(E7="","",VLOOKUP($E7,códigos!$E:$F,2,FALSE)) | K7: =IF($C7="","",VLOOKUP(C7,códigos!$B:$C,2,FALSE)) | N7: {=INDEX(códigos!E:E,MATCH(D7,códigos!F:F,0))} -> #N/A
A8: 7 | B8: =IF($E8="","",VLOOKUP(D8,códigos!$F:$G,2,FALSE)) | D8: =IF(E8="","",VLOOKUP($E8,códigos!$E:$F,2,FALSE)) | K8: =IF($C8="","",VLOOKUP(C8,códigos!$B:$C,2,FALSE)) | N8: {=INDEX(códigos!E:E,MATCH(D8,códigos!F:F,0))} -> #N/A
A9: 7 | B9: =IF($E9="","",VLOOKUP(D9,códigos!$F:$G,2,FALSE)) | D9: =IF(E9="","",VLOOKUP($E9,códigos!$E:$F,2,FALSE)) | K9: =IF($C9="","",VLOOKUP(C9,códigos!$B:$C,2,FALSE)) | N9: {=INDEX(códigos!E:E,MATCH(D9,códigos!F:F,0))} -> #N/A
A10: 7 | B10: =IF($E10="","",VLOOKUP(D10,códigos!$F:$G,2,FALSE)) | D10: =IF(E10="","",VLOOKUP($E10,códigos!$E:$F,2,FALSE)) | K10: =IF($C10="","",VLOOKUP(C10,códigos!$B:$C,2,FALSE)) | N10: {=INDEX(códigos!E:E,MATCH(D10,códigos!F:F,0))} -> #N/A
A11: 7 | B11: =IF($E11="","",VLOOKUP(D11,códigos!$F:$G,2,FALSE)) | D11: =IF(E11="","",VLOOKUP($E11,códigos!$E:$F,2,FALSE)) | K11: =IF($C11="","",VLOOKUP(C11,códigos!$B:$C,2,FALSE)) | N11: {=INDEX(códigos!E:E,MATCH(D11,códigos!F:F,0))} -> #N/A
A12: 7 | B12: =IF($E12="","",VLOOKUP(D12,códigos!$F:$G,2,FALSE)) | D12: =IF(E12="","",VLOOKUP($E12,códigos!$E:$F,2,FALSE)) | K12: =IF($C12="","",VLOOKUP(C12,códigos!$B:$C,2,FALSE)) | N12: {=INDEX(códigos!E:E,MATCH(D12,códigos!F:F,0))} -> #N/A
A13: 7 | B13: =IF($E13="","",VLOOKUP(D13,códigos!$F:$G,2,FALSE)) | D13: =IF(E13="","",VLOOKUP($E13,códigos!$E:$F,2,FALSE)) | K13: =IF($C13="","",VLOOKUP(C13,códigos!$B:$C,2,FALSE)) | N13: {=INDEX(códigos!E:E,MATCH(D13,códigos!F:F,0))} -> #N/A
A14: 7 | B14: =IF($E14="","",VLOOKUP(D14,códigos!$F:$G,2,FALSE)) | D14: =IF(E14="","",VLOOKUP($E14,códigos!$E:$F,2,FALSE)) | K14: =IF($C14="","",VLOOKUP(C14,códigos!$B:$C,2,FALSE)) | N14: {=INDEX(códigos!E:E,MATCH(D14,códigos!F:F,0))} -> #N/A
A15: 7 | B15: =IF($E15="","",VLOOKUP(D15,códigos!$F:$G,2,FALSE)) | D15: =IF(E15="","",VLOOKUP($E15,códigos!$E:$F,2,FALSE)) | K15: =IF($C15="","",VLOOKUP(C15,códigos!$B:$C,2,FALSE)) | N15: {=INDEX(códigos!E:E,MATCH(D15,códigos!F:F,0))} -> #N/A
A16: 7 | B16: =IF($E16="","",VLOOKUP(D16,códigos!$F:$G,2,FALSE)) | D16: =IF(E16="","",VLOOKUP($E16,códigos!$E:$F,2,FALSE)) | K16: =IF($C16="","",VLOOKUP(C16,códigos!$B:$C,2,FALSE))
A17: 7 | B17: =IF($E17="","",VLOOKUP(D17,códigos!$F:$G,2,FALSE)) | D17: =IF(E17="","",VLOOKUP($E17,códigos!$E:$F,2,FALSE)) | K17: =IF($C17="","",VLOOKUP(C17,códigos!$B:$C,2,FALSE))
A18: 7 | B18: =IF($E18="","",VLOOKUP(D18,códigos!$F:$G,2,FALSE)) | D18: =IF(E18="","",VLOOKUP($E18,códigos!$E:$F,2,FALSE)) | K18: =IF($C18="","",VLOOKUP(C18,códigos!$B:$C,2,FALSE))
A19: 7 | B19: =IF($E19="","",VLOOKUP(D19,códigos!$F:$G,2,FALSE)) | D19: =IF(E19="","",VLOOKUP($E19,códigos!$E:$F,2,FALSE)) | K19: =IF($C19="","",VLOOKUP(C19,códigos!$B:$C,2,FALSE))
A20: 7 | B20: =IF($E20="","",VLOOKUP(D20,códigos!$F:$G,2,FALSE)) | D20: =IF(E20="","",VLOOKUP($E20,códigos!$E:$F,2,FALSE)) | K20: =IF($C20="","",VLOOKUP(C20,códigos!$B:$C,2,FALSE))
A21: 7 | B21: =IF($E21="","",VLOOKUP(D21,códigos!$F:$G,2,FALSE)) | D21: =IF(E21="","",VLOOKUP($E21,códigos!$E:$F,2,FALSE)) | K21: =IF($C21="","",VLOOKUP(C21,códigos!$B:$C,2,FALSE))
A22: 7 | B22: =IF($E22="","",VLOOKUP(D22,códigos!$F:$G,2,FALSE)) | D22: =IF(E22="","",VLOOKUP($E22,códigos!$E:$F,2,FALSE)) | K22: =IF($C22="","",VLOOKUP(C22,códigos!$B:$C,2,FALSE))
A23: 7 | B23: =IF($E23="","",VLOOKUP(D23,códigos!$F:$G,2,FALSE)) | D23: =IF(E23="","",VLOOKUP($E23,códigos!$E:$F,2,FALSE)) | K23: =IF($C23="","",VLOOKUP(C23,códigos!$B:$C,2,FALSE))
A24: 7 | B24: =IF($E24="","",VLOOKUP(D24,códigos!$F:$G,2,FALSE)) | D24: =IF(E24="","",VLOOKUP($E24,códigos!$E:$F,2,FALSE)) | K24: =IF($C24="","",VLOOKUP(C24,códigos!$B:$C,2,FALSE))
A25: 7 | B25: =IF($E25="","",VLOOKUP(D25,códigos!$F:$G,2,FALSE)) | D25: =IF(E25="","",VLOOKUP($E25,códigos!$E:$F,2,FALSE)) | K25: =IF($C25="","",VLOOKUP(C25,códigos!$B:$C,2,FALSE))
A26: 7 | B26: =IF($E26="","",VLOOKUP(D26,códigos!$F:$G,2,FALSE)) | D26: =IF(E26="","",VLOOKUP($E26,códigos!$E:$F,2,FALSE)) | K26: =IF($C26="","",VLOOKUP(C26,códigos!$B:$C,2,FALSE))
A27: 7 | B27: =IF($E27="","",VLOOKUP(D27,códigos!$F:$G,2,FALSE)) | D27: =IF(E27="","",VLOOKUP($E27,códigos!$E:$F,2,FALSE)) | K27: =IF($C27="","",VLOOKUP(C27,códigos!$B:$C,2,FALSE))
... A30: 7 | B30: =IF($E30="","",VLOOKUP(D30,códigos!$F:$G,2,FALSE)) | D30: =IF(E30="","",VLOOKUP($E30,códigos!$E:$F,2,FALSE)) | K30: =IF($C30="","",VLOOKUP(C30,códigos!$B:$C,2,FALSE))
E53: ORL
E103: ORL
E153: ORL
E203: ORL
E253: ORL
E303: ORL
E353: ORL
E403: ORL
E453: ORL
E503: ORL
E553: ORL
E603: ORL
... E853: ORL

Sheet AGOSTO
B1: PETICIONES ORL 2026
A3: MES | B3: VISITADOR | C3: CENTRO | D3: COD.CONTRATO | E3: ORL | F3: ACCION MKT | G3: CATEGORÍAS | H3: FECHA P/ | I3: FECHA PETICION | J3: IMPORTE | K3: EMPRESA | L3: OBSERVACIONES
A4: 8 | B4: =IF($E4="","",VLOOKUP(D4,códigos!$F:$G,2,FALSE)) | C4: Clínica | D4: =IF(E4="","",VLOOKUP($E4,códigos!$E:$F,2,FALSE)) | K4: =IF($C4="","",VLOOKUP(C4,códigos!$B:$C,2,FALSE)) -> Empresa
A5: 8 | B5: =IF($E5="","",VLOOKUP(D5,códigos!$F:$G,2,FALSE)) | D5: =IF(E5="","",VLOOKUP($E5,códigos!$E:$F,2,FALSE)) | K5: =IF($C5="","",VLOOKUP(C5,códigos!$B:$C,2,FALSE)) | N5: {=INDEX(códigos!E:E,MATCH(D5,códigos!F:F,0))} -> #N/A
A6: 8 | B6: =IF($E6="","",VLOOKUP(D6,códigos!$F:$G,2,FALSE)) | D6: =IF(E6="","",VLOOKUP($E6,códigos!$E:$F,2,FALSE)) | K6: =IF($C6="","",VLOOKUP(C6,códigos!$B:$C,2,FALSE)) | N6: {=INDEX(códigos!E:E,MATCH(D6,códigos!F:F,0))} -> #N/A
A7: 8 | B7: =IF($E7="","",VLOOKUP(D7,códigos!$F:$G,2,FALSE)) | D7: =IF(E7="","",VLOOKUP($E7,códigos!$E:$F,2,FALSE)) | K7: =IF($C7="","",VLOOKUP(C7,códigos!$B:$C,2,FALSE)) | N7: {=INDEX(códigos!E:E,MATCH(D7,códigos!F:F,0))} -> #N/A
A8: 8 | B8: =IF($E8="","",VLOOKUP(D8,códigos!$F:$G,2,FALSE)) | D8: =IF(E8="","",VLOOKUP($E8,códigos!$E:$F,2,FALSE)) | K8: =IF($C8="","",VLOOKUP(C8,códigos!$B:$C,2,FALSE)) | N8: {=INDEX(códigos!E:E,MATCH(D8,códigos!F:F,0))} -> #N/A
A9: 8 | B9: =IF($E9="","",VLOOKUP(D9,códigos!$F:$G,2,FALSE)) | D9: =IF(E9="","",VLOOKUP($E9,códigos!$E:$F,2,FALSE)) | K9: =IF($C9="","",VLOOKUP(C9,códigos!$B:$C,2,FALSE)) | N9: {=INDEX(códigos!E:E,MATCH(D9,códigos!F:F,0))} -> #N/A
A10: 8 | B10: =IF($E10="","",VLOOKUP(D10,códigos!$F:$G,2,FALSE)) | D10: =IF(E10="","",VLOOKUP($E10,códigos!$E:$F,2,FALSE)) | K10: =IF($C10="","",VLOOKUP(C10,códigos!$B:$C,2,FALSE))
A11: 8 | B11: =IF($E11="","",VLOOKUP(D11,códigos!$F:$G,2,FALSE)) | D11: =IF(E11="","",VLOOKUP($E11,códigos!$E:$F,2,FALSE)) | K11: =IF($C11="","",VLOOKUP(C11,códigos!$B:$C,2,FALSE))
A12: 8 | B12: =IF($E12="","",VLOOKUP(D12,códigos!$F:$G,2,FALSE)) | D12: =IF(E12="","",VLOOKUP($E12,códigos!$E:$F,2,FALSE)) | K12: =IF($C12="","",VLOOKUP(C12,códigos!$B:$C,2,FALSE))
A13: 8 | B13: =IF($E13="","",VLOOKUP(D13,códigos!$F:$G,2,FALSE)) | D13: =IF(E13="","",VLOOKUP($E13,códigos!$E:$F,2,FALSE)) | K13: =IF($C13="","",VLOOKUP(C13,códigos!$B:$C,2,FALSE))
A14: 8 | B14: =IF($E14="","",VLOOKUP(D14,códigos!$F:$G,2,FALSE)) | D14: =IF(E14="","",VLOOKUP($E14,códigos!$E:$F,2,FALSE)) | K14: =IF($C14="","",VLOOKUP(C14,códigos!$B:$C,2,FALSE))
A15: 8 | B15: =IF($E15="","",VLOOKUP(D15,códigos!$F:$G,2,FALSE)) | D15: =IF(E15="","",VLOOKUP($E15,códigos!$E:$F,2,FALSE)) | K15: =IF($C15="","",VLOOKUP(C15,códigos!$B:$C,2,FALSE))
A16: 8 | B16: =IF($E16="","",VLOOKUP(D16,códigos!$F:$G,2,FALSE)) | D16: =IF(E16="","",VLOOKUP($E16,códigos!$E:$F,2,FALSE)) | K16: =IF($C16="","",VLOOKUP(C16,códigos!$B:$C,2,FALSE))
A17: 8 | B17: =IF($E17="","",VLOOKUP(D17,códigos!$F:$G,2,FALSE)) | D17: =IF(E17="","",VLOOKUP($E17,códigos!$E:$F,2,FALSE)) | K17: =IF($C17="","",VLOOKUP(C17,códigos!$B:$C,2,FALSE))
A18: 8 | B18: =IF($E18="","",VLOOKUP(D18,códigos!$F:$G,2,FALSE)) | D18: =IF(E18="","",VLOOKUP($E18,códigos!$E:$F,2,FALSE)) | K18: =IF($C18="","",VLOOKUP(C18,códigos!$B:$C,2,FALSE))
A19: 8 | B19: =IF($E19="","",VLOOKUP(D19,códigos!$F:$G,2,FALSE)) | D19: =IF(E19="","",VLOOKUP($E19,códigos!$E:$F,2,FALSE)) | K19: =IF($C19="","",VLOOKUP(C19,códigos!$B:$C,2,FALSE))
A20: 8 | B20: =IF($E20="","",VLOOKUP(D20,códigos!$F:$G,2,FALSE)) | D20: =IF(E20="","",VLOOKUP($E20,códigos!$E:$F,2,FALSE)) | K20: =IF($C20="","",VLOOKUP(C20,códigos!$B:$C,2,FALSE))
A21: 8 | B21: =IF($E21="","",VLOOKUP(D21,códigos!$F:$G,2,FALSE)) | D21: =IF(E21="","",VLOOKUP($E21,códigos!$E:$F,2,FALSE)) | K21: =IF($C21="","",VLOOKUP(C21,códigos!$B:$C,2,FALSE))
... A30: 8 | B30: =IF($E30="","",VLOOKUP(D30,códigos!$F:$G,2,FALSE)) | D30: =IF(E30="","",VLOOKUP($E30,códigos!$E:$F,2,FALSE)) | K30: =IF($C30="","",VLOOKUP(C30,códigos!$B:$C,2,FALSE))
E53: ORL
E103: ORL
E153: ORL
E203: ORL
E253: ORL
E303: ORL
E353: ORL
E403: ORL
E453: ORL
E503: ORL
E553: ORL
E603: ORL
... E853: ORL

Sheet SEPTIEMBRE
B1: PETICIONES ORL 2026
A3: MES | B3: VISITADOR | C3: CENTRO | D3: COD.CONTRATO | E3: ORL | F3: ACCION MKT | G3: CATEGORÍAS | H3: FECHA P/ | I3: FECHA PETICION | J3: IMPORTE | K3: EMPRESA | L3: OBSERVACIONES
A4: 9 | B4: =IF($E4="","",VLOOKUP(D4,códigos!$F:$G,2,FALSE)) | C4: Clínica | D4: =IF(E4="","",VLOOKUP($E4,códigos!$E:$F,2,FALSE)) | K4: =IF($C4="","",VLOOKUP(C4,códigos!$B:$C,2,FALSE)) -> Empresa | N4: {=INDEX(códigos!E:E,MATCH(D4,códigos!F:F,0))} -> #N/A
A5: 9 | B5: =IF($E5="","",VLOOKUP(D5,códigos!$F:$G,2,FALSE)) | D5: =IF(E5="","",VLOOKUP($E5,códigos!$E:$F,2,FALSE)) | K5: =IF($C5="","",VLOOKUP(C5,códigos!$B:$C,2,FALSE)) | N5: {=INDEX(códigos!E:E,MATCH(D5,códigos!F:F,0))} -> #N/A
A6: 9 | B6: =IF($E6="","",VLOOKUP(D6,códigos!$F:$G,2,FALSE)) | D6: =IF(E6="","",VLOOKUP($E6,códigos!$E:$F,2,FALSE)) | K6: =IF($C6="","",VLOOKUP(C6,códigos!$B:$C,2,FALSE)) | N6: {=INDEX(códigos!E:E,MATCH(D6,códigos!F:F,0))} -> #N/A
A7: 9 | B7: =IF($E7="","",VLOOKUP(D7,códigos!$F:$G,2,FALSE)) | D7: =IF(E7="","",VLOOKUP($E7,códigos!$E:$F,2,FALSE)) | K7: =IF($C7="","",VLOOKUP(C7,códigos!$B:$C,2,FALSE)) | N7: {=INDEX(códigos!E:E,MATCH(D7,códigos!F:F,0))} -> #N/A
A8: 9 | B8: =IF($E8="","",VLOOKUP(D8,códigos!$F:$G,2,FALSE)) | D8: =IF(E8="","",VLOOKUP($E8,códigos!$E:$F,2,FALSE)) | K8: =IF($C8="","",VLOOKUP(C8,códigos!$B:$C,2,FALSE)) | N8: {=INDEX(códigos!E:E,MATCH(D8,códigos!F:F,0))} -> #N/A
A9: 9 | B9: =IF($E9="","",VLOOKUP(D9,códigos!$F:$G,2,FALSE)) | D9: =IF(E9="","",VLOOKUP($E9,códigos!$E:$F,2,FALSE)) | K9: =IF($C9="","",VLOOKUP(C9,códigos!$B:$C,2,FALSE)) | N9: {=INDEX(códigos!E:E,MATCH(D9,códigos!F:F,0))} -> #N/A
A10: 9 | B10: =IF($E10="","",VLOOKUP(D10,códigos!$F:$G,2,FALSE)) | D10: =IF(E10="","",VLOOKUP($E10,códigos!$E:$F,2,FALSE)) | K10: =IF($C10="","",VLOOKUP(C10,códigos!$B:$C,2,FALSE)) | N10: {=INDEX(códigos!E:E,MATCH(D10,códigos!F:F,0))} -> #N/A
A11: 9 | B11: =IF($E11="","",VLOOKUP(D11,códigos!$F:$G,2,FALSE)) | D11: =IF(E11="","",VLOOKUP($E11,códigos!$E:$F,2,FALSE)) | K11: =IF($C11="","",VLOOKUP(C11,códigos!$B:$C,2,FALSE)) | N11: {=INDEX(códigos!E:E,MATCH(D11,códigos!F:F,0))} -> #N/A
A12: 9 | B12: =IF($E12="","",VLOOKUP(D12,códigos!$F:$G,2,FALSE)) | D12: =IF(E12="","",VLOOKUP($E12,códigos!$E:$F,2,FALSE)) | K12: =IF($C12="","",VLOOKUP(C12,códigos!$B:$C,2,FALSE)) | N12: {=INDEX(códigos!E:E,MATCH(D12,códigos!F:F,0))} -> #N/A
A13: 9 | B13: =IF($E13="","",VLOOKUP(D13,códigos!$F:$G,2,FALSE)) | D13: =IF(E13="","",VLOOKUP($E13,códigos!$E:$F,2,FALSE)) | K13: =IF($C13="","",VLOOKUP(C13,códigos!$B:$C,2,FALSE)) | N13: {=INDEX(códigos!E:E,MATCH(D13,códigos!F:F,0))} -> #N/A
A14: 9 | B14: =IF($E14="","",VLOOKUP(D14,códigos!$F:$G,2,FALSE)) | D14: =IF(E14="","",VLOOKUP($E14,códigos!$E:$F,2,FALSE)) | K14: =IF($C14="","",VLOOKUP(C14,códigos!$B:$C,2,FALSE)) | N14: {=INDEX(códigos!E:E,MATCH(D14,códigos!F:F,0))} -> #N/A
A15: 9 | B15: =IF($E15="","",VLOOKUP(D15,códigos!$F:$G,2,FALSE)) | D15: =IF(E15="","",VLOOKUP($E15,códigos!$E:$F,2,FALSE)) | K15: =IF($C15="","",VLOOKUP(C15,códigos!$B:$C,2,FALSE)) | N15: {=INDEX(códigos!E:E,MATCH(D15,códigos!F:F,0))} -> #N/A
A16: 9 | B16: =IF($E16="","",VLOOKUP(D16,códigos!$F:$G,2,FALSE)) | D16: =IF(E16="","",VLOOKUP($E16,códigos!$E:$F,2,FALSE)) | K16: =IF($C16="","",VLOOKUP(C16,códigos!$B:$C,2,FALSE)) | N16: {=INDEX(códigos!E:E,MATCH(D16,códigos!F:F,0))} -> #N/A
... A20: 9 | B20: =IF($E20="","",VLOOKUP(D20,códigos!$F:$G,2,FALSE)) | D20: =IF(E20="","",VLOOKUP($E20,códigos!$E:$F,2,FALSE)) | K20: =IF($C20="","",VLOOKUP(C20,códigos!$B:$C,2,FALSE)) | N20: {=INDEX(códigos!E:E,MATCH(D20,códigos!F:F,0))} -> #N/A
A21: 9 | B21: =IF($E21="","",VLOOKUP(D21,códigos!$F:$G,2,FALSE)) | D21: =IF(E21="","",VLOOKUP($E21,códigos!$E:$F,2,FALSE)) | K21: =IF($C21="","",VLOOKUP(C21,códigos!$B:$C,2,FALSE))
A22: 9 | B22: =IF($E22="","",VLOOKUP(D22,códigos!$F:$G,2,FALSE)) | D22: =IF(E22="","",VLOOKUP($E22,códigos!$E:$F,2,FALSE)) | K22: =IF($C22="","",VLOOKUP(C22,códigos!$B:$C,2,FALSE))
A23: 9 | B23: =IF($E23="","",VLOOKUP(D23,códigos!$F:$G,2,FALSE)) | D23: =IF(E23="","",VLOOKUP($E23,códigos!$E:$F,2,FALSE)) | K23: =IF($C23="","",VLOOKUP(C23,códigos!$B:$C,2,FALSE))
A24: 9 | B24: =IF($E24="","",VLOOKUP(D24,códigos!$F:$G,2,FALSE)) | D24: =IF(E24="","",VLOOKUP($E24,códigos!$E:$F,2,FALSE)) | K24: =IF($C24="","",VLOOKUP(C24,códigos!$B:$C,2,FALSE))
A25: 9 | B25: =IF($E25="","",VLOOKUP(D25,códigos!$F:$G,2,FALSE)) | D25: =IF(E25="","",VLOOKUP($E25,códigos!$E:$F,2,FALSE)) | K25: =IF($C25="","",VLOOKUP(C25,códigos!$B:$C,2,FALSE))
A26: 9 | B26: =IF($E26="","",VLOOKUP(D26,códigos!$F:$G,2,FALSE)) | D26: =IF(E26="","",VLOOKUP($E26,códigos!$E:$F,2,FALSE)) | K26: =IF($C26="","",VLOOKUP(C26,códigos!$B:$C,2,FALSE))
A27: 9 | B27: =IF($E27="","",VLOOKUP(D27,códigos!$F:$G,2,FALSE)) | D27: =IF(E27="","",VLOOKUP($E27,códigos!$E:$F,2,FALSE)) | K27: =IF($C27="","",VLOOKUP(C27,códigos!$B:$C,2,FALSE))
A28: 9 | B28: =IF($E28="","",VLOOKUP(D28,códigos!$F:$G,2,FALSE)) | D28: =IF(E28="","",VLOOKUP($E28,códigos!$E:$F,2,FALSE)) | K28: =IF($C28="","",VLOOKUP(C28,códigos!$B:$C,2,FALSE))
A29: 9 | B29: =IF($E29="","",VLOOKUP(D29,códigos!$F:$G,2,FALSE)) | D29: =IF(E29="","",VLOOKUP($E29,códigos!$E:$F,2,FALSE)) | K29: =IF($C29="","",VLOOKUP(C29,códigos!$B:$C,2,FALSE))
A30: 9 | B30: =IF($E30="","",VLOOKUP(D30,códigos!$F:$G,2,FALSE)) | D30: =IF(E30="","",VLOOKUP($E30,códigos!$E:$F,2,FALSE)) | K30: =IF($C30="","",VLOOKUP(C30,códigos!$B:$C,2,FALSE))
E53: ORL
E103: ORL
E153: ORL
E203: ORL
E253: ORL
E303: ORL
E353: ORL
E403: ORL
E453: ORL
E503: ORL
E553: ORL
E603: ORL
... E853: ORL

Sheet OCTUBRE
B1: PETICIONES ORL 2026
A3: MES | B3: VISITADOR | C3: CENTRO | D3: COD.CONTRATO | E3: ORL | F3: ACCION MKT | G3: CATEGORÍAS | H3: FECHA P/ | I3: FECHA PETICION | J3: IMPORTE | K3: EMPRESA | L3: OBSERVACIONES
A4: 10 | B4: =IF($E4="","",VLOOKUP(D4,códigos!$F:$G,2,FALSE)) | C4: Clínica | D4: =IF(E4="","",VLOOKUP($E4,códigos!$E:$F,2,FALSE)) | K4: =IF($C4="","",VLOOKUP(C4,códigos!$B:$C,2,FALSE)) -> Empresa | N4: {=INDEX(códigos!E:E,MATCH(D4,códigos!F:F,0))} -> #N/A
A5: 10 | B5: =IF($E5="","",VLOOKUP(D5,códigos!$F:$G,2,FALSE)) | D5: =IF(E5="","",VLOOKUP($E5,códigos!$E:$F,2,FALSE)) | K5: =IF($C5="","",VLOOKUP(C5,códigos!$B:$C,2,FALSE)) | N5: {=INDEX(códigos!E:E,MATCH(D5,códigos!F:F,0))} -> #N/A
A6: 10 | B6: =IF($E6="","",VLOOKUP(D6,códigos!$F:$G,2,FALSE)) | D6: =IF(E6="","",VLOOKUP($E6,códigos!$E:$F,2,FALSE)) | K6: =IF($C6="","",VLOOKUP(C6,códigos!$B:$C,2,FALSE)) | N6: {=INDEX(códigos!E:E,MATCH(D6,códigos!F:F,0))} -> #N/A
A7: 10 | B7: =IF($E7="","",VLOOKUP(D7,códigos!$F:$G,2,FALSE)) | D7: =IF(E7="","",VLOOKUP($E7,códigos!$E:$F,2,FALSE)) | K7: =IF($C7="","",VLOOKUP(C7,códigos!$B:$C,2,FALSE)) | N7: {=INDEX(códigos!E:E,MATCH(D7,códigos!F:F,0))} -> #N/A
A8: 10 | B8: =IF($E8="","",VLOOKUP(D8,códigos!$F:$G,2,FALSE)) | D8: =IF(E8="","",VLOOKUP($E8,códigos!$E:$F,2,FALSE)) | K8: =IF($C8="","",VLOOKUP(C8,códigos!$B:$C,2,FALSE)) | N8: {=INDEX(códigos!E:E,MATCH(D8,códigos!F:F,0))} -> #N/A
A9: 10 | B9: =IF($E9="","",VLOOKUP(D9,códigos!$F:$G,2,FALSE)) | D9: =IF(E9="","",VLOOKUP($E9,códigos!$E:$F,2,FALSE)) | K9: =IF($C9="","",VLOOKUP(C9,códigos!$B:$C,2,FALSE)) | N9: {=INDEX(códigos!E:E,MATCH(D9,códigos!F:F,0))} -> #N/A
A10: 10 | B10: =IF($E10="","",VLOOKUP(D10,códigos!$F:$G,2,FALSE)) | D10: =IF(E10="","",VLOOKUP($E10,códigos!$E:$F,2,FALSE)) | K10: =IF($C10="","",VLOOKUP(C10,códigos!$B:$C,2,FALSE)) | N10: {=INDEX(códigos!E:E,MATCH(D10,códigos!F:F,0))} -> #N/A
A11: 10 | B11: =IF($E11="","",VLOOKUP(D11,códigos!$F:$G,2,FALSE)) | D11: =IF(E11="","",VLOOKUP($E11,códigos!$E:$F,2,FALSE)) | K11: =IF($C11="","",VLOOKUP(C11,códigos!$B:$C,2,FALSE)) | N11: {=INDEX(códigos!E:E,MATCH(D11,códigos!F:F,0))} -> #N/A
A12: 10 | B12: =IF($E12="","",VLOOKUP(D12,códigos!$F:$G,2,FALSE)) | D12: =IF(E12="","",VLOOKUP($E12,códigos!$E:$F,2,FALSE)) | K12: =IF($C12="","",VLOOKUP(C12,códigos!$B:$C,2,FALSE)) | N12: {=INDEX(códigos!E:E,MATCH(D12,códigos!F:F,0))} -> #N/A
A13: 10 | B13: =IF($E13="","",VLOOKUP(D13,códigos!$F:$G,2,FALSE)) | D13: =IF(E13="","",VLOOKUP($E13,códigos!$E:$F,2,FALSE)) | K13: =IF($C13="","",VLOOKUP(C13,códigos!$B:$C,2,FALSE)) | N13: {=INDEX(códigos!E:E,MATCH(D13,códigos!F:F,0))} -> #N/A
A14: 10 | B14: =IF($E14="","",VLOOKUP(D14,códigos!$F:$G,2,FALSE)) | D14: =IF(E14="","",VLOOKUP($E14,códigos!$E:$F,2,FALSE)) | K14: =IF($C14="","",VLOOKUP(C14,códigos!$B:$C,2,FALSE)) | N14: {=INDEX(códigos!E:E,MATCH(D14,códigos!F:F,0))} -> #N/A
A15: 10 | B15: =IF($E15="","",VLOOKUP(D15,códigos!$F:$G,2,FALSE)) | D15: =IF(E15="","",VLOOKUP($E15,códigos!$E:$F,2,FALSE)) | K15: =IF($C15="","",VLOOKUP(C15,códigos!$B:$C,2,FALSE)) | N15: {=INDEX(códigos!E:E,MATCH(D15,códigos!F:F,0))} -> #N/A
A16: 10 | B16: =IF($E16="","",VLOOKUP(D16,códigos!$F:$G,2,FALSE)) | D16: =IF(E16="","",VLOOKUP($E16,códigos!$E:$F,2,FALSE)) | K16: =IF($C16="","",VLOOKUP(C16,códigos!$B:$C,2,FALSE)) | N16: {=INDEX(códigos!E:E,MATCH(D16,códigos!F:F,0))} -> #N/A
... A25: 10 | B25: =IF($E25="","",VLOOKUP(D25,códigos!$F:$G,2,FALSE)) | D25: =IF(E25="","",VLOOKUP($E25,códigos!$E:$F,2,FALSE)) | K25: =IF($C25="","",VLOOKUP(C25,códigos!$B:$C,2,FALSE)) | N25: {=INDEX(códigos!E:E,MATCH(D25,códigos!F:F,0))} -> #N/A
A26: 10 | B26: =IF($E26="","",VLOOKUP(D26,códigos!$F:$G,2,FALSE)) | D26: =IF(E26="","",VLOOKUP($E26,códigos!$E:$F,2,FALSE)) | K26: =IF($C26="","",VLOOKUP(C26,códigos!$B:$C,2,FALSE))
A27: 10 | B27: =IF($E27="","",VLOOKUP(D27,códigos!$F:$G,2,FALSE)) | D27: =IF(E27="","",VLOOKUP($E27,códigos!$E:$F,2,FALSE)) | K27: =IF($C27="","",VLOOKUP(C27,códigos!$B:$C,2,FALSE))
A28: 10 | B28: =IF($E28="","",VLOOKUP(D28,códigos!$F:$G,2,FALSE)) | D28: =IF(E28="","",VLOOKUP($E28,códigos!$E:$F,2,FALSE)) | K28: =IF($C28="","",VLOOKUP(C28,códigos!$B:$C,2,FALSE))
A29: 10 | B29: =IF($E29="","",VLOOKUP(D29,códigos!$F:$G,2,FALSE)) | D29: =IF(E29="","",VLOOKUP($E29,códigos!$E:$F,2,FALSE)) | K29: =IF($C29="","",VLOOKUP(C29,códigos!$B:$C,2,FALSE))
A30: 10 | B30: =IF($E30="","",VLOOKUP(D30,códigos!$F:$G,2,FALSE)) | D30: =IF(E30="","",VLOOKUP($E30,códigos!$E:$F,2,FALSE)) | K30: =IF($C30="","",VLOOKUP(C30,códigos!$B:$C,2,FALSE))
E53: ORL
E103: ORL
E153: ORL
E203: ORL
E253: ORL
E303: ORL
E353: ORL
E403: ORL
E453: ORL
E503: ORL
E553: ORL
E603: ORL
... E903: ORL

Sheet NOVIEMBRE
B1: PETICIONES ORL 2026
A3: MES | B3: VISITADOR | C3: CENTRO | D3: COD.CONTRATO | E3: ORL | F3: ACCION MKT | G3: CATEGORÍAS | H3: FECHA P/ | I3: FECHA PETICION | J3: IMPORTE | K3: EMPRESA | L3: OBSERVACIONES
A4: 11 | B4: =IF($E4="","",VLOOKUP(D4,códigos!$F:$G,2,FALSE)) | C4: Clínica | D4: =IF(E4="","",VLOOKUP($E4,códigos!$E:$F,2,FALSE)) | K4: =IF($C4="","",VLOOKUP(C4,códigos!$B:$C,2,FALSE)) -> Empresa | N4: {=INDEX(códigos!E:E,MATCH(D4,códigos!F:F,0))} -> #N/A
A5: 11 | B5: =IF($E5="","",VLOOKUP(D5,códigos!$F:$G,2,FALSE)) | D5: =IF(E5="","",VLOOKUP($E5,códigos!$E:$F,2,FALSE)) | K5: =IF($C5="","",VLOOKUP(C5,códigos!$B:$C,2,FALSE)) | N5: {=INDEX(códigos!E:E,MATCH(D5,códigos!F:F,0))} -> #N/A
A6: 11 | B6: =IF($E6="","",VLOOKUP(D6,códigos!$F:$G,2,FALSE)) | D6: =IF(E6="","",VLOOKUP($E6,códigos!$E:$F,2,FALSE)) | K6: =IF($C6="","",VLOOKUP(C6,códigos!$B:$C,2,FALSE)) | N6: {=INDEX(códigos!E:E,MATCH(D6,códigos!F:F,0))} -> #N/A
A7: 11 | B7: =IF($E7="","",VLOOKUP(D7,códigos!$F:$G,2,FALSE)) | D7: =IF(E7="","",VLOOKUP($E7,códigos!$E:$F,2,FALSE)) | K7: =IF($C7="","",VLOOKUP(C7,códigos!$B:$C,2,FALSE)) | N7: {=INDEX(códigos!E:E,MATCH(D7,códigos!F:F,0))} -> #N/A
A8: 11 | B8: =IF($E8="","",VLOOKUP(D8,códigos!$F:$G,2,FALSE)) | D8: =IF(E8="","",VLOOKUP($E8,códigos!$E:$F,2,FALSE)) | K8: =IF($C8="","",VLOOKUP(C8,códigos!$B:$C,2,FALSE)) | N8: {=INDEX(códigos!E:E,MATCH(D8,códigos!F:F,0))} -> #N/A
A9: 10 | B9: =IF($E9="","",VLOOKUP(D9,códigos!$F:$G,2,FALSE)) | D9: =IF(E9="","",VLOOKUP($E9,códigos!$E:$F,2,FALSE)) | K9: =IF($C9="","",VLOOKUP(C9,códigos!$B:$C,2,FALSE))
A10: 10 | B10: =IF($E10="","",VLOOKUP(D10,códigos!$F:$G,2,FALSE)) | D10: =IF(E10="","",VLOOKUP($E10,códigos!$E:$F,2,FALSE)) | K10: =IF($C10="","",VLOOKUP(C10,códigos!$B:$C,2,FALSE))
A11: 11 | B11: =IF($E11="","",VLOOKUP(D11,códigos!$F:$G,2,FALSE)) | D11: =IF(E11="","",VLOOKUP($E11,códigos!$E:$F,2,FALSE)) | K11: =IF($C11="","",VLOOKUP(C11,códigos!$B:$C,2,FALSE)) | N11: {=INDEX(códigos!E:E,MATCH(D11,códigos!F:F,0))} -> #N/A
A12: 10 | B12: =IF($E12="","",VLOOKUP(D12,códigos!$F:$G,2,FALSE)) | D12: =IF(E12="","",VLOOKUP($E12,códigos!$E:$F,2,FALSE)) | K12: =IF($C12="","",VLOOKUP(C12,códigos!$B:$C,2,FALSE))
A13: 11 | B13: =IF($E13="","",VLOOKUP(D13,códigos!$F:$G,2,FALSE)) | D13: =IF(E13="","",VLOOKUP($E13,códigos!$E:$F,2,FALSE)) | K13: =IF($C13="","",VLOOKUP(C13,códigos!$B:$C,2,FALSE)) | N13: {=INDEX(códigos!E:E,MATCH(D13,códigos!F:F,0))} -> #N/A
A14: 11 | B14: =IF($E14="","",VLOOKUP(D14,códigos!$F:$G,2,FALSE)) | D14: =IF(E14="","",VLOOKUP($E14,códigos!$E:$F,2,FALSE)) | K14: =IF($C14="","",VLOOKUP(C14,códigos!$B:$C,2,FALSE)) | N14: {=INDEX(códigos!E:E,MATCH(D14,códigos!F:F,0))} -> #N/A
A15: 11 | B15: =IF($E15="","",VLOOKUP(D15,códigos!$F:$G,2,FALSE)) | D15: =IF(E15="","",VLOOKUP($E15,códigos!$E:$F,2,FALSE)) | K15: =IF($C15="","",VLOOKUP(C15,códigos!$B:$C,2,FALSE)) | N15: {=INDEX(códigos!E:E,MATCH(D15,códigos!F:F,0))} -> #N/A
A16: 11 | B16: =IF($E16="","",VLOOKUP(D16,códigos!$F:$G,2,FALSE)) | D16: =IF(E16="","",VLOOKUP($E16,códigos!$E:$F,2,FALSE)) | K16: =IF($C16="","",VLOOKUP(C16,códigos!$B:$C,2,FALSE)) | N16: {=INDEX(códigos!E:E,MATCH(D16,códigos!F:F,0))} -> #N/A
A17: 11 | B17: =IF($E17="","",VLOOKUP(D17,códigos!$F:$G,2,FALSE)) | D17: =IF(E17="","",VLOOKUP($E17,códigos!$E:$F,2,FALSE)) | K17: =IF($C17="","",VLOOKUP(C17,códigos!$B:$C,2,FALSE)) | N17: {=INDEX(códigos!E:E,MATCH(D17,códigos!F:F,0))} -> #N/A
A18: 11 | B18: =IF($E18="","",VLOOKUP(D18,códigos!$F:$G,2,FALSE)) | D18: =IF(E18="","",VLOOKUP($E18,códigos!$E:$F,2,FALSE)) | K18: =IF($C18="","",VLOOKUP(C18,códigos!$B:$C,2,FALSE)) | N18: {=INDEX(códigos!E:E,MATCH(D18,códigos!F:F,0))} -> #N/A
A19: 11 | B19: =IF($E19="","",VLOOKUP(D19,códigos!$F:$G,2,FALSE)) | D19: =IF(E19="","",VLOOKUP($E19,códigos!$E:$F,2,FALSE)) | K19: =IF($C19="","",VLOOKUP(C19,códigos!$B:$C,2,FALSE)) | N19: {=INDEX(códigos!E:E,MATCH(D19,códigos!F:F,0))} -> #N/A
A20: 11 | B20: =IF($E20="","",VLOOKUP(D20,códigos!$F:$G,2,FALSE)) | D20: =IF(E20="","",VLOOKUP($E20,códigos!$E:$F,2,FALSE)) | K20: =IF($C20="","",VLOOKUP(C20,códigos!$B:$C,2,FALSE)) | N20: {=INDEX(códigos!E:E,MATCH(D20,códigos!F:F,0))} -> #N/A
A21: 11 | B21: =IF($E21="","",VLOOKUP(D21,códigos!$F:$G,2,FALSE)) | D21: =IF(E21="","",VLOOKUP($E21,códigos!$E:$F,2,FALSE)) | K21: =IF($C21="","",VLOOKUP(C21,códigos!$B:$C,2,FALSE))
A22: 11 | B22: =IF($E22="","",VLOOKUP(D22,códigos!$F:$G,2,FALSE)) | D22: =IF(E22="","",VLOOKUP($E22,códigos!$E:$F,2,FALSE)) | K22: =IF($C22="","",VLOOKUP(C22,códigos!$B:$C,2,FALSE)) | N22: {=INDEX(códigos!E:E,MATCH(D22,códigos!F:F,0))} -> #N/A
A23: 11 | B23: =IF($E23="","",VLOOKUP(D23,códigos!$F:$G,2,FALSE)) | D23: =IF(E23="","",VLOOKUP($E23,códigos!$E:$F,2,FALSE)) | K23: =IF($C23="","",VLOOKUP(C23,códigos!$B:$C,2,FALSE))
A24: 11 | B24: =IF($E24="","",VLOOKUP(D24,códigos!$F:$G,2,FALSE)) | D24: =IF(E24="","",VLOOKUP($E24,códigos!$E:$F,2,FALSE)) | K24: =IF($C24="","",VLOOKUP(C24,códigos!$B:$C,2,FALSE)) | N24: {=INDEX(códigos!E:E,MATCH(D24,códigos!F:F,0))} -> #N/A
A25: 11 | B25: =IF($E25="","",VLOOKUP(D25,códigos!$F:$G,2,FALSE)) | D25: =IF(E25="","",VLOOKUP($E25,códigos!$E:$F,2,FALSE)) | K25: =IF($C25="","",VLOOKUP(C25,códigos!$B:$C,2,FALSE)) | N25: {=INDEX(códigos!E:E,MATCH(D25,códigos!F:F,0))} -> #N/A
A26: 11 | B26: =IF($E26="","",VLOOKUP(D26,códigos!$F:$G,2,FALSE)) | D26: =IF(E26="","",VLOOKUP($E26,códigos!$E:$F,2,FALSE)) | K26: =IF($C26="","",VLOOKUP(C26,códigos!$B:$C,2,FALSE))
A27: 11 | B27: =IF($E27="","",VLOOKUP(D27,códigos!$F:$G,2,FALSE)) | D27: =IF(E27="","",VLOOKUP($E27,códigos!$E:$F,2,FALSE)) | K27: =IF($C27="","",VLOOKUP(C27,códigos!$B:$C,2,FALSE))
A28: 11 | B28: =IF($E28="","",VLOOKUP(D28,códigos!$F:$G,2,FALSE)) | D28: =IF(E28="","",VLOOKUP($E28,códigos!$E:$F,2,FALSE)) | K28: =IF($C28="","",VLOOKUP(C28,códigos!$B:$C,2,FALSE))
A29: 11 | B29: =IF($E29="","",VLOOKUP(D29,códigos!$F:$G,2,FALSE)) | D29: =IF(E29="","",VLOOKUP($E29,códigos!$E:$F,2,FALSE)) | K29: =IF($C29="","",VLOOKUP(C29,códigos!$B:$C,2,FALSE))
A30: 11 | B30: =IF($E30="","",VLOOKUP(D30,códigos!$F:$G,2,FALSE)) | D30: =IF(E30="","",VLOOKUP($E30,códigos!$E:$F,2,FALSE)) | K30: =IF($C30="","",VLOOKUP(C30,códigos!$B:$C,2,FALSE))
E53: ORL
E103: ORL
E153: ORL
E203: ORL
E253: ORL
E303: ORL
E353: ORL
E403: ORL
E453: ORL
E503: ORL
E553: ORL
E603: ORL
... E853: ORL

Sheet DICIEMBRE
B1: PETICIONES ORL 2026
A3: MES | B3: VISITADOR | C3: CENTRO | D3: COD.CONTRATO | E3: ORL | F3: ACCION MKT | G3: CATEGORÍAS | H3: FECHA P/ | I3: FECHA PETICION | J3: IMPORTE | K3: EMPRESA | L3: OBSERVACIONES
A4: 12 | B4: =IF($E4="","",VLOOKUP(D4,códigos!$F:$G,2,FALSE)) | C4: Clínica | D4: =IF(E4="","",VLOOKUP($E4,códigos!$E:$F,2,FALSE)) | K4: =IF($C4="","",VLOOKUP(C4,códigos!$B:$C,2,FALSE)) -> Empresa
A5: 12 | B5: =IF($E5="","",VLOOKUP(D5,códigos!$F:$G,2,FALSE)) | D5: =IF(E5="","",VLOOKUP($E5,códigos!$E:$F,2,FALSE)) | K5: =IF($C5="","",VLOOKUP(C5,códigos!$B:$C,2,FALSE)) | N5: {=INDEX(códigos!E:E,MATCH(D5,códigos!F:F,0))} -> #N/A
A6: 12 | B6: =IF($E6="","",VLOOKUP(D6,códigos!$F:$G,2,FALSE)) | D6: =IF(E6="","",VLOOKUP($E6,códigos!$E:$F,2,FALSE)) | K6: =IF($C6="","",VLOOKUP(C6,códigos!$B:$C,2,FALSE)) | N6: {=INDEX(códigos!E:E,MATCH(D6,códigos!F:F,0))} -> #N/A
A7: 12 | B7: =IF($E7="","",VLOOKUP(D7,códigos!$F:$G,2,FALSE)) | D7: =IF(E7="","",VLOOKUP($E7,códigos!$E:$F,2,FALSE)) | K7: =IF($C7="","",VLOOKUP(C7,códigos!$B:$C,2,FALSE))
A8: 12 | B8: =IF($E8="","",VLOOKUP(D8,códigos!$F:$G,2,FALSE)) | D8: =IF(E8="","",VLOOKUP($E8,códigos!$E:$F,2,FALSE)) | K8: =IF($C8="","",VLOOKUP(C8,códigos!$B:$C,2,FALSE)) | N8: {=INDEX(códigos!E:E,MATCH(D8,códigos!F:F,0))} -> #N/A
A9: 12 | B9: =IF($E9="","",VLOOKUP(D9,códigos!$F:$G,2,FALSE)) | D9: =IF(E9="","",VLOOKUP($E9,códigos!$E:$F,2,FALSE)) | K9: =IF($C9="","",VLOOKUP(C9,códigos!$B:$C,2,FALSE)) | N9: {=INDEX(códigos!E:E,MATCH(D9,códigos!F:F,0))} -> #N/A
A10: 12 | B10: =IF($E10="","",VLOOKUP(D10,códigos!$F:$G,2,FALSE)) | D10: =IF(E10="","",VLOOKUP($E10,códigos!$E:$F,2,FALSE)) | K10: =IF($C10="","",VLOOKUP(C10,códigos!$B:$C,2,FALSE)) | N10: {=INDEX(códigos!E:E,MATCH(D10,códigos!F:F,0))} -> #N/A
A11: 12 | B11: =IF($E11="","",VLOOKUP(D11,códigos!$F:$G,2,FALSE)) | D11: =IF(E11="","",VLOOKUP($E11,códigos!$E:$F,2,FALSE)) | K11: =IF($C11="","",VLOOKUP(C11,códigos!$B:$C,2,FALSE)) | N11: {=INDEX(códigos!E:E,MATCH(D11,códigos!F:F,0))} -> #N/A
A12: 12 | B12: =IF($E12="","",VLOOKUP(D12,códigos!$F:$G,2,FALSE)) | D12: =IF(E12="","",VLOOKUP($E12,códigos!$E:$F,2,FALSE)) | K12: =IF($C12="","",VLOOKUP(C12,códigos!$B:$C,2,FALSE)) | N12: {=INDEX(códigos!E:E,MATCH(D12,códigos!F:F,0))} -> #N/A
A13: 12 | B13: =IF($E13="","",VLOOKUP(D13,códigos!$F:$G,2,FALSE)) | D13: =IF(E13="","",VLOOKUP($E13,códigos!$E:$F,2,FALSE)) | K13: =IF($C13="","",VLOOKUP(C13,códigos!$B:$C,2,FALSE)) | N13: {=INDEX(códigos!E:E,MATCH(D13,códigos!F:F,0))} -> #N/A
A14: 12 | B14: =IF($E14="","",VLOOKUP(D14,códigos!$F:$G,2,FALSE)) | D14: =IF(E14="","",VLOOKUP($E14,códigos!$E:$F,2,FALSE)) | K14: =IF($C14="","",VLOOKUP(C14,códigos!$B:$C,2,FALSE)) | N14: {=INDEX(códigos!E:E,MATCH(D14,códigos!F:F,0))} -> #N/A
A15: 12 | B15: =IF($E15="","",VLOOKUP(D15,códigos!$F:$G,2,FALSE)) | D15: =IF(E15="","",VLOOKUP($E15,códigos!$E:$F,2,FALSE)) | K15: =IF($C15="","",VLOOKUP(C15,códigos!$B:$C,2,FALSE)) | N15: {=INDEX(códigos!E:E,MATCH(D15,códigos!F:F,0))} -> #N/A
A16: 12 | B16: =IF($E16="","",VLOOKUP(D16,códigos!$F:$G,2,FALSE)) | D16: =IF(E16="","",VLOOKUP($E16,códigos!$E:$F,2,FALSE)) | K16: =IF($C16="","",VLOOKUP(C16,códigos!$B:$C,2,FALSE)) | N16: {=INDEX(códigos!E:E,MATCH(D16,códigos!F:F,0))} -> #N/A
A17: 12 | B17: =IF($E17="","",VLOOKUP(D17,códigos!$F:$G,2,FALSE)) | D17: =IF(E17="","",VLOOKUP($E17,códigos!$E:$F,2,FALSE)) | K17: =IF($C17="","",VLOOKUP(C17,códigos!$B:$C,2,FALSE)) | N17: {=INDEX(códigos!E:E,MATCH(D17,códigos!F:F,0))} -> #N/A
A18: 12 | B18: =IF($E18="","",VLOOKUP(D18,códigos!$F:$G,2,FALSE)) | D18: =IF(E18="","",VLOOKUP($E18,códigos!$E:$F,2,FALSE)) | K18: =IF($C18="","",VLOOKUP(C18,códigos!$B:$C,2,FALSE)) | N18: {=INDEX(códigos!E:E,MATCH(D18,códigos!F:F,0))} -> #N/A
A19: 12 | B19: =IF($E19="","",VLOOKUP(D19,códigos!$F:$G,2,FALSE)) | D19: =IF(E19="","",VLOOKUP($E19,códigos!$E:$F,2,FALSE)) | K19: =IF($C19="","",VLOOKUP(C19,códigos!$B:$C,2,FALSE)) | N19: {=INDEX(códigos!E:E,MATCH(D19,códigos!F:F,0))} -> #N/A
... A30: 12 | B30: =IF($E30="","",VLOOKUP(D30,códigos!$F:$G,2,FALSE)) | D30: =IF(E30="","",VLOOKUP($E30,códigos!$E:$F,2,FALSE)) | K30: =IF($C30="","",VLOOKUP(C30,códigos!$B:$C,2,FALSE)) | N30: {=INDEX(códigos!E:E,MATCH(D30,códigos!F:F,0))} -> #N/A
E53: ORL
E103: ORL
E153: ORL
E203: ORL
E253: ORL
E303: ORL
E353: ORL
E403: ORL
E453: ORL
E503: ORL
E553: ORL
E603: ORL
... E853: ORL

Sheet gastosporcentro
A1: CENTRO | B1: COD.CONTRATO | C1: CATEGORÍAS | D1: SUM of IMPORTE
A2: Alcorcón | D2: -310.5
A3: Alicante | D3: -1456.5
A4: Clínica | C4: (en blanco)
A5: Total Clínica
A6: El Albir (Benidorm) | B6: ISL104 | C6: Alojamiento | D6: -285.73
C7: Congreso internacional personal | D7: -4957.1
C8: Traslado | D8: -783.74
B9: ISL54 | C9: Congreso internacional | D9: -4000
B10: RFV38 | C10: Material para centro | D10: -1500
A11: Total El Albir (Benidorm) | D11: -11526.57
A12: Fuenlabrada | D12: -7542.52
A13: Getafe | D13: -5788.4
A14: Jerez de la Frontera | D14: -5603.53
A15: Logroño | D15: -9543.92
A16: Madrid- Canillas | D16: 1759.08
A17: Madrid- Juan Bravo | D17: -5696.64
A18: Madrid- La Oca | D18: -4926.99
A19: Murcia | D19: -3416
A20: Orihuela | D20: -11084.65
A21: San Javier | D21: 2176.19
A22: Sevilla- Montoto | D22: -16868.85
A23: Torrejón De Ardoz | D23: -2978
A24: Valencia- Cadiz | B24: RFV26 | C24: Inscripción | D24: -490.51
B25: RFV48 | C25: Inscripción | D25: -133.07
A26: Total Valencia- Cadiz | D26: -623.58
A27: Valencia- Parra | D27: -899
A28: (en blanco) | B28: (en blanco) | C28: (en blanco)
A29: Total (en blanco)

Sheet solocontratosorl
A1: SUM of IMPORTE | D1: MES
A2: CONTRATO | B2: CENTRO | C2: CATEGORÍAS | D2: 2 | E2: 3 | F2: Total general
A3: ISL14 | B3: Alicante | C3: Traslado | E3: -856.98 | F3: -856.98
B4: Total Alicante | E4: -856.98 | F4: -856.98
B5: Orihuela | C5: Alojamiento y traslado | E5: -2286.1 | F5: -2286.1
C6: Inscripción | E6: -568.7 | F6: -568.7
C7: Obras acondicionamiento centro | D7: -2085.24 | F7: -2085.24
B8: Total Orihuela | D8: -2085.24 | E8: -2854.8 | F8: -4940.04
A9: Total ISL14 | D9: -2085.24 | E9: -3711.78 | F9: -5797.02
A10: Total general | D10: -2085.24 | E10: -3711.78 | F10: -5797.02

Sheet gastosorl
A1: SUM of IMPORTE | C1: MES
A2: ORL | B2: CATEGORÍAS | C2: 1 | D2: 2 | E2: 3 | F2: 4 | G2: 5 | H2: 6 | I2: 7 | J2: 8 | K2: 9 | L2: 10 | M2: 11 | N2: 12 | O2: (en blanco) | P2: Total general
A3: Abel Bogoya Castaño | B3: Inscripción
A4: Total Abel Bogoya Castaño
A5: Ainhoa García-Lliberos de Miguel | B5: Inscripción | E5: -490.51 | P5: -490.51
A6: Total Ainhoa García-Lliberos de Miguel | E6: -490.51 | P6: -490.51
A7: Ángel Onofre Pérez Coll | B7: Inscripción | E7: 2176.19 | P7: 2176.19
A8: Total Ángel Onofre Pérez Coll | E8: 2176.19 | P8: 2176.19
A9: Beatriz Santos Duque | B9: Inscripción | D9: -609.9 | P9: -609.9
A10: Total Beatriz Santos Duque | D10: -609.9 | P10: -609.9
A11: Carlos Barajas Del Rosal | B11: Gastos de personal | C11: -1398.88 | D11: -1398.88 | E11: -1398.88 | P11: -4196.64
A12: Total Carlos Barajas Del Rosal | C12: -1398.88 | D12: -1398.88 | E12: -1398.88 | P12: -4196.64
A13: Carlos Velásquez Fermín | B13: Alojamiento y traslado | E13: -2286.1 | P13: -2286.1
B14: Inscripción | E14: -568.7 | P14: -568.7
B15: Obras acondicionamiento centro | D15: -2085.24 | P15: -2085.24
B16: Traslado | E16: -856.98 | P16: -856.98
A17: Total Carlos Velásquez Fermín | D17: -2085.24 | E17: -3711.78 | P17: -5797.02
A18: Carmen Delgado Muñoz | B18: Material para centro | D18: -626.99 | P18: -626.99
A19: Total Carmen Delgado Muñoz | D19: -626.99 | P19: -626.99
A20: Cristina García García | B20: Inscripción | C20: -2772.26 | P20: -2772.26
A21: Total Cristina García García | C21: -2772.26 | P21: -2772.26
A22: Cristina Ibañez Muñoz | B22: Congreso internacional personal | C22: -4701.07 | P22: -4701.07
A23: Total Cristina Ibañez Muñoz | C23: -4701.07 | P23: -4701.07
A24: Cristina Vaduva | B24: Material para centro | E24: -2268.6 | P24: -2268.6
A25: Total Cristina Vaduva | E25: -2268.6 | P25: -2268.6
A26: Daniel Briones Crespo | B26: Alojamiento y traslado | E26: -4215.86 | P26: -4215.86
A27: Total Daniel Briones Crespo | E27: -4215.86 | P27: -4215.86
A28: Daniel Rodríguez Ocaña | B28: Inscripción | D28: -1000 | P28: -1000
A29: Total Daniel Rodríguez Ocaña | D29: -1000 | P29: -1000
A30: Daniela Carrillo Moreno | B30: Inscripción | D30: -600 | P30: -600
A31: Total Daniela Carrillo Moreno | D31: -600 | P31: -600
A32: David Castro Gutiérrez de Agüero | B32: Material para centro | C32: -1289 | F32: -899 | P32: -2188
A33: Total David Castro Gutiérrez de Agüero | C33: -1289 | F33: -899 | P33: -2188
A34: Elena González Turienzo | B34: Inscripción | C34: -133.07 | P34: -133.07
A35: Total Elena González Turienzo | C35: -133.07 | P35: -133.07
A36: Elisabeth Amarillo Espitia | B36: Inscripción | C36: -1663.35 | P36: -1663.35
A37: Total Elisabeth Amarillo Espitia | C37: -1663.35 | P37: -1663.35
A38: Enrique López Meseguer | B38: Congreso internacional personal | D38: -3098 | P38: -3098
B39: Congreso nacional personal | E39: -318 | P39: -318
A40: Total Enrique López Meseguer | D40: -3098 | E40: -318 | P40: -3416
A41: Estefanía Berrocal Postigo | B41: Congreso internacional personal | E41: -13700 | P41: -13700
A42: Total Estefanía Berrocal Postigo | E42: -13700 | P42: -13700
A43: Gerardo Monedero Rodrigo | B43: Inscripción | D43: -609.9 | P43: -609.9
A44: Total Gerardo Monedero Rodrigo | D44: -609.9 | P44: -609.9
A45: Isabel Polo Tomás | B45: Alojamiento | E45: -285.73 | P45: -285.73
B46: Congreso internacional personal | D46: -4957.1 | P46: -4957.1
B47: Traslado | D47: -783.74 | P47: -783.74
A48: Total Isabel Polo Tomás | D48: -5740.84 | E48: -285.73 | P48: -6026.57
A49: Itziar Jimenez Gomez | B49: Inscripción | E49: -600 | P49: -600
A50: Total Itziar Jimenez Gomez | E50: -600 | P50: -600
A51: Jean Franco Intraprendente Martini | B51: Material para centro | D51: -899 | P51: -899
A52: Total Jean Franco Intraprendente Martini | D52: -899 | P52: -899
A53: José Gustavo Barroso Braojos | B53: Material para centro | C53: -899.98 | P53: -899.98
B54: Publicidad | D54: 5025 | E54: -2365.94 | P54: 2659.06
A55: Total José Gustavo Barroso Braojos | C55: -899.98 | D55: 5025 | E55: -2365.94 | P55: 1759.08
A56: José Joaquín Gutiérrez Barquín | B56: Mobiliario | C56: -973 | P56: -973
A57: Total José Joaquín Gutiérrez Barquín | C57: -973 | P57: -973
A58: José María Laborda Margolles | B58: Congreso internacional | D58: -4000 | P58: -4000
A59: Total José María Laborda Margolles | D59: -4000 | P59: -4000
A60: José Miguel Aparicio Fernández | B60: Inscripción | C60: -310.5 | P60: -310.5
A61: Total José Miguel Aparicio Fernández | C61: -310.5 | P61: -310.5
A62: Juan Javier Álvarez López | B62: Material para centro | E62: -2568 | F62: -1400.42 | P62: -3968.42
A63: Total Juan Javier Álvarez López | E63: -2568 | F63: -1400.42 | P63: -3968.42
A64: Julie Múñoz Freitez | B64: Inscripción | D64: -2772.25 | P64: -2772.25
A65: Total Julie Múñoz Freitez | D65: -2772.25 | P65: -2772.25
A66: Karen Rojas Crespo | B66: Inscripción | E66: -599.52 | P66: -599.52
A67: Total Karen Rojas Crespo | E67: -599.52 | P67: -599.52
A68: Lorena Sanz López | B68: Inscripción | C68: -205.75 | P68: -205.75
A69: Total Lorena Sanz López | C69: -205.75 | P69: -205.75
A70: Manuel Tucciarone | B70: Alojamiento | E70: -1171.53 | P70: -1171.53
A71: Total Manuel Tucciarone | E71: -1171.53 | P71: -1171.53
A72: Maria Del Carmen Salom Coveñas | B72: Publicidad | C72: -4432 | P72: -4432
A73: Total Maria Del Carmen Salom Coveñas | C73: -4432 | P73: -4432
A74: María Emilia García Ruiz | B74: Material para centro | C74: -1500 | P74: -1500
A75: Total María Emilia García Ruiz | C75: -1500 | P75: -1500
A76: María Estefanía Hernández García | B76: Inscripción | D76: -443.56 | P76: -443.56
A77: Total María Estefanía Hernández García | D77: -443.56 | P77: -443.56
A78: María Garrote Garrote | B78: Alojamiento | C78: -1700 | P78: -1700
A79: Total María Garrote Garrote | C79: -1700 | P79: -1700
A80: Marina Pérez Grau | B80: Inscripción | E80: -2176.19 | P80: -2176.19
A81: Total Marina Pérez Grau | E81: -2176.19 | P81: -2176.19
A82: Miguel Garikoitz Calzada Uriondo | B82: Alojamiento
A83: Total Miguel Garikoitz Calzada Uriondo
A84: Miguel Rodriguez Pérez | B84: Alojamiento | D84: -980.85 | P84: -980.85
A85: Total Miguel Rodriguez Pérez | D85: -980.85 | P85: -980.85
A86: Oscar A, Sánchez Valenzuela | B86: Material para centro | D86: -3353.99 | P86: -3353.99
A87: Total Oscar A, Sánchez Valenzuela | D87: -3353.99 | P87: -3353.99
A88: Paloma Martín-Aragón Martín | B88: Inscripción | C88: -1663.35 | P88: -1663.35
A89: Total Paloma Martín-Aragón Martín | C89: -1663.35 | P89: -1663.35
A90: Raquel de Lama Bermejo | B90: Inscripción | D90: -900 | P90: -900
A91: Total Raquel de Lama Bermejo | D91: -900 | P91: -900
A92: Roberto Sanz Garzón | B92: Inscripción | C92: -600 | P92: -600
A93: Total Roberto Sanz Garzón | C93: -600 | P93: -600
A94: (en blanco) | B94: (en blanco)
A95: Total (en blanco)
A96: Total general | C96: -24242.21 | D96: -24094.4 | E96: -33694.35 | F96: -2299.42 | P96: -84330.38

Sheet códigos
A1: centro | B1: Clínica | C1: Empresa | E1: =IFERROR(__xludf.DUMMYFUNCTION("QUERY(IMPORTRANGE(""1vYjGeYY0Fv1uPTb97Gbjvlxd4khfYQOQJB5UlsSt3ZY/edit?gid=0#gid=0"",""CODORL!A2:F""),""select Col5, Col3, Col1 where Col3 is not null"",2)"),"NOMBRE ORL ") -> NOMBRE ORL | F1: =IFERROR(__xludf.DUMMYFUNCTION("""COMPUTED_VALUE"""),"CODORL ") -> CODORL | G1: =IFERROR(__xludf.DUMMYFUNCTION("""COMPUTED_VALUE"""),"VISITADOR ") -> VISITADOR | K1: ORL | L1: nombre compoloeto | M1: código | O1: Alojamiento | R1: CONTRATOS
A2: Albacete | B2: Albacete | C2: AUDICANTE | E2: =IFERROR(__xludf.DUMMYFUNCTION("""COMPUTED_VALUE"""),"Julio César Ariza Lizcano") -> Julio César Ariza Lizcano | F2: =IFERROR(__xludf.DUMMYFUNCTION("""COMPUTED_VALUE"""),"LAA91") -> LAA91 | G2: =IFERROR(__xludf.DUMMYFUNCTION("""COMPUTED_VALUE"""),"Luis Alberto Rodríguez") -> Luis Alberto Rodríguez | K2: ADOLFO TOLEDANO | L2: Adolfo Toledano Muñoz | M2: MBM01 | O2: Alojamiento y traslado | R2: =IFERROR(__xludf.DUMMYFUNCTION("QUERY(IMPORTRANGE(""1epD6BbEEqvSFzxfUWydVvHuch-VRXVJ5kS2QdVOG-_A/edit?gid=1595812126#gid=1595812126"",""DatosSignature!G:G""),""SELECT *"",1)"),"signature name") -> signature name
A3: Alcorcón | B3: Alcorcón | C3: CLINICA DOS DE MAYO | E3: =IFERROR(__xludf.DUMMYFUNCTION("""COMPUTED_VALUE"""),"Ane Díez Fernández") -> Ane Díez Fernández | F3: =IFERROR(__xludf.DUMMYFUNCTION("""COMPUTED_VALUE"""),"LRM274") -> LRM274 | G3: =IFERROR(__xludf.DUMMYFUNCTION("""COMPUTED_VALUE"""),"Lisandro Russian") -> Lisandro Russian | K3: ALBA MOLINA MORENO | L3: Alba Molina Moreno | M3: ISL84 | O3: Congreso internacional | R3: =IFERROR(__xludf.DUMMYFUNCTION("""COMPUTED_VALUE"""),"MCC43") -> MCC43
A4: Alicante | B4: Alicante | C4: AUDICANTE | E4: =IFERROR(__xludf.DUMMYFUNCTION("""COMPUTED_VALUE"""),"Andrés Bejarano Bueno") -> Andrés Bejarano Bueno | F4: =IFERROR(__xludf.DUMMYFUNCTION("""COMPUTED_VALUE"""),"MBM235") -> MBM235 | G4: =IFERROR(__xludf.DUMMYFUNCTION("""COMPUTED_VALUE"""),"Maika Blázquez") -> Maika Blázquez | K4: ALBERTO RAPOSO | L4: Alberto Raposo Jiménez | M4: ISL01 | O4: Congreso internacional personal | R4: =IFERROR(__xludf.DUMMYFUNCTION("""COMPUTED_VALUE"""),"RFV19") -> RFV19
A5: Almería | B5: Almería | C5: AUDICOST, S.L.U | E5: =IFERROR(__xludf.DUMMYFUNCTION("""COMPUTED_VALUE"""),"Andreina Betancourt Martínez") -> Andreina Betancourt Martínez | F5: =IFERROR(__xludf.DUMMYFUNCTION("""COMPUTED_VALUE"""),"ISL155") -> ISL155 | G5: =IFERROR(__xludf.DUMMYFUNCTION("""COMPUTED_VALUE"""),"Iván Sánchez") -> Iván Sánchez | K5: ALBERTO TAUSTE | L5: Alberto Tauste Gómez | M5: MBM02 | O5: Congreso nacional personal | R5: =IFERROR(__xludf.DUMMYFUNCTION("""COMPUTED_VALUE"""),"LAA31") -> LAA31
A6: Badajoz | B6: Badajoz | C6: CENTRO OPTICO RODRIGUEZ VIÑALS, S.L | E6: =IFERROR(__xludf.DUMMYFUNCTION("""COMPUTED_VALUE"""),"Andrea López") -> Andrea López | F6: =IFERROR(__xludf.DUMMYFUNCTION("""COMPUTED_VALUE"""),"MBM234") -> MBM234 | G6: =IFERROR(__xludf.DUMMYFUNCTION("""COMPUTED_VALUE"""),"Maika Blázquez") -> Maika Blázquez | K6: ALEJANDRA JARA | L6: Alejandra Jara Maquilón | M6: ISL91 | O6: Equipos informaticos | R6: =IFERROR(__xludf.DUMMYFUNCTION("""COMPUTED_VALUE"""),"MBM65") -> MBM65
A7: Córcega | B7: Barcelona- Córcega | C7: INVERSIONS DEL BAIX | E7: =IFERROR(__xludf.DUMMYFUNCTION("""COMPUTED_VALUE"""),"Ana Clemente Arias") -> Ana Clemente Arias | F7: =IFERROR(__xludf.DUMMYFUNCTION("""COMPUTED_VALUE"""),"MBM233") -> MBM233 | G7: =IFERROR(__xludf.DUMMYFUNCTION("""COMPUTED_VALUE"""),"Maika Blázquez") -> Maika Blázquez | K7: ALEJANDRO DIAZ UÑA | L7: Alejandro Díaz Uña | M7: RPG01 | O7: Gasto de representación | R7: =IFERROR(__xludf.DUMMYFUNCTION("""COMPUTED_VALUE"""),"ISL91") -> ISL91
A8: Fabra | B8: Barcelona- Fabra I Puig | C8: INVERSIONS DEL BAIX | E8: =IFERROR(__xludf.DUMMYFUNCTION("""COMPUTED_VALUE"""),"Amparo Postigo Madueño") -> Amparo Postigo Madueño | F8: =IFERROR(__xludf.DUMMYFUNCTION("""COMPUTED_VALUE"""),"LAA90") -> LAA90 | G8: =IFERROR(__xludf.DUMMYFUNCTION("""COMPUTED_VALUE"""),"Luis Alberto Rodríguez") -> Luis Alberto Rodríguez | K8: ANA G. JOVER | L8: Ana Gabriela Jover Espla | M8: ISL89 | O8: Gastos de personal | R8: =IFERROR(__xludf.DUMMYFUNCTION("""COMPUTED_VALUE"""),"LAA09") -> LAA09
A9: Boiro | B9: Boiro | C9: AUDIBOISALNES, S.L. | E9: =IFERROR(__xludf.DUMMYFUNCTION("""COMPUTED_VALUE"""),"Ali Ibrahim Farhat") -> Ali Ibrahim Farhat | F9: =IFERROR(__xludf.DUMMYFUNCTION("""COMPUTED_VALUE"""),"MBM232") -> MBM232 | G9: =IFERROR(__xludf.DUMMYFUNCTION("""COMPUTED_VALUE"""),"Maika Blázquez") -> Maika Blázquez | K9: ANA QUINTANA SANJUAS | L9: Ana Quintana Sanjuan | M9: RPG37 | O9: Inscripción | R9: =IFERROR(__xludf.DUMMYFUNCTION("""COMPUTED_VALUE"""),"Prueba") -> Prueba
A10: Caceres | B10: Caceres | C10: FLORENCIO AYUSO SANCHEZ | E10: =IFERROR(__xludf.DUMMYFUNCTION("""COMPUTED_VALUE"""),"Itziar Jimenez Gomez") -> Itziar Jimenez Gomez | F10: =IFERROR(__xludf.DUMMYFUNCTION("""COMPUTED_VALUE"""),"MBM231") -> MBM231 | G10: =IFERROR(__xludf.DUMMYFUNCTION("""COMPUTED_VALUE"""),"Maika Blázquez") -> Maika Blázquez | K10: ANASTASIA AVDIYUC | L10: Anastasiya Audiyuk Martynyuk | M10: MBM195 | O10: Instalaciones centro | R10: =IFERROR(__xludf.DUMMYFUNCTION("""COMPUTED_VALUE"""),"RPG51") -> RPG51
A11: Cambados | B11: Cambados | C11: AUDIBOISALNES, S.L. | E11: =IFERROR(__xludf.DUMMYFUNCTION("""COMPUTED_VALUE"""),"Alfonso Rodríguez Fabio") -> Alfonso Rodríguez Fabio | F11: =IFERROR(__xludf.DUMMYFUNCTION("""COMPUTED_VALUE"""),"ISL154") -> ISL154 | G11: =IFERROR(__xludf.DUMMYFUNCTION("""COMPUTED_VALUE"""),"Iván Sánchez") -> Iván Sánchez | K11: ANTONIO GALINDO | L11: Antonio Galindo Fernandez | M11: ISL10 | O11: Material para centro | R11: =IFERROR(__xludf.DUMMYFUNCTION("""COMPUTED_VALUE"""),"MCC04") -> MCC04
A12: Carballo | B12: Carballo | C12: CENTROS AUDITIVOS NORDES 3J S.L. | E12: =IFERROR(__xludf.DUMMYFUNCTION("""COMPUTED_VALUE"""),"Alejandra Arellano Bárcenas") -> Alejandra Arellano Bárcenas | F12: =IFERROR(__xludf.DUMMYFUNCTION("""COMPUTED_VALUE"""),"ISL153") -> ISL153 | G12: =IFERROR(__xludf.DUMMYFUNCTION("""COMPUTED_VALUE"""),"Iván Sánchez") -> Iván Sánchez | K12: ANTONIO LIROLA DELGADO | L12: Antonio Gustavo Lirola Delgado | M12: RPG05 | O12: Mobiliario | R12: =IFERROR(__xludf.DUMMYFUNCTION("""COMPUTED_VALUE"""),"ISL122") -> ISL122
A13: Cuenca | B13: Cuenca | E13: =IFERROR(__xludf.DUMMYFUNCTION("""COMPUTED_VALUE"""),"Ainhoa Leceta Sáez de Cámara") -> Ainhoa Leceta Sáez de Cámara | F13: =IFERROR(__xludf.DUMMYFUNCTION("""COMPUTED_VALUE"""),"LRM273") -> LRM273 | G13: =IFERROR(__xludf.DUMMYFUNCTION("""COMPUTED_VALUE"""),"Lisandro Russian") -> Lisandro Russian | K13: RIVERO | L13: Antonio Rodríguez Rivero | M13: MBM11 | O13: Obras acondicionamiento centro | R13: =IFERROR(__xludf.DUMMYFUNCTION("""COMPUTED_VALUE"""),"RFV11") -> RFV11
A14: Culleredo | B14: Culleredo | C14: MARJENA ASESORES, S.L | E14: =IFERROR(__xludf.DUMMYFUNCTION("""COMPUTED_VALUE"""),"Agustín Alcalá Fernández") -> Agustín Alcalá Fernández | F14: =IFERROR(__xludf.DUMMYFUNCTION("""COMPUTED_VALUE"""),"LAA89") -> LAA89 | G14: =IFERROR(__xludf.DUMMYFUNCTION("""COMPUTED_VALUE"""),"Luis Alberto Rodríguez") -> Luis Alberto Rodríguez | K14: BARAJAS | L14: Carlos Barajas del Rosal | M14: LRM239 | O14: Prestación de servicios | R14: =IFERROR(__xludf.DUMMYFUNCTION("""COMPUTED_VALUE"""),"MCC07") -> MCC07
A15: El Albir (Benidorm) | B15: El Albir (Benidorm) | C15: AUDICANTE | E15: =IFERROR(__xludf.DUMMYFUNCTION("""COMPUTED_VALUE"""),"Abel Bogoya Castaño") -> Abel Bogoya Castaño | F15: =IFERROR(__xludf.DUMMYFUNCTION("""COMPUTED_VALUE"""),"MBM187") -> MBM187 | G15: =IFERROR(__xludf.DUMMYFUNCTION("""COMPUTED_VALUE"""),"Maika Blázquez") -> Maika Blázquez | K15: CARLOS VELASQUEZ | L15: Carlos Velasquez Fermín | M15: ISL14 | O15: Publicidad | R15: =IFERROR(__xludf.DUMMYFUNCTION("""COMPUTED_VALUE"""),"MBM131") -> MBM131
A16: Elda | B16: Elda | C16: AUDIBOISALNES, S.L. | E16: =IFERROR(__xludf.DUMMYFUNCTION("""COMPUTED_VALUE"""),"Abel Guzmán Calvete") -> Abel Guzmán Calvete | F16: =IFERROR(__xludf.DUMMYFUNCTION("""COMPUTED_VALUE"""),"RFV08") -> RFV08 | G16: =IFERROR(__xludf.DUMMYFUNCTION("""COMPUTED_VALUE"""),"Ramon Ferrando") -> Ramon Ferrando | K16: CARLOS VELASQUEZ FERMIN | L16: Carlos Velasquez Fermín | M16: ISL14 | O16: Traslado | R16: =IFERROR(__xludf.DUMMYFUNCTION("""COMPUTED_VALUE"""),"RFV33") -> RFV33
A17: Elda | B17: Elda | C17: AUDIBOISALNES, S.L. | E17: =IFERROR(__xludf.DUMMYFUNCTION("""COMPUTED_VALUE"""),"Adela Cordero Devesa") -> Adela Cordero Devesa | F17: =IFERROR(__xludf.DUMMYFUNCTION("""COMPUTED_VALUE"""),"MBM86") -> MBM86 | G17: =IFERROR(__xludf.DUMMYFUNCTION("""COMPUTED_VALUE"""),"Maika Blázquez") -> Maika Blázquez | K17: CARLOS VIDAL | L17: Carlos Vidal Redondo | M17: RPG09 | O17: Congreso nacional | R17: =IFERROR(__xludf.DUMMYFUNCTION("""COMPUTED_VALUE"""),"MBM114") -> MBM114
A18: Fuenlabrada | B18: Fuenlabrada | C18: AUDIBRADA | E18: =IFERROR(__xludf.DUMMYFUNCTION("""COMPUTED_VALUE"""),"Adela Pérez-Caro Ríos") -> Adela Pérez-Caro Ríos | F18: =IFERROR(__xludf.DUMMYFUNCTION("""COMPUTED_VALUE"""),"RPG33") -> RPG33 | G18: =IFERROR(__xludf.DUMMYFUNCTION("""COMPUTED_VALUE"""),"Roberto Pereira") -> Roberto Pereira | K18: CRISTINA ESTHER TORREGROSA | L18: Cristina Esther Torregrosa Carrasquer | M18: ISL98 | R18: =IFERROR(__xludf.DUMMYFUNCTION("""COMPUTED_VALUE"""),"MBM109") -> MBM109
A19: Getafe | B19: Getafe | C19: AUDIBRADA | E19: =IFERROR(__xludf.DUMMYFUNCTION("""COMPUTED_VALUE"""),"Adolfo Carlos Hinojar Gutierrez") -> Adolfo Carlos Hinojar Gutierrez | F19: =IFERROR(__xludf.DUMMYFUNCTION("""COMPUTED_VALUE"""),"LRM01") -> LRM01 | G19: =IFERROR(__xludf.DUMMYFUNCTION("""COMPUTED_VALUE"""),"Lisandro Russian") -> Lisandro Russian | K19: CRISTINA GARCIA | L19: Cristina García García | M19: MBM190 | R19: =IFERROR(__xludf.DUMMYFUNCTION("""COMPUTED_VALUE"""),"LAA64") -> LAA64
A20: Gijón | B20: Gijón | C20: AUDICOST ASTURIAS | E20: =IFERROR(__xludf.DUMMYFUNCTION("""COMPUTED_VALUE"""),"Adolfo del Valle Zapico") -> Adolfo del Valle Zapico | F20: =IFERROR(__xludf.DUMMYFUNCTION("""COMPUTED_VALUE"""),"AMM01") -> AMM01 | G20: =IFERROR(__xludf.DUMMYFUNCTION("""COMPUTED_VALUE"""),"Alberto Moreno") -> Alberto Moreno | K20: CRISTINA IBAÑEZ MUÑOZ | L20: Cristina Ibañez Muñoz | M20: LRM151 | R20: =IFERROR(__xludf.DUMMYFUNCTION("""COMPUTED_VALUE"""),"MCC12") -> MCC12
A21: Girona | B21: Girona | C21: INVERSIONS DEL BAIX | E21: =IFERROR(__xludf.DUMMYFUNCTION("""COMPUTED_VALUE"""),"Adolfo Toledano Muñoz") -> Adolfo Toledano Muñoz | F21: =IFERROR(__xludf.DUMMYFUNCTION("""COMPUTED_VALUE"""),"MBM01") -> MBM01 | G21: =IFERROR(__xludf.DUMMYFUNCTION("""COMPUTED_VALUE"""),"Maika Blázquez") -> Maika Blázquez | K21: CRISTINA POVEDANO | L21: Cristina Povedano Fernandez | M21: MBM107 | R21: =IFERROR(__xludf.DUMMYFUNCTION("""COMPUTED_VALUE"""),"MBM60") -> MBM60
A22: Hospitalet | B22: Hospitalet De Llobregat | C22: INVERSIONS DEL BAIX | E22: =IFERROR(__xludf.DUMMYFUNCTION("""COMPUTED_VALUE"""),"Adriana Pardo Maza") -> Adriana Pardo Maza | F22: =IFERROR(__xludf.DUMMYFUNCTION("""COMPUTED_VALUE"""),"LRM123") -> LRM123 | G22: =IFERROR(__xludf.DUMMYFUNCTION("""COMPUTED_VALUE"""),"Lisandro Russian") -> Lisandro Russian | K22: DANIEL BRIONES CRESPO | L22: Daniel Briones Crespo | M22: LRM249 | R22: =IFERROR(__xludf.DUMMYFUNCTION("""COMPUTED_VALUE"""),"MCC32") -> MCC32
A23: Huelva | B23: Huelva | C23: AUDICOST, S.L.U | E23: =IFERROR(__xludf.DUMMYFUNCTION("""COMPUTED_VALUE"""),"Adriana Pérez García") -> Adriana Pérez García | F23: =IFERROR(__xludf.DUMMYFUNCTION("""COMPUTED_VALUE"""),"MBM87") -> MBM87 | G23: =IFERROR(__xludf.DUMMYFUNCTION("""COMPUTED_VALUE"""),"Maika Blázquez") -> Maika Blázquez | K23: ANTUNES | L23: Dinis Antunes Silva | M23: ISL19 | R23: =IFERROR(__xludf.DUMMYFUNCTION("""COMPUTED_VALUE"""),"RPG31") -> RPG31
A24: Jerez | B24: Jerez de la Frontera | C24: AUDICOST, S.L.U | E24: =IFERROR(__xludf.DUMMYFUNCTION("""COMPUTED_VALUE"""),"Africa Jiménez de la Rosa") -> Africa Jiménez de la Rosa | F24: =IFERROR(__xludf.DUMMYFUNCTION("""COMPUTED_VALUE"""),"ISL82") -> ISL82 | G24: =IFERROR(__xludf.DUMMYFUNCTION("""COMPUTED_VALUE"""),"Iván Sánchez") -> Iván Sánchez | K24: DINIS ANTUNES SILVA | L24: Dinis Antunes Silva | M24: ISL19 | R24: =IFERROR(__xludf.DUMMYFUNCTION("""COMPUTED_VALUE"""),"ISL104") -> ISL104
A25: Lalín | B25: Lalín | C25: AUDIBOISALNES, S.L. | E25: =IFERROR(__xludf.DUMMYFUNCTION("""COMPUTED_VALUE"""),"Agustín Campos Catalá") -> Agustín Campos Catalá | F25: =IFERROR(__xludf.DUMMYFUNCTION("""COMPUTED_VALUE"""),"RFV09") -> RFV09 | G25: =IFERROR(__xludf.DUMMYFUNCTION("""COMPUTED_VALUE"""),"Ramon Ferrando") -> Ramon Ferrando | K25: DINIS PAULO ANTUNES SILVA | L25: Dinis Antunes Silva | M25: ISL19 | R25: =IFERROR(__xludf.DUMMYFUNCTION("""COMPUTED_VALUE"""),"ISL53") -> ISL53
A26: Leganés | B26: Leganés | C26: AUDICOST LEGANES | E26: =IFERROR(__xludf.DUMMYFUNCTION("""COMPUTED_VALUE"""),"Agustina Nicole Arbia Kalutich") -> Agustina Nicole Arbia Kalutich | F26: =IFERROR(__xludf.DUMMYFUNCTION("""COMPUTED_VALUE"""),"MBM205") -> MBM205 | G26: =IFERROR(__xludf.DUMMYFUNCTION("""COMPUTED_VALUE"""),"Maika Blázquez") -> Maika Blázquez | K26: ELENA MARTIN BEJARANO | L26: Elena Martín Bejerano | M26: MBM191 | R26: =IFERROR(__xludf.DUMMYFUNCTION("""COMPUTED_VALUE"""),"MBM20") -> MBM20
A27: León | B27: León | C27: DAVID DE LA PUENTE MENCIA | E27: =IFERROR(__xludf.DUMMYFUNCTION("""COMPUTED_VALUE"""),"Aida Aviñoa Arias") -> Aida Aviñoa Arias | F27: =IFERROR(__xludf.DUMMYFUNCTION("""COMPUTED_VALUE"""),"ISL83") -> ISL83 | G27: =IFERROR(__xludf.DUMMYFUNCTION("""COMPUTED_VALUE"""),"Iván Sánchez") -> Iván Sánchez | K27: ELENA SEVILLA HERAS | L27: Elena Sevilla Heras | M27: ISL145 | R27: =IFERROR(__xludf.DUMMYFUNCTION("""COMPUTED_VALUE"""),"MBM153") -> MBM153
A28: Logroño | B28: Logroño | C28: AUDICOST LOGROÑO | E28: =IFERROR(__xludf.DUMMYFUNCTION("""COMPUTED_VALUE"""),"Aina Brunet García") -> Aina Brunet García | F28: =IFERROR(__xludf.DUMMYFUNCTION("""COMPUTED_VALUE"""),"MCC35") -> MCC35 | G28: =IFERROR(__xludf.DUMMYFUNCTION("""COMPUTED_VALUE"""),"Mercè Cabrera") -> Mercè Cabrera | K28: ALBERTO ESTEBAN SCOLA | L28: Esteban Scola Pliego | M28: MBM18 | R28: =IFERROR(__xludf.DUMMYFUNCTION("""COMPUTED_VALUE"""),"MCC38") -> MCC38
A29: Lugo | B29: Lugo | C29: CONTRERAS RAPOSO | E29: =IFERROR(__xludf.DUMMYFUNCTION("""COMPUTED_VALUE"""),"Ainhoa Beato Martínez") -> Ainhoa Beato Martínez | F29: =IFERROR(__xludf.DUMMYFUNCTION("""COMPUTED_VALUE"""),"LRM124") -> LRM124 | G29: =IFERROR(__xludf.DUMMYFUNCTION("""COMPUTED_VALUE"""),"Lisandro Russian") -> Lisandro Russian | K29: ESTEFANIA BERROCAL | L29: Estefanía Berrocal Postigo | M29: LAA47 | R29: =IFERROR(__xludf.DUMMYFUNCTION("""COMPUTED_VALUE"""),"MBM186") -> MBM186
A30: Canillas | B30: Madrid- Canillas | C30: AUDICOST, S.L.U | E30: =IFERROR(__xludf.DUMMYFUNCTION("""COMPUTED_VALUE"""),"Ainhoa García-Lliberos de Miguel") -> Ainhoa García-Lliberos de Miguel | F30: =IFERROR(__xludf.DUMMYFUNCTION("""COMPUTED_VALUE"""),"RFV26") -> RFV26 | G30: =IFERROR(__xludf.DUMMYFUNCTION("""COMPUTED_VALUE"""),"Ramon Ferrando") -> Ramon Ferrando | K30: ESTEFANIA MIRANDA | L30: Estefania Miranda Sanchez | M30: MBM113 | R30: =IFERROR(__xludf.DUMMYFUNCTION("""COMPUTED_VALUE"""),"MCC50") -> MCC50
A31: Costa Rica | B31: Madrid- Costa Rica | C31: APLICACIONES JORVIK | E31: =IFERROR(__xludf.DUMMYFUNCTION("""COMPUTED_VALUE"""),"Ainhoa Moreno Bravo") -> Ainhoa Moreno Bravo | F31: =IFERROR(__xludf.DUMMYFUNCTION("""COMPUTED_VALUE"""),"LRM125") -> LRM125 | G31: =IFERROR(__xludf.DUMMYFUNCTION("""COMPUTED_VALUE"""),"Lisandro Russian") -> Lisandro Russian | K31: M.DE LA FE RUBIO ESCOLANO | L31: Fe Rubio Escolano | M31: RFV29 | R31: =IFERROR(__xludf.DUMMYFUNCTION("""COMPUTED_VALUE"""),"MBM189") -> MBM189
A32: Moncloa | B32: Madrid- Galileo | C32: AUDICOST GARRAF PENEDES, S.L | E32: =IFERROR(__xludf.DUMMYFUNCTION("""COMPUTED_VALUE"""),"Alba Carrero González") -> Alba Carrero González | F32: =IFERROR(__xludf.DUMMYFUNCTION("""COMPUTED_VALUE"""),"RPG34") -> RPG34 | G32: =IFERROR(__xludf.DUMMYFUNCTION("""COMPUTED_VALUE"""),"Roberto Pereira") -> Roberto Pereira | K32: FRANCISCO AGUILAR | L32: Francisco Javier Aguilar Vera | M32: LAA13 | R32: =IFERROR(__xludf.DUMMYFUNCTION("""COMPUTED_VALUE"""),"MCC65") -> MCC65
A33: Juan Bravo | B33: Madrid- Juan Bravo | C33: AUDICOST, S.L.U | E33: =IFERROR(__xludf.DUMMYFUNCTION("""COMPUTED_VALUE"""),"Alba Domínguez Palos") -> Alba Domínguez Palos | F33: =IFERROR(__xludf.DUMMYFUNCTION("""COMPUTED_VALUE"""),"MBM88") -> MBM88 | G33: =IFERROR(__xludf.DUMMYFUNCTION("""COMPUTED_VALUE"""),"Maika Blázquez") -> Maika Blázquez | K33: PACO PASTOR | L33: Francisco Pastor Bevia | M33: ISL34 | R33: =IFERROR(__xludf.DUMMYFUNCTION("""COMPUTED_VALUE"""),"MBM75") -> MBM75
A34: La Oca | B34: Madrid- La Oca | C34: SIEMA BLINK, S.L | E34: =IFERROR(__xludf.DUMMYFUNCTION("""COMPUTED_VALUE"""),"Alba Molina Moreno") -> Alba Molina Moreno | F34: =IFERROR(__xludf.DUMMYFUNCTION("""COMPUTED_VALUE"""),"ISL84") -> ISL84 | G34: =IFERROR(__xludf.DUMMYFUNCTION("""COMPUTED_VALUE"""),"Iván Sánchez") -> Iván Sánchez | K34: GABRIEL MARTINEZ CAPOCCIONI | L34: Gabriel Martínez Capoccini | M34: RPG14 | R34: =IFERROR(__xludf.DUMMYFUNCTION("""COMPUTED_VALUE"""),"MBM24") -> MBM24
A35: La Vaguada | B35: Madrid- Monforte de Lemos | C35: AUDICOST, S.L.U | E35: =IFERROR(__xludf.DUMMYFUNCTION("""COMPUTED_VALUE"""),"Albert Llansana Ríos") -> Albert Llansana Ríos | F35: =IFERROR(__xludf.DUMMYFUNCTION("""COMPUTED_VALUE"""),"MCC01") -> MCC01 | G35: =IFERROR(__xludf.DUMMYFUNCTION("""COMPUTED_VALUE"""),"Mercè Cabrera") -> Mercè Cabrera | K35: MIGUEL GARIKOITZ CALZADA URIONDO | L35: Garikoitz Calzada Uriondo | M35: LRM48 | R35: =IFERROR(__xludf.DUMMYFUNCTION("""COMPUTED_VALUE"""),"MBM11") -> MBM11
A36: Moratalaz | B36: Madrid- Moratalaz | C36: AUDICOST, S.L.U | E36: =IFERROR(__xludf.DUMMYFUNCTION("""COMPUTED_VALUE"""),"Albert Pla Esperanzi") -> Albert Pla Esperanzi | F36: =IFERROR(__xludf.DUMMYFUNCTION("""COMPUTED_VALUE"""),"MCC76") -> MCC76 | G36: =IFERROR(__xludf.DUMMYFUNCTION("""COMPUTED_VALUE"""),"Mercè Cabrera") -> Mercè Cabrera | K36: GLENDYS REYES DE LA CRUZ | L36: Glendis Reyes de la Cruz | M36: LRM161 | R36: =IFERROR(__xludf.DUMMYFUNCTION("""COMPUTED_VALUE"""),"ISL95") -> ISL95
A37: Móstoles | B37: Móstoles | C37: CLINICA DOS DE MAYO | E37: =IFERROR(__xludf.DUMMYFUNCTION("""COMPUTED_VALUE"""),"Alberto García Guzmán") -> Alberto García Guzmán | F37: =IFERROR(__xludf.DUMMYFUNCTION("""COMPUTED_VALUE"""),"LRM02") -> LRM02 | G37: =IFERROR(__xludf.DUMMYFUNCTION("""COMPUTED_VALUE"""),"Lisandro Russian") -> Lisandro Russian | K37: IGNACIO ALBALADEJO DEVIS | L37: Ignacio Albaladejo Devis | M37: ISL39 | R37: =IFERROR(__xludf.DUMMYFUNCTION("""COMPUTED_VALUE"""),"MBM40") -> MBM40
A38: Murcia | B38: Murcia | C38: AUDICANTE | E38: =IFERROR(__xludf.DUMMYFUNCTION("""COMPUTED_VALUE"""),"Alberto Guillén Martínez") -> Alberto Guillén Martínez | F38: =IFERROR(__xludf.DUMMYFUNCTION("""COMPUTED_VALUE"""),"ISL152") -> ISL152 | G38: =IFERROR(__xludf.DUMMYFUNCTION("""COMPUTED_VALUE"""),"Iván Sánchez") -> Iván Sánchez | K38: INES PASTOR BASTERRA | L38: Inés Pastor Basterra | M38: LRM162 | R38: =IFERROR(__xludf.DUMMYFUNCTION("""COMPUTED_VALUE"""),"LRM246") -> LRM246
A39: O Barco | B39: O Barco De Valdeorras | C39: AUDICOST PONFERRADA, S.L | E39: =IFERROR(__xludf.DUMMYFUNCTION("""COMPUTED_VALUE"""),"Alberto Raposo Jiménez") -> Alberto Raposo Jiménez | F39: =IFERROR(__xludf.DUMMYFUNCTION("""COMPUTED_VALUE"""),"ISL01") -> ISL01 | G39: =IFERROR(__xludf.DUMMYFUNCTION("""COMPUTED_VALUE"""),"Iván Sánchez") -> Iván Sánchez | K39: IVAN MENDEZ BENEGASSI | L39: Ivan Mendez- Benegassi Silva | M39: MBM35 | R39: =IFERROR(__xludf.DUMMYFUNCTION("""COMPUTED_VALUE"""),"LRM125") -> LRM125
A40: Oleiros | B40: Oleiros | C40: PABLO DURAN, S.L. | E40: =IFERROR(__xludf.DUMMYFUNCTION("""COMPUTED_VALUE"""),"Alberto Tauste Gómez") -> Alberto Tauste Gómez | F40: =IFERROR(__xludf.DUMMYFUNCTION("""COMPUTED_VALUE"""),"MBM02") -> MBM02 | G40: =IFERROR(__xludf.DUMMYFUNCTION("""COMPUTED_VALUE"""),"Maika Blázquez") -> Maika Blázquez | K40: JAIME OCHOA | L40: Jaime Alonso Ochoa Ríos | M40: LAA21 | R40: =IFERROR(__xludf.DUMMYFUNCTION("""COMPUTED_VALUE"""),"MCC27") -> MCC27
A41: La Zenia | B41: Orihuela | C41: AUDICOST, S.L.U | E41: =IFERROR(__xludf.DUMMYFUNCTION("""COMPUTED_VALUE"""),"Alejandra Aguirre Figueroa") -> Alejandra Aguirre Figueroa | F41: =IFERROR(__xludf.DUMMYFUNCTION("""COMPUTED_VALUE"""),"LRM126") -> LRM126 | G41: =IFERROR(__xludf.DUMMYFUNCTION("""COMPUTED_VALUE"""),"Lisandro Russian") -> Lisandro Russian | K41: JAVIER ALONSO | L41: Javier Alonso Ortega | M41: MBM37 | R41: =IFERROR(__xludf.DUMMYFUNCTION("""COMPUTED_VALUE"""),"MBM41") -> MBM41
A42: Orense | B42: Ourense | C42: AUDICOST ASTURIAS | E42: =IFERROR(__xludf.DUMMYFUNCTION("""COMPUTED_VALUE"""),"Alejandra Alvarado Namen") -> Alejandra Alvarado Namen | F42: =IFERROR(__xludf.DUMMYFUNCTION("""COMPUTED_VALUE"""),"ISL150") -> ISL150 | G42: =IFERROR(__xludf.DUMMYFUNCTION("""COMPUTED_VALUE"""),"Iván Sánchez") -> Iván Sánchez | K42: JAVIER GARCIA DUEÑAS | L42: Javier García-Dueñas Gonzalez | M42: ISL41 | R42: =IFERROR(__xludf.DUMMYFUNCTION("""COMPUTED_VALUE"""),"LRM220") -> LRM220
A43: Oviedo | B43: Oviedo | C43: AUDICOST ASTURIAS | E43: =IFERROR(__xludf.DUMMYFUNCTION("""COMPUTED_VALUE"""),"Alejandra Carrasco Gómez") -> Alejandra Carrasco Gómez | F43: =IFERROR(__xludf.DUMMYFUNCTION("""COMPUTED_VALUE"""),"MBM89") -> MBM89 | G43: =IFERROR(__xludf.DUMMYFUNCTION("""COMPUTED_VALUE"""),"Maika Blázquez") -> Maika Blázquez | K43: JEAN FRANCO INTRAPRENDENTE | L43: Jean Franco Intraprendente Martini | M43: RFV15 | R43: =IFERROR(__xludf.DUMMYFUNCTION("""COMPUTED_VALUE"""),"ISL14") -> ISL14
A44: Palencia | B44: Palencia | C44: AUDICOST CASTILLA LEÓN | E44: =IFERROR(__xludf.DUMMYFUNCTION("""COMPUTED_VALUE"""),"Alejandra Jara Maquilón") -> Alejandra Jara Maquilón | F44: =IFERROR(__xludf.DUMMYFUNCTION("""COMPUTED_VALUE"""),"ISL91") -> ISL91 | G44: =IFERROR(__xludf.DUMMYFUNCTION("""COMPUTED_VALUE"""),"Iván Sánchez") -> Iván Sánchez | K44: JESUS CROVATO | L44: Jesús Crovato Rojas | M44: LAA24 | R44: =IFERROR(__xludf.DUMMYFUNCTION("""COMPUTED_VALUE"""),"MBM125") -> MBM125
A45: Plasencia | B45: Plasencia | C45: ALEJANDRO CID GARCIA | E45: =IFERROR(__xludf.DUMMYFUNCTION("""COMPUTED_VALUE"""),"Alejandra Pérez Ferrando") -> Alejandra Pérez Ferrando | F45: =IFERROR(__xludf.DUMMYFUNCTION("""COMPUTED_VALUE"""),"ISL86") -> ISL86 | G45: =IFERROR(__xludf.DUMMYFUNCTION("""COMPUTED_VALUE"""),"Iván Sánchez") -> Iván Sánchez | K45: JESUS INIESTA | L45: Jesús Miguel Iniesta Turpín | M45: ISL45 | R45: =IFERROR(__xludf.DUMMYFUNCTION("""COMPUTED_VALUE"""),"ISL136") -> ISL136
A46: Ponferrada | B46: Ponferrada | C46: AUDICOST PONFERRADA, S.L | E46: =IFERROR(__xludf.DUMMYFUNCTION("""COMPUTED_VALUE"""),"Alejandro Díaz Uña") -> Alejandro Díaz Uña | F46: =IFERROR(__xludf.DUMMYFUNCTION("""COMPUTED_VALUE"""),"RPG01") -> RPG01 | G46: =IFERROR(__xludf.DUMMYFUNCTION("""COMPUTED_VALUE"""),"Roberto Pereira") -> Roberto Pereira | K46: DR.GRASA | L46: Jesus-Maria Grasa Pérez | M46: MCC18 | R46: =IFERROR(__xludf.DUMMYFUNCTION("""COMPUTED_VALUE"""),"MCC64") -> MCC64
A47: Salamanca | B47: Salamanca | C47: AUDICOST SALAMANCA S.L | E47: =IFERROR(__xludf.DUMMYFUNCTION("""COMPUTED_VALUE"""),"Alejandro Harguindey Antoli-Candela") -> Alejandro Harguindey Antoli-Candela | F47: =IFERROR(__xludf.DUMMYFUNCTION("""COMPUTED_VALUE"""),"MBM03") -> MBM03 | G47: =IFERROR(__xludf.DUMMYFUNCTION("""COMPUTED_VALUE"""),"Maika Blázquez") -> Maika Blázquez | K47: ANTONIO GARCIA MORILLAS | L47: JOSE GARCIA MORILLAS | M47: ISL50 | R47: =IFERROR(__xludf.DUMMYFUNCTION("""COMPUTED_VALUE"""),"ISL75") -> ISL75
A48: San Javier | B48: San Javier | C48: AUDICOST, S.L.U | E48: =IFERROR(__xludf.DUMMYFUNCTION("""COMPUTED_VALUE"""),"Alejandro Martínez Morán") -> Alejandro Martínez Morán | F48: =IFERROR(__xludf.DUMMYFUNCTION("""COMPUTED_VALUE"""),"LRM03") -> LRM03 | G48: =IFERROR(__xludf.DUMMYFUNCTION("""COMPUTED_VALUE"""),"Lisandro Russian") -> Lisandro Russian | K48: BARROSO | L48: José Gustavo Barroso Braojos | M48: MBM50 | R48: =IFERROR(__xludf.DUMMYFUNCTION("""COMPUTED_VALUE"""),"LRM227") -> LRM227
A49: Santiago | B49: Santiago de Compostela | C49: AUDICOST GALICIA | E49: =IFERROR(__xludf.DUMMYFUNCTION("""COMPUTED_VALUE"""),"Alejandro Tejero-Garcés Monclús") -> Alejandro Tejero-Garcés Monclús | F49: =IFERROR(__xludf.DUMMYFUNCTION("""COMPUTED_VALUE"""),"LRM04") -> LRM04 | G49: =IFERROR(__xludf.DUMMYFUNCTION("""COMPUTED_VALUE"""),"Lisandro Russian") -> Lisandro Russian | K49: GUSTAVO BARROSO | L49: José Gustavo Barroso Braojos | M49: MBM50 | R49: =IFERROR(__xludf.DUMMYFUNCTION("""COMPUTED_VALUE"""),"MCC67") -> MCC67
A50: Sevilla Este | B50: Sevilla- Ciencias | C50: SOLUCIONES AUDITIVAS AUDIORO 2021, S.L. | E50: =IFERROR(__xludf.DUMMYFUNCTION("""COMPUTED_VALUE"""),"Alex Portillo Medina") -> Alex Portillo Medina | F50: =IFERROR(__xludf.DUMMYFUNCTION("""COMPUTED_VALUE"""),"MCC02") -> MCC02 | G50: =IFERROR(__xludf.DUMMYFUNCTION("""COMPUTED_VALUE"""),"Mercè Cabrera") -> Mercè Cabrera | K50: JOSE JOAQUIN GUTIERREZ BARQUIN | L50: Jose Joaquín Gutiérrez Barquín | M50: MBM52 | R50: =IFERROR(__xludf.DUMMYFUNCTION("""COMPUTED_VALUE"""),"RFV28") -> RFV28
A51: Montoto | B51: Sevilla- Montoto | C51: OIR VITAL CENTROS AUDITIVOS | E51: =IFERROR(__xludf.DUMMYFUNCTION("""COMPUTED_VALUE"""),"Àlex Ramírez Rosa") -> Àlex Ramírez Rosa | F51: =IFERROR(__xludf.DUMMYFUNCTION("""COMPUTED_VALUE"""),"MBM04") -> MBM04 | G51: =IFERROR(__xludf.DUMMYFUNCTION("""COMPUTED_VALUE"""),"Maika Blázquez") -> Maika Blázquez | K51: JOSE MIGUEL OSETE ALBALADEJO | L51: José Miguel Osete Albaladejo | M51: ISL56 | R51: =IFERROR(__xludf.DUMMYFUNCTION("""COMPUTED_VALUE"""),"MCC69") -> MCC69
A52: Talavera | B52: Talavera | C52: AUDICOST TALAVERA, S.L | E52: =IFERROR(__xludf.DUMMYFUNCTION("""COMPUTED_VALUE"""),"Alfonso Aracil Montesinos") -> Alfonso Aracil Montesinos | F52: =IFERROR(__xludf.DUMMYFUNCTION("""COMPUTED_VALUE"""),"ISL02") -> ISL02 | G52: =IFERROR(__xludf.DUMMYFUNCTION("""COMPUTED_VALUE"""),"Iván Sánchez") -> Iván Sánchez | K52: JUAN JAVIER ALVAREZ | L52: Juan Javier alvarez López | M52: ISL58 | R52: =IFERROR(__xludf.DUMMYFUNCTION("""COMPUTED_VALUE"""),"MBM145") -> MBM145
A53: Terrassa | B53: Terrassa | C53: SERGIO QUESADA GARCIA | E53: =IFERROR(__xludf.DUMMYFUNCTION("""COMPUTED_VALUE"""),"Alfonso Campos González") -> Alfonso Campos González | F53: =IFERROR(__xludf.DUMMYFUNCTION("""COMPUTED_VALUE"""),"LRM05") -> LRM05 | G53: =IFERROR(__xludf.DUMMYFUNCTION("""COMPUTED_VALUE"""),"Lisandro Russian") -> Lisandro Russian | K53: JUAN JAVIER ALVAREZ LOPEZ | L53: Juan Javier alvarez López | M53: ISL58 | R53: =IFERROR(__xludf.DUMMYFUNCTION("""COMPUTED_VALUE"""),"MBM36") -> MBM36
A54: Toledo | B54: Toledo | C54: AUDICOST, S.L.U | E54: =IFERROR(__xludf.DUMMYFUNCTION("""COMPUTED_VALUE"""),"Alfonso Capitan Guarnizo") -> Alfonso Capitan Guarnizo | F54: =IFERROR(__xludf.DUMMYFUNCTION("""COMPUTED_VALUE"""),"ISL03") -> ISL03 | G54: =IFERROR(__xludf.DUMMYFUNCTION("""COMPUTED_VALUE"""),"Iván Sánchez") -> Iván Sánchez | K54: JULISSA AIDA VIZCARRA MELGAR | L54: Julissa Vizcarra | M54: MCC64 | R54: =IFERROR(__xludf.DUMMYFUNCTION("""COMPUTED_VALUE"""),"RFV22") -> RFV22
A55: Torrejón | B55: Torrejón De Ardoz | C55: AUDICOST LEGANES | E55: =IFERROR(__xludf.DUMMYFUNCTION("""COMPUTED_VALUE"""),"Alfonso García Piñero") -> Alfonso García Piñero | F55: =IFERROR(__xludf.DUMMYFUNCTION("""COMPUTED_VALUE"""),"ISL04") -> ISL04 | G55: =IFERROR(__xludf.DUMMYFUNCTION("""COMPUTED_VALUE"""),"Iván Sánchez") -> Iván Sánchez | K55: LAURA GAÑAN ALBUISECH | L55: Laura Gañan Albuisech | M55: ISL108 | R55: =IFERROR(__xludf.DUMMYFUNCTION("""COMPUTED_VALUE"""),"LAA71") -> LAA71
A56: Valencia | B56: Valencia- Cadiz | C56: AUDICANTE | E56: =IFERROR(__xludf.DUMMYFUNCTION("""COMPUTED_VALUE"""),"Alfonso Marco Garrido") -> Alfonso Marco Garrido | F56: =IFERROR(__xludf.DUMMYFUNCTION("""COMPUTED_VALUE"""),"ISL05") -> ISL05 | G56: =IFERROR(__xludf.DUMMYFUNCTION("""COMPUTED_VALUE"""),"Iván Sánchez") -> Iván Sánchez | K56: LAURA RUANO | L56: Laura Ruano De Pablo | M56: MBM132 | R56: =IFERROR(__xludf.DUMMYFUNCTION("""COMPUTED_VALUE"""),"RFV21") -> RFV21
A57: Valencia- Cadiz | B57: Valencia- Cadiz | C57: AUDICANTE | E57: =IFERROR(__xludf.DUMMYFUNCTION("""COMPUTED_VALUE"""),"Alfonso María Pérez Sánchez") -> Alfonso María Pérez Sánchez | F57: =IFERROR(__xludf.DUMMYFUNCTION("""COMPUTED_VALUE"""),"LAA83") -> LAA83 | G57: =IFERROR(__xludf.DUMMYFUNCTION("""COMPUTED_VALUE"""),"Luis Alberto Rodríguez") -> Luis Alberto Rodríguez | K57: LORENA SANZ | L57: Lorena Sanz López | M57: MBM136 | R57: =IFERROR(__xludf.DUMMYFUNCTION("""COMPUTED_VALUE"""),"MBM128") -> MBM128
A58: Valencia- Parra | B58: Valencia- Parra | C58: AUDICOST, S.L.U | E58: =IFERROR(__xludf.DUMMYFUNCTION("""COMPUTED_VALUE"""),"Alfonso Plaza López") -> Alfonso Plaza López | F58: =IFERROR(__xludf.DUMMYFUNCTION("""COMPUTED_VALUE"""),"LRM06") -> LRM06 | G58: =IFERROR(__xludf.DUMMYFUNCTION("""COMPUTED_VALUE"""),"Lisandro Russian") -> Lisandro Russian | K58: ACUÑA | L58: Manuel Acuña García | M58: PSC23 | R58: =IFERROR(__xludf.DUMMYFUNCTION("""COMPUTED_VALUE"""),"MCC74") -> MCC74
A59: Valladolid | B59: Valladolid | C59: DIEGO RICO PEREZ | E59: =IFERROR(__xludf.DUMMYFUNCTION("""COMPUTED_VALUE"""),"Alfonso Santamaría Gadea") -> Alfonso Santamaría Gadea | F59: =IFERROR(__xludf.DUMMYFUNCTION("""COMPUTED_VALUE"""),"MBM05") -> MBM05 | G59: =IFERROR(__xludf.DUMMYFUNCTION("""COMPUTED_VALUE"""),"Maika Blázquez") -> Maika Blázquez | K59: MANUEL GONZALEZ JULIAO | L59: Manuel Gonzalez Juliao | M59: MBM65 | R59: =IFERROR(__xludf.DUMMYFUNCTION("""COMPUTED_VALUE"""),"RFV24") -> RFV24
A60: Verín | B60: Verín | C60: AUDIBOISALNES, S.L. | E60: =IFERROR(__xludf.DUMMYFUNCTION("""COMPUTED_VALUE"""),"Alicia Gómez cabezas") -> Alicia Gómez cabezas | F60: =IFERROR(__xludf.DUMMYFUNCTION("""COMPUTED_VALUE"""),"LRM255") -> LRM255 | G60: =IFERROR(__xludf.DUMMYFUNCTION("""COMPUTED_VALUE"""),"Lisandro Russian") -> Lisandro Russian | K60: MARIA DE LA PAZ COLOMA GRAU | L60: María de la Paz Coloma Grau | M60: LRM149 | R60: =IFERROR(__xludf.DUMMYFUNCTION("""COMPUTED_VALUE"""),"MCC40") -> MCC40
A61: Vigo | B61: Vigo | C61: YOSILPE, S.L | E61: =IFERROR(__xludf.DUMMYFUNCTION("""COMPUTED_VALUE"""),"Alicia González Moreno") -> Alicia González Moreno | F61: =IFERROR(__xludf.DUMMYFUNCTION("""COMPUTED_VALUE"""),"MCC36") -> MCC36 | G61: =IFERROR(__xludf.DUMMYFUNCTION("""COMPUTED_VALUE"""),"Mercè Cabrera") -> Mercè Cabrera | K61: 5 RESIDENTES (MAR MEDINA) | L61: María del Mar Medina Gonzalez | M61: MBM146 | R61: =IFERROR(__xludf.DUMMYFUNCTION("""COMPUTED_VALUE"""),"LRM06") -> LRM06
A62: Vilagarcía | B62: Vilagarcía De Arousa | C62: VARELA CARRERA, S.L. | E62: =IFERROR(__xludf.DUMMYFUNCTION("""COMPUTED_VALUE"""),"Alicia Mateo Espinosa") -> Alicia Mateo Espinosa | F62: =IFERROR(__xludf.DUMMYFUNCTION("""COMPUTED_VALUE"""),"ISL87") -> ISL87 | G62: =IFERROR(__xludf.DUMMYFUNCTION("""COMPUTED_VALUE"""),"Iván Sánchez") -> Iván Sánchez | K62: EMILIA GARCIA RUIZ | L62: María Emilia García Ruiz | M62: RFV38 | R62: =IFERROR(__xludf.DUMMYFUNCTION("""COMPUTED_VALUE"""),"RFV10") -> RFV10
A63: Vilanova | B63: Vilanova | C63: INVERSIONS DEL BAIX | E63: =IFERROR(__xludf.DUMMYFUNCTION("""COMPUTED_VALUE"""),"Alicia Suárez Calvo") -> Alicia Suárez Calvo | F63: =IFERROR(__xludf.DUMMYFUNCTION("""COMPUTED_VALUE"""),"LRM127") -> LRM127 | G63: =IFERROR(__xludf.DUMMYFUNCTION("""COMPUTED_VALUE"""),"Lisandro Russian") -> Lisandro Russian | K63: M.ESTRELLA GOMEZ TOMÉ | L63: María Estrella Gomez Tomé | M63: LRM185 | R63: =IFERROR(__xludf.DUMMYFUNCTION("""COMPUTED_VALUE"""),"LAA77") -> LAA77
A64: Vitoria | B64: Vitoria | C64: aLVARO MOLLa GÓMEZ | E64: =IFERROR(__xludf.DUMMYFUNCTION("""COMPUTED_VALUE"""),"Alvaro Borque Sanz") -> Alvaro Borque Sanz | F64: =IFERROR(__xludf.DUMMYFUNCTION("""COMPUTED_VALUE"""),"MBM206") -> MBM206 | G64: =IFERROR(__xludf.DUMMYFUNCTION("""COMPUTED_VALUE"""),"Maika Blázquez") -> Maika Blázquez | K64: GABRIELA MORALES | L64: María Gabriela Bosco Morales | M64: MBM148 | R64: =IFERROR(__xludf.DUMMYFUNCTION("""COMPUTED_VALUE"""),"LAA72") -> LAA72
A65: Zaragoza | B65: Zaragoza- León XIII | C65: BERDEGAGO, S.L. | E65: =IFERROR(__xludf.DUMMYFUNCTION("""COMPUTED_VALUE"""),"Álvaro Carrillo Sotos") -> Álvaro Carrillo Sotos | F65: =IFERROR(__xludf.DUMMYFUNCTION("""COMPUTED_VALUE"""),"MBM06") -> MBM06 | G65: =IFERROR(__xludf.DUMMYFUNCTION("""COMPUTED_VALUE"""),"Maika Blázquez") -> Maika Blázquez | K65: MARIA GARROTE | L65: María Garrote Garrote | M65: MBM149 | R65: =IFERROR(__xludf.DUMMYFUNCTION("""COMPUTED_VALUE"""),"LRM266") -> LRM266
A66: Zaragoza- Santander | B66: Zaragoza- Santander | C66: BERDEGAGO, S.L. | E66: =IFERROR(__xludf.DUMMYFUNCTION("""COMPUTED_VALUE"""),"Álvaro Pérez Llinares") -> Álvaro Pérez Llinares | F66: =IFERROR(__xludf.DUMMYFUNCTION("""COMPUTED_VALUE"""),"RFV10") -> RFV10 | G66: =IFERROR(__xludf.DUMMYFUNCTION("""COMPUTED_VALUE"""),"Ramon Ferrando") -> Ramon Ferrando | K66: M.JOSE GAMIZ MAROTO | L66: María José Gamiz Maroto | M66: RFV07 | R66: =IFERROR(__xludf.DUMMYFUNCTION("""COMPUTED_VALUE"""),"ISL119") -> ISL119
A67: SAN BOI | B67: SANT BOI | C67: AUDICOST, S.L.U | E67: =IFERROR(__xludf.DUMMYFUNCTION("""COMPUTED_VALUE"""),"Álvaro Sánchez Álvarez") -> Álvaro Sánchez Álvarez | F67: =IFERROR(__xludf.DUMMYFUNCTION("""COMPUTED_VALUE"""),"LRM07") -> LRM07 | G67: =IFERROR(__xludf.DUMMYFUNCTION("""COMPUTED_VALUE"""),"Lisandro Russian") -> Lisandro Russian | K67: M.LUISA CALERO RAMOS | L67: María Luisa Calero Ramos | M67: LAA54 | R67: =IFERROR(__xludf.DUMMYFUNCTION("""COMPUTED_VALUE"""),"LAA27") -> LAA27
E68: =IFERROR(__xludf.DUMMYFUNCTION("""COMPUTED_VALUE"""),"Álvaro Sánchez Barrueco") -> Álvaro Sánchez Barrueco | F68: =IFERROR(__xludf.DUMMYFUNCTION("""COMPUTED_VALUE"""),"LRM08") -> LRM08 | G68: =IFERROR(__xludf.DUMMYFUNCTION("""COMPUTED_VALUE"""),"Lisandro Russian") -> Lisandro Russian | K68: MARIA MENDIGUCHIA | L68: María Mendiguchía Simón | M68: LRM199
E69: =IFERROR(__xludf.DUMMYFUNCTION("""COMPUTED_VALUE"""),"Álvaro Sánchez de Arriba") -> Álvaro Sánchez de Arriba | F69: =IFERROR(__xludf.DUMMYFUNCTION("""COMPUTED_VALUE"""),"LRM09") -> LRM09 | G69: =IFERROR(__xludf.DUMMYFUNCTION("""COMPUTED_VALUE"""),"Lisandro Russian") -> Lisandro Russian | K69: SOLEDAD FRIAS MOYA-ANGELER | L69: María Soledad Frías Moya-Angeler | M69: RFV25
E70: =IFERROR(__xludf.DUMMYFUNCTION("""COMPUTED_VALUE"""),"Amalia Fiestas Tartiere") -> Amalia Fiestas Tartiere | F70: =IFERROR(__xludf.DUMMYFUNCTION("""COMPUTED_VALUE"""),"MBM207") -> MBM207 | G70: =IFERROR(__xludf.DUMMYFUNCTION("""COMPUTED_VALUE"""),"Maika Blázquez") -> Maika Blázquez | K70: MARINA CACEDA | L70: Marina Caceda Chumbiauca | M70: ISL125
E71: =IFERROR(__xludf.DUMMYFUNCTION("""COMPUTED_VALUE"""),"Amaya Lázaro Sánchez") -> Amaya Lázaro Sánchez | F71: =IFERROR(__xludf.DUMMYFUNCTION("""COMPUTED_VALUE"""),"MCC37") -> MCC37 | G71: =IFERROR(__xludf.DUMMYFUNCTION("""COMPUTED_VALUE"""),"Mercè Cabrera") -> Mercè Cabrera | K71: CEBALLOS | L71: Mercedes Ceballos Cauto | M71: LAA56
E72: =IFERROR(__xludf.DUMMYFUNCTION("""COMPUTED_VALUE"""),"Amer Souki Chmeitt") -> Amer Souki Chmeitt | F72: =IFERROR(__xludf.DUMMYFUNCTION("""COMPUTED_VALUE"""),"RPG64") -> RPG64 | G72: =IFERROR(__xludf.DUMMYFUNCTION("""COMPUTED_VALUE"""),"Roberto Pereira") -> Roberto Pereira | K72: MIRIAM GARCIA LERMA | L72: Miriam García Lerma | M72: LRM219
E73: =IFERROR(__xludf.DUMMYFUNCTION("""COMPUTED_VALUE"""),"Amparo Castellote Armero") -> Amparo Castellote Armero | F73: =IFERROR(__xludf.DUMMYFUNCTION("""COMPUTED_VALUE"""),"LRM128") -> LRM128 | G73: =IFERROR(__xludf.DUMMYFUNCTION("""COMPUTED_VALUE"""),"Lisandro Russian") -> Lisandro Russian | K73: MONICA RODRIGUEZ | L73: Mónica Rodríguez Briceño | M73: ISL126
E74: =IFERROR(__xludf.DUMMYFUNCTION("""COMPUTED_VALUE"""),"Amparo Roca Martínez") -> Amparo Roca Martínez | F74: =IFERROR(__xludf.DUMMYFUNCTION("""COMPUTED_VALUE"""),"ISL88") -> ISL88 | G74: =IFERROR(__xludf.DUMMYFUNCTION("""COMPUTED_VALUE"""),"Iván Sánchez") -> Iván Sánchez | K74: MONICA RODRIGUEZ BRICEÑO | L74: Mónica Rodríguez Briceño | M74: ISL126
E75: =IFERROR(__xludf.DUMMYFUNCTION("""COMPUTED_VALUE"""),"Ana Belén Herrero Egea") -> Ana Belén Herrero Egea | F75: =IFERROR(__xludf.DUMMYFUNCTION("""COMPUTED_VALUE"""),"LRM129") -> LRM129 | G75: =IFERROR(__xludf.DUMMYFUNCTION("""COMPUTED_VALUE"""),"Lisandro Russian") -> Lisandro Russian | K75: NESLY GONZALEZ | L75: Nesly IIlely Gonzalez Sanchez | M75: MCC70
E76: =IFERROR(__xludf.DUMMYFUNCTION("""COMPUTED_VALUE"""),"Ana Belén Rodríguez Vences") -> Ana Belén Rodríguez Vences | F76: =IFERROR(__xludf.DUMMYFUNCTION("""COMPUTED_VALUE"""),"LRM130") -> LRM130 | G76: =IFERROR(__xludf.DUMMYFUNCTION("""COMPUTED_VALUE"""),"Lisandro Russian") -> Lisandro Russian | K76: Agustina Nicole Arbia Kalutich | L76: NO ENCONTRADO | M76: MBM205 | N76: =VLOOKUP(K76,$E:$F,2,FALSE) -> MBM205
E77: =IFERROR(__xludf.DUMMYFUNCTION("""COMPUTED_VALUE"""),"Ana Faraldo García") -> Ana Faraldo García | F77: =IFERROR(__xludf.DUMMYFUNCTION("""COMPUTED_VALUE"""),"RPG35") -> RPG35 | G77: =IFERROR(__xludf.DUMMYFUNCTION("""COMPUTED_VALUE"""),"Roberto Pereira") -> Roberto Pereira | K77: ALVARO BORQUE SANZ | L77: NO ENCONTRADO | M77: MBM206 | N77: =VLOOKUP(K77,$E:$F,2,FALSE) -> MBM206
E78: =IFERROR(__xludf.DUMMYFUNCTION("""COMPUTED_VALUE"""),"Ana Fernández Rodríguez") -> Ana Fernández Rodríguez | F78: =IFERROR(__xludf.DUMMYFUNCTION("""COMPUTED_VALUE"""),"PSC31") -> PSC31 | G78: =IFERROR(__xludf.DUMMYFUNCTION("""COMPUTED_VALUE"""),"Patricia Solache") -> Patricia Solache | K78: Amalia Fiestas Tartiere | L78: NO ENCONTRADO | M78: MBM207 | N78: =VLOOKUP(K78,$E:$F,2,FALSE) -> MBM207
E79: =IFERROR(__xludf.DUMMYFUNCTION("""COMPUTED_VALUE"""),"Ana Gabriela Jover Espla") -> Ana Gabriela Jover Espla | F79: =IFERROR(__xludf.DUMMYFUNCTION("""COMPUTED_VALUE"""),"ISL89") -> ISL89 | G79: =IFERROR(__xludf.DUMMYFUNCTION("""COMPUTED_VALUE"""),"Iván Sánchez") -> Iván Sánchez | K79: Ana Solís Fesser | L79: NO ENCONTRADO | M79: MBM208 | N79: =VLOOKUP(K79,$E:$F,2,FALSE) -> MBM208
E80: =IFERROR(__xludf.DUMMYFUNCTION("""COMPUTED_VALUE"""),"Ana Giribet Fernández-Pacheco") -> Ana Giribet Fernández-Pacheco | F80: =IFERROR(__xludf.DUMMYFUNCTION("""COMPUTED_VALUE"""),"ISL90") -> ISL90 | G80: =IFERROR(__xludf.DUMMYFUNCTION("""COMPUTED_VALUE"""),"Iván Sánchez") -> Iván Sánchez | K80: Andrea Gil Pro | L80: NO ENCONTRADO | M80: MBM209 | N80: =VLOOKUP(K80,$E:$F,2,FALSE) -> #N/A
E81: =IFERROR(__xludf.DUMMYFUNCTION("""COMPUTED_VALUE"""),"Ana Herrero Egea") -> Ana Herrero Egea | F81: =IFERROR(__xludf.DUMMYFUNCTION("""COMPUTED_VALUE"""),"LRM131") -> LRM131 | G81: =IFERROR(__xludf.DUMMYFUNCTION("""COMPUTED_VALUE"""),"Lisandro Russian") -> Lisandro Russian | K81: Antonio Ballesteros Chozas | L81: NO ENCONTRADO | M81: LRM260 | N81: =VLOOKUP(K81,$E:$F,2,FALSE) -> LRM260
E82: =IFERROR(__xludf.DUMMYFUNCTION("""COMPUTED_VALUE"""),"Ana Isabel Lorenzo Lorenzo") -> Ana Isabel Lorenzo Lorenzo | F82: =IFERROR(__xludf.DUMMYFUNCTION("""COMPUTED_VALUE"""),"RPG36") -> RPG36 | G82: =IFERROR(__xludf.DUMMYFUNCTION("""COMPUTED_VALUE"""),"Roberto Pereira") -> Roberto Pereira | K82: Carlos Carazo Casas | L82: NO ENCONTRADO | M82: MBM210 | N82: =VLOOKUP(K82,$E:$F,2,FALSE) -> MBM210
E83: =IFERROR(__xludf.DUMMYFUNCTION("""COMPUTED_VALUE"""),"Ana María Sánchez-Prieto Fernández") -> Ana María Sánchez-Prieto Fernández | F83: =IFERROR(__xludf.DUMMYFUNCTION("""COMPUTED_VALUE"""),"LRM132") -> LRM132 | G83: =IFERROR(__xludf.DUMMYFUNCTION("""COMPUTED_VALUE"""),"Lisandro Russian") -> Lisandro Russian | K83: Carlos Fernandez-Navarro García | L83: NO ENCONTRADO | M83: MBM211 | N83: =VLOOKUP(K83,$E:$F,2,FALSE) -> #N/A
E84: =IFERROR(__xludf.DUMMYFUNCTION("""COMPUTED_VALUE"""),"Ana Moreno Valor") -> Ana Moreno Valor | F84: =IFERROR(__xludf.DUMMYFUNCTION("""COMPUTED_VALUE"""),"MCC38") -> MCC38 | G84: =IFERROR(__xludf.DUMMYFUNCTION("""COMPUTED_VALUE"""),"Mercè Cabrera") -> Mercè Cabrera | K84: Cecilia Pérez Martínez | L84: Cecilia Pérez Martínez | M84: MBM100 | N84: =VLOOKUP(K84,$E:$F,2,FALSE) -> MBM100
E85: =IFERROR(__xludf.DUMMYFUNCTION("""COMPUTED_VALUE"""),"Ana Pérez del Notario") -> Ana Pérez del Notario | F85: =IFERROR(__xludf.DUMMYFUNCTION("""COMPUTED_VALUE"""),"LRM133") -> LRM133 | G85: =IFERROR(__xludf.DUMMYFUNCTION("""COMPUTED_VALUE"""),"Lisandro Russian") -> Lisandro Russian | K85: Edson Robles Castilla | L85: NO ENCONTRADO | M85: MBM212 | N85: =VLOOKUP(K85,$E:$F,2,FALSE) -> MBM212
E86: =IFERROR(__xludf.DUMMYFUNCTION("""COMPUTED_VALUE"""),"Ana Quintana Sanjuan") -> Ana Quintana Sanjuan | F86: =IFERROR(__xludf.DUMMYFUNCTION("""COMPUTED_VALUE"""),"RPG37") -> RPG37 | G86: =IFERROR(__xludf.DUMMYFUNCTION("""COMPUTED_VALUE"""),"Roberto Pereira") -> Roberto Pereira | K86: Elena Vazquez Becerra | L86: NO ENCONTRADO | M86: LAA79 | N86: =VLOOKUP(K86,$E:$F,2,FALSE) -> #N/A
E87: =IFERROR(__xludf.DUMMYFUNCTION("""COMPUTED_VALUE"""),"Ana Rodríguez Rodríguez") -> Ana Rodríguez Rodríguez | F87: =IFERROR(__xludf.DUMMYFUNCTION("""COMPUTED_VALUE"""),"MCC62") -> MCC62 | G87: =IFERROR(__xludf.DUMMYFUNCTION("""COMPUTED_VALUE"""),"Mercè Cabrera") -> Mercè Cabrera | K87: Irene Gómez Frias | L87: NO ENCONTRADO | M87: MBM213 | N87: =VLOOKUP(K87,$E:$F,2,FALSE) -> MBM213
E88: =IFERROR(__xludf.DUMMYFUNCTION("""COMPUTED_VALUE"""),"Ana Ruiz Fornells Noreña") -> Ana Ruiz Fornells Noreña | F88: =IFERROR(__xludf.DUMMYFUNCTION("""COMPUTED_VALUE"""),"MBM90") -> MBM90 | G88: =IFERROR(__xludf.DUMMYFUNCTION("""COMPUTED_VALUE"""),"Maika Blázquez") -> Maika Blázquez | K88: Isabel Bueno Aventin | L88: NO ENCONTRADO | M88: MBM214 | N88: =VLOOKUP(K88,$E:$F,2,FALSE) -> MBM214
E89: =IFERROR(__xludf.DUMMYFUNCTION("""COMPUTED_VALUE"""),"Ana Solís Fesser") -> Ana Solís Fesser | F89: =IFERROR(__xludf.DUMMYFUNCTION("""COMPUTED_VALUE"""),"MBM208") -> MBM208 | G89: =IFERROR(__xludf.DUMMYFUNCTION("""COMPUTED_VALUE"""),"Maika Blázquez") -> Maika Blázquez | K89: Ismael Soriano Martínez | L89: NO ENCONTRADO | M89: MBM215 | N89: =VLOOKUP(K89,$E:$F,2,FALSE) -> MBM215
E90: =IFERROR(__xludf.DUMMYFUNCTION("""COMPUTED_VALUE"""),"Anastasiya Audiyuk Martynyuk") -> Anastasiya Audiyuk Martynyuk | F90: =IFERROR(__xludf.DUMMYFUNCTION("""COMPUTED_VALUE"""),"MBM195") -> MBM195 | G90: =IFERROR(__xludf.DUMMYFUNCTION("""COMPUTED_VALUE"""),"Maika Blázquez") -> Maika Blázquez | K90: Kurt Liebner Martínez | L90: NO ENCONTRADO | M90: MBM216 | N90: =VLOOKUP(K90,$E:$F,2,FALSE) -> MBM216
E91: =IFERROR(__xludf.DUMMYFUNCTION("""COMPUTED_VALUE"""),"Andrea Cifuentes Navas") -> Andrea Cifuentes Navas | F91: =IFERROR(__xludf.DUMMYFUNCTION("""COMPUTED_VALUE"""),"LRM258") -> LRM258 | G91: =IFERROR(__xludf.DUMMYFUNCTION("""COMPUTED_VALUE"""),"Lisandro Russian") -> Lisandro Russian | K91: María Lluc Montaña Frau | L91: NO ENCONTRADO | M91: MBM217 | N91: =VLOOKUP(K91,$E:$F,2,FALSE) -> MBM217
E92: =IFERROR(__xludf.DUMMYFUNCTION("""COMPUTED_VALUE"""),"Andrea Escribano Peñalva") -> Andrea Escribano Peñalva | F92: =IFERROR(__xludf.DUMMYFUNCTION("""COMPUTED_VALUE"""),"LRM135") -> LRM135 | G92: =IFERROR(__xludf.DUMMYFUNCTION("""COMPUTED_VALUE"""),"Lisandro Russian") -> Lisandro Russian | K92: Mar Gimeno Coret | L92: NO ENCONTRADO | M92: RFV46 | N92: =VLOOKUP(K92,$E:$F,2,FALSE) -> RFV46
E93: =IFERROR(__xludf.DUMMYFUNCTION("""COMPUTED_VALUE"""),"Andrea Gil Pro") -> Andrea Gil Pro | F93: =IFERROR(__xludf.DUMMYFUNCTION("""COMPUTED_VALUE"""),"MBM209") -> MBM209 | G93: =IFERROR(__xludf.DUMMYFUNCTION("""COMPUTED_VALUE"""),"Maika Blázquez") -> Maika Blázquez | K93: Miguel Lucas Herrera | L93: NO ENCONTRADO | M93: ISL147 | N93: =VLOOKUP(K93,$E:$F,2,FALSE) -> ISL147
E94: =IFERROR(__xludf.DUMMYFUNCTION("""COMPUTED_VALUE"""),"Andrea López Salcedo") -> Andrea López Salcedo | F94: =IFERROR(__xludf.DUMMYFUNCTION("""COMPUTED_VALUE"""),"MBM91") -> MBM91 | G94: =IFERROR(__xludf.DUMMYFUNCTION("""COMPUTED_VALUE"""),"Maika Blázquez") -> Maika Blázquez | K94: María Montserrat Asensi Díaz | L94: NO ENCONTRADO | M94: MBM218 | N94: =VLOOKUP(K94,$E:$F,2,FALSE) -> MBM218
E95: =IFERROR(__xludf.DUMMYFUNCTION("""COMPUTED_VALUE"""),"Andreas Schilling Borghesi") -> Andreas Schilling Borghesi | F95: =IFERROR(__xludf.DUMMYFUNCTION("""COMPUTED_VALUE"""),"MBM07") -> MBM07 | G95: =IFERROR(__xludf.DUMMYFUNCTION("""COMPUTED_VALUE"""),"Maika Blázquez") -> Maika Blázquez | K95: Paula Morales Chacchi | L95: NO ENCONTRADO | M95: MBM219 | N95: =VLOOKUP(K95,$E:$F,2,FALSE) -> MBM219
E96: =IFERROR(__xludf.DUMMYFUNCTION("""COMPUTED_VALUE"""),"Andrés Barrios Recio") -> Andrés Barrios Recio | F96: =IFERROR(__xludf.DUMMYFUNCTION("""COMPUTED_VALUE"""),"ISL06") -> ISL06 | G96: =IFERROR(__xludf.DUMMYFUNCTION("""COMPUTED_VALUE"""),"Iván Sánchez") -> Iván Sánchez | K96: NURIA SALAS BARRIOS | L96: Nuria Salas Barrio | M96: ISL128
E97: =IFERROR(__xludf.DUMMYFUNCTION("""COMPUTED_VALUE"""),"Andrés González Fernández") -> Andrés González Fernández | F97: =IFERROR(__xludf.DUMMYFUNCTION("""COMPUTED_VALUE"""),"LRM271") -> LRM271 | G97: =IFERROR(__xludf.DUMMYFUNCTION("""COMPUTED_VALUE"""),"Lisandro Russian") -> Lisandro Russian | K97: OLGA ALDECOA JIMENEZ | L97: Olga Aldecoa Jiménez | M97: LRM224
E98: =IFERROR(__xludf.DUMMYFUNCTION("""COMPUTED_VALUE"""),"Andrés Paulino Herrera") -> Andrés Paulino Herrera | F98: =IFERROR(__xludf.DUMMYFUNCTION("""COMPUTED_VALUE"""),"LRM240") -> LRM240 | G98: =IFERROR(__xludf.DUMMYFUNCTION("""COMPUTED_VALUE"""),"Lisandro Russian") -> Lisandro Russian | K98: OSCAR SANCHEZ | L98: Oscar A, Sanchez Valenzuela | M98: MBM69
E99: =IFERROR(__xludf.DUMMYFUNCTION("""COMPUTED_VALUE"""),"Andrés Ruiz Moreno") -> Andrés Ruiz Moreno | F99: =IFERROR(__xludf.DUMMYFUNCTION("""COMPUTED_VALUE"""),"LAA01") -> LAA01 | G99: =IFERROR(__xludf.DUMMYFUNCTION("""COMPUTED_VALUE"""),"Luis Alberto Rodríguez") -> Luis Alberto Rodríguez | K99: SANCHEZ VALENZUELA | L99: Oscar A, Sanchez Valenzuela | M99: MBM69
E100: =IFERROR(__xludf.DUMMYFUNCTION("""COMPUTED_VALUE"""),"Andrés Soto Varela") -> Andrés Soto Varela | F100: =IFERROR(__xludf.DUMMYFUNCTION("""COMPUTED_VALUE"""),"RPG02") -> RPG02 | G100: =IFERROR(__xludf.DUMMYFUNCTION("""COMPUTED_VALUE"""),"Roberto Pereira") -> Roberto Pereira | K100: PABLO VERGES | L100: Pablo Vergés Fort | M100: MCC29
...

Sheet Resumen 2026
A1: RESUMEN TOTAL 2026 — VISITADOR / MÉDICO / IMPORTE
A3: RESUMEN POR VISITADOR
A4: VISITADOR | B4: Nº MÉDICOS | C4: Nº ACCIONES | D4: IMPORTE TOTAL
A5: Iván Sánchez | B5: 7 | C5: =COUNTIF(TOTAL2026!C$2:C$1001,A5) -> 13 | D5: =SUMIF(TOTAL2026!C$2:C$1001,A5,TOTAL2026!K$2:K$1001) -> -17780.96
A6: Lisandro Russian | B6: 6 | C6: =COUNTIF(TOTAL2026!C$2:C$1001,A6) -> 8 | D6: =SUMIF(TOTAL2026!C$2:C$1001,A6,TOTAL2026!K$2:K$1001) -> -14051.06
A7: Luis Alberto Rodríguez | B7: 5 | C7: =COUNTIF(TOTAL2026!C$2:C$1001,A7) -> 6 | D7: =SUMIF(TOTAL2026!C$2:C$1001,A7,TOTAL2026!K$2:K$1001) -> -22472.38
A8: Maika Blázquez | B8: 19 | C8: =COUNTIF(TOTAL2026!C$2:C$1001,A8) -> 28 | D8: =SUMIF(TOTAL2026!C$2:C$1001,A8,TOTAL2026!K$2:K$1001) -> -20976.83
A9: Ramon Ferrando | B9: 5 | C9: =COUNTIF(TOTAL2026!C$2:C$1001,A9) -> 9 | D9: =SUMIF(TOTAL2026!C$2:C$1001,A9,TOTAL2026!K$2:K$1001) -> -9049.15
A10: TOTAL | B10: =SUM(B5:B9) -> 42 | C10: =SUM(C5:C9) -> 64 | D10: =SUM(D5:D9) -> -84330.38
A12: DETALLE POR VISITADOR Y MÉDICO
A13: VISITADOR | B13: MÉDICO (ORL) | C13: Nº ACCIONES | D13: IMPORTE
A14: Iván Sánchez | B14: Carlos Velásquez Fermín | C14: =COUNTIFS(TOTAL2026!C$2:C$1001,A14,TOTAL2026!F$2:F$1001,B14) -> 4 | D14: =SUMIFS(TOTAL2026!K$2:K$1001,TOTAL2026!C$2:C$1001,A14,TOTAL2026!F$2:F$1001,B14) -> -5797.02
A15: Iván Sánchez | B15: Enrique López Meseguer | C15: =COUNTIFS(TOTAL2026!C$2:C$1001,A15,TOTAL2026!F$2:F$1001,B15) -> 2 | D15: =SUMIFS(TOTAL2026!K$2:K$1001,TOTAL2026!C$2:C$1001,A15,TOTAL2026!F$2:F$1001,B15) -> -3416
A16: Iván Sánchez | B16: José María Laborda Margolles | C16: =COUNTIFS(TOTAL2026!C$2:C$1001,A16,TOTAL2026!F$2:F$1001,B16) -> 1 | D16: =SUMIFS(TOTAL2026!K$2:K$1001,TOTAL2026!C$2:C$1001,A16,TOTAL2026!F$2:F$1001,B16) -> -4000
A17: Iván Sánchez | B17: Juan Javier Álvarez López | C17: =COUNTIFS(TOTAL2026!C$2:C$1001,A17,TOTAL2026!F$2:F$1001,B17) -> 3 | D17: =SUMIFS(TOTAL2026!K$2:K$1001,TOTAL2026!C$2:C$1001,A17,TOTAL2026!F$2:F$1001,B17) -> -3968.42
A18: Iván Sánchez | B18: Karen Rojas Crespo | C18: =COUNTIFS(TOTAL2026!C$2:C$1001,A18,TOTAL2026!F$2:F$1001,B18) -> 1 | D18: =SUMIFS(TOTAL2026!K$2:K$1001,TOTAL2026!C$2:C$1001,A18,TOTAL2026!F$2:F$1001,B18) -> -599.52
